Workbook

Sheet 目录
A1: 华东区-同行价格 目录表
A2: 服务 | B2: 渠道名称 | C2: 价格表链接 | D2: 派送参考时效
A3: 海卡价格快捷查询 | B3: 海卡价格快捷查询 | C3: 点击进入 | D3: -
A4: 联邦超大件海派 | B4: 联邦超大件海派 | C4: 点击进入 | D4: 14、18天 赔付时效承诺
A5: 自提-自打单-仓储 | B5: 自提-自打单-仓储 | C5: 点击进入 | D5: CLX MAX EXX OA普船 美中美东普船全渠道自提/仓储服务
A6: 海派汇总表 海派汇总表—DY | B6: 海派 美森极速达 13天赔付 （CLX） | C6: 点击进入 | D6: 13天 赔付时效承诺
B7: 海派 美森极速达 14天赔付 （CLX） | D7: 14天 赔付时效承诺
B8: 海派 美森加班限时达 18天赔付 （MAX） | D8: 18天 赔付时效承诺
B9: 海派 美森加班船 （MAX） | D9: 开船后16天-18天提取
B10: 海派 普船经济线 | D10: 开船后25-30天左右提取
B11: 海派 OA普船定提统配 | D11: 开船后22-25天左右提取
B12: 海派 OA稳速达统配 25天赔付 （OA统配） | D12: 25天 赔付时效承诺
B13: 海派 稳速达统配 22天赔付 （OA/合德/以星 统配） | D13: 22天 赔付时效承诺
B14: 海派 合德快提 18天赔付 | D14: 18天 赔付时效承诺
B15: 海派 EXX限时达 18天赔付 | D15: 18天 赔付时效承诺
B16: 海派 合德/以星统配 20天赔付 | D16: 20天 赔付时效承诺
B17: 海派 休斯顿OA快普 | D17: 开船后35-40天内提取
B18: 海派 芝加哥OA快普 | D18: 开船后35-40天内提取
B19: 海派 美东OA快普 | D19: 开船后35-40天内提取
A20: 海卡汇总表 | B20: 海卡/美森极速达（CLX）【带赔付】 | C20: 点击进入 | D20: 卡派19天起赔
B21: 海卡/美森极速达（CLX） | D21: 14-18天签收提供POD
B22: 海卡/美森加班船（MAX ）【带赔付】 | D22: 卡派20天起赔
B23: 海卡/美森加班船（MAX ） | D23: 16-19天签收提供POD
B24: 海卡/EXX限时达【带赔付】 | D24: 卡派21天起赔
B25: 海卡/合德限时达【带赔付】 | D25: 卡派25天起赔
B26: 海卡/OA稳速达【带赔付】 | D26: 卡派28天起赔
B27: 海卡/OA普船定提统配 | D27: 20-25天提供POD
B28: 海卡/普船经济线 | D28: 25-30天提供POD
A29: 普船海卡整柜直送 | B29: 普船海卡整柜直送 | C29: 点击进入 | D29: 西雅图、洛杉矶直送，开船后20-35天提供POD
A30: 美中专线（休斯顿、芝加哥） | B30: 美中专线（休斯顿、芝加哥） | C30: 点击进入 | D30: 35-40天时效
A31: 萨凡纳海卡专线 | B31: 萨凡纳海卡专线 | C31: 点击进入 | D31: 35-45天时效
A32: 美东纽约海卡专线 | B32: 美东纽约海卡专线 | C32: 点击进入 | D32: 35-40天时效；含纽约海铁赔付渠道
A33: 全美私人卡派 | B33: 全美私人卡派 | C33: 点击进入 | D33: 渠道丰富，对应渠道可以做到秒报价： CLX MAX EXX 以星 洛杉矶普船 奥克兰/纽约/休斯顿/芝加哥普船
A34: 美国转加拿大海派 | B34: 美国转加拿大海派 | C34: 点击进入 | D34: 赔付时效为：18天、20天、25天不等
A35: 奥克兰卡派专线 | B35: 奥克兰普船海卡/散货特价 | C35: 点击进入 | D35: 开船后25-35天提供POD
A36: 西雅图卡派专线 | B36: 西雅图海卡/散货特价 | C36: 点击进入 | D36: 开船后25-35天提供POD
A37: UPS海运小包特价 | B37: UPS海运小包特价 | C37: 点击进入 | D37: 16、18天 赔付时效承诺
A38: 美西海外仓收费标准 | B38: 美西海外仓收费标准 | C38: 点击进入 | D38: /
A39: 奥克兰、芝加哥、休斯顿、纽约海外仓收费标准 | B39: 奥克兰、芝加哥、休斯顿、纽约海外仓收费标准 | C39: 点击进入 | D39: /
A40: 各分公司联系电话；仓库收货联系人，写我司业务员，方便我司识别是哪个业务员的货
A41: 义乌总公司（办公室） | B41: 浙江省金华市义乌市城西街道鸿运路313号国际陆港电商城1期11C 5楼整层
A42: 华南运营中心（办公室） | B42: 深圳市宝安区福园一路35号伟丰互联网创业园A5栋903-904-905室
A43: 广州运营中心（办公室） | B43: 广东省广州市白云区鹤龙街联边彭上德兴路12号 中喜大厦301室
A44: 义乌总仓（海运部） | B44: 金华市金东区孝顺镇广顺南街与集贤路十字路口，进门右拐第一栋3楼（第一个斜坡上来3楼） 收件人：飞迹业务员名字 18257908085
A45: 深圳分公司（福永海运部） | B45: 深圳市宝安区同富路1号科聚通工业园6栋一整平层 收件人：飞迹业务员名字 17301951252
A46: 深圳分公司（龙华海运部） | B46: 深圳龙华区云海库坑产业园 收件人：飞迹业务员名字 15396509121
A47: 广州分公司（广州海运部） | B47: 广州市白云区人和镇镜塘路388号基实白云空港产业园B栋4楼B4-1 收件人：飞迹业务员名字 13177527849
A48: 泉州分公司（海运部） | B48: 福建省泉州市晋江市磁灶镇 开元路18号 一楼 收件人：飞迹业务员名字 15396505662
A49: 厦门分公司（海运部） | B49: 福建省厦门市海沧区海沧街道港南路336号 收件人：飞迹业务员名字 15159232894

Sheet 注意事项及赔偿标准
A1: 海派海卡类：美国海运注意事项、收费标准及赔偿标准
A2: 货物包装要求： 1、亚马逊仓外箱要贴两张入仓条码。 2、海派：单件最低计费重12KG，重量不超过22Kg；海卡：单件重量不超过30Kg。 3、外箱规则，坚固，防止货物损坏，否则我司不承担亚马逊仓库拒收所造成的货物丢失。 4、货物外箱上贴上made in china的字样（内部货物产品也需贴有MADE IN CHINA标签。如因包装及标签问题导致亚马逊仓库拒收或清关出现问题，所有责任及费用由发货人承担。) 5、发货前请贴好货物的SKU条码以及FBA箱子标签并用透明胶纸封好，如因标签条码问题无法递送产生的相关费用则由发件人承担。
A3: ★★★ 一、注意事项 ★★★
A4: 1、只收普货。带电产品只接内置纽扣电池类。眼镜类需要FDA跟落球证书才能出。材质是原木或带有原木的货物要求熏蒸商检，商检费：RMB 300/票。需要商检的货物：木家私，木制工艺品，木架，竹制品，藤制品，草制品，植物制品等（仅供参考），客户可自行安排熏蒸和商检。 1）不接产品：玩具产品、仿牌、液体、粉末、美国对华反倾销产品等敏感货物。 2）不接食品类、医疗类产品类、婴儿用品类、童装、童鞋、汽车灯、化妆品类（含纹身美妆产品）、电子烟及烟草相关产品、动物皮毛制品类、激光产品类、成人用品类、管制刀具和警棍、电棒类、植物种子类、强磁类（磁铁、冰箱贴等）、灭蚊、捕鼠、杀虫类产品、杂志书籍出版，如发现冲货或者带电不备注行为没收货物并罚款RMB1000-RMB50000元：不接收木箱；木架；及托盘货物。 3）毛绒玩具 需要CPC认证+申报费：收300元一票。
A5: 2、以上价格为本区域仓库交货价。货物体积重计算方式为长x宽x高(CM)/6000。单票一件的品名超过2个不接，多件的，品名超过5个，按照30元/个收取。
A6: 3、海关要求如实申报，否则造成延误和丢失以及扣关我司一概不负责。
A7: 4、因服务商原因产生海外退件，退件运费及相关退件费用将无条件由发件人支付。
A8: 5、重量尺寸限制明细如下,超重费注：22kg<单箱产品<30kg，收150元/箱；30kg<单箱产品<35kg，收300元/箱；且单件货物不能低于12KG，不足12KG按12KG计算(包装限制：只接受纸箱包装货物)。非规则箱规，收异形费150/件。不收凹凸严重不整齐的异形箱规尺寸！！
A9: 1）0<单件重量<22KG 2）0CM<最长单边长度<120CM 超出+120一件 3）0CM<第二边<75CM 超出+120一件 4）260CM<周长（长+2宽+2高）<320CM 超出+150一件 5）320CM<周长（长+2宽+2高）<410CM 超出+1500一件 6）超410不收
A10: 6、不收地址： 阿拉斯加，夏威夷，波多黎各，关岛，及各岛屿。
A11: 7、以上货物服务仅限于美国48洲，邮箱BOX，军方地址不收(阿拉斯加，夏威夷，波多黎各,关岛，及各岛屿美国直接不收，可中转这几个城市,请咨询)偏远费单询。如果地址错误产生联邦IP/UPS更改地址和扣件费用的，所产生的具体费用需要单独咨询我司客服。海关要求如实申报，否则造成延误和丢失以及扣关我司一概不负责。
A12: 8、有关品牌侵权产品问题： 如美国海关认定货物涉及品牌侵权或蓝牙、HDMI、FCC、UL、FDA、DOT等认证问题，客户需按要求提供相关认证和品牌授权书等文件，如因无法提供或者提供的文件得不到美国海关及相关部门的认可而导致扣货或者退运，所有责任和费用由该发货人承担。
... A28: 以上条款最终解释权归义乌飞迹国际公司所有！

Sheet 海卡价格快捷查询
A1: FBA仓库代码 （请在右侧【C1】输入大小写均可） | C1: ont8 | D1: =UPPER(C1) -> ONT8 | E1: 温馨提示： 关于冷门仓卡派超大件尺寸附加费，比重优惠，带赔付的时效赔付等其他问题，详情请参考的具体价格表！！！
A2: 派送类型 | B2: 渠道 | C2: 价格 | D2: 参考时效
A3: 美西卡派 （热门仓12kg+起收，冷门仓100kg+起收） | B3: 海卡/美森极速达（CLX） 【带赔付】 | C3: {=IFERROR(INDEX(美西海卡汇总表!D4:D345,MATCH(D1,美西海卡汇总表!A4:A345,0)),"-")} -> 8.3 | D3: {=IFERROR(INDEX(美西海卡汇总表!E4:E345,MATCH(D1,美西海卡汇总表!A4:A345,0)),"-")} -> 19天赔付
B4: 海卡/美森极速达（CLX） | C4: {=IFERROR(INDEX(美西海卡汇总表!F4:F345,MATCH(D1,美西海卡汇总表!A4:A345,0)),"-")} -> 8 | D4: {=IFERROR(INDEX(美西海卡汇总表!G4:G345,MATCH(D1,美西海卡汇总表!A4:A345,0)),"-")} -> 15-22天
B5: 海卡/美森加班船（MAX） 【带赔付】 | C5: {=IFERROR(INDEX(美西海卡汇总表!H4:H345,MATCH(D1,美西海卡汇总表!A4:A345,0)),"-")} -> 7.3 | D5: {=IFERROR(INDEX(美西海卡汇总表!I4:I345,MATCH(D1,美西海卡汇总表!A4:A345,0)),"-")} -> 20天赔付
B6: 海卡/美森加班船（MAX） | C6: {=IFERROR(INDEX(美西海卡汇总表!J4:J345,MATCH(D1,美西海卡汇总表!A4:A345,0)),"-")} -> 7 | D6: {=IFERROR(INDEX(美西海卡汇总表!K4:K345,MATCH(D1,美西海卡汇总表!A4:A345,0)),"-")} -> 17-23天
B7: 海卡/EXX限时达【带赔付】 | C7: {=IFERROR(INDEX(美西海卡汇总表!L4:L345,MATCH(D1,美西海卡汇总表!A4:A345,0)),"-")} -> 5.3 | D7: {=IFERROR(INDEX(美西海卡汇总表!M4:M345,MATCH(D1,美西海卡汇总表!A4:A345,0)),"-")} -> 21天赔付
B8: 海卡/华东合德限时达【带赔付】 （最晚周二进仓） | C8: {=IFERROR(INDEX(美西海卡汇总表!N4:N345,MATCH(D1,美西海卡汇总表!A4:A345,0)),"-")} -> 4.7 | D8: {=IFERROR(INDEX(美西海卡汇总表!O4:O345,MATCH(D1,美西海卡汇总表!A4:A345,0)),"-")} -> 25天赔付
B9: 海卡/OA稳速达【带赔付】 （最晚周一进仓） | C9: {=IFERROR(INDEX(美西海卡汇总表!P4:P345,MATCH(D1,美西海卡汇总表!A4:A345,0)),"-")} -> 4.4 | D9: {=IFERROR(INDEX(美西海卡汇总表!Q4:Q345,MATCH(D1,美西海卡汇总表!A4:A345,0)),"-")} -> 28天赔付
B10: 海卡/OA普船定提统配 | C10: {=IFERROR(INDEX(美西海卡汇总表!R4:R345,MATCH(D1,美西海卡汇总表!A4:A345,0)),"-")} -> 4.3 | D10: {=IFERROR(INDEX(美西海卡汇总表!S4:S345,MATCH(D1,美西海卡汇总表!A4:A345,0)),"-")} -> 20-25天
B11: 海卡/普船经济线 （周六开船，25天航程） | C11: {=IFERROR(INDEX(美西海卡汇总表!T4:T345,MATCH(D1,美西海卡汇总表!A4:A345,0)),"-")} -> 4.2 | D11: {=IFERROR(INDEX(美西海卡汇总表!U4:U345,MATCH(D1,美西海卡汇总表!A4:A345,0)),"-")} -> 25-30天
A12: 普船海卡整柜直送 （12kg+起收） | B12: 西雅图普船海卡/整柜直送 | C12: =IFERROR(INDEX(普船海卡整柜直送!#REF!,MATCH(D1,普船海卡整柜直送!#REF!,0)),"-") -> - | D12: =IFERROR(INDEX(普船海卡整柜直送!#REF!,MATCH(D1,普船海卡整柜直送!#REF!,0)),"-") -> -
B13: 美西普船海卡/整柜直送 | C13: {=IFERROR(INDEX(普船海卡整柜直送!D4:D22,MATCH(D1,普船海卡整柜直送!A4:A22,0)),"-")} -> 4.1 | D13: {=IFERROR(INDEX(普船海卡整柜直送!F4:F22,MATCH(D1,普船海卡整柜直送!A4:A22,0)),"-")} -> 25-32天
B14: 奥克兰普船海卡/整柜直送 | C14: {=IFERROR(INDEX(普船海卡整柜直送!D26:D31,MATCH(D1,普船海卡整柜直送!A26:A31,0)),"-")} -> - | D14: {=IFERROR(INDEX(普船海卡整柜直送!F26:F31,MATCH(D1,普船海卡整柜直送!A26:A31,0)),"-")} -> -
B15: 美西普船海卡/整柜直送 普船经济线 | C15: {=IFERROR(INDEX(普船海卡整柜直送!D35:D53,MATCH(D1,普船海卡整柜直送!A35:A53,0)),"-")} -> 4 | D15: {=IFERROR(INDEX(普船海卡整柜直送!F35:F53,MATCH(D1,普船海卡整柜直送!A35:A53,0)),"-")} -> 30-35天
A16: 美中专线 （休斯顿、芝加哥） 12kg+起收 | B16: 芝加哥 普船海卡/美中专线 | C16: {=IFERROR(INDEX('美中专线（休斯顿、芝加哥）'!C4:C35,MATCH(D1,'美中专线（休斯顿、芝加哥）'!A4:A35,0)),"-")} -> - | D16: {=IFERROR(INDEX('美中专线（休斯顿、芝加哥）'!D4:D35,MATCH(D1,'美中专线（休斯顿、芝加哥）'!A4:A35,0)),"-")} -> -
B17: 休斯顿 普船海卡/美中专线 | C17: {=IFERROR(INDEX('美中专线（休斯顿、芝加哥）'!C43:C59,MATCH(D1,'美中专线（休斯顿、芝加哥）'!A43:A59,0)),"-")} -> - | D17: {=IFERROR(INDEX('美中专线（休斯顿、芝加哥）'!D43:D59,MATCH(D1,'美中专线（休斯顿、芝加哥）'!A43:A59,0)),"-")} -> -
A18: 萨凡纳海卡专线 （12KG+起收） | B18: 海卡/萨凡纳直航普船 | C18: {=IFERROR(INDEX(萨凡纳海卡专线!C3:C42,MATCH(D1,萨凡纳海卡专线!A3:A42,0)),"-")} -> - | D18: {=IFERROR(INDEX(萨凡纳海卡专线!D3:D42,MATCH(D1,萨凡纳海卡专线!A3:A42,0)),"-")} -> -
A19: 美东纽约海卡专线 | B19: 海卡/纽约直航普船-包税 （1方起收） | C19: {=IFERROR(INDEX(美东纽约海卡专线!C5:C87,MATCH(D1,美东纽约海卡专线!A5:A87,0)),"-")} -> - | D19: {=IFERROR(INDEX(美东纽约海卡专线!E5:E87,MATCH(D1,美东纽约海卡专线!A5:A87,0)),"-")} -> -
B20: 海卡/纽约直航普船 （12kg+起收） | C20: {=IFERROR(INDEX(美东纽约海卡专线!D5:D87,MATCH(D1,美东纽约海卡专线!A5:A87,0)),"-")} -> - | D20: {=IFERROR(INDEX(美东纽约海卡专线!E5:E87,MATCH(D1,美东纽约海卡专线!A5:A87,0)),"-")} -> -
A21: 奥克兰卡派专线 （12kg+起收） | B21: 奥克兰普船海卡/散货特价 | C21: {=IFERROR(INDEX(奥克兰卡派专线!C4:C19,MATCH(D1,奥克兰卡派专线!A4:A19,0)),"-")} -> - | D21: {=IFERROR(INDEX(奥克兰卡派专线!E4:E19,MATCH(D1,奥克兰卡派专线!A4:A19,0)),"-")} -> -
A22: 西雅图卡派专线 （12kg+起收） | B22: 西雅图海卡/散货特价 | C22: {=IFERROR(INDEX(西雅图卡派专线!C4:C9,MATCH(D1,西雅图卡派专线!A4:A9,0)),"-")} -> - | D22: {=IFERROR(INDEX(西雅图卡派专线!E4:E9,MATCH(D1,西雅图卡派专线!A4:A9,0)),"-")} -> -

Sheet 联邦超大件海派
A1: 华东区-同行价格表
A2: 联邦超大件海派 美森正班极速达 14天赔付 （CLX）
A3: 邮编/计费重 | B3: 22-68KG | C3: 普通超大尺寸：备注 （可一票多件） | D3: 40-68KG | E3: 超级大尺寸：备注 （可一票多件） | F3: 下单渠道：联邦超大件海派 美森正班极速达 14天赔付 （CLX）
A4: 邮编90-92 | B4: 22.5 | C4: 尺寸数据不能偏离以下要求： 1、 22KG ≤ 单件计费重 < 68KG 2、 240＞最大边≥125CM 第二边≥80CM 3、 270CM≤长+2*（宽+高）＜320CM | D4: 23.5 | E4: 尺寸数据不能偏离以下要求： 1、 40KG ≤ 单件计费重 < 68KG 2、 270CM>最大边≥245CM 3、 330CM≤长+2*（宽+高）＜400CM 数据超出以上任一条件，需要2500美金/件的附加费 注：单件计费重不低于40kg，不足40kg按40kg计费。 | F4: 开船后第二天开始算第14天提取 第15天开始赔偿1元/kg*天 最高赔付2元每公斤 （如遇海关查验，赔偿1元每公斤） （如遇节假日、码头停摆、港口罢工等非人为因素，不参与赔付）
A5: 邮编 8 9 （除90-92范围） | B5: 23.5 | C5: 尺寸数据不能偏离以下要求： 1、 22KG ≤ 单件计费重 < 65KG 2、 240＞最大边≥125CM 第二边≥80CM 3、 270CM≤长+2*（宽+高）＜320CM | D5: 24.5 | E5: 尺寸数据不能偏离以下要求： 1、 40KG ≤ 单件计费重 < 65KG 2、 270CM>最大边≥245CM 3、 330CM≤长+2*（宽+高）＜400CM 数据超出以上任一条件，需要2500美金/件的附加费 | F5: 开船后第二天开始算第14天提取 第15天开始赔偿1元/kg*天 最高赔付2元每公斤 （如遇海关查验，赔偿1元每公斤） （如遇节假日、码头停摆、港口罢工等非人为因素，不参与赔付）
A6: 邮编5 6 7 | B6: 24.5 | D6: 25.5
A7: 邮编 0 1 2 3 4 | B7: 24.5 | D7: 25.5
A8: 重货比优惠：整票实重大于30公斤以上，1:250 减0.5元 / 1:300 减1元 / 1:400以上 减2元；整票实重/整票方数=货重比
A10: 联邦超大件海派 美森加班限时达 18天赔付 （MAX）
A11: 邮编/计费重 | B11: 22-68KG | C11: 普通超大尺寸：备注 （可一票多件） | D11: 40-68KG | E11: 超级大尺寸：备注 （可一票多件） | F11: 下单渠道：联邦超大件海派 美森加班限时达 18天赔付 （MAX）
A12: 邮编90-92 | B12: 21.5 | C12: 尺寸数据不能偏离以下要求： 1、 22KG ≤ 单件计费重 < 68KG 2、 240＞最大边≥125CM 第二边≥80CM 3、 270CM≤长+2*（宽+高）＜320CM | D12: 22.5 | E12: 尺寸数据不能偏离以下要求： 1、 40KG ≤ 单件计费重 < 68KG 2、 270CM>最大边≥245CM 3、 330CM≤长+2*（宽+高）＜400CM 数据超出以上任一条件，需要2500美金/件的附加费 注：单件计费重不低于40kg，不足40kg按40kg计费。 | F12: 开船后第二天开始算18天提取 第19天开始赔偿1元/kg*天 最高赔付2元每公斤 （如遇海关查验，赔偿1元每公斤） （如遇节假日、码头停摆、港口罢工等非人为因素，不参与赔付）
A13: 邮编 8 9 （除90-92范围） | B13: 22.5 | C13: 尺寸数据不能偏离以下要求： 1、 22KG ≤ 单件计费重 < 65KG 2、 240＞最大边≥125CM 第二边≥80CM 3、 270CM≤长+2*（宽+高）＜320CM | D13: 23.5 | E13: 尺寸数据不能偏离以下要求： 1、 40KG ≤ 单件计费重 < 65KG 2、 270CM>最大边≥245CM 3、 330CM≤长+2*（宽+高）＜400CM 数据超出以上任一条件，需要2500美金/件的附加费
A14: 邮编5 6 7 | B14: 23.5 | D14: 24.5
A15: 邮编 0 1 2 3 4 | B15: 23.5 | D15: 24.5
A16: 重货比优惠：整票实重大于30公斤以上，1:250 减0.5元 / 1:300 减1元 / 1:400以上 减2元；整票实重/整票方数=货重比
A18: 联邦超大件海派 EXX限时达 18天赔付
A19: 邮编/计费重 | B19: 22-68KG | C19: 普通超大尺寸：备注 （可一票多件） | D19: 40-68KG | E19: 超级大尺寸：备注 （可一票多件） | F19: 下单渠道：联邦超大件海派 EXX限时达 18天赔付
A20: 邮编90-92 | B20: 19.5 | C20: 尺寸数据不能偏离以下要求： 1、 22KG ≤ 单件计费重 < 68KG 2、 240＞最大边≥125CM 第二边≥80CM 3、 270CM≤长+2*（宽+高）＜320CM | D20: 20.5 | E20: 尺寸数据不能偏离以下要求： 1、 40KG ≤ 单件计费重 < 68KG 2、 270CM>最大边≥245CM 3、 330CM≤长+2*（宽+高）＜400CM 数据超出以上任一条件，需要2500美金/件的附加费 注：单件计费重不低于40kg，不足40kg按40kg计费。 | F20: 开船后第二天开始算18天提取 第19天开始赔偿1元/kg*天 最高赔付2元每公斤 （如遇海关查验，赔偿1元每公斤） （如遇节假日、码头停摆、港口罢工等非人为因素，不参与赔付）
A21: 邮编 8 9 （除90-92范围） | B21: 20.5 | C21: 尺寸数据不能偏离以下要求： 1、 22KG ≤ 单件计费重 < 65KG 2、 240＞最大边≥125CM 第二边≥80CM 3、 270CM≤长+2*（宽+高）＜320CM | D21: 21.5 | E21: 尺寸数据不能偏离以下要求： 1、 40KG ≤ 单件计费重 < 65KG 2、 270CM>最大边≥245CM 3、 330CM≤长+2*（宽+高）＜400CM 数据超出以上任一条件，需要2500美金/件的附加费
A22: 邮编5 6 7 | B22: 21.5 | D22: 22.5
A23: 邮编 0 1 2 3 4 | B23: 21.5 | D23: 22.5
A24: 重货比优惠：整票实重大于30公斤以上，1:250 减0.5元 / 1:300 减1元 / 1:400以上 减2元；整票实重/整票方数=货重比
A26: 联邦超大件海派 合德限时达（带车架） 18天赔付
A27: 邮编/计费重 | B27: 22-68KG | C27: 普通超大尺寸：备注 （可一票多件） | D27: 40-68KG | E27: 超级大尺寸：备注 （可一票多件） | F27: 下单渠道：联邦超大件海派 合德限时达（带车架） 18天赔付
A28: 邮编90-92 | B28: 19.3 | C28: 尺寸数据不能偏离以下要求： 1、 22KG ≤ 单件计费重 < 68KG 2、 240＞最大边≥125CM 第二边≥80CM 3、 270CM≤长+2*（宽+高）＜320CM | D28: 20.3 | E28: 尺寸数据不能偏离以下要求： 1、 40KG ≤ 单件计费重 < 68KG 2、 270CM>最大边≥245CM 3、 330CM≤长+2*（宽+高）＜400CM 数据超出以上任一条件，需要2500美金/件的附加费 注：单件计费重不低于40kg，不足40kg按40kg计费。 | F28: 开船后第二天开始算18天提取 第19天开始赔偿1元/kg*天 最高赔付2元每公斤 （如遇海关查验，赔偿1元每公斤） （如遇节假日、码头停摆、港口罢工等非人为因素，不参与赔付）
A29: 邮编 8 9 （除90-92范围） | B29: 20.3 | C29: 尺寸数据不能偏离以下要求： 1、 22KG ≤ 单件计费重 < 65KG 2、 240＞最大边≥125CM 第二边≥80CM 3、 270CM≤长+2*（宽+高）＜320CM | D29: 21.3 | E29: 尺寸数据不能偏离以下要求： 1、 40KG ≤ 单件计费重 < 65KG 2、 270CM>最大边≥245CM 3、 330CM≤长+2*（宽+高）＜400CM 数据超出以上任一条件，需要2500美金/件的附加费
A30: 邮编5 6 7 | B30: 21.3 | D30: 22.3
A31: 邮编 0 1 2 3 4 | B31: 21.3 | D31: 22.3
A32: 重货比优惠：整票实重大于30公斤以上，1:250 减0.5元 / 1:300 减1元 / 1:400以上 减2元；整票实重/整票方数=货重比
A34: 联邦超大件海派 普船
A35: 邮编/计费重 | B35: 22-68KG | C35: 普通超大尺寸：备注 （可一票多件） | D35: 40-68KG | E35: 超级大尺寸：备注 （可一票多件） | F35: 下单渠道：联邦超大件海派 普船
A36: 邮编90-92 | B36: 18.3 | C36: 尺寸数据不能偏离以下要求： 1、 22KG ≤ 单件计费重 < 68KG 2、 240＞最大边≥125CM 第二边≥80CM 3、 270CM≤长+2*（宽+高）＜320CM | D36: 19.3 | E36: 尺寸数据不能偏离以下要求： 1、 40KG ≤ 单件计费重 < 68KG 2、 270CM>最大边≥245CM 3、 330CM≤长+2*（宽+高）＜400CM 数据超出以上任一条件，需要2500美金/件的附加费 注：单件计费重不低于40kg，不足40kg按40kg计费。
A37: 邮编 8 9 （除90-92范围） | B37: 19.3 | C37: 尺寸数据不能偏离以下要求： 1、 22KG ≤ 单件计费重 < 65KG 2、 240＞最大边≥125CM 第二边≥80CM 3、 270CM≤长+2*（宽+高）＜320CM | D37: 20.3 | E37: 尺寸数据不能偏离以下要求： 1、 40KG ≤ 单件计费重 < 65KG 2、 270CM>最大边≥245CM 3、 330CM≤长+2*（宽+高）＜400CM 数据超出以上任一条件，需要2500美金/件的附加费
A38: 邮编5 6 7 | B38: 20.3 | D38: 21.3
A39: 邮编 0 1 2 3 4 | B39: 20.3 | D39: 21.3
A40: 重货比优惠：整票实重大于30公斤以上，1:250 减0.5元 / 1:300 减1元 / 1:400以上 减2元；整票实重/整票方数=货重比
A42: 联邦超大件海派 普船经济线
A43: 邮编/计费重 | B43: 22-68KG | C43: 普通超大尺寸：备注 （可一票多件） | D43: 40-68KG | E43: 超级大尺寸：备注 （可一票多件） | F43: 下单渠道：联邦超大件海派 普船经济线
A44: 邮编90-92 | B44: 18 | C44: 尺寸数据不能偏离以下要求： 1、 22KG ≤ 单件计费重 < 68KG 2、 240＞最大边≥125CM 第二边≥80CM 3、 270CM≤长+2*（宽+高）＜320CM | D44: 19 | E44: 尺寸数据不能偏离以下要求： 1、 40KG ≤ 单件计费重 < 68KG 2、 270CM>最大边≥245CM 3、 330CM≤长+2*（宽+高）＜400CM 数据超出以上任一条件，需要2500美金/件的附加费 注：单件计费重不低于40kg，不足40kg按40kg计费。
A45: 邮编 8 9 （除90-92范围） | B45: 19 | C45: 尺寸数据不能偏离以下要求： 1、 22KG ≤ 单件计费重 < 65KG 2、 240＞最大边≥125CM 第二边≥80CM 3、 270CM≤长+2*（宽+高）＜320CM | D45: 20 | E45: 尺寸数据不能偏离以下要求： 1、 40KG ≤ 单件计费重 < 65KG 2、 270CM>最大边≥245CM 3、 330CM≤长+2*（宽+高）＜400CM 数据超出以上任一条件，需要2500美金/件的附加费
A46: 邮编5 6 7 | B46: 20 | D46: 21
A47: 邮编 0 1 2 3 4 | B47: 20 | D47: 21
A48: 重货比优惠：整票实重大于30公斤以上，1:250 减0.5元 / 1:300 减1元 / 1:400以上 减2元；整票实重/整票方数=货重比
A49: 报关件 350元/票 // 商检费 300/票
A50: 非FBA地址（私人地址）：+1元/KG； 偏远收费：商业地址偏远和住宅私人地址偏远，统收30元/件。（如私人地址偏远，私人地址+1，以及住宅偏远30元/件；）
A51: 可接木箱、航空箱、木架、圆形、提桶、鼓等非四方正规比例的箱规，异形费需加收250元/箱； 强烈建议用硬纸箱规整包装，否则会有拒收风险！如因包装问题导致联邦拒收或者半路退回，客户承担退回运费和重派费用。
A52: 请注意：极少数情况，会使用UPS打单；主要以联邦超大件打单为主；丢件按照 40元/KG 赔付

Sheet 自提-自打单-仓储
A1: 华东区-同行价格表
A2: 美国海外仓 自提 价格表
A3: 海外仓/邮编 | B3: 自提/仓储 | C3: 12KG-99KG | D3: 100KG+ | E3: 参考时效 | F3: 备注
A4: 洛杉矶海外仓 92337 | B4: 自提 美森正班船（CLX） | C4: 9.8 | D4: 8.8 | E4: 13-15天 | F4: 1、自提服务，无时效赔付 若需要做时效赔付，另行单询 | G4: 下单渠道：自提 美森正班船（CLX）
B5: 自提 美森加班船（MAX） | C5: 8.5 | D5: 7.5 | E5: 14-16天 | G5: 下单渠道：自提 美森加班船（MAX）
B6: 自提 EXX | C6: 7 | D6: 6 | E6: 15-18天 | G6: 下单渠道：自提 EXX
B7: 自提 华东合德/以星统配 （最晚周一进仓） | C7: 6.2 | D7: 5.2 | E7: 15-18天 | G7: 下单渠道：自提 华东合德/以星统配（最晚周一进仓）
B8: 自提 OA普船-LA | C8: 5.5 | D8: 4.5 | E8: 18-25天 | G8: 下单渠道：自提 OA普船-LA
B9: 自提 普船经济线-LA | C9: 5.4 | D9: 4.4 | E9: 25-30天 | G9: 下单渠道：自提 普船经济线-LA
A10: 奥克兰海外仓 94545 | B10: 自提 OA普船-OAK | C10: 5.7 | D10: 4.7 | E10: 18-25天 | G10: 下单渠道：自提 OA普船-OAK
A11: 芝加哥海外仓 60106 | B11: 自提 芝加哥普船 | C11: 7.1 | D11: 6.1 | E11: 30-40天 | G11: 下单渠道：自提 芝加哥普船
A12: 休斯顿海外仓 77091 | B12: 自提 休斯顿普船 | C12: 6.4 | D12: 5.4 | E12: 30-40天 | G12: 下单渠道：自提 休斯顿普船
A13: 萨凡纳海外仓 31407 | B13: 自提 萨凡纳普船 | C13: 6.4 | D13: 5.4 | E13: 35-45天 | G13: 下单渠道：自提 萨凡纳普船
A14: 纽约海外仓 08817 | B14: 自提 纽约普船 | C14: 6.2 | D14: 5.2 | E14: 35-45天 | G14: 下单渠道：自提 纽约普船
A15: 货重比：整票实重大于100公斤以上，享受重货比优惠：整票实重/整票方数=货重比 1:190 减0.2元 / 1:200 减0.3元 / 1:220 减0.5元 / 1:250 减0.8元 / 1:300 减1.2元 / 1:350 减1.5元 / 1:400 减1.8元 / 1:450 减2元 / 1:500 减2.2元 / 1:550 减2.5元 / ；超550以上单询；
A16: 超高加费：超过2.3米高度货物，需要加收200美金操作困难费。（原因1：影响国内装柜，顶柜货物无法装满浪费空间 原因2：海外仓卸货费时费力！） 超长附加费：超过3米长度的货物，加收200美金操作困难费。
A18: 美国海外仓 自打单 价格表
A19: 海外仓/邮编 | B19: 自提/仓储 | C19: 12KG-99KG | D19: 100KG+ | E19: 参考时效 | F19: 备注
A20: 洛杉矶海外仓 92337 | B20: 自打单 美森正班船（CLX） | C20: 9.8 | D20: 8.8 | E20: 13-15天 | F20: 1、自打单服务，无时效赔付 若需要做时效赔付，另行单询 2、请务必告知业务员，是联邦还是UPS自打单，以免我司港后无法分辨，导致海外仓分拣错误 | G20: 下单渠道：自打单 美森正班船（CLX）
B21: 自打单 美森加班船（MAX） | C21: 8.5 | D21: 7.5 | E21: 14-16天 | G21: 下单渠道：自打单 美森加班船（MAX）
B22: 自打单 EXX | C22: 7 | D22: 6 | E22: 15-18天 | G22: 下单渠道：自打单 EXX
B23: 自打单 华东合德/以星统配 （最晚周一进仓） | C23: 6.2 | D23: 5.2 | E23: 15-18天 | G23: 下单渠道：自打单 华东合德/以星统配（最晚周一进仓）
B24: 自打单 OA普船-LA | C24: 5.5 | D24: 4.5 | E24: 18-25天 | G24: 下单渠道：自打单 OA普船-LA
B25: 自打单 普船经济线-LA | C25: 5.4 | D25: 4.4 | E25: 25-30天 | G25: 下单渠道：自打单 普船经济线-LA
A26: 奥克兰海外仓 94545 | B26: 自打单 OA普船-OAK | C26: 5.7 | D26: 4.7 | E26: 18-25天 | G26: 下单渠道：自打单 OA普船-OAK
A27: 芝加哥海外仓 60106 | B27: 自打单 芝加哥普船 | C27: 7.1 | D27: 6.1 | E27: 30-40天 | G27: 下单渠道：自打单 芝加哥普船
A28: 休斯顿海外仓 77091 | B28: 自打单 休斯顿普船 | C28: 6.4 | D28: 5.4 | E28: 30-40天 | G28: 下单渠道：自打单 休斯顿普船
A29: 萨凡纳海外仓 31407 | B29: 自打单 萨凡纳普船 | C29: 6.4 | D29: 5.4 | E29: 35-45天 | G29: 下单渠道：自打单 萨凡纳普船
A30: 纽约海外仓 08817 | B30: 自打单 纽约普船 | C30: 6.2 | D30: 5.2 | E30: 35-45天 | G30: 下单渠道：自打单 纽约普船
A31: 货重比：整票实重大于100公斤以上，享受重货比优惠：整票实重/整票方数=货重比 1:190 减0.2元 / 1:200 减0.3元 / 1:220 减0.5元 / 1:250 减0.8元 / 1:300 减1.2元 / 1:350 减1.5元 / 1:400 减1.8元 / 1:450 减2元 / 1:500 减2.2元 / 1:550 减2.5元 / ；超550以上单询；
A33: 美国海外仓 仓储 价格表
A34: 海外仓/邮编 | B34: 自提/仓储 | C34: 12KG-99KG | D34: 100KG+ | E34: 参考时效 | F34: 备注
A35: 洛杉矶海外仓 92337 | B35: 仓储 美森正班船（CLX） | C35: 9.8 | D35: 8.8 | E35: 13-15天 | F35: 1、仓储服务，无时效赔付 若需要做时效赔付，另行单询 2、仓储服务，进入到美国海外仓以后，将按照客户的需求进行仓储、贴换标、派送等服务。具体费用详见海外仓价格表！！ | G35: 下单渠道：仓储 美森正班船（CLX）
B36: 仓储 美森加班船（MAX） | C36: 8.5 | D36: 7.5 | E36: 14-16天 | G36: 下单渠道：仓储 美森加班船（MAX）
B37: 仓储 EXX | C37: 7 | D37: 6 | E37: 15-18天 | G37: 下单渠道：仓储 EXX
B38: 仓储 华东合德/以星统配 （最晚周一进仓） | C38: 6.2 | D38: 5.2 | E38: 15-18天 | G38: 下单渠道：仓储 华东合德/以星统配（最晚周一进仓）
B39: 仓储 OA普船-LA | C39: 5.5 | D39: 4.5 | E39: 18-25天 | G39: 下单渠道：仓储 OA普船-LA
B40: 仓储 普船经济线-LA | C40: 5.4 | D40: 4.4 | E40: 25-30天 | G40: 下单渠道：仓储 普船经济线-LA
A41: 奥克兰海外仓 94545 | B41: 仓储 OA普船-OAK | C41: 5.7 | D41: 4.7 | E41: 18-25天 | G41: 下单渠道：仓储 OA普船-OAK
A42: 芝加哥海外仓 60106 | B42: 仓储 芝加哥普船 | C42: 7.1 | D42: 6.1 | E42: 30-40天 | G42: 下单渠道：仓储 芝加哥普船
A43: 休斯顿海外仓 77091 | B43: 仓储 休斯顿普船 | C43: 6.4 | D43: 5.4 | E43: 30-40天 | G43: 下单渠道：仓储 休斯顿普船
A44: 萨凡纳海外仓 31407 | B44: 仓储 萨凡纳普船 | C44: 6.4 | D44: 5.4 | E44: 35-45天 | G44: 下单渠道：仓储 萨凡纳普船
A45: 纽约海外仓 08817 | B45: 仓储 纽约普船 | C45: 6.2 | D45: 5.2 | E45: 35-45天 | G45: 下单渠道：仓储 纽约普船
A46: 货重比：整票实重大于100公斤以上，享受重货比优惠：整票实重/整票方数=货重比 1:190 减0.2元 / 1:200 减0.3元 / 1:220 减0.5元 / 1:250 减0.8元 / 1:300 减1.2元 / 1:350 减1.5元 / 1:400 减1.8元 / 1:450 减2元 / 1:500 减2.2元 / 1:550 减2.5元 / ；超550以上单询；
A47: 超高加费：超过2.3米高度货物，需要加收200美金操作困难费。（原因1：影响国内装柜，顶柜货物无法装满浪费空间 原因2：海外仓卸货费时费力！） 超长附加费：超过3米长度的货物，加收200美金操作困难费。

Sheet 海派汇总表—DY
A1: 华东区-同行价格表 【此渠道为FBA唛头与UPS/FEDEX子单号一 一对应贴单渠道，需要额外收3元/箱操作费！！！即表价相同，额外收费！】
B2: 海派 美森极速达 14天赔付 （CLX） | E2: 海派 美森加班限时达 16天赔付 （MAX） | H2: 海派 美森加班船 （MAX） | K2: 如需要走13天的CLX时效赔付，按照海派极速达表价+0.5； 下单渠道：海派 美森极速达 13天赔付 （CLX）—DY 第14天开始赔偿1元/kg*天 最高赔付2元每公斤
A3: 国家/重量 | B3: 12KG-49KG | C3: 50KG-99KG | D3: 100KG+ | E3: 12KG-49KG | F3: 50KG-99KG | G3: 100KG+ | H3: 12KG-49KG | I3: 50KG-99KG | J3: 100KG+
A4: 美西(USW) 邮编8.9 | B4: 14.8 | C4: 12.8 | D4: 11.8 | E4: 13.8 | F4: 11.8 | G4: 10.8 | H4: 13.4 | I4: 11.4 | J4: 10.4
A5: 美中(USM) 邮编4.5.6.7 | B5: 16.3 | C5: 14.3 | D5: 13.3 | E5: 15.3 | F5: 13.3 | G5: 12.3 | H5: 14.9 | I5: 12.9 | J5: 11.9
A6: 美东(USE) 邮编0.1.2.3 | B6: 17.3 | C6: 15.3 | D6: 14.3 | E6: 16.3 | F6: 14.3 | G6: 13.3 | H6: 15.9 | I6: 13.9 | J6: 12.9
A7: 下单渠道 | B7: 下单渠道：海派 美森极速达 14天赔付 （CLX）—DY | E7: 下单渠道：海派 美森加班限时达 16天赔付 （MAX）—DY | H7: 下单渠道：海派 美森加班船—DY | K7: 如需要走12天的CLX时效赔付，按照海派极速达表价+1.5； 下单渠道：海派 美森极速达 12天赔付 （CLX）—DY 第13天开始赔偿1元/kg*天 最高赔付2元每公斤
A8: 承诺时效 | B8: 开船后第二天开始算第14天提取 第15天开始赔偿1元/kg*天 最高赔付2元每公斤 （如遇海关查验，赔偿1元每公斤） （如遇节假日、码头停摆、港口罢工、晚到港等非人为因素，不参与赔付） | E8: 开船后第二天开始算16天提取 第17天开始赔偿1元/kg*天 最高赔付2元每公斤 （如遇海关查验，赔偿1元每公斤） 如遇节假日、码头停摆、港口罢工、晚到港等非人为因素，不参与赔付） | H8: 开船后16天-20天提取
B11: 海派 普船经济线 （周六开船，25天航程，开船后30天内提取） | E11: 海派 OA普船定提统配 | H11: 海派 OA稳速达统配 25天赔付 （OA 统配） | K11: 海派 稳速达统配 22天赔付 （OA/合德/以星 统配）
A12: 国家/重量 | B12: 12KG-49KG | C12: 50KG-99KG | D12: 100KG+ | E12: 12KG-49KG | F12: 50KG-99KG | G12: 100KG+ | H12: 12KG-49KG | I12: 50KG-99KG | J12: 100KG+ | K12: 12KG-49KG | L12: 50KG-99KG | M12: 100KG+
A13: 美西(USW) 邮编8.9 | B13: 10.7 | C13: 8.7 | D13: 7.7 | E13: 10.8 | F13: 8.8 | G13: 7.8 | H13: 10.9 | I13: 8.9 | J13: 7.9 | K13: 11.2 | L13: 9.2 | M13: 8.2
A14: 美中(USM) 邮编4.5.6.7 | B14: 12.2 | C14: 10.2 | D14: 9.2 | E14: 12.3 | F14: 10.3 | G14: 9.3 | H14: 12.4 | I14: 10.4 | J14: 9.4 | K14: 12.7 | L14: 10.7 | M14: 9.7
A15: 美东(USE) 邮编0.1.2.3 | B15: 13.2 | C15: 11.2 | D15: 10.2 | E15: 13.3 | F15: 11.3 | G15: 10.3 | H15: 13.4 | I15: 11.4 | J15: 10.4 | K15: 13.7 | L15: 11.7 | M15: 10.7
A16: 下单渠道 | B16: 下单渠道：海派 普船经济线—DY | E16: 下单渠道：海派 OA普船定提统配—DY | H16: 下单渠道：海派 稳速达统配 25天赔付—DY | K16: 下单渠道：海派 稳速达统配 22天赔付—DY
A17: 承诺时效 | B17: 开船后25-30天左右提取 【宁波万海、SLS 、TSL、CMA、CUL为主】 不走杨明、马士基、现代、地中海等慢船 | E17: 开船后22-25天左右提取 【周三OA 、保舱CMA、周四SML、周日EX1、周日以星 、合德为主】 不走杨明、马士基、中联、现代、地中海等慢船 | H17: 开船后第二天开始算25天提取 第26天开始赔偿0.5元/kg*天 最高赔付1元每公斤 （如遇海关查验，赔偿0.5元每公斤） 如遇节假日、码头停摆、港口罢工、晚到港等非人为因素，不参与赔付） | K17: 开船后第二天开始算22天提取 第23天开始赔偿0.5元/kg*天 最高赔付1元每公斤 （如遇海关查验，赔偿0.5元每公斤） 如遇节假日、码头停摆、港口罢工、晚到港等非人为因素，不参与赔付）
B20: 海派 EXX限时达 18天赔付 | E20: 海派 华东合德/以星快提统配 18天赔付 华东开 二截四开 最晚周二进仓 | H20: 海派 合德/以星统配 20天赔付
A21: 国家/重量 | B21: 12KG-49KG | C21: 50KG-99KG | D21: 100KG+ | E21: 12KG-49KG | F21: 50KG-99KG | G21: 100KG+ | H21: 12KG-49KG | I21: 50KG-99KG | J21: 100KG+
A22: 美西(USW) 邮编8.9 | B22: 12 | C22: 10 | D22: 9 | E22: 11.7 | F22: 9.7 | G22: 8.7 | H22: 11.5 | I22: 9.5 | J22: 8.5
A23: 美中(USM) 邮编4.5.6.7 | B23: 13.5 | C23: 11.5 | D23: 10.5 | E23: 13.2 | F23: 11.2 | G23: 10.2 | H23: 13 | I23: 11 | J23: 10
A24: 美东(USE) 邮编0.1.2.3 | B24: 14.5 | C24: 12.5 | D24: 11.5 | E24: 14.2 | F24: 12.2 | G24: 11.2 | H24: 14 | I24: 12 | J24: 11
A25: 下单渠道 | B25: 下单渠道：海派 EXX限时达 18天赔付—DY | E25: 下单渠道：海派 华东合德/以星快提统配 18天赔付—DY | H25: 下单渠道：海派 合德/以星统配 20天赔付—DY
A26: 承诺时效 | B26: 开船后第二天开始算18天提取 第19天开始赔偿1元/kg*天 最高赔付2元每公斤 （如遇海关查验，赔偿1元每公斤） 如遇节假日、码头停摆、港口罢工、晚到港等非人为因素，不参与赔付） | E26: 开船后第二天开始算18天提取 第19天开始赔偿0.5元/kg*天 最高赔付1元每公斤 （如遇海关查验，赔偿0.5元每公斤） 如遇节假日、码头停摆、港口罢工、晚到港等非人为因素，不参与赔付 | H26: 开船后第二天开始算20天提取 第21天开始赔偿0.5元/kg*天 最高赔付1元每公斤 （如遇海关查验，赔偿0.5元每公斤） 如遇节假日、码头停摆、港口罢工、晚到港等非人为因素，不参与赔付）
B29: 海派 休斯顿OA快普 （开船后35-40天内提取） | E29: 海派 芝加哥OA快普 （开船后35-40天内提取） | H29: 海派 美东OA快普 （开船后35-40天内提取）
A30: 国家/重量 | B30: 12KG-49KG | C30: 50KG-99KG | D30: 100KG+ | E30: 12KG-49KG | F30: 50KG-99KG | G30: 100KG+ | H30: 12KG-49KG | I30: 50KG-99KG | J30: 100KG+
A31: 邮编7 | B31: 11.9 | C31: 9.9 | D31: 8.9 | E31: / | F31: / | G31: / | H31: / | I31: / | J31: /
A32: 邮编4.5.6 | B32: / | C32: / | D32: / | E32: 12.2 | F32: 10.2 | G32: 9.2 | H32: / | I32: / | J32: /
A33: 邮编0.1.2.3 | B33: / | C33: / | D33: / | E33: / | F33: / | G33: / | H33: 11.9 | I33: 9.9 | J33: 8.9
A34: 下单渠道 | B34: 下单渠道：海派 休斯顿OA快普—DY | E34: 下单渠道：海派 芝加哥OA快普—DY | H34: 下单渠道：海派 美东OA快普—DY
A35: 承诺时效 | B35: 开船后30-40天左右提取 以OA船直航为主 | E35: 开船后25-35天左右提取 以EXX-芝加哥、OA船为主 | H35: 开船后35-45天左右提取 以OA船直航为主
A36: 货重比：整票实重大于100公斤以上，享受重货比优惠：整票实重/整票方数=货重比 美森/EXX货重比优惠：1:190 减0.2元 / 1:200 减0.3元 / 1:220 减0.5元 / 1:250 减0.8元 / 1:300 减1.2元 / 1:350 减1.5元 / 1:400 减1.8元 / 1:450 减2元 / 1:500 减2.2元 / 1:550 减2.5元 / ；超550以上单询； 合德/以星/普船： 1:220 减0.2元 / 1:250 减0.5元 / 1:300 减0.8元 / 1:400 减1.5元 / 1:500 减1.8元 ；超550以上单询；
A37: 单件最低计费12KG，单件不超22公斤； 非FBA地址（私人地址）：+1元/KG； 免商业地址附加费 后程UPS/联邦双渠道派送，亚马逊地址以UPS打单为主，指定打单（需单独申请，如打单不亏损情况下允许指定打单+1） 偏远收费：商业地址偏远和住宅私人地址偏远，统收30元/件。（如私人地址偏远，私人地址+1，以及住宅偏远30元/件；） 报关件的商检费实报实销，最低收300/票 报关费统收200元/票。合并报关费，收250元/票。
A38: 我司承诺：所有客户送我司美森货物如我司装非美森渠道，退运费且赔偿40元/公斤，货物正常转运派送

Sheet 海派汇总表
A1: 华东区-同行价格表
B2: 海派 美森极速达 14天赔付 （CLX） | E2: 海派 美森加班限时达 16天赔付 （MAX） | H2: 海派 美森加班船 （MAX） | K2: 如需要走13天的CLX时效赔付，按照海派极速达表价+0.5； 下单渠道：海派 美森极速达 13天赔付 （CLX） 第14天开始赔偿1元/kg*天 最高赔付2元每公斤
A3: 国家/重量 | B3: 12KG-49KG | C3: 50KG-99KG | D3: 100KG+ | E3: 12KG-49KG | F3: 50KG-99KG | G3: 100KG+ | H3: 12KG-49KG | I3: 50KG-99KG | J3: 100KG+
A4: 美西(USW) 邮编8.9 | B4: 14.8 | C4: 12.8 | D4: 11.8 | E4: 13.8 | F4: 11.8 | G4: 10.8 | H4: 13.4 | I4: 11.4 | J4: 10.4
A5: 美中(USM) 邮编4.5.6.7 | B5: 16.3 | C5: 14.3 | D5: 13.3 | E5: 15.3 | F5: 13.3 | G5: 12.3 | H5: 14.9 | I5: 12.9 | J5: 11.9
A6: 美东(USE) 邮编0.1.2.3 | B6: 17.3 | C6: 15.3 | D6: 14.3 | E6: 16.3 | F6: 14.3 | G6: 13.3 | H6: 15.9 | I6: 13.9 | J6: 12.9
A7: 下单渠道 | B7: 下单渠道：海派 美森极速达 14天赔付 （CLX） | E7: 下单渠道：海派 美森加班限时达 16天赔付 （MAX） | H7: 下单渠道：海派 美森加班船 | K7: 如需要走12天的CLX时效赔付，按照海派极速达表价+1.5； 下单渠道：海派 美森极速达 12天赔付 （CLX） 第13天开始赔偿1元/kg*天 最高赔付2元每公斤
A8: 承诺时效 | B8: 开船后第二天开始算第14天提取 第15天开始赔偿1元/kg*天 最高赔付2元每公斤 （如遇海关查验，赔偿1元每公斤） （如遇节假日、码头停摆、港口罢工、晚到港等非人为因素，不参与赔付） | E8: 开船后第二天开始算16天提取 第17天开始赔偿1元/kg*天 最高赔付2元每公斤 （如遇海关查验，赔偿1元每公斤） 如遇节假日、码头停摆、港口罢工、晚到港等非人为因素，不参与赔付） | H8: 开船后16天-20天提取
B11: 海派 普船经济线 （周六开船，25天航程，开船后30天内提取） | E11: 海派 OA普船定提统配 | H11: 海派 OA稳速达统配 25天赔付 （OA 统配） | K11: 海派 稳速达统配 22天赔付 （OA/合德/以星 统配）
A12: 国家/重量 | B12: 12KG-49KG | C12: 50KG-99KG | D12: 100KG+ | E12: 12KG-49KG | F12: 50KG-99KG | G12: 100KG+ | H12: 12KG-49KG | I12: 50KG-99KG | J12: 100KG+ | K12: 12KG-49KG | L12: 50KG-99KG | M12: 100KG+
A13: 美西(USW) 邮编8.9 | B13: 10.7 | C13: 8.7 | D13: 7.7 | E13: 10.8 | F13: 8.8 | G13: 7.8 | H13: 10.9 | I13: 8.9 | J13: 7.9 | K13: 11.2 | L13: 9.2 | M13: 8.2
A14: 美中(USM) 邮编4.5.6.7 | B14: 12.2 | C14: 10.2 | D14: 9.2 | E14: 12.3 | F14: 10.3 | G14: 9.3 | H14: 12.4 | I14: 10.4 | J14: 9.4 | K14: 12.7 | L14: 10.7 | M14: 9.7
A15: 美东(USE) 邮编0.1.2.3 | B15: 13.2 | C15: 11.2 | D15: 10.2 | E15: 13.3 | F15: 11.3 | G15: 10.3 | H15: 13.4 | I15: 11.4 | J15: 10.4 | K15: 13.7 | L15: 11.7 | M15: 10.7
A16: 下单渠道 | B16: 下单渠道：海派 普船经济线 | E16: 下单渠道：海派 OA普船定提统配 | H16: 下单渠道：海派 稳速达统配 25天赔付 | K16: 下单渠道：海派 稳速达统配 22天赔付
A17: 承诺时效 | B17: 开船后25-30天左右提取 【宁波万海、SLS 、TSL、CMA、CUL为主】 不走杨明、马士基、现代、地中海等慢船 | E17: 开船后22-25天左右提取 【周三OA 、保舱CMA、周四SML、周日EX1、周日以星 、合德为主】 不走杨明、马士基、中联、现代、地中海等慢船 | H17: 开船后第二天开始算25天提取 第26天开始赔偿0.5元/kg*天 最高赔付1元每公斤 （如遇海关查验，赔偿0.5元每公斤） 如遇节假日、码头停摆、港口罢工、晚到港等非人为因素，不参与赔付） | K17: 开船后第二天开始算22天提取 第23天开始赔偿0.5元/kg*天 最高赔付1元每公斤 （如遇海关查验，赔偿0.5元每公斤） 如遇节假日、码头停摆、港口罢工、晚到港等非人为因素，不参与赔付）
B20: 海派 EXX限时达 18天赔付 | E20: 海派 华东合德/以星快提统配 18天赔付 华东开 二截四开 最晚周二进仓 | H20: 海派 合德/以星统配 20天赔付
A21: 国家/重量 | B21: 12KG-49KG | C21: 50KG-99KG | D21: 100KG+ | E21: 12KG-49KG | F21: 50KG-99KG | G21: 100KG+ | H21: 12KG-49KG | I21: 50KG-99KG | J21: 100KG+
A22: 美西(USW) 邮编8.9 | B22: 12 | C22: 10 | D22: 9 | E22: 11.7 | F22: 9.7 | G22: 8.7 | H22: 11.5 | I22: 9.5 | J22: 8.5
A23: 美中(USM) 邮编4.5.6.7 | B23: 13.5 | C23: 11.5 | D23: 10.5 | E23: 13.2 | F23: 11.2 | G23: 10.2 | H23: 13 | I23: 11 | J23: 10
A24: 美东(USE) 邮编0.1.2.3 | B24: 14.5 | C24: 12.5 | D24: 11.5 | E24: 14.2 | F24: 12.2 | G24: 11.2 | H24: 14 | I24: 12 | J24: 11
A25: 下单渠道 | B25: 下单渠道：海派 EXX限时达 18天赔付 | E25: 下单渠道：海派 华东合德/以星快提统配 18天赔付 | H25: 下单渠道：海派 合德/以星统配 20天赔付
A26: 承诺时效 | B26: 开船后第二天开始算18天提取 第19天开始赔偿1元/kg*天 最高赔付2元每公斤 （如遇海关查验，赔偿1元每公斤） 如遇节假日、码头停摆、港口罢工、晚到港等非人为因素，不参与赔付） | E26: 开船后第二天开始算18天提取 第19天开始赔偿0.5元/kg*天 最高赔付1元每公斤 （如遇海关查验，赔偿0.5元每公斤） 如遇节假日、码头停摆、港口罢工、晚到港等非人为因素，不参与赔付 | H26: 开船后第二天开始算20天提取 第21天开始赔偿0.5元/kg*天 最高赔付1元每公斤 （如遇海关查验，赔偿0.5元每公斤） 如遇节假日、码头停摆、港口罢工、晚到港等非人为因素，不参与赔付）
B29: 海派 休斯顿OA快普 （开船后35-40天内提取） | E29: 海派 芝加哥OA快普 （开船后35-40天内提取） | H29: 海派 美东OA快普 （开船后35-40天内提取）
A30: 国家/重量 | B30: 12KG-49KG | C30: 50KG-99KG | D30: 100KG+ | E30: 12KG-49KG | F30: 50KG-99KG | G30: 100KG+ | H30: 12KG-49KG | I30: 50KG-99KG | J30: 100KG+
A31: 邮编7 | B31: 11.9 | C31: 9.9 | D31: 8.9 | E31: / | F31: / | G31: / | H31: / | I31: / | J31: /
A32: 邮编4.5.6 | B32: / | C32: / | D32: / | E32: 12.2 | F32: 10.2 | G32: 9.2 | H32: / | I32: / | J32: /
A33: 邮编0.1.2.3 | B33: / | C33: / | D33: / | E33: / | F33: / | G33: / | H33: 11.9 | I33: 9.9 | J33: 8.9
A34: 下单渠道 | B34: 下单渠道：海派 休斯顿OA快普 | E34: 下单渠道：海派 芝加哥OA快普 | H34: 下单渠道：海派 美东OA快普
A35: 承诺时效 | B35: 开船后30-40天左右提取 以OA船直航为主 | E35: 开船后25-35天左右提取 以EXX-芝加哥、OA船为主 | H35: 开船后35-45天左右提取 以OA船直航为主
A36: 货重比：整票实重大于100公斤以上，享受重货比优惠：整票实重/整票方数=货重比 美森/EXX货重比优惠：1:190 减0.2元 / 1:200 减0.3元 / 1:220 减0.5元 / 1:250 减0.8元 / 1:300 减1.2元 / 1:350 减1.5元 / 1:400 减1.8元 / 1:450 减2元 / 1:500 减2.2元 / 1:550 减2.5元 / ；超550以上单询； 合德/以星/普船： 1:220 减0.2元 / 1:250 减0.5元 / 1:300 减0.8元 / 1:400 减1.5元 / 1:500 减1.8元 ；超550以上单询；
A37: 单件最低计费12KG，单件不超22公斤； 非FBA地址（私人地址）：+1元/KG； 免商业地址附加费 后程UPS/联邦双渠道派送，亚马逊地址以UPS打单为主，指定打单（需单独申请，如打单不亏损情况下允许指定打单+1） 偏远收费：商业地址偏远和住宅私人地址偏远，统收30元/件。（如私人地址偏远，私人地址+1，以及住宅偏远30元/件；） 报关件的商检费实报实销，最低收300/票 报关费统收200元/票。合并报关费，收250元/票。
A38: 我司承诺：所有客户送我司美森货物如我司装非美森渠道，退运费且赔偿40元/公斤，货物正常转运派送

Sheet 美西海卡汇总表
A1: 华东区-美西海卡各渠道拆柜汇总表
A2: FBA仓库代码 | B2: 目的邮编 | C2: 计费重起收点 | D2: 下单渠道： 海卡/美森极速达（CLX） 【带赔付】 | F2: 下单渠道： 海卡/美森极速达（CLX） | H2: 下单渠道： 海卡/美森加班船（MAX ） 【带赔付】 | J2: 下单渠道： 海卡/美森加班船（MAX ） | L2: 下单渠道： 海卡/EXX限时达【带赔付】 | N2: 下单渠道： 海卡/华东合德/以星限时达统配 【带赔付】 （最晚周二进仓） | P2: 下单渠道： 海卡/OA稳速达【带赔付】 （最晚周一进仓） | R2: 下单渠道： 海卡/OA普船定提统配 | T2: 下单渠道： 海卡/普船经济线 （周六开船，25天航程）
D3: CLX 周三开 | E3: 赔付时效 签收提供POD | F3: CLX 周三开 | G3: 最快时效 | H3: MAX周四开 | I3: 赔付时效 签收提供POD | J3: MAX 周四开 | K3: 最快时效 | L3: 周四开 | M3: 赔付时效 签收提供POD | N3: 二截四开 | O3: 赔付时效 签收提供POD | P3: 周四开 | Q3: 赔付时效 签收提供POD
A4: ONT8 | B4: 92551 | C4: A【一区】 12KG+ | D4: 8.3 | E4: 19天赔付 | F4: 8 | G4: 15-22天 | H4: 7.3 | I4: 20天赔付 | J4: 7 | K4: 17-23天 | L4: 5.3 | M4: 21天赔付 | N4: 4.7 | O4: 25天赔付 | P4: 4.4 | Q4: 28天赔付 | R4: 4.3 | S4: 20-25天 | T4: 4.2 | U4: 25-30天
A5: LAX9 | B5: 92337 | D5: 8.3 | E5: 19天赔付 | F5: 8 | G5: 15-22天 | H5: 7.3 | I5: 20天赔付 | J5: 7 | K5: 17-23天 | L5: 5.3 | M5: 21天赔付 | N5: 4.7 | O5: 25天赔付 | P5: 4.4 | Q5: 28天赔付 | R5: 4.3 | S5: 20-25天 | T5: 4.2 | U5: 25-30天
A6: LGB8 | B6: 92376 | D6: 8.3 | E6: 19天赔付 | F6: 8 | G6: 15-22天 | H6: 7.3 | I6: 20天赔付 | J6: 7 | K6: 17-23天 | L6: 5.3 | M6: 21天赔付 | N6: 4.7 | O6: 25天赔付 | P6: 4.4 | Q6: 28天赔付 | R6: 4.3 | S6: 20-25天 | T6: 4.2 | U6: 25-30天
A7: SBD1 | B7: 92316-3819 | D7: 8.3 | E7: 19天赔付 | F7: 8 | G7: 15-22天 | H7: 7.3 | I7: 20天赔付 | J7: 7 | K7: 17-23天 | L7: 5.3 | M7: 21天赔付 | N7: 4.7 | O7: 25天赔付 | P7: 4.4 | Q7: 28天赔付 | R7: 4.3 | S7: 20-25天 | T7: 4.2 | U7: 25-30天
A8: SNA4 | B8: 92376 | C8: B【一区】 12KG+ | D8: 8.4 | E8: 19天赔付 | F8: 8.1 | G8: 15-22天 | H8: 7.4 | I8: 20天赔付 | J8: 7.1 | K8: 17-23天 | L8: 5.4 | M8: 21天赔付 | N8: 4.8 | O8: 25天赔付 | P8: 4.5 | Q8: 28天赔付 | R8: 4.4 | S8: 20-25天 | T8: 4.3 | U8: 25-30天
A9: SBD2 | B9: 92408 | D9: 8.4 | E9: 19天赔付 | F9: 8.1 | G9: 15-22天 | H9: 7.4 | I9: 20天赔付 | J9: 7.1 | K9: 17-23天 | L9: 5.4 | M9: 21天赔付 | N9: 4.8 | O9: 25天赔付 | P9: 4.5 | Q9: 28天赔付 | R9: 4.4 | S9: 20-25天 | T9: 4.3 | U9: 25-30天
A10: SBD3 | B10: 92407 | D10: 8.4 | E10: 19天赔付 | F10: 8.1 | G10: 15-22天 | H10: 7.4 | I10: 20天赔付 | J10: 7.1 | K10: 17-23天 | L10: 5.4 | M10: 21天赔付 | N10: 4.8 | O10: 25天赔付 | P10: 4.5 | Q10: 28天赔付 | R10: 4.4 | S10: 20-25天 | T10: 4.3 | U10: 25-30天
A11: LGB4 | B11: 92374 | D11: 8.4 | E11: 19天赔付 | F11: 8.1 | G11: 15-22天 | H11: 7.4 | I11: 20天赔付 | J11: 7.1 | K11: 17-23天 | L11: 5.4 | M11: 21天赔付 | N11: 4.8 | O11: 25天赔付 | P11: 4.5 | Q11: 28天赔付 | R11: 4.4 | S11: 20-25天 | T11: 4.3 | U11: 25-30天
A12: LGB6 | B12: 92518-1513 | D12: 8.4 | E12: 19天赔付 | F12: 8.1 | G12: 15-22天 | H12: 7.4 | I12: 20天赔付 | J12: 7.1 | K12: 17-23天 | L12: 5.4 | M12: 21天赔付 | N12: 4.8 | O12: 25天赔付 | P12: 4.5 | Q12: 28天赔付 | R12: 4.4 | S12: 20-25天 | T12: 4.3 | U12: 25-30天
A13: LGB9 | B13: 90810 | D13: 8.4 | E13: 19天赔付 | F13: 8.1 | G13: 15-22天 | H13: 7.4 | I13: 20天赔付 | J13: 7.1 | K13: 17-23天 | L13: 5.4 | M13: 21天赔付 | N13: 4.8 | O13: 25天赔付 | P13: 4.5 | Q13: 28天赔付 | R13: 4.4 | S13: 20-25天 | T13: 4.3 | U13: 25-30天
A14: ONT2 | B14: 92408-0123 | D14: 8.4 | E14: 19天赔付 | F14: 8.1 | G14: 15-22天 | H14: 7.4 | I14: 20天赔付 | J14: 7.1 | K14: 17-23天 | L14: 5.4 | M14: 21天赔付 | N14: 4.8 | O14: 25天赔付 | P14: 4.5 | Q14: 28天赔付 | R14: 4.4 | S14: 20-25天 | T14: 4.3 | U14: 25-30天
A15: ONT6 | B15: 92551-9561 | D15: 8.4 | E15: 19天赔付 | F15: 8.1 | G15: 15-22天 | H15: 7.4 | I15: 20天赔付 | J15: 7.1 | K15: 17-23天 | L15: 5.4 | M15: 21天赔付 | N15: 4.8 | O15: 25天赔付 | P15: 4.5 | Q15: 28天赔付 | R15: 4.4 | S15: 20-25天 | T15: 4.3 | U15: 25-30天
A16: ONT9 | B16: 92374 | D16: 8.4 | E16: 19天赔付 | F16: 8.1 | G16: 15-22天 | H16: 7.4 | I16: 20天赔付 | J16: 7.1 | K16: 17-23天 | L16: 5.4 | M16: 21天赔付 | N16: 4.8 | O16: 25天赔付 | P16: 4.5 | Q16: 28天赔付 | R16: 4.4 | S16: 20-25天 | T16: 4.3 | U16: 25-30天
A17: XLX7 | B17: 92394 | D17: 8.4 | E17: 19天赔付 | F17: 8.1 | G17: 15-22天 | H17: 7.4 | I17: 20天赔付 | J17: 7.1 | K17: 17-23天 | L17: 5.4 | M17: 21天赔付 | N17: 4.8 | O17: 25天赔付 | P17: 4.5 | Q17: 28天赔付 | R17: 4.4 | S17: 20-25天 | T17: 4.3 | U17: 25-30天
A18: IUSJ | B18: 92223 | D18: 8.4 | E18: 19天赔付 | F18: 8.1 | G18: 15-22天 | H18: 7.4 | I18: 20天赔付 | J18: 7.1 | K18: 17-23天 | L18: 5.4 | M18: 21天赔付 | N18: 4.8 | O18: 25天赔付 | P18: 4.5 | Q18: 28天赔付 | R18: 4.4 | S18: 20-25天 | T18: 4.3 | U18: 25-30天
A19: IUSQ | B19: 92374 | D19: 8.4 | E19: 19天赔付 | F19: 8.1 | G19: 15-22天 | H19: 7.4 | I19: 20天赔付 | J19: 7.1 | K19: 17-23天 | L19: 5.4 | M19: 21天赔付 | N19: 4.8 | O19: 25天赔付 | P19: 4.5 | Q19: 28天赔付 | R19: 4.4 | S19: 20-25天 | T19: 4.3 | U19: 25-30天
A20: IUSP | B20: 92344 | D20: 8.4 | E20: 19天赔付 | F20: 8.1 | G20: 15-22天 | H20: 7.4 | I20: 20天赔付 | J20: 7.1 | K20: 17-23天 | L20: 5.4 | M20: 21天赔付 | N20: 4.8 | O20: 25天赔付 | P20: 4.5 | Q20: 28天赔付 | R20: 4.4 | S20: 20-25天 | T20: 4.3 | U20: 25-30天
A21: POC1 | B21: 92336-1123 | D21: 8.4 | E21: 19天赔付 | F21: 8.1 | G21: 15-22天 | H21: 7.4 | I21: 20天赔付 | J21: 7.1 | K21: 17-23天 | L21: 5.4 | M21: 21天赔付 | N21: 4.8 | O21: 25天赔付 | P21: 4.5 | Q21: 28天赔付 | R21: 4.4 | S21: 20-25天 | T21: 4.3 | U21: 25-30天
A22: POC2 | B22: 91761 | D22: 8.4 | E22: 19天赔付 | F22: 8.1 | G22: 15-22天 | H22: 7.4 | I22: 20天赔付 | J22: 7.1 | K22: 17-23天 | L22: 5.4 | M22: 21天赔付 | N22: 4.8 | O22: 25天赔付 | P22: 4.5 | Q22: 28天赔付 | R22: 4.4 | S22: 20-25天 | T22: 4.3 | U22: 25-30天
A23: POC3 | B23: 92509 | D23: 8.4 | E23: 19天赔付 | F23: 8.1 | G23: 15-22天 | H23: 7.4 | I23: 20天赔付 | J23: 7.1 | K23: 17-23天 | L23: 5.4 | M23: 21天赔付 | N23: 4.8 | O23: 25天赔付 | P23: 4.5 | Q23: 28天赔付 | R23: 4.4 | S23: 20-25天 | T23: 4.3 | U23: 25-30天
A24: IUTI | B24: 92374-5015 | D24: 8.4 | E24: 19天赔付 | F24: 8.1 | G24: 15-22天 | H24: 7.4 | I24: 20天赔付 | J24: 7.1 | K24: 17-23天 | L24: 5.4 | M24: 21天赔付 | N24: 4.8 | O24: 25天赔付 | P24: 4.5 | Q24: 28天赔付 | R24: 4.4 | S24: 20-25天 | T24: 4.3 | U24: 25-30天
A25: IUSW | B25: 92344 | D25: 8.4 | E25: 19天赔付 | F25: 8.1 | G25: 15-22天 | H25: 7.4 | I25: 20天赔付 | J25: 7.1 | K25: 17-23天 | L25: 5.4 | M25: 21天赔付 | N25: 4.8 | O25: 25天赔付 | P25: 4.5 | Q25: 28天赔付 | R25: 4.4 | S25: 20-25天 | T25: 4.3 | U25: 25-30天
A26: IUTE | B26: 85338 | D26: 8.4 | E26: 19天赔付 | F26: 8.1 | G26: 15-22天 | H26: 7.4 | I26: 20天赔付 | J26: 7.1 | K26: 17-23天 | L26: 5.4 | M26: 21天赔付 | N26: 4.8 | O26: 25天赔付 | P26: 4.5 | Q26: 28天赔付 | R26: 4.4 | S26: 20-25天 | T26: 4.3 | U26: 25-30天
A27: LAS1 | B27: 89044 | C27: A【二区】 12KG+ | D27: 9 | E27: 21天赔付 | F27: 8.7 | G27: 15-22天 | H27: 8 | I27: 22天赔付 | J27: 7.7 | K27: 17-23天 | L27: 6 | M27: 23天赔付 | N27: 5.4 | O27: 28天赔付 | P27: 5.1 | Q27: 31天赔付 | R27: 5 | S27: 23-30天 | T27: 4.9 | U27: 25-35天
A28: VGT2 | B28: 89115 | D28: 9 | E28: 21天赔付 | F28: 8.7 | G28: 15-22天 | H28: 8 | I28: 22天赔付 | J28: 7.7 | K28: 17-23天 | L28: 6 | M28: 23天赔付 | N28: 5.4 | O28: 28天赔付 | P28: 5.1 | Q28: 31天赔付 | R28: 5 | S28: 23-30天 | T28: 4.9 | U28: 25-35天
A29: GYR2 | B29: 85395 | D29: 9 | E29: 21天赔付 | F29: 8.7 | G29: 15-22天 | H29: 8 | I29: 22天赔付 | J29: 7.7 | K29: 17-23天 | L29: 6 | M29: 23天赔付 | N29: 5.4 | O29: 28天赔付 | P29: 5.1 | Q29: 31天赔付 | R29: 5 | S29: 23-30天 | T29: 4.9 | U29: 25-35天
A30: GYR3 | B30: 85043 | D30: 9 | E30: 21天赔付 | F30: 8.7 | G30: 15-22天 | H30: 8 | I30: 22天赔付 | J30: 7.7 | K30: 17-23天 | L30: 6 | M30: 23天赔付 | N30: 5.4 | O30: 28天赔付 | P30: 5.1 | Q30: 31天赔付 | R30: 5 | S30: 23-30天 | T30: 4.9 | U30: 25-35天
A31: SMF3 | B31: 95206 | D31: 9 | E31: 21天赔付 | F31: 8.7 | G31: 15-22天 | H31: 8 | I31: 22天赔付 | J31: 7.7 | K31: 17-23天 | L31: 6 | M31: 23天赔付 | N31: 5.4 | O31: 28天赔付 | P31: 5.1 | Q31: 31天赔付 | R31: 5 | S31: 23-30天 | T31: 4.9 | U31: 25-35天
A32: SCK4 | B32: 95215 | D32: 9 | E32: 21天赔付 | F32: 8.7 | G32: 15-22天 | H32: 8 | I32: 22天赔付 | J32: 7.7 | K32: 17-23天 | L32: 6 | M32: 23天赔付 | N32: 5.4 | O32: 28天赔付 | P32: 5.1 | Q32: 31天赔付 | R32: 5 | S32: 23-30天 | T32: 4.9 | U32: 25-35天
A33: MIT2 | B33: 93263 | D33: 9 | E33: 21天赔付 | F33: 8.7 | G33: 15-22天 | H33: 8 | I33: 22天赔付 | J33: 7.7 | K33: 17-23天 | L33: 6 | M33: 23天赔付 | N33: 5.4 | O33: 28天赔付 | P33: 5.1 | Q33: 31天赔付 | R33: 5 | S33: 23-30天 | T33: 4.9 | U33: 25-35天
A34: GEU2 | B34: 85340 | D34: 9 | E34: 21天赔付 | F34: 8.7 | G34: 15-22天 | H34: 8 | I34: 22天赔付 | J34: 7.7 | K34: 17-23天 | L34: 6 | M34: 23天赔付 | N34: 5.4 | O34: 28天赔付 | P34: 5.1 | Q34: 31天赔付 | R34: 5 | S34: 23-30天 | T34: 4.9 | U34: 25-35天
A35: GEU3 | B35: 85326 | D35: 9 | E35: 21天赔付 | F35: 8.7 | G35: 15-22天 | H35: 8 | I35: 22天赔付 | J35: 7.7 | K35: 17-23天 | L35: 6 | M35: 23天赔付 | N35: 5.4 | O35: 28天赔付 | P35: 5.1 | Q35: 31天赔付 | R35: 5 | S35: 23-30天 | T35: 4.9 | U35: 25-35天
A36: GEU5 | B36: 85395 | D36: 9 | E36: 21天赔付 | F36: 8.7 | G36: 15-22天 | H36: 8 | I36: 22天赔付 | J36: 7.7 | K36: 17-23天 | L36: 6 | M36: 23天赔付 | N36: 5.4 | O36: 28天赔付 | P36: 5.1 | Q36: 31天赔付 | R36: 5 | S36: 23-30天 | T36: 4.9 | U36: 25-35天
A37: HLI2 | B37: 95023 | D37: 9 | E37: 21天赔付 | F37: 8.7 | G37: 15-22天 | H37: 8 | I37: 22天赔付 | J37: 7.7 | K37: 17-23天 | L37: 6 | M37: 23天赔付 | N37: 5.4 | O37: 28天赔付 | P37: 5.1 | Q37: 31天赔付 | R37: 5 | S37: 23-30天 | T37: 4.9 | U37: 25-35天
A38: TCY1 | B38: 95206 | D38: 9 | E38: 21天赔付 | F38: 8.7 | G38: 15-22天 | H38: 8 | I38: 22天赔付 | J38: 7.7 | K38: 17-23天 | L38: 6 | M38: 23天赔付 | N38: 5.4 | O38: 28天赔付 | P38: 5.1 | Q38: 31天赔付 | R38: 5 | S38: 23-30天 | T38: 4.9 | U38: 25-35天
A39: TCY2 | B39: 95215 | D39: 9 | E39: 21天赔付 | F39: 8.7 | G39: 15-22天 | H39: 8 | I39: 22天赔付 | J39: 7.7 | K39: 17-23天 | L39: 6 | M39: 23天赔付 | N39: 5.4 | O39: 28天赔付 | P39: 5.1 | Q39: 31天赔付 | R39: 5 | S39: 23-30天 | T39: 4.9 | U39: 25-35天
A40: SCK8 | B40: 94561 | D40: 9 | E40: 21天赔付 | F40: 8.7 | G40: 15-22天 | H40: 8 | I40: 22天赔付 | J40: 7.7 | K40: 17-23天 | L40: 6 | M40: 23天赔付 | N40: 5.4 | O40: 28天赔付 | P40: 5.1 | Q40: 31天赔付 | R40: 5 | S40: 23-30天 | T40: 4.9 | U40: 25-35天
A41: QXY8 | B41: 93725-1962 | D41: 9 | E41: 21天赔付 | F41: 8.7 | G41: 15-22天 | H41: 8 | I41: 22天赔付 | J41: 7.7 | K41: 17-23天 | L41: 6 | M41: 23天赔付 | N41: 5.4 | O41: 28天赔付 | P41: 5.1 | Q41: 31天赔付 | R41: 5 | S41: 23-30天 | T41: 4.9 | U41: 25-35天
A42: PSP3 | B42: 92240 | D42: 9 | E42: 21天赔付 | F42: 8.7 | G42: 15-22天 | H42: 8 | I42: 22天赔付 | J42: 7.7 | K42: 17-23天 | L42: 6 | M42: 23天赔付 | N42: 5.4 | O42: 28天赔付 | P42: 5.1 | Q42: 31天赔付 | R42: 5 | S42: 23-30天 | T42: 4.9 | U42: 25-35天
A43: MCC1 | B43: 95742 | D43: 9 | E43: 21天赔付 | F43: 8.7 | G43: 15-22天 | H43: 8 | I43: 22天赔付 | J43: 7.7 | K43: 17-23天 | L43: 6 | M43: 23天赔付 | N43: 5.4 | O43: 28天赔付 | P43: 5.1 | Q43: 31天赔付 | R43: 5 | S43: 23-30天 | T43: 4.9 | U43: 25-35天
A44: SMF6 | B44: 95837 | C44: B【二区】 12KG+ | D44: 9.2 | E44: 21天赔付 | F44: 8.9 | G44: 15-22天 | H44: 8.2 | I44: 22天赔付 | J44: 7.9 | K44: 17-23天 | L44: 6.2 | M44: 23天赔付 | N44: 5.6 | O44: 28天赔付 | P44: 5.3 | Q44: 31天赔付 | R44: 5.2 | S44: 23-30天 | T44: 5.1 | U44: 25-35天
A45: SJC7 | B45: 95377 | D45: 9.2 | E45: 21天赔付 | F45: 8.9 | G45: 15-22天 | H45: 8.2 | I45: 22天赔付 | J45: 7.9 | K45: 17-23天 | L45: 6.2 | M45: 23天赔付 | N45: 5.6 | O45: 28天赔付 | P45: 5.3 | Q45: 31天赔付 | R45: 5.2 | S45: 23-30天 | T45: 5.1 | U45: 25-35天
A46: OAK3 | B46: 95363 | D46: 9.2 | E46: 21天赔付 | F46: 8.9 | G46: 15-22天 | H46: 8.2 | I46: 22天赔付 | J46: 7.9 | K46: 17-23天 | L46: 6.2 | M46: 23天赔付 | N46: 5.6 | O46: 28天赔付 | P46: 5.3 | Q46: 31天赔付 | R46: 5.2 | S46: 23-30天 | T46: 5.1 | U46: 25-35天
A47: SCK1 | B47: 95215 | D47: 9.2 | E47: 21天赔付 | F47: 8.9 | G47: 15-22天 | H47: 8.2 | I47: 22天赔付 | J47: 7.9 | K47: 17-23天 | L47: 6.2 | M47: 23天赔付 | N47: 5.6 | O47: 28天赔付 | P47: 5.3 | Q47: 31天赔付 | R47: 5.2 | S47: 23-30天 | T47: 5.1 | U47: 25-35天
A48: MCE1 | B48: 95380 | D48: 9.2 | E48: 21天赔付 | F48: 8.9 | G48: 15-22天 | H48: 8.2 | I48: 22天赔付 | J48: 7.9 | K48: 17-23天 | L48: 6.2 | M48: 23天赔付 | N48: 5.6 | O48: 28天赔付 | P48: 5.3 | Q48: 31天赔付 | R48: 5.2 | S48: 23-30天 | T48: 5.1 | U48: 25-35天
A49: FAT2 | B49: 93291 | D49: 9.2 | E49: 21天赔付 | F49: 8.9 | G49: 15-22天 | H49: 8.2 | I49: 22天赔付 | J49: 7.9 | K49: 17-23天 | L49: 6.2 | M49: 23天赔付 | N49: 5.6 | O49: 28天赔付 | P49: 5.3 | Q49: 31天赔付 | R49: 5.2 | S49: 23-30天 | T49: 5.1 | U49: 25-35天
A50: LAS6 | B50: 89115 | D50: 9.2 | E50: 21天赔付 | F50: 8.9 | G50: 15-22天 | H50: 8.2 | I50: 22天赔付 | J50: 7.9 | K50: 17-23天 | L50: 6.2 | M50: 23天赔付 | N50: 5.6 | O50: 28天赔付 | P50: 5.3 | Q50: 31天赔付 | R50: 5.2 | S50: 23-30天 | T50: 5.1 | U50: 25-35天
A51: PHX5 | B51: 85338 | D51: 9.2 | E51: 21天赔付 | F51: 8.9 | G51: 15-22天 | H51: 8.2 | I51: 22天赔付 | J51: 7.9 | K51: 17-23天 | L51: 6.2 | M51: 23天赔付 | N51: 5.6 | O51: 28天赔付 | P51: 5.3 | Q51: 31天赔付 | R51: 5.2 | S51: 23-30天 | T51: 5.1 | U51: 25-35天
A52: PHX7 | B52: 85043 | D52: 9.2 | E52: 21天赔付 | F52: 8.9 | G52: 15-22天 | H52: 8.2 | I52: 22天赔付 | J52: 7.9 | K52: 17-23天 | L52: 6.2 | M52: 23天赔付 | N52: 5.6 | O52: 28天赔付 | P52: 5.3 | Q52: 31天赔付 | R52: 5.2 | S52: 23-30天 | T52: 5.1 | U52: 25-35天
A53: BFL2 | B53: 93263-2246 | D53: 9.2 | E53: 21天赔付 | F53: 8.9 | G53: 15-22天 | H53: 8.2 | I53: 22天赔付 | J53: 7.9 | K53: 17-23天 | L53: 6.2 | M53: 23天赔付 | N53: 5.6 | O53: 28天赔付 | P53: 5.3 | Q53: 31天赔付 | R53: 5.2 | S53: 23-30天 | T53: 5.1 | U53: 25-35天
A54: ABQ2 | B54: 87031 | C54: A【三区】 12KG+ | D54: 9.7 | E54: 25天赔付 | F54: 9.4 | G54: 15-25天 | H54: 8.8 | I54: 26天赔付 | J54: 8.5 | K54: 17-28天 | L54: 7.6 | M54: 27天赔付 | N54: 7 | O54: 30天赔付 | P54: 6.7 | Q54: 33天赔付 | R54: 6.6 | S54: 25-35天 | T54: 6.5 | U54: 25-38天
A55: FTW1 | B55: 75241 | D55: 9.7 | E55: 25天赔付 | F55: 9.4 | G55: 15-25天 | H55: 8.8 | I55: 26天赔付 | J55: 8.5 | K55: 17-28天 | L55: 7.6 | M55: 27天赔付 | N55: 7 | O55: 30天赔付 | P55: 6.7 | Q55: 33天赔付 | R55: 6.6 | S55: 25-35天 | T55: 6.5 | U55: 25-38天
A56: IUSF | B56: 75241 | D56: 9.7 | E56: 25天赔付 | F56: 9.4 | G56: 15-25天 | H56: 8.8 | I56: 26天赔付 | J56: 8.5 | K56: 17-28天 | L56: 7.6 | M56: 27天赔付 | N56: 7 | O56: 30天赔付 | P56: 6.7 | Q56: 33天赔付 | R56: 6.6 | S56: 25-35天 | T56: 6.5 | U56: 25-38天
A57: DFW6 | B57: 75019 | D57: 10 | E57: 28天赔付 | F57: 9.7 | G57: 20-28天 | H57: 9.1 | I57: 29天赔付 | J57: 8.8 | K57: 20-30天 | L57: 7.9 | M57: 30天赔付 | N57: 7.3 | O57: 33天赔付 | P57: 7 | Q57: 36天赔付 | R57: 6.9 | S57: 25-35天 | T57: 6.8 | U57: 25-38天
A58: HOU8 | B58: 77423 | D58: 10 | E58: 28天赔付 | F58: 9.7 | G58: 20-28天 | H58: 9.1 | I58: 29天赔付 | J58: 8.8 | K58: 20-30天 | L58: 7.9 | M58: 30天赔付 | N58: 7.3 | O58: 33天赔付 | P58: 7 | Q58: 36天赔付 | R58: 6.9 | S58: 25-35天 | T58: 6.8 | U58: 25-38天
A59: IAH3 | B59: 77032 | D59: 10 | E59: 28天赔付 | F59: 9.7 | G59: 20-28天 | H59: 9.1 | I59: 29天赔付 | J59: 8.8 | K59: 20-30天 | L59: 7.9 | M59: 30天赔付 | N59: 7.3 | O59: 33天赔付 | P59: 7 | Q59: 36天赔付 | R59: 6.9 | S59: 25-35天 | T59: 6.8 | U59: 25-38天
A60: AMA1 | B60: 79108 | D60: 10 | E60: 28天赔付 | F60: 9.7 | G60: 20-28天 | H60: 9.1 | I60: 29天赔付 | J60: 8.8 | K60: 20-30天 | L60: 7.9 | M60: 30天赔付 | N60: 7.3 | O60: 33天赔付 | P60: 7 | Q60: 36天赔付 | R60: 6.9 | S60: 25-35天 | T60: 6.8 | U60: 25-38天
A61: SAT1 | B61: 78154 | D61: 10 | E61: 28天赔付 | F61: 9.7 | G61: 20-28天 | H61: 9.1 | I61: 29天赔付 | J61: 8.8 | K61: 20-30天 | L61: 7.9 | M61: 30天赔付 | N61: 7.3 | O61: 33天赔付 | P61: 7 | Q61: 36天赔付 | R61: 6.9 | S61: 25-35天 | T61: 6.8 | U61: 25-38天
A62: SAT4 | B62: 78245 | D62: 10 | E62: 28天赔付 | F62: 9.7 | G62: 20-28天 | H62: 9.1 | I62: 29天赔付 | J62: 8.8 | K62: 20-30天 | L62: 7.9 | M62: 30天赔付 | N62: 7.3 | O62: 33天赔付 | P62: 7 | Q62: 36天赔付 | R62: 6.9 | S62: 25-35天 | T62: 6.8 | U62: 25-38天
A63: IUTH | B63: 78666 | D63: 10 | E63: 28天赔付 | F63: 9.7 | G63: 20-28天 | H63: 9.1 | I63: 29天赔付 | J63: 8.8 | K63: 20-30天 | L63: 7.9 | M63: 30天赔付 | N63: 7.3 | O63: 33天赔付 | P63: 7 | Q63: 36天赔付 | R63: 6.9 | S63: 25-35天 | T63: 6.8 | U63: 25-38天
A64: PSC2 | B64: 99301 | C64: B【三区】 12KG+ | D64: 9.7 | E64: 25天赔付 | F64: 9.4 | G64: 15-25天 | H64: 8.8 | I64: 26天赔付 | J64: 8.5 | K64: 17-28天 | L64: 7.6 | M64: 27天赔付 | N64: 7 | O64: 30天赔付 | P64: 6.7 | Q64: 33天赔付 | R64: 6.6 | S64: 25-35天 | T64: 6.5 | U64: 25-38天
A65: IND9 | B65: 46143 | D65: 9.7 | E65: 25天赔付 | F65: 9.4 | G65: 15-25天 | H65: 8.8 | I65: 26天赔付 | J65: 8.5 | K65: 17-28天 | L65: 7.6 | M65: 27天赔付 | N65: 7 | O65: 30天赔付 | P65: 6.7 | Q65: 33天赔付 | R65: 6.6 | S65: 25-35天 | T65: 6.5 | U65: 25-38天
A66: MDW2 | B66: 60433 | D66: 9.7 | E66: 25天赔付 | F66: 9.4 | G66: 15-25天 | H66: 8.8 | I66: 26天赔付 | J66: 8.5 | K66: 17-28天 | L66: 7.6 | M66: 27天赔付 | N66: 7 | O66: 30天赔付 | P66: 6.7 | Q66: 33天赔付 | R66: 6.6 | S66: 25-35天 | T66: 6.5 | U66: 25-38天
A67: FWA4 | B67: 46809-9771 | D67: 9.7 | E67: 25天赔付 | F67: 9.4 | G67: 15-25天 | H67: 8.8 | I67: 26天赔付 | J67: 8.5 | K67: 17-28天 | L67: 7.6 | M67: 27天赔付 | N67: 7 | O67: 30天赔付 | P67: 6.7 | Q67: 33天赔付 | R67: 6.6 | S67: 25-35天 | T67: 6.5 | U67: 25-38天
A68: MEM1 | B68: 38118 | D68: 9.7 | E68: 25天赔付 | F68: 9.4 | G68: 15-25天 | H68: 8.8 | I68: 26天赔付 | J68: 8.5 | K68: 17-28天 | L68: 7.6 | M68: 27天赔付 | N68: 7 | O68: 30天赔付 | P68: 6.7 | Q68: 33天赔付 | R68: 6.6 | S68: 25-35天 | T68: 6.5 | U68: 25-38天
A69: MQJ1 | B69: 46140 | D69: 9.7 | E69: 25天赔付 | F69: 9.4 | G69: 15-25天 | H69: 8.8 | I69: 26天赔付 | J69: 8.5 | K69: 17-28天 | L69: 7.6 | M69: 27天赔付 | N69: 7 | O69: 30天赔付 | P69: 6.7 | Q69: 33天赔付 | R69: 6.6 | S69: 25-35天 | T69: 6.5 | U69: 25-38天
A70: RFD2 | B70: 60142 | D70: 10.3 | E70: 28天赔付 | F70: 10 | G70: 20-28天 | H70: 9.4 | I70: 29天赔付 | J70: 9.1 | K70: 20-30天 | L70: 8.2 | M70: 30天赔付 | N70: 7.6 | O70: 33天赔付 | P70: 7.3 | Q70: 36天赔付 | R70: 7.2 | S70: 25-35天 | T70: 7.1 | U70: 25-38天
A71: RFD4 | B71: 60142 | D71: 10.3 | E71: 28天赔付 | F71: 10 | G71: 20-28天 | H71: 9.4 | I71: 29天赔付 | J71: 9.1 | K71: 20-30天 | L71: 8.2 | M71: 30天赔付 | N71: 7.6 | O71: 33天赔付 | P71: 7.3 | Q71: 36天赔付 | R71: 7.2 | S71: 25-35天 | T71: 7.1 | U71: 25-38天
A72: SLC2 | B72: 84081 | C72: C【三区】 12KG+ | D72: 9.1 | E72: 28天赔付 | F72: 8.8 | G72: 20-28天 | H72: 8.2 | I72: 29天赔付 | J72: 7.9 | K72: 20-30天 | L72: 7 | M72: 30天赔付 | N72: 6.4 | O72: 33天赔付 | P72: 6.1 | Q72: 36天赔付 | R72: 6 | S72: 25-35天 | T72: 5.9 | U72: 25-38天
A73: SLC3 | B73: 84116 | D73: 9.1 | E73: 28天赔付 | F73: 8.8 | G73: 20-28天 | H73: 8.2 | I73: 29天赔付 | J73: 7.9 | K73: 20-30天 | L73: 7 | M73: 30天赔付 | N73: 6.4 | O73: 33天赔付 | P73: 6.1 | Q73: 36天赔付 | R73: 6 | S73: 25-35天 | T73: 5.9 | U73: 25-38天
A74: PDX7 | B74: 97317 | C74: D【三区】 12KG+ | D74: 10 | E74: 28天赔付 | F74: 9.7 | G74: 20-28天 | H74: 9.1 | I74: 29天赔付 | J74: 8.8 | K74: 20-30天 | L74: 7.9 | M74: 30天赔付 | N74: 7.3 | O74: 33天赔付 | P74: 7 | Q74: 36天赔付 | R74: 6.9 | S74: 25-35天 | T74: 6.8 | U74: 25-38天
A75: BFI3 | B75: 98327-9607 | D75: 10 | E75: 28天赔付 | F75: 9.7 | G75: 20-28天 | H75: 9.1 | I75: 29天赔付 | J75: 8.8 | K75: 20-30天 | L75: 7.9 | M75: 30天赔付 | N75: 7.3 | O75: 33天赔付 | P75: 7 | Q75: 36天赔付 | R75: 6.9 | S75: 25-35天 | T75: 6.8 | U75: 25-38天
A76: GEG2 | B76: 99216 | D76: 10 | E76: 28天赔付 | F76: 9.7 | G76: 20-28天 | H76: 9.1 | I76: 29天赔付 | J76: 8.8 | K76: 20-30天 | L76: 7.9 | M76: 30天赔付 | N76: 7.3 | O76: 33天赔付 | P76: 7 | Q76: 36天赔付 | R76: 6.9 | S76: 25-35天 | T76: 6.8 | U76: 25-38天
A77: DEN2 | B77: 80019-3710 | D77: 10 | E77: 28天赔付 | F77: 9.7 | G77: 20-28天 | H77: 9.1 | I77: 29天赔付 | J77: 8.8 | K77: 20-30天 | L77: 7.9 | M77: 30天赔付 | N77: 7.3 | O77: 33天赔付 | P77: 7 | Q77: 36天赔付 | R77: 6.9 | S77: 25-35天 | T77: 6.8 | U77: 25-38天
A78: DEN8 | B78: 80018 | D78: 10 | E78: 28天赔付 | F78: 9.7 | G78: 20-28天 | H78: 9.1 | I78: 29天赔付 | J78: 8.8 | K78: 20-30天 | L78: 7.9 | M78: 30天赔付 | N78: 7.3 | O78: 33天赔付 | P78: 7 | Q78: 36天赔付 | R78: 6.9 | S78: 25-35天 | T78: 6.8 | U78: 25-38天
A79: OKC2 | B79: 73159 | D79: 10 | E79: 28天赔付 | F79: 9.7 | G79: 20-28天 | H79: 9.1 | I79: 29天赔付 | J79: 8.8 | K79: 20-30天 | L79: 7.9 | M79: 30天赔付 | N79: 7.3 | O79: 33天赔付 | P79: 7 | Q79: 36天赔付 | R79: 6.9 | S79: 25-35天 | T79: 6.8 | U79: 25-38天
A80: FTW2 | B80: 75019 | C80: E【三区】 12KG+ | D80: 10 | E80: 28天赔付 | F80: 9.7 | G80: 20-28天 | H80: 9.1 | I80: 29天赔付 | J80: 8.8 | K80: 20-30天 | L80: 7.9 | M80: 30天赔付 | N80: 7.3 | O80: 33天赔付 | P80: 7 | Q80: 36天赔付 | R80: 6.9 | S80: 25-35天 | T80: 6.8 | U80: 25-38天
A81: FTW5 | B81: 75126-3566 | D81: 10 | E81: 28天赔付 | F81: 9.7 | G81: 20-28天 | H81: 9.1 | I81: 29天赔付 | J81: 8.8 | K81: 20-30天 | L81: 7.9 | M81: 30天赔付 | N81: 7.3 | O81: 33天赔付 | P81: 7 | Q81: 36天赔付 | R81: 6.9 | S81: 25-35天 | T81: 6.8 | U81: 25-38天
A82: HOU7 | B82: 77064 | D82: 10 | E82: 28天赔付 | F82: 9.7 | G82: 20-28天 | H82: 9.1 | I82: 29天赔付 | J82: 8.8 | K82: 20-30天 | L82: 7.9 | M82: 30天赔付 | N82: 7.3 | O82: 33天赔付 | P82: 7 | Q82: 36天赔付 | R82: 6.9 | S82: 25-35天 | T82: 6.8 | U82: 25-38天
A83: FOE1 | B83: 66109 | D83: 10 | E83: 28天赔付 | F83: 9.7 | G83: 20-28天 | H83: 9.1 | I83: 29天赔付 | J83: 8.8 | K83: 20-30天 | L83: 7.9 | M83: 30天赔付 | N83: 7.3 | O83: 33天赔付 | P83: 7 | Q83: 36天赔付 | R83: 6.9 | S83: 25-35天 | T83: 6.8 | U83: 25-38天
A84: ICT2 | B84: 67219-1410 | D84: 10 | E84: 28天赔付 | F84: 9.7 | G84: 20-28天 | H84: 9.1 | I84: 29天赔付 | J84: 8.8 | K84: 20-30天 | L84: 7.9 | M84: 30天赔付 | N84: 7.3 | O84: 33天赔付 | P84: 7 | Q84: 36天赔付 | R84: 6.9 | S84: 25-35天 | T84: 6.8 | U84: 25-38天
A85: MKC4 | B85: 66021-9588 | D85: 10 | E85: 28天赔付 | F85: 9.7 | G85: 20-28天 | H85: 9.1 | I85: 29天赔付 | J85: 8.8 | K85: 20-30天 | L85: 7.9 | M85: 30天赔付 | N85: 7.3 | O85: 33天赔付 | P85: 7 | Q85: 36天赔付 | R85: 6.9 | S85: 25-35天 | T85: 6.8 | U85: 25-38天
A86: LIT2 | B86: 72117 | D86: 10 | E86: 28天赔付 | F86: 9.7 | G86: 20-28天 | H86: 9.1 | I86: 29天赔付 | J86: 8.8 | K86: 20-30天 | L86: 7.9 | M86: 30天赔付 | N86: 7.3 | O86: 33天赔付 | P86: 7 | Q86: 36天赔付 | R86: 6.9 | S86: 25-35天 | T86: 6.8 | U86: 25-38天
A87: SAT6 | B87: 78666 | D87: 10 | E87: 28天赔付 | F87: 9.7 | G87: 20-28天 | H87: 9.1 | I87: 29天赔付 | J87: 8.8 | K87: 20-30天 | L87: 7.9 | M87: 30天赔付 | N87: 7.3 | O87: 33天赔付 | P87: 7 | Q87: 36天赔付 | R87: 6.9 | S87: 25-35天 | T87: 6.8 | U87: 25-38天
A88: LFT1 | B88: 70507 | D88: 10 | E88: 28天赔付 | F88: 9.7 | G88: 20-28天 | H88: 9.1 | I88: 29天赔付 | J88: 8.8 | K88: 20-30天 | L88: 7.9 | M88: 30天赔付 | N88: 7.3 | O88: 33天赔付 | P88: 7 | Q88: 36天赔付 | R88: 6.9 | S88: 25-35天 | T88: 6.8 | U88: 25-38天
A89: MDW6 | B89: 60446 | C89: F【三区】 12KG+ | D89: 10.3 | E89: 28天赔付 | F89: 10 | G89: 20-28天 | H89: 9.4 | I89: 29天赔付 | J89: 9.1 | K89: 20-30天 | L89: 8.2 | M89: 30天赔付 | N89: 7.6 | O89: 33天赔付 | P89: 7.3 | Q89: 36天赔付 | R89: 7.2 | S89: 25-35天 | T89: 7.1 | U89: 25-38天
A90: MDW9 | B90: 60502 | D90: 10.3 | E90: 28天赔付 | F90: 10 | G90: 20-28天 | H90: 9.4 | I90: 29天赔付 | J90: 9.1 | K90: 20-30天 | L90: 8.2 | M90: 30天赔付 | N90: 7.6 | O90: 33天赔付 | P90: 7.3 | Q90: 36天赔付 | R90: 7.2 | S90: 25-35天 | T90: 7.1 | U90: 25-38天
A91: ORD2 | B91: 60410 | D91: 10.3 | E91: 28天赔付 | F91: 10 | G91: 20-28天 | H91: 9.4 | I91: 29天赔付 | J91: 9.1 | K91: 20-30天 | L91: 8.2 | M91: 30天赔付 | N91: 7.6 | O91: 33天赔付 | P91: 7.3 | Q91: 36天赔付 | R91: 7.2 | S91: 25-35天 | T91: 7.1 | U91: 25-38天
A92: STL3 | B92: 65738-2779 | D92: 10.3 | E92: 28天赔付 | F92: 10 | G92: 20-28天 | H92: 9.4 | I92: 29天赔付 | J92: 9.1 | K92: 20-30天 | L92: 8.2 | M92: 30天赔付 | N92: 7.6 | O92: 33天赔付 | P92: 7.3 | Q92: 36天赔付 | R92: 7.2 | S92: 25-35天 | T92: 7.1 | U92: 25-38天
A93: STL4 | B93: 62025-2815 | D93: 10.3 | E93: 28天赔付 | F93: 10 | G93: 20-28天 | H93: 9.4 | I93: 29天赔付 | J93: 9.1 | K93: 20-30天 | L93: 8.2 | M93: 30天赔付 | N93: 7.6 | O93: 33天赔付 | P93: 7.3 | Q93: 36天赔付 | R93: 7.2 | S93: 25-35天 | T93: 7.1 | U93: 25-38天
A94: JVL1 | B94: 53511 | D94: 10.3 | E94: 28天赔付 | F94: 10 | G94: 20-28天 | H94: 9.4 | I94: 29天赔付 | J94: 9.1 | K94: 20-30天 | L94: 8.2 | M94: 30天赔付 | N94: 7.6 | O94: 33天赔付 | P94: 7.3 | Q94: 36天赔付 | R94: 7.2 | S94: 25-35天 | T94: 7.1 | U94: 25-38天
A95: IGQ2 | B95: 60484 | D95: 10.3 | E95: 28天赔付 | F95: 10 | G95: 20-28天 | H95: 9.4 | I95: 29天赔付 | J95: 9.1 | K95: 20-30天 | L95: 8.2 | M95: 30天赔付 | N95: 7.6 | O95: 33天赔付 | P95: 7.3 | Q95: 36天赔付 | R95: 7.2 | S95: 25-35天 | T95: 7.1 | U95: 25-38天
A96: CMH3 | B96: 45050 | D96: 10.3 | E96: 28天赔付 | F96: 10 | G96: 20-28天 | H96: 9.4 | I96: 29天赔付 | J96: 9.1 | K96: 20-30天 | L96: 8.2 | M96: 30天赔付 | N96: 7.6 | O96: 33天赔付 | P96: 7.3 | Q96: 36天赔付 | R96: 7.2 | S96: 25-35天 | T96: 7.1 | U96: 25-38天
A97: CMH2 | B97: 43125 | D97: 10.3 | E97: 28天赔付 | F97: 10 | G97: 20-28天 | H97: 9.4 | I97: 29天赔付 | J97: 9.1 | K97: 20-30天 | L97: 8.2 | M97: 30天赔付 | N97: 7.6 | O97: 33天赔付 | P97: 7.3 | Q97: 36天赔付 | R97: 7.2 | S97: 25-35天 | T97: 7.1 | U97: 25-38天
A98: MEM6 | B98: 38654-2510 | D98: 10.3 | E98: 28天赔付 | F98: 10 | G98: 20-28天 | H98: 9.4 | I98: 29天赔付 | J98: 9.1 | K98: 20-30天 | L98: 8.2 | M98: 30天赔付 | N98: 7.6 | O98: 33天赔付 | P98: 7.3 | Q98: 36天赔付 | R98: 7.2 | S98: 25-35天 | T98: 7.1 | U98: 25-38天
A99: PPO4 | B99: 46140 | D99: 10.3 | E99: 28天赔付 | F99: 10 | G99: 20-28天 | H99: 9.4 | I99: 29天赔付 | J99: 9.1 | K99: 20-30天 | L99: 8.2 | M99: 30天赔付 | N99: 7.6 | O99: 33天赔付 | P99: 7.3 | Q99: 36天赔付 | R99: 7.2 | S99: 25-35天 | T99: 7.1 | U99: 25-38天
A100: CLT2 | B100: 28214 | C100: A【四区】 12KG+ | D100: 11.3 | E100: 30天赔付 | F100: 11 | G100: 20-32天 | H100: 10.4 | I100: 31天赔付 | J100: 10.1 | K100: 22-33天 | L100: 9.2 | M100: 32天赔付 | N100: 8.6 | O100: 34天赔付 | P100: 8.3 | Q100: 36天赔付 | R100: 8.2 | S100: 25-38天 | T100: 8.1 | U100: 25-38天
...

Sheet 普船海卡整柜直送
A1: 华东区-普船整柜直送汇总表
A2: 美西 七大仓直送价
A3: FBA仓库代码 | B3: 目的邮编 | C3: 计费重起收点 | D3: 价格 | E3: 整柜直送 整柜价 （我司仓库装柜，全包到门） | F3: 签收时效 | G3: 配送方式 | H3: 下单渠道：美西普船海卡/整柜直送
A4: ONT8 | B4: 92551 | C4: 12KG+ | D4: 4.1 | E4: / | F4: 25-32天 | G4: 专车配送 | H4: 指定船型：周三OA普船、周四SML、周四合德/以星
A5: LAX9 | B5: 92337 | C5: 12KG+ | D5: 4.1 | F5: 25-32天 | G5: 专车配送
A6: LGB8 | B6: 92376 | C6: 12KG+ | D6: 4.1 | F6: 25-32天 | G6: 专车配送
A7: SBD1 | B7: 92316-3819 | C7: 12KG+ | D7: 4.1 | F7: 25-32天 | G7: 专车配送
A8: IUSJ | B8: 92223 | C8: 12KG+ | D8: 4.3 | F8: 25-32天 | G8: 专车配送
A9: IUSQ | B9: 92374 | C9: 12KG+ | D9: 4.3 | F9: 25-32天 | G9: 专车配送
A10: IUSP | B10: 92344 | C10: 12KG+ | D10: 4.3 | F10: 25-32天 | G10: 专车配送
A11: POC1 | B11: 92336-1123 | C11: 12KG+ | D11: 4.3 | F11: 25-32天 | G11: 专车配送
A12: POC2 | B12: 91761 | C12: 12KG+ | D12: 4.3 | F12: 25-32天 | G12: 专车配送
A13: POC3 | B13: 92509 | C13: 12KG+ | D13: 4.3 | F13: 25-32天 | G13: 专车配送
A14: VGT2 | B14: 89115 | C14: 12KG+ | D14: 4.6 | E14: / | F14: 25-32天 | G14: 专车配送
A15: LAS1 | B15: 89044 | C15: 12KG+ | D15: 4.6 | F15: 25-32天 | G15: 专车配送
A16: GYR3 | B16: 85043 | C16: 12KG+ | D16: 4.6 | F16: 25-32天 | G16: 专车配送
A17: GYR2 | B17: 85395 | C17: 12KG+ | D17: 4.6 | F17: 25-32天 | G17: 专车配送
A18: MIT2 | B18: 93263 | C18: 12KG+ | D18: 4.6 | F18: 25-32天 | G18: 专车配送
A19: GEU2 | B19: 85340 | C19: 12KG+ | D19: 4.6 | F19: 25-32天 | G19: 专车配送
A20: GEU3 | B20: 85326 | C20: 12KG+ | D20: 4.6 | F20: 25-32天 | G20: 专车配送
A21: GEU5 | B21: 85395 | C21: 12KG+ | D21: 4.6 | F21: 25-32天 | G21: 专车配送
A22: ABQ2 | B22: 87031 | C22: 12KG+ | D22: 6 | E22: / | F22: 25-32天 | G22: 专车配送
A24: 奥克兰 三大仓直送价
A25: FBA仓库代码 | B25: 目的邮编 | C25: 计费重起收点 | D25: 价格 | E25: 整柜直送 整柜价 （我司仓库装柜，全包到门） | F25: 签收时效 | G25: 配送方式 | H25: 下单渠道：奥克兰普船海卡/整柜直送
A26: SCK4 | B26: 95215 | C26: 12KG+ | D26: 4.6 | E26: / | F26: 25-32天 | G26: 专车配送 | H26: 指定船型：OA普船、EXX、EX1统配
A27: SMF3 | B27: 95206 | C27: 12KG+ | D27: 4.6 | F27: 25-32天 | G27: 专车配送
A28: OAK3 | B28: 95363 | C28: 12KG+ | D28: 4.6 | F28: 25-32天 | G28: 专车配送
A29: HLI2 | B29: 95023 | C29: 12KG+ | D29: 4.6 | F29: 25-32天 | G29: 专车配送
A30: TCY1 | B30: 95206 | C30: 12KG+ | D30: 4.6 | F30: 25-32天 | G30: 专车配送
A31: TCY2 | B31: 95215 | C31: 12KG+ | D31: 4.6 | F31: 25-32天 | G31: 专车配送
A33: 美西 七大仓直送价 盐田普船经济线 （周日开船，25天航程）
A34: FBA仓库代码 | B34: 目的邮编 | C34: 计费重起收点 | D34: 价格 | E34: 整柜直送 整柜价 （我司仓库装柜，全包到门） | F34: 签收时效 | G34: 配送方式 | H34: 下单渠道：美西普船海卡/整柜直送 普船经济线
A35: ONT8 | B35: 92551 | C35: 12KG+ | D35: 4 | E35: / | F35: 30-35天 | G35: 专车配送 | H35: 指定船型：宁波万海 宁波海领 宁波CUL
A36: LAX9 | B36: 92337 | C36: 12KG+ | D36: 4 | F36: 30-35天 | G36: 专车配送
A37: LGB8 | B37: 92376 | C37: 12KG+ | D37: 4 | F37: 30-35天 | G37: 专车配送
A38: SBD1 | B38: 92316-3819 | C38: 12KG+ | D38: 4 | F38: 30-35天 | G38: 专车配送
A39: IUSJ | B39: 92223 | C39: 12KG+ | D39: 4.2 | F39: 25-32天 | G39: 专车配送
A40: IUSQ | B40: 92374 | C40: 12KG+ | D40: 4.2 | F40: 25-32天 | G40: 专车配送
A41: IUSP | B41: 92344 | C41: 12KG+ | D41: 4.2 | F41: 25-32天 | G41: 专车配送
A42: POC1 | B42: 92336-1123 | C42: 12KG+ | D42: 4.2 | F42: 25-32天 | G42: 专车配送
A43: POC2 | B43: 91761 | C43: 12KG+ | D43: 4.2 | F43: 25-32天 | G43: 专车配送
A44: POC3 | B44: 92509 | C44: 12KG+ | D44: 4.2 | F44: 25-32天 | G44: 专车配送
A45: VGT2 | B45: 89115 | C45: 12KG+ | D45: 4.5 | E45: / | F45: 30-35天 | G45: 专车配送
A46: LAS1 | B46: 89044 | C46: 12KG+ | D46: 4.5 | F46: 30-35天 | G46: 专车配送
A47: GYR3 | B47: 85043 | C47: 12KG+ | D47: 4.5 | F47: 30-35天 | G47: 专车配送
A48: GYR2 | B48: 85395 | C48: 12KG+ | D48: 4.5 | F48: 30-35天 | G48: 专车配送
A49: MIT2 | B49: 93263 | C49: 12KG+ | D49: 4.5 | F49: 30-35天 | G49: 专车配送
A50: GEU2 | B50: 85340 | C50: 12KG+ | D50: 4.5 | F50: 25-32天 | G50: 专车配送
A51: GEU3 | B51: 85326 | C51: 12KG+ | D51: 4.5 | F51: 30-35天 | G51: 专车配送
A52: GEU5 | B52: 85395 | C52: 12KG+ | D52: 4.5 | F52: 30-35天 | G52: 专车配送
A53: ABQ2 | B53: 87031 | C53: 12KG+ | D53: 5.9 | E53: / | F53: 25-32天 | G53: 专车配送
A54: 货重比：整票实重大于100公斤以上，享受重货比优惠：整票实重/整票方数=货重比 1:190 减0.2元 / 1:200 减0.3元 / 1:220 减0.5元 / 1:250 减0.8元 / 1:300 减1.2元 / 1:350 减1.5元 / 1:400 减1.8元 / 1:450 减2元 / 1:500 减2.2元 / 1:550 减2.5元 / ；超550以上单询；
A56: 【注意事项】亚马逊标准尺寸为63*63*63以内，单件实重22.5KG以内，如因超大超重导致拒收，费用补差如下： ONT8 LAX9 LGB8 SBD1 卡派由于超长被拒 差价1200美金 VGT2 LAS1 GYR3 GYR2 卡派由于超长被拒 差价1500美金 SCK4 SMF3 OAK3 卡派由于超长被拒 差价1500美金 --------- 【大家可以参考以前的数据和情况，其实拒收主要是针对肉眼可见的又长又扁的超大件，63±2的尺寸，不管是普船直送卡派还是拆送卡派，大概率都是没问题的！！】 【亚马逊仓库过机器的，机器和传送带都是有尺寸限制的，虽然官方要求63尺寸，但是亚马逊一般都会把过机尺寸和传送带的“包容性”增大一些，防止有些卡边货，传送不进去！！】

Sheet 美中专线（休斯顿、芝加哥）
A1: 华东区-美中卡派专线
A2: 芝加哥 普船海卡/美中专线
A3: FBA仓库代码 | B3: 目的邮编 | C3: 12KG+ | D3: 签收时效 | E3: 配送方式 | F3: 下单渠道：芝加哥 普船海卡/美中专线
A4: MDW2 | B4: 60433 | C4: 6.3 | D4: 30-38天 | E4: 专车配送 | F4: 指定船型：EXX、OA船、以星统配
A5: ORD2 | B5: 60410 | C5: 6.3 | D5: 30-38天 | E5: 专车配送
A6: IGQ2 | B6: 60484 | C6: 6.3 | D6: 30-38天 | E6: 专车配送 | F6: 沃尔玛下单渠道：芝加哥 沃尔玛卡派
A7: MDW6 | B7: 60446 | C7: 6.3 | D7: 30-38天 | E7: 专车配送
A8: MDW9 | B8: 60502 | C8: 6.3 | D8: 30-38天 | E8: 专车配送
A9: RFD2 | B9: 60142 | C9: 6.3 | D9: 30-38天 | E9: 专车配送
A10: RFD4 | B10: 60142 | C10: 6.3 | D10: 30-38天 | E10: 专车配送
A11: JVL1 | B11: 53511 | C11: 6.3 | D11: 30-38天 | E11: 专车配送
A12: 沃尔玛—ORD1S | B12: / | C12: 6.3 | D12: 30-38天 | E12: 专车配送
A13: IND9 | B13: 46143 | C13: 7.5 | D13: 30-38天 | E13: 专车配送
A14: FWA4 | B14: 46809-9771 | C14: 7.5 | D14: 30-38天 | E14: 专车配送
A15: MQJ1 | B15: 46140-7099 | C15: 7.5 | D15: 30-38天 | E15: 专车配送
A16: MQJ2 | B16: 46184 | C16: 7.5 | D16: 30-38天 | E16: 专车配送
A17: STL4 | B17: 62025-2815 | C17: 7.5 | D17: 30-38天 | E17: 专车配送
A18: IND2 | B18: 46168 | C18: 7.5 | D18: 30-38天 | E18: 专车配送
A19: IND4 | B19: 46231 | C19: 7.5 | D19: 30-38天 | E19: 专车配送
A20: IND5 | B20: 46168 | C20: 7.5 | D20: 30-38天 | E20: 专车配送
A21: PPO4 | B21: 46410 | C21: 7.5 | D21: 30-38天 | E21: 专车配送
A22: 沃尔玛—IND2 | B22: / | C22: 7.5 | D22: 30-38天 | E22: 专车配送
A23: 沃尔玛—IND3 | B23: / | C23: 7.5 | D23: 30-38天 | E23: 专车配送
A24: DET1 | B24: 48150 | C24: 7.8 | D24: 35-45天 | E24: 专车配送
A25: DET2 | B25: 48317 | C25: 7.8 | D25: 35-45天 | E25: 专车配送
A26: LAN2 | B26: 48917 | C26: 7.8 | D26: 35-45天 | E26: 专车配送
A27: CMH2 | B27: 43125 | C27: 7.8 | D27: 35-45天 | E27: 专车配送
A28: CMH3 | B28: 45050 | C28: 7.8 | D28: 35-45天 | E28: 专车配送
A29: CMH7 | B29: 43054-7762 | C29: 7.8 | D29: 35-45天 | E29: 专车配送
A30: FOE1 | B30: 66109 | C30: 8.1 | D30: 35-45天 | E30: 专车配送
A31: MKC4 | B31: 66021-9588 | C31: 8.1 | D31: 35-45天 | E31: 专车配送
A32: MEM1 | B32: 38118-8102 | C32: 8.1 | D32: 35-45天 | E32: 专车配送
A33: MEM6 | B33: 38654-2510 | C33: 8.1 | D33: 35-45天 | E33: 专车配送
A34: MCI3 | B34: 64068 | C34: 8.1 | D34: 35-45天 | E34: 专车配送
A35: STL3 | B35: 65738-2779 | C35: 8.1 | D35: 35-45天 | E35: 专车配送
A36: 沃尔玛—MCI1N | B36: / | C36: 8.1 | D36: 35-45天 | E36: 专车配送
A37: 沃尔玛—KS1 | B37: / | C37: 8.1 | D37: 35-45天 | E37: 专车配送
A38: 请注意：非以上芝加哥渠道的代码请务必单询，并且价格会比较高昂！！
A39: 货重比：整票实重大于100公斤以上，享受重货比优惠：整票实重/整票方数=货重比 1:190 减0.2元 / 1:200 减0.3元 / 1:220 减0.5元 / 1:250 减0.8元 / 1:300 减1.2元 / 1:350 减1.5元 / 1:400 减1.8元 / 1:450 减2元 / 1:500 减2.2元 / 1:550 减2.5元 / ；超550以上单询；
A41: 休斯顿专线 卡派特价
A42: FBA仓库代码 | B42: 目的邮编 | C42: 12KG+ | D42: 签收时效 | E42: 配送方式 | F42: 下单渠道：休斯顿 普船海卡/美中专线
A43: HOU1 | B43: 77338 | C43: 5.1 | D43: 35-40天 | E43: 专车配送 | F43: 指定船型：OA船、以星
A44: HOU2 | B44: 77038-2324 | C44: 5.1 | D44: 35-40天 | E44: 专车配送
A45: HOU3 | B45: 77423-2769 | C45: 5.1 | D45: 35-40天 | E45: 专车配送
A46: HOU7 | B46: 77064-1111 | C46: 5.1 | D46: 35-40天 | E46: 专车配送
A47: HOU8 | B47: 77545-1129 | C47: 5.1 | D47: 35-40天 | E47: 专车配送
A48: IAH3 | B48: 77032 | C48: 5.1 | D48: 35-40天 | E48: 专车配送
A49: FTW1 | B49: 75241 | C49: 5.7 | D49: 35-40天 | E49: 专车配送
A50: FTW5 | B50: 75126-3566 | C50: 5.7 | D50: 35-40天 | E50: 专车配送
A51: DFW6 | B51: 75019-4424 | C51: 5.7 | D51: 35-40天 | E51: 专车配送
A52: SAT1 | B52: 78154-1461 | C52: 5.7 | D52: 35-40天 | E52: 专车配送
A53: SAT4 | B53: 78245-9512 | C53: 5.7 | D53: 35-40天 | E53: 专车配送
A54: SAT6 | B54: 78666-0001 | C54: 5.7 | D54: 35-40天 | E54: 专车配送
A55: IUSF | B55: 75241 | C55: 5.7 | D55: 35-40天 | E55: 专车配送
A56: OKC2 | B56: 73159-0003 | C56: 6.7 | D56: 35-40天 | E56: 专车配送
A57: LFT1 | B57: 70520-5976 | C57: 6.7 | D57: 35-40天 | E57: 专车配送
A58: LIT2 | B58: 72117-5026 | C58: 6.7 | D58: 35-40天 | E58: 专车配送
A59: ICT2 | B59: 67219-1410 | C59: 6.7 | D59: 35-40天 | E59: 专车配送
A60: 货重比：整票实重大于100公斤以上，享受重货比优惠：整票实重/整票方数=货重比 1:190 减0.2元 / 1:200 减0.3元 / 1:220 减0.5元 / 1:250 减0.8元 / 1:300 减1.2元 / 1:350 减1.5元 / 1:400 减1.8元 / 1:450 减2元 / 1:500 减2.2元 / 1:550 减2.5元 / ；超550以上单询；
A62: 芝加哥 EXX海卡/美中专线【带赔付】
A63: FBA仓库代码 | B63: 目的邮编 | C63: 12KG+ | D63: 签收时效 | E63: 配送方式 | F63: 下单渠道：芝加哥 EXX海卡/美中专线【带赔付】
A64: MDW2 | B64: 60433 | C64: 13.4 | D64: 30天签收提供POD | E64: 专车配送 | F64: 指定船型：只做EXX
A65: MDW6 | B65: 60446 | C65: 13.9 | D65: 30天签收提供POD | E65: 专车配送
A66: MDW9 | B66: 60502 | C66: 13.9 | D66: 30天签收提供POD | E66: 专车配送
A67: ORD2 | B67: 60410 | C67: 13.9 | D67: 30天签收提供POD | E67: 专车配送
A68: IGQ2 | B68: 60484 | C68: 14.2 | D68: 30天签收提供POD | E68: 专车配送
A69: IND9 | B69: 46143 | C69: 14.2 | D69: 32天签收提供POD | E69: 专车配送
A70: JVL1 | B70: 53511 | C70: 14.4 | D70: 32天签收提供POD | E70: 专车配送
A71: CMH2 | B71: 43125 | C71: 14.5 | D71: 32天签收提供POD | E71: 专车配送
A72: CMH3 | B72: 45050 | C72: 14.5 | D72: 32天签收提供POD | E72: 专车配送
A73: RFD4 | B73: 60142 | C73: 14.5 | D73: 32天签收提供POD | E73: 专车配送
A74: DET1 | B74: 48150 | C74: 15.1 | D74: 32天签收提供POD | E74: 专车配送
A75: DET2 | B75: 48317 | C75: 15.1 | D75: 32天签收提供POD | E75: 专车配送
A76: IND2 | B76: 46168 | C76: 14.2 | D76: 35天签收提供POD | E76: 专车配送
A77: MKE1 | B77: 53144 | C77: 14.5 | D77: 35天签收提供POD | E77: 专车配送
A78: STL3 | B78: 65738-2779 | C78: 14.5 | D78: 35天签收提供POD | E78: 专车配送
A79: STL4 | B79: 62025-2815 | C79: 14.5 | D79: 35天签收提供POD | E79: 专车配送
A80: FWA4 | B80: 46809-9771 | C80: 15.9 | D80: 35天签收提供POD | E80: 专车配送
A81: MKC4 | B81: 66021-9588 | C81: 15.9 | D81: 35天签收提供POD | E81: 专车配送
A82: FOE1 | B82: 66109 | C82: 16.9 | D82: 35天签收提供POD | E82: 专车配送
A83: MDW8 | B83: 60085 | C83: 13.9 | D83: 35-40天 | E83: 30-45天
A84: STL6 | B84: 62025-2801 | C84: 14.4 | D84: 35-40天 | E84: 30-45天
A85: IND4 | B85: 46231 | C85: 14.2 | D85: 35-40天 | E85: 30-45天
A86: IND5 | B86: 46168 | C86: 14.2 | D86: 35-40天 | E86: 30-45天
A87: MQJ2 | B87: 46184 | C87: 14.4 | D87: 35-40天 | E87: 30-45天
A88: CMH1 | B88: 43062 | C88: 14.5 | D88: 35-40天 | E88: 30-45天
A89: CLE3 | B89: 44132 | C89: 14.5 | D89: 35-40天 | E89: 30-45天
A90: CMH6 | B90: 43137 | C90: 14.5 | D90: 35-40天 | E90: 30-45天
A91: PCW1 | B91: 43460 | C91: 15.1 | D91: 35-40天 | E91: 30-45天
A92: CVG1 | B92: 41048 | C92: 14.5 | D92: 35-40天 | E92: 30-45天
A93: SDF4 | B93: 40165 | C93: 15.1 | D93: 35-40天 | E93: 30-45天
A94: 货重比：整票实重大于100公斤以上，享受重货比优惠：整票实重/整票方数=货重比 1:190 减0.2元 / 1:200 减0.3元 / 1:220 减0.5元 / 1:250 减0.8元 / 1:300 减1.2元 / 1:350 减1.5元 / 1:400 减1.8元 / 1:450 减2元 / 1:500 减2.2元 / 1:550 减2.5元 / ；超550以上单询；

Sheet 萨凡纳海卡专线
A1: 华东区-萨凡纳海卡专线
A2: FBA仓库代码 | B2: 目的邮编 | C2: 12KG+ | D2: 签收时效 | E2: 配送方式 | F2: 下单渠道：海卡/萨凡纳直航普船
A3: XLX6 | B3: 28134 | C3: 5.6 | D3: 30-38天 | E3: 专车配送 | F3: 指定船型：OA普船AWE快线、以星
A4: SAV3 | B4: 31216-6427 | C4: 5.6 | D4: 30-38天 | E4: 专车配送
A5: XAV3 | B5: 31407 | C5: 5.6 | D5: 30-38天 | E5: 专车配送 | F5: 沃尔玛下单渠道：萨凡纳 沃尔玛卡派
A6: CLT2 | B6: 28214 | C6: 5.6 | D6: 30-38天 | E6: 专车配送
A7: CLT3 | B7: 28027-7995 | C7: 5.6 | D7: 30-38天 | E7: 专车配送
A8: GSP1 | B8: 29303 | C8: 5.6 | D8: 30-38天 | E8: 专车配送
A9: IUSR | B9: 29330 | C9: 5.6 | D9: 30-38天 | E9: 专车配送
A10: ATL8 | B10: 30122 | C10: 5.6 | D10: 30-38天 | E10: 专车配送
A11: RDU4 | B11: 28303 | C11: 5.6 | D11: 30-38天 | E11: 专车配送
A12: RYY2 | B12: 30184 | C12: 5.6 | D12: 30-38天 | E12: 专车配送
A13: MGE1 | B13: 30517 | C13: 5.6 | D13: 30-38天 | E13: 专车配送
A14: MGE3 | B14: 30549 | C14: 5.6 | D14: 30-38天 | E14: 专车配送
A15: JAX3 | B15: 32210-8686 | C15: 5.6 | D15: 30-38天 | E15: 专车配送
A16: GSO1 | B16: 27284 | C16: 5.9 | D16: 30-38天 | E16: 专车配送
A17: CLT6 | B17: 28134-9457 | C17: 5.9 | D17: 30-38天 | E17: 专车配送
A18: CLT4 | B18: 28214 | C18: 5.9 | D18: 30-38天 | E18: 专车配送
A19: MCO2 | B19: 32725 | C19: 5.9 | D19: 30-38天 | E19: 专车配送
A20: TPA2 | B20: 33811-1808 | C20: 5.9 | D20: 30-38天 | E20: 专车配送
A21: TPA3 | B21: 33823-9429 | C21: 5.9 | D21: 35-45天 | E21: 专车配送
A22: TPA6 | B22: 33811 | C22: 5.9 | D22: 35-45天 | E22: 专车配送
A23: RDU2 | B23: 27577 | C23: 5.9 | D23: 35-45天 | E23: 专车配送
A24: ATL2 | B24: 30087-3506 | C24: 5.9 | D24: 35-45天 | E24: 专车配送
A25: Walmart-ATL3 | B25: / | C25: 5.9 | D25: 35-45天 | E25: 专车配送
A26: Walmart-ATL2n | B26: / | C26: 5.9 | D26: 35-45天 | E26: 专车配送
A27: Walmart-ATL1 | B27: / | C27: 5.9 | D27: 35-45天 | E27: 专车配送
A28: Walmart-MCO1 | B28: / | C28: 5.9 | D28: 35-45天 | E28: 专车配送
A29: CHA2 | B29: 37310 | C29: 6.2 | D29: 35-45天 | E29: 专车配送
A30: BNA2 | B30: 37090-8123 | C30: 6.2 | D30: 35-45天 | E30: 专车配送
A31: BNA6 | B31: 37040-5502 | C31: 6.2 | D31: 35-45天 | E31: 专车配送
A32: PBI3 | B32: 34986 | C32: 6.2 | D32: 35-45天 | E32: 专车配送
A33: MQY1 | B33: 37122 | C33: 6.2 | D33: 35-45天 | E33: 专车配送
A34: ORF2 | B34: 23297 | C34: 6.2 | D34: 35-45天 | E34: 专车配送
A35: RMN3 | B35: 22406 | C35: 6.2 | D35: 35-45天 | E35: 专车配送
A36: TMB8 | B36: 33032 | C36: 6.2 | D36: 35-45天 | E36: 专车配送
A37: MEM8 | B37: 38611 | C37: 6.2 | D37: 35-45天 | E37: 专车配送
A38: HSV1 | B38: 35756-4403 | C38: 6.2 | D38: 35-45天 | E38: 专车配送
A39: HSV2 | B39: 35676 | C39: 6.2 | D39: 35-45天 | E39: 专车配送
A40: PBI2 | B40: 33478 | C40: 6.2 | D40: 35-45天 | E40: 专车配送
A41: XPB2 | B41: 32712 | C41: 6.2 | D41: 35-45天 | E41: 专车配送
A42: Walmart-MEM1s | B42: / | C42: 6.2 | D42: 35-45天 | E42: 专车配送
A43: 请注意：非以上萨凡纳渠道的代码请务必单询，并且价格会比较高昂！！
A44: 货重比：整票实重大于100公斤以上，享受重货比优惠：整票实重/整票方数=货重比 1:190 减0.2元 / 1:200 减0.3元 / 1:220 减0.5元 / 1:250 减0.8元 / 1:300 减1.2元 / 1:350 减1.5元 / 1:400 减1.8元 / 1:450 减2元 / 1:500 减2.2元 / 1:550 减2.5元 / ；超550以上单询；

Sheet 美东纽约海卡专线
A1: 海卡/纽约直航普船 （以星/OA船） | F1: 海卡/纽约以星海铁快线
A2: FBA仓库代码 （红色字体为美东热门仓） | B2: 目的邮编 | C2: 海卡包税 | E2: 签收时效 | F2: 海卡包税 | H2: 签收时效
C3: 下单渠道： 海卡/纽约直航普船 | D3: 下单渠道： 海卡/纽约直航普船 | F3: 下单渠道：海卡/纽约海铁快线【带赔付】 | I3: 注意：以星LA转铁路 或者 EXX LA 转铁路
C4: 1方起收；400折算 | D4: 12KG+ | F4: 12KG-99KG 价格 | G4: 100KG+ 价格
A5: ABE8 | B5: 08518-2200 | C5: =D5*200 -> 960 | D5: 4.8 | E5: 35-45天 | F5: 15.22 | G5: 14.22 | H5: 30天签收提供POD
A6: TEB9 | B6: 08873 | C6: =D6*200 -> 960 | D6: 4.8 | E6: 35-45天 | F6: 15.22 | G6: 14.22 | H6: 30天签收提供POD
A7: XEW5 | B7: 08077 | C7: =D7*200 -> 960 | D7: 4.8 | E7: 35-45天 | F7: 15.22 | G7: 14.22 | H7: 30天签收提供POD
A8: ACY2 | B8: 08016-1934 | C8: =D8*200 -> 960 | D8: 4.8 | E8: 35-45天 | F8: 15.22 | G8: 14.22 | H8: 30天签收提供POD
A9: ABE3 | B9: 18031 | C9: =D9*200 -> 960 | D9: 4.8 | E9: 35-45天 | F9: 15.22 | G9: 14.22 | H9: 30天签收提供POD
A10: ABE4 | B10: 18045 | C10: =D10*200 -> 960 | D10: 4.8 | E10: 35-45天 | F10: 15.22 | G10: 14.22 | H10: 30天签收提供POD
A11: TEB3 | B11: 08085-4503 | C11: =D11*200 -> 960 | D11: 4.8 | E11: 35-45天 | F11: 15.22 | G11: 14.22 | H11: 30天签收提供POD
A12: TEB4 | B12: 08069 | C12: =D12*200 -> 960 | D12: 4.8 | E12: 35-45天 | F12: 15.22 | G12: 14.22 | H12: 30天签收提供POD
A13: TEB6 | B13: 08873 | C13: =D13*200 -> 960 | D13: 4.8 | E13: 35-45天 | F13: 15.22 | G13: 14.22 | H13: 30天签收提供POD
A14: TTN2 | B14: 08512-3253 | C14: =D14*200 -> 960 | D14: 4.8 | E14: 35-45天 | F14: 15.72 | G14: 14.72 | H14: 30天签收提供POD
A15: AVP1 | B15: 18202-9361 | C15: =D15*200 -> 1100 | D15: 5.5 | E15: 35-45天 | F15: 16.24 | G15: 15.24 | H15: 30天签收提供POD
A16: AVP3 | B16: 18424-9492 | C16: =D16*200 -> 1100 | D16: 5.5 | E16: 35-45天 | F16: 16.24 | G16: 15.24 | H16: 30天签收提供POD
A17: AVP9 | B17: 18434-1153 | C17: =D17*200 -> 1100 | D17: 5.5 | E17: 35-45天 | F17: 16.24 | G17: 15.24 | H17: 30天签收提供POD
A18: ILG1 | B18: 19720-4610 | C18: =D18*200 -> 1100 | D18: 5.5 | E18: 35-45天 | F18: 15.93 | G18: 14.93 | H18: 30天签收提供POD
A19: SWF1 | B19: 12575 | C19: =D19*200 -> 1100 | D19: 5.5 | E19: 35-45天 | F19: 15.22 | G19: 14.22 | H19: 30天签收提供POD
A20: SWF2 | B20: 12533 | C20: =D20*200 -> 1100 | D20: 5.5 | E20: 35-45天 | F20: 15.22 | G20: 14.22 | H20: 30天签收提供POD
A21: PHL4 | B21: 17015 | C21: =D21*200 -> 1100 | D21: 5.5 | E21: 35-45天 | F21: 15.74 | G21: 14.74 | H21: 30天签收提供POD
A22: PHL5 | B22: 17339-8725 | C22: =D22*200 -> 1100 | D22: 5.5 | E22: 35-45天 | F22: 15.74 | G22: 14.74 | H22: 30天签收提供POD
A23: PHL6 | B23: 17015 | C23: =D23*200 -> 1100 | D23: 5.5 | E23: 35-45天 | F23: 15.74 | G23: 14.74 | H23: 30天签收提供POD
A24: PHL7 | B24: 19709 | C24: =D24*200 -> 1100 | D24: 5.5 | E24: 35-45天 | F24: 15.74 | G24: 14.74 | H24: 30天签收提供POD
A25: MDT1 | B25: 17015 | C25: =D25*200 -> 1100 | D25: 5.5 | E25: 35-45天 | F25: 16.24 | G25: 15.24 | H25: 30天签收提供POD
A26: MDT2 | B26: 21901 | C26: =D26*200 -> 1100 | D26: 5.5 | E26: 35-45天 | F26: 16.24 | G26: 15.24 | H26: 30天签收提供POD
A27: MDT4 | B27: 17408 | C27: =D27*200 -> 1100 | D27: 5.5 | E27: 35-45天 | F27: 16.24 | G27: 15.24 | H27: 30天签收提供POD
A28: WBW2 | B28: 18447 | C28: =D28*200 -> 1100 | D28: 5.5 | E28: 35-45天 | F28: 16.24 | G28: 15.24 | H28: 30天签收提供POD
A29: HEA2 | B29: 18031-1536 | C29: =D29*200 -> 1100 | D29: 5.5 | E29: 35-45天 | F29: 16.24 | G29: 15.24 | H29: 30天签收提供POD
A30: XLX1 | B30: 21740-8126 | C30: =D30*200 -> 1180 | D30: 5.9 | E30: 35-45天 | F30: 16.26 | G30: 15.26 | H30: 32天签收提供POD
A31: DCA6 | B31: 21219 | C31: =D31*200 -> 1180 | D31: 5.9 | E31: 35-45天 | F31: 16.56 | G31: 15.56 | H31: 32天签收提供POD
A32: ALB1 | B32: 12033 | C32: =D32*200 -> 1180 | D32: 5.9 | E32: 35-45天 | F32: 18.1 | G32: 17.1 | H32: 32天签收提供POD
A33: HGR2 | B33: 21901 | C33: =D33*200 -> 1180 | D33: 5.9 | E33: 35-45天 | F33: 18.9 | G33: 17.9 | H33: 32天签收提供POD
A34: HGR6 | B34: 21740-7301 | C34: =D34*200 -> 1180 | D34: 5.9 | E34: 35-45天 | F34: 18.9 | G34: 17.9 | H34: 32天签收提供POD
A35: BWI4 | B35: 22624-1568 | C35: =D35*200 -> 1180 | D35: 5.9 | E35: 35-45天 | F35: 18.9 | G35: 17.9 | H35: 32天签收提供POD
A36: HIA1 | B36: 17057 | C36: =D36*200 -> 1180 | D36: 5.9 | E36: 35-45天 | F36: 18.9 | G36: 17.9 | H36: 32天签收提供POD
A37: BDL3 | B37: 06473 | C37: =D37*200 -> 1260 | D37: 6.3 | E37: 40-45天 | F37: 17.9 | G37: 16.9 | H37: 32天签收提供POD
A38: BDL6 | B38: 06416 | C38: =D38*200 -> 1260 | D38: 6.3 | E38: 40-45天 | F38: 17.9 | G38: 16.9 | H38: 32天签收提供POD
A39: BOS7 | B39: 02720 | C39: =D39*200 -> 1260 | D39: 6.3 | E39: 40-45天 | F39: 18.4 | G39: 17.4 | H39: 32天签收提供POD
A40: RIC1 | B40: 23803 | C40: =D40*200 -> 1260 | D40: 6.3 | E40: 40-45天 | F40: 17.39 | G40: 16.39 | H40: 32天签收提供POD
A41: RIC3 | B41: 23234 | C41: =D41*200 -> 1260 | D41: 6.3 | E41: 40-45天 | F41: 17.39 | G41: 16.39 | H41: 32天签收提供POD
A42: RMN3 | B42: 22406 | C42: =D42*200 -> 1260 | D42: 6.3 | E42: 40-45天 | F42: 16.99 | G42: 15.99 | H42: 32天签收提供POD
A43: CHO1 | B43: 22939-2437 | C43: =D43*200 -> 1260 | D43: 6.3 | E43: 40-45天 | F43: 16.79 | G43: 15.79 | H43: 32天签收提供POD
A44: ORF2 | B44: 23297 | C44: =D44*200 -> 1260 | D44: 6.3 | E44: 40-45天 | F44: 17.9 | G44: 16.9 | H44: 32天签收提供POD
A45: XRI3 | B45: 23234 | C45: =D45*200 -> 1260 | D45: 6.3 | E45: 40-45天 | F45: 16.79 | G45: 15.79 | H45: 32天签收提供POD
A46: LBE1 | B46: 15672-9703 | C46: =D46*200 -> 1260 | D46: 6.3 | E46: 40-45天 | F46: 16.79 | G46: 15.79 | H46: 32天签收提供POD
A47: IUST | B47: 17225 | C47: =D47*200 -> 1260 | D47: 6.3 | E47: 40-45天 | F47: 16.79 | G47: 15.79 | H47: 32天签收提供POD
A48: IUSL | B48: 21901-2914 | C48: =D48*200 -> 1260 | D48: 6.3 | E48: 40-45天 | F48: 16.79 | G48: 15.79 | H48: 32天签收提供POD
A49: PIT2 | B49: 15126-1002 | C49: =D49*200 -> 1260 | D49: 6.3 | E49: 40-45天 | F49: 16.79 | G49: 15.79 | H49: 32天签收提供POD
A50: PIT3 | B50: - | C50: =D50*200 -> 1260 | D50: 6.3 | E50: 40-45天 | F50: 16.79 | G50: 15.79 | H50: 32天签收提供POD
A51: RDU2 | B51: 27577 | C51: =D51*200 -> 1320 | D51: 6.6 | E51: 40-45天 | F51: 18.22 | G51: 17.22 | H51: 35天签收提供POD
A52: RDU4 | B52: 28303 | C52: =D52*200 -> 1320 | D52: 6.6 | E52: 40-45天 | F52: 18.22 | G52: 17.22 | H52: 35天签收提供POD
A53: CLT2 | B53: 28214 | C53: =D53*200 -> 1320 | D53: 6.6 | E53: 40-45天 | F53: 18.4 | G53: 17.4 | H53: 35天签收提供POD
A54: CLT3 | B54: 28027-7995 | C54: =D54*200 -> 1320 | D54: 6.6 | E54: 40-45天 | F54: 18.4 | G54: 17.4 | H54: 35天签收提供POD
A55: CLT6 | B55: 28134-9457 | C55: =D55*200 -> 1320 | D55: 6.6 | E55: 40-45天 | F55: 18.4 | G55: 17.4 | H55: 35天签收提供POD
A56: GSO1 | B56: 27284-6855 | C56: =D56*200 -> 1320 | D56: 6.6 | E56: 40-45天 | F56: 18.4 | G56: 17.4 | H56: 35天签收提供POD
A57: XLX6 | B57: 28134 | C57: =D57*200 -> 1320 | D57: 6.6 | E57: 40-45天 | F57: 18.4 | G57: 17.4 | H57: 35天签收提供POD
A58: TPA2 | B58: 33811-1808 | C58: =D58*200 -> 1520 | D58: 7.6 | E58: 40-45天 | F58: 18.6 | G58: 17.6 | H58: 35天签收提供POD
A59: TPA3 | B59: 33823-9429 | C59: =D59*200 -> 1520 | D59: 7.6 | E59: 40-45天 | F59: 18.6 | G59: 17.6 | H59: 35天签收提供POD
A60: TPA6 | B60: 34475-4625 | C60: =D60*200 -> 1520 | D60: 7.6 | E60: 40-45天 | F60: 18.6 | G60: 17.6 | H60: 35天签收提供POD
A61: MCO2 | B61: 32725 | C61: =D61*200 -> 1520 | D61: 7.6 | E61: 40-45天 | F61: 18.9 | G61: 17.9 | H61: 35天签收提供POD
A62: RYY2 | B62: 30184 | C62: =D62*200 -> 1520 | D62: 7.6 | E62: 40-45天 | F62: 19.4 | G62: 18.4 | H62: 35天签收提供POD
A63: PBI3 | B63: 34986 | C63: =D63*200 -> 1520 | D63: 7.6 | E63: 40-45天 | F63: 18.6 | G63: 17.6 | H63: 35天签收提供POD
A64: IUSR | B64: 29330 | C64: =D64*200 -> 1520 | D64: 7.6 | E64: 40-45天 | F64: 19.4 | G64: 18.4 | H64: 35天签收提供POD
A65: GSP1 | B65: 29303-6312 | C65: =D65*200 -> 1520 | D65: 7.6 | E65: 40-45天 | F65: 19.4 | G65: 18.4 | H65: 35天签收提供POD
A66: MGE3 | B66: 30549-2010 | C66: =D66*200 -> 1520 | D66: 7.6 | E66: 40-45天 | F66: 19.4 | G66: 18.4 | H66: 35天签收提供POD
A67: SAV3 | B67: 31216-6427 | C67: =D67*200 -> 1520 | D67: 7.6 | E67: 40-45天 | F67: 19.4 | G67: 18.4 | H67: 35天签收提供POD
A68: AKR1 | B68: 44705 | C68: =D68*200 -> 1520 | D68: 7.6 | E68: 40-45天 | F68: 19.4 | G68: 18.4 | H68: 35天签收提供POD
A69: CMH3 | B69: 45050 | C69: =D69*200 -> 1420 | D69: 7.1 | E69: 40-45天 | F69: 18.54 | G69: 17.54 | H69: 35天签收提供POD
A70: CMH2 | B70: 43125 | C70: =D70*200 -> 1420 | D70: 7.1 | E70: 40-45天 | F70: 18.54 | G70: 17.54 | H70: 35天签收提供POD
A71: DET1 | B71: 48150 | C71: =D71*200 -> 1420 | D71: 7.1 | E71: 40-45天 | F71: 18.54 | G71: 17.54 | H71: 35天签收提供POD
A72: DET2 | B72: 48317 | C72: =D72*200 -> 1420 | D72: 7.1 | E72: 40-45天 | F72: 18.54 | G72: 17.54 | H72: 35天签收提供POD
A73: MQJ1 | B73: 46140-7099 | C73: =D73*200 -> 1420 | D73: 7.1 | E73: 40-45天 | F73: 18.54 | G73: 17.54 | H73: 35天签收提供POD
A74: MQJ2 | B74: 46184-9108 | C74: =D74*200 -> 1420 | D74: 7.1 | E74: 40-45天 | F74: 18.54 | G74: 17.54 | H74: 35天签收提供POD
A75: IND2 | B75: 46168-7442 | C75: =D75*200 -> 1420 | D75: 7.1 | E75: 40-45天 | F75: 18.54 | G75: 17.54 | H75: 35天签收提供POD
A76: IND4 | B76: 46231-1132 | C76: =D76*200 -> 1420 | D76: 7.1 | E76: 40-45天 | F76: 18.54 | G76: 17.54 | H76: 35天签收提供POD
A77: IND5 | B77: 46168 | C77: =D77*200 -> 1420 | D77: 7.1 | E77: 40-45天 | F77: 18.54 | G77: 17.54 | H77: 35天签收提供POD
A78: IND9 | B78: 46143 | C78: =D78*200 -> 1420 | D78: 7.1 | E78: 40-45天 | F78: 18.54 | G78: 17.54 | H78: 35天签收提供POD
A79: MDW2 | B79: 60433 | C79: =D79*200 -> 1420 | D79: 7.1 | E79: 40-45天 | F79: 18.54 | G79: 17.54 | H79: 35天签收提供POD
A80: MDW6 | B80: 60446 | C80: =D80*200 -> 1420 | D80: 7.1 | E80: 40-45天 | F80: 18.54 | G80: 17.54 | H80: 35天签收提供POD
A81: MDW9 | B81: 60502 | C81: =D81*200 -> 1420 | D81: 7.1 | E81: 40-45天 | F81: 18.54 | G81: 17.54 | H81: 35天签收提供POD
A82: ORD2 | B82: 60410 | C82: =D82*200 -> 1420 | D82: 7.1 | E82: 40-45天 | F82: 18.54 | G82: 17.54 | H82: 35天签收提供POD
A83: IGQ2 | B83: 60484 | C83: =D83*200 -> 1420 | D83: 7.1 | E83: 40-45天 | F83: 18.54 | G83: 17.54 | H83: 35天签收提供POD
A84: FWA4 | B84: 46809-9771 | C84: =D84*200 -> 1420 | D84: 7.1 | E84: 40-45天 | F84: 18.54 | G84: 17.54 | H84: 35天签收提供POD
A85: JVL1 | B85: 53511 | C85: =D85*200 -> 1420 | D85: 7.1 | E85: 40-45天 | F85: 18.54 | G85: 17.54 | H85: 35天签收提供POD
A86: RFD2 | B86: 60142 | C86: =D86*200 -> 1420 | D86: 7.1 | E86: 40-45天 | F86: 18.54 | G86: 17.54 | H86: 35天签收提供POD
A87: JAX3 | B87: 32210-8686 | C87: =D87*200 -> 1720 | D87: 8.6 | E87: 40-45天 | F87: 20.4 | G87: 19.4 | H87: 35天签收提供POD
A88: 沃尔玛 NJ3 | B88: 08067 | C88: =D88*200 -> 1260 | D88: 6.3 | I88: 沃尔玛下单渠道： 纽约 沃尔玛卡派
A89: 沃尔玛 PHL4N | B89: 17257 | C89: =D89*200 -> 1320 | D89: 6.6
A90: 沃尔玛 PHL1S | B90: 18015 | C90: =D90*200 -> 1340 | D90: 6.7
A91: 沃尔玛 PHL5S | B91: 17225 | C91: =D91*200 -> 1340 | D91: 6.7
A92: 沃尔玛 CVG1N | B92: 45050 | C92: =D92*200 -> 1520 | D92: 7.6
A93: 沃尔玛 KY1 | B93: 40165 | C93: =D93*200 -> 1520 | D93: 7.6
A94: 沃尔玛 IND2T | B94: 46168 | C94: =D94*200 -> 1580 | D94: 7.9
A95: 沃尔玛 IND2N | B95: 46168 | C95: =D95*200 -> 1580 | D95: 7.9
A96: 沃尔玛 IND3 | B96: 46055 | C96: =D96*200 -> 1580 | D96: 7.9
A97: 沃尔玛 ORD1S | B97: 60436 | C97: =D97*200 -> 1720 | D97: 8.6
A98: 沃尔玛 MCI1N | B98: 66619 | C98: =D98*200 -> 2020 | D98: 10.1
A99: 沃尔玛 MEM1S | B99: 38654 | C99: =D99*200 -> 1680 | D99: 8.4
A100: 沃尔玛 ATL1 | B100: 30349 | C100: =D100*200 -> 1720 | D100: 8.6
...

Sheet 全美私人卡派
A1: 华东区-全美私人卡派
A2: 美森正班私人卡派（CLX）
A3: 国家/重量 | B3: 350KG+ | C3: 700KG+ | D3: 1000KG+ | E3: 1500KG+ | F3: 2000KG+ | G3: 3000KG+ | H3: 4000KG+ | I3: 5000KG+ | J3: 6000KG+ | K3: 6吨以上单询
A4: 90-92邮编 （50miles内商业地址） | B4: 15 | C4: 12.5 | D4: 11.5 | E4: 11 | F4: 10.5 | G4: 10.5 | H4: 10.5 | I4: 10.3 | J4: 10.3 | K4: 单询
A5: 下单渠道：美森正班/私人卡派—50英里内（CLX） 注意：务必找我司业务员确认是否为50英里范围内
A6: 美西(USW) 邮编8.9 商业地址 （不含97、98、99邮编区域） | B6: 18.33 | C6: 16.33 | D6: 13.83 | E6: 13.83 | F6: 13.33 | G6: 13.33 | H6: 12.83 | I6: 12.83 | J6: 12.83 | K6: 单询
A7: 美中(USM) 邮编4.5.6.7 商业地址 （含97、98、99邮编区域） | B7: 20.33 | C7: 17.33 | D7: 15.83 | E7: 15.33 | F7: 14.83 | G7: 14.83 | H7: 14.33 | I7: 14.33 | J7: 14.33 | K7: 单询
A8: 美东(USE) 邮编0.1.2.3 商业地址 | B8: 22.83 | C8: 18.83 | D8: 17.33 | E8: 16.83 | F8: 16.83 | G8: 16.33 | H8: 15.83 | I8: 15.83 | J8: 15.83 | K8: 单询
A9: 下单渠道：美森正班/私人卡派（CLX）
A11: 美森加班私人卡派（MAX）
A12: 国家/重量 | B12: 350KG+ | C12: 700KG+ | D12: 1000KG+ | E12: 1500KG+ | F12: 2000KG+ | G12: 3000KG+ | H12: 4000KG+ | I12: 5000KG+ | J12: 6000KG+ | K12: 6吨以上单询
A13: 90-92邮编 （50miles内商业地址） | B13: 14.2 | C13: 11.7 | D13: 10.7 | E13: 10.2 | F13: 9.7 | G13: 9.7 | H13: 9.7 | I13: 9.5 | J13: 9.5 | K13: 单询
A14: 下单渠道：美森加班/私人卡派—50英里内（MAX） 注意：务必找我司业务员确认是否为50英里范围内
A15: 美西(USW) 邮编8.9 商业地址 （不含97、98、99邮编区域） | B15: 17.53 | C15: 15.53 | D15: 13.03 | E15: 13.03 | F15: 12.53 | G15: 12.53 | H15: 12.03 | I15: 12.03 | J15: 12.03 | K15: 单询
A16: 美中(USM) 邮编4.5.6.7 商业地址 （含97、98、99邮编区域） | B16: 19.53 | C16: 16.53 | D16: 15.03 | E16: 14.53 | F16: 14.03 | G16: 14.03 | H16: 13.53 | I16: 13.53 | J16: 13.53 | K16: 单询
A17: 美东(USE) 邮编0.1.2.3 商业地址 | B17: 22.03 | C17: 18.03 | D17: 16.53 | E17: 16.03 | F17: 16.03 | G17: 15.53 | H17: 15.03 | I17: 15.03 | J17: 15.03 | K17: 单询
A18: 下单渠道：美森加班/私人卡派（MAX）
A20: EXX/私人卡派
A21: 国家/重量 | B21: 350KG+ | C21: 700KG+ | D21: 1000KG+ | E21: 1500KG+ | F21: 2000KG+ | G21: 3000KG+ | H21: 4000KG+ | I21: 5000KG+ | J21: 6000KG+ | K21: 6吨以上单询
A22: 90-92邮编 （50miles内商业地址） | B22: 10.9 | C22: 8.4 | D22: 7.4 | E22: 6.9 | F22: 6.4 | G22: 6.4 | H22: 6.4 | I22: 6.2 | J22: 6.2 | K22: 单询
A23: 下单渠道：EXX/私人卡派—50英里内 注意：务必找我司业务员确认是否为50英里范围内
A24: 美西(USW) 邮编8.9 商业地址 （不含97、98、99邮编区域） | B24: 14.43 | C24: 12.43 | D24: 9.93 | E24: 9.93 | F24: 9.43 | G24: 9.43 | H24: 8.93 | I24: 8.93 | J24: 8.93 | K24: 单询
A25: 美中(USM) 邮编4.5.6.7 商业地址 （含97、98、99邮编区域） | B25: 16.43 | C25: 13.43 | D25: 11.93 | E25: 11.43 | F25: 10.93 | G25: 10.93 | H25: 10.43 | I25: 10.43 | J25: 10.43 | K25: 单询
A26: 美东(USE) 邮编0.1.2.3 商业地址 | B26: 18.43 | C26: 14.43 | D26: 12.93 | E26: 12.43 | F26: 12.43 | G26: 11.93 | H26: 11.43 | I26: 11.43 | J26: 11.43 | K26: 单询
A27: 下单渠道：EXX/私人卡派
A29: 华东合德/以星统配 私人卡派 最晚周一进仓
A30: 国家/重量 | B30: 350KG+ | C30: 700KG+ | D30: 1000KG+ | E30: 1500KG+ | F30: 2000KG+ | G30: 3000KG+ | H30: 4000KG+ | I30: 5000KG+ | J30: 6000KG+ | K30: 6吨以上单询
A31: 90-92邮编 （50miles内商业地址） | B31: 10.2 | C31: 7.7 | D31: 6.7 | E31: 6.2 | F31: 5.7 | G31: 5.7 | H31: 5.7 | I31: 5.5 | J31: 5.5 | K31: 单询
A32: 下单渠道：华东合德/以星统配 私人卡派—50英里内 注意：务必找我司业务员确认是否为50英里范围内
A33: 美西(USW) 邮编8.9 商业地址 （不含97、98、99邮编区域） | B33: 13.73 | C33: 11.73 | D33: 9.23 | E33: 9.23 | F33: 8.73 | G33: 8.73 | H33: 8.23 | I33: 8.23 | J33: 8.23 | K33: 单询
A34: 美中(USM) 邮编4.5.6.7 商业地址 （含97、98、99邮编区域） | B34: 15.73 | C34: 12.73 | D34: 11.23 | E34: 10.73 | F34: 10.23 | G34: 10.23 | H34: 9.73 | I34: 9.73 | J34: 9.73 | K34: 单询
A35: 美东(USE) 邮编0.1.2.3 商业地址 | B35: 17.73 | C35: 13.73 | D35: 12.23 | E35: 11.73 | F35: 11.73 | G35: 11.23 | H35: 10.73 | I35: 10.73 | J35: 10.73 | K35: 单询
A36: 下单渠道：华东合德/以星统配 私人卡派
A38: 美西洛杉矶普船私人卡派 | L38: 这是洛杉矶海外仓普船渠道，OA、合德统配
A39: 国家/重量 | B39: 350KG+ | C39: 700KG+ | D39: 1000KG+ | E39: 1500KG+ | F39: 2000KG+ | G39: 3000KG+ | H39: 4000KG+ | I39: 5000KG+ | J39: 6000KG+ | K39: 6吨以上单询
A40: 90-92邮编 （50miles内商业地址） | B40: 9.9 | C40: 7.4 | D40: 6.4 | E40: 5.9 | F40: 5.4 | G40: 5.4 | H40: 5.4 | I40: 5.2 | J40: 5.2 | K40: 单询
A41: 下单渠道：美西普船/私人卡派—50英里内 注意：务必找我司业务员确认是否为50英里范围内
A42: 美西(USW) 邮编8.9 商业地址 （不含97、98、99邮编区域） | B42: 13.43 | C42: 11.43 | D42: 8.93 | E42: 8.93 | F42: 8.43 | G42: 8.43 | H42: 7.93 | I42: 7.93 | J42: 7.93 | K42: 单询
A43: 美中(USM) 邮编4.5.6.7 商业地址 （含97、98、99邮编区域） | B43: 15.43 | C43: 12.43 | D43: 10.93 | E43: 10.43 | F43: 9.93 | G43: 9.93 | H43: 9.43 | I43: 9.43 | J43: 9.43 | K43: 单询
A44: 美东(USE) 邮编0.1.2.3 商业地址 | B44: 17.43 | C44: 13.43 | D44: 11.93 | E44: 11.43 | F44: 11.43 | G44: 10.93 | H44: 10.43 | I44: 10.43 | J44: 10.43 | K44: 单询
A45: 下单渠道：美西普船/私人卡派
A47: 美西洛杉矶普船私人卡派—经济线 | L47: 这是洛杉矶海外仓普船渠道，经济线，航程22-25天，周六开船
A48: 国家/重量 | B48: 350KG+ | C48: 700KG+ | D48: 1000KG+ | E48: 1500KG+ | F48: 2000KG+ | G48: 3000KG+ | H48: 4000KG+ | I48: 5000KG+ | J48: 6000KG+ | K48: 6吨以上单询
A49: 90-92邮编 （50miles内商业地址） | B49: 9.8 | C49: 7.3 | D49: 6.3 | E49: 5.8 | F49: 5.3 | G49: 5.3 | H49: 5.3 | I49: 5.1 | J49: 5.1 | K49: 单询
A50: 下单渠道：美西普船/私人卡派—50英里内—经济线 注意：务必找我司业务员确认是否为50英里范围内
A51: 美西(USW) 邮编8.9 商业地址 （不含97、98、99邮编区域） | B51: 13.33 | C51: 11.33 | D51: 8.83 | E51: 8.83 | F51: 8.33 | G51: 8.33 | H51: 7.83 | I51: 7.83 | J51: 7.83 | K51: 单询
A52: 美中(USM) 邮编4.5.6.7 商业地址 （含97、98、99邮编区域） | B52: 15.33 | C52: 12.33 | D52: 10.83 | E52: 10.33 | F52: 9.83 | G52: 9.83 | H52: 9.33 | I52: 9.33 | J52: 9.33 | K52: 单询
A53: 美东(USE) 邮编0.1.2.3 商业地址 | B53: 17.33 | C53: 13.33 | D53: 11.83 | E53: 11.33 | F53: 11.33 | G53: 10.83 | H53: 10.33 | I53: 10.33 | J53: 10.33 | K53: 单询
A54: 下单渠道：美西普船/私人卡派—经济线
A56: 美西奥克兰普船私人卡派 | L56: 这是奥克兰海外仓普船渠道，OA或者CMA柜子
A57: 国家/重量 | B57: 350KG+ | C57: 700KG+ | D57: 1000KG+ | E57: 1500KG+ | F57: 2000KG+ | G57: 3000KG+ | H57: 4000KG+ | I57: 5000KG+ | J57: 6000KG+ | K57: 6吨以上单询
A58: 94-95邮编 （50miles内商业地址） | B58: 10.2 | C58: 7.7 | D58: 6.7 | E58: 6.2 | F58: 5.7 | G58: 5.7 | H58: 5.7 | I58: 5.5 | J58: 5.5 | K58: 单询
A59: 下单渠道：美西奥克兰普船/私人卡派—50英里内 注意：务必找我司业务员确认是否为50英里范围内
A60: 美西(USW) 邮编8.9 商业地址 （不含97、98、99邮编区域） | B60: 13.73 | C60: 11.73 | D60: 9.23 | E60: 9.23 | F60: 8.73 | G60: 8.73 | H60: 8.23 | I60: 8.23 | J60: 8.23 | K60: 单询
A61: 美中(USM) 邮编4.5.6.7 商业地址 （含97、98、99邮编区域） | B61: 15.73 | C61: 12.73 | D61: 11.23 | E61: 10.73 | F61: 10.23 | G61: 10.23 | H61: 9.73 | I61: 9.73 | J61: 9.73 | K61: 单询
A62: 美东(USE) 邮编0.1.2.3 商业地址 | B62: 17.73 | C62: 13.73 | D62: 12.23 | E62: 11.73 | F62: 11.73 | G62: 11.23 | H62: 10.73 | I62: 10.73 | J62: 10.73 | K62: 单询
A63: 下单渠道：美西奥克兰普船/私人卡派
A65: 纽约普船私人卡派
A66: 国家/重量 | B66: 350KG+ | C66: 700KG+ | D66: 1000KG+ | E66: 1500KG+ | F66: 2000KG+ | G66: 3000KG+ | H66: 4000KG+ | I66: 5000KG+ | J66: 6000KG+ | K66: 6吨以上单询
A67: 08817邮编 （50miles内商业地址） | B67: 10.6 | C67: 8.1 | D67: 7.1 | E67: 6.6 | F67: 6.1 | G67: 6.1 | H67: 6.1 | I67: 5.9 | J67: 5.9 | K67: 单询
A68: 下单渠道：纽约普船/私人卡派—50英里内 注意：务必找我司业务员确认是否为50英里范围内
A69: 08817邮编 （80-300公里） | B69: 13.1 | C69: 10.6 | D69: 9.6 | E69: 9.1 | F69: 8.6 | G69: 8.6 | H69: 8.6 | I69: 8.4 | J69: 8.4 | K69: 单询 | L69: 某些0、1、2邮编区域，距离海外仓是300公里内的价格；3吨以上大货可以单询
A70: 美东(USE) 邮编0.1.商业地址 | B70: 15.9 | C70: 12.9 | D70: 10.4 | E70: 10.4 | F70: 10.4 | G70: 9.9 | H70: 9.9 | I70: 9.9 | J70: 9.9 | K70: 单询
A71: 美东(USE) 邮编2.3 商业地址 | B71: 17.9 | C71: 13.9 | D71: 12.4 | E71: 11.9 | F71: 11.4 | G71: 11.4 | H71: 10.9 | I71: 10.9 | J71: 10.9 | K71: 单询
A72: 下单渠道：纽约普船/私人卡派
A74: 休斯顿专线 私人卡派 （35-40天）
A75: 国家/重量 | B75: 350KG+ | C75: 700KG+ | D75: 1000KG+ | E75: 1500KG+ | F75: 2000KG+ | G75: 3000KG+ | H75: 4000KG+ | I75: 5000KG+ | J75: 6000KG+ | K75: 6吨以上单询
A76: 77091邮编 （50miles内商业地址） | B76: 10.9 | C76: 8.4 | D76: 7.4 | E76: 6.9 | F76: 6.4 | G76: 6.4 | H76: 6.4 | I76: 6.2 | J76: 6.2 | K76: 单询
A77: 下单渠道：休斯顿 私人卡派/美中专线—50英里内 注意：务必找我司业务员确认是否为50英里范围内
A78: 77091邮编 （80-300公里） | B78: 13.4 | C78: 10.9 | D78: 9.9 | E78: 9.4 | F78: 8.9 | G78: 8.9 | H78: 8.9 | I78: 8.7 | J78: 8.7 | K78: 单询 | L78: 300公里以上，单询
A79: 下单渠道：休斯顿 私人卡派/美中专线—（80-300公里）
A81: 萨凡纳私人卡派 （35-40天）
A82: 国家/重量 | B82: 350KG+ | C82: 700KG+ | D82: 1000KG+ | E82: 1500KG+ | F82: 2000KG+ | G82: 3000KG+ | H82: 4000KG+ | I82: 5000KG+ | J82: 6000KG+ | K82: 6吨以上单询
A83: 31407邮编 （50miles内商业地址） | B83: 10.9 | C83: 8.4 | D83: 7.4 | E83: 6.9 | F83: 6.4 | G83: 6.4 | H83: 6.4 | I83: 6.2 | J83: 6.2 | K83: 单询
A84: 下单渠道：萨凡纳 私人卡派/美中专线—50英里内 注意：务必找我司业务员确认是否为50英里范围内
A85: 31407邮编 （80-300公里） | B85: 13.4 | C85: 10.9 | D85: 9.9 | E85: 9.4 | F85: 8.9 | G85: 8.9 | H85: 8.9 | I85: 8.7 | J85: 8.7 | K85: 单询 | L85: 300公里以上，单询
A86: 下单渠道：萨凡纳 私人卡派/美中专线—（80-300公里）
A88: 芝加哥专线 私人卡派 （35-40天）
A89: 国家/重量 | B89: 350KG+ | C89: 700KG+ | D89: 1000KG+ | E89: 1500KG+ | F89: 2000KG+ | G89: 3000KG+ | H89: 4000KG+ | I89: 5000KG+ | J89: 6000KG+ | K89: 6吨以上单询
A90: 60106邮编 （50miles内商业地址） | B90: 11.4 | C90: 8.9 | D90: 7.9 | E90: 7.4 | F90: 6.9 | G90: 6.9 | H90: 6.9 | I90: 6.7 | J90: 6.7 | K90: 单询
A91: 下单渠道：芝加哥 私人卡派/美中专线—50英里内 注意：务必找我司业务员确认是否为50英里范围内
A92: 60106邮编 （80-300公里） | B92: 13.9 | C92: 11.4 | D92: 10.4 | E92: 9.9 | F92: 9.4 | G92: 9.4 | H92: 9.4 | I92: 9.2 | J92: 9.2 | K92: 单询 | L92: 300公里以上，单询
A93: 下单渠道：芝加哥 私人卡派/美中专线—（80-300公里）
A94: 双清包税； 体积除6000； 不分泡； 如打木托需要商检费300/票 ； 报关费350/票；
A95: 私人住宅地址+1元/KG； 商业地址不用+1元/KG； 最长单边长度<100cm；第二边长<75cm，则视为普通箱规；没有超大附加费！！任意边长超出则视为超大件，超大附加费单询，一般距离越远附加费越贵！！
A96: 远距离超大件，务必上报准确的箱规尺寸，方便报价！ 如因打托货物或者远距离超大件，未通知我司，直接发货后被装走的，后期出现尾端价格过高导致亏损，客户自行承担！！！！
A97: 货重比：整票实重大于100公斤以上，享受重货比优惠：整票实重/整票方数=货重比 1:190 减0.2元 / 1:200 减0.3元 / 1:220 减0.5元 / 1:250 减0.8元 / 1:300 减1.2元 / 1:350 减1.5元 / 1:400 减1.8元 / 1:450 减2元 / 1:500 减2.2元 / 1:550 减2.5元 / ；超550以上单询；
A102: 以下为商业地址/私人住宅地址查询方法（也可以找我司客服查询是否为商业地址）：
A103: 网址：https://smartystreets.com/products/single-address
A104: 打开网站进入界面如下图
A122: 下滑一点看到这个页面
A140: 步骤1.以美国为例，选择美国.
A141: 步骤2.从Address type中选择Freeform address格式
A142: 步骤3.输入要查询地址
... A195: 输入查询后是Residential，也就是住宅地址.

Sheet 美国转加拿大海派
A1: 华东区-同行价格表
A2: 加拿大 美森海派 极速达 18天赔付（指定正班船CLX，美国稳定提取）
A3: FBA仓库/重量 | B3: 21KG+ | C3: 51KG+ | D3: 71KG+ | E3: 101KG+ | F3: 备注 | G3: 下单渠道：加拿大 美森海派 极速达
A4: 亚马逊 （多伦多、渥太华）-只接FBA （YYZ/YOO/YHM/YOW/YXU1) | B4: 21.5 | C4: 18.5 | D4: 17.5 | E4: 16.5 | F4: 开船后第二天开始算18天提取 第19天开始赔偿1元/kg*天 最高赔付3元每公斤 （如遇海关查验，赔偿1元每公斤） （如遇节假日、码头停摆、港口罢工等非人为因素，不参与赔付） | G4: 一截三开
A5: 亚马逊 （温哥华、卡尔加里）-只接FBA （YVR/YXX/YYC/YEG ） | B5: 22.5 | C5: 19.5 | D5: 18.5 | E5: 17.5
A6: 其他亚马逊仓库 | B6: 23.5 | C6: 20.5 | D6: 19.5 | E6: 18.5
A7: 商业地址/私人地址 | B7: 24.5 | C7: 21.5 | D7: 20.5 | E7: 19.5
A8: 重货比优惠：整票实重大于100公斤以上，1:220 减0.2元 / 1:250 减0.5元 / 1:300 减1元 / 1:400以上 减2元；超500以上单询；整票实重/整票方数=货重比
A10: 加拿大 美森海派 限时达 20天赔付（指定加班船MAX，美国稳定提取）
A11: FBA仓库/重量 | B11: 21KG+ | C11: 51KG+ | D11: 71KG+ | E11: 101KG+ | F11: 备注 | G11: 下单渠道：加拿大 美森海派 限时达
A12: 亚马逊 （多伦多、渥太华）-只接FBA （YYZ/YOO/YHM/YOW/YXU1) | B12: 20.5 | C12: 17.5 | D12: 16.5 | E12: 15.5 | F12: 开船后第二天开始算20天提取 第21天开始赔偿1元/kg*天 最高赔付3元每公斤 （如遇海关查验，赔偿1元每公斤） （如遇节假日、码头停摆、港口罢工等非人为因素，不参与赔付） | G12: 二截四开
A13: 亚马逊 （温哥华、卡尔加里）-只接FBA （YVR/YXX/YYC/YEG ） | B13: 21.5 | C13: 18.5 | D13: 17.5 | E13: 16.5
A14: 其他亚马逊仓库 | B14: 22.5 | C14: 19.5 | D14: 18.5 | E14: 17.5
A15: 商业地址/私人地址 | B15: 23.5 | C15: 20.5 | D15: 19.5 | E15: 18.5
A16: 重货比优惠：整票实重大于100公斤以上，1:220 减0.2元 / 1:250 减0.5元 / 1:300 减1元 / 1:400以上 减2元；超500以上单询；整票实重/整票方数=货重比
A18: 加拿大 EXX 限时达 20天赔付（美国稳定提取）
A19: FBA仓库/重量 | B19: 21KG+ | C19: 51KG+ | D19: 71KG+ | E19: 101KG+ | F19: 备注 | G19: 下单渠道：加拿大 EXX海派 限时达
A20: 亚马逊 （多伦多、渥太华）-只接FBA （YYZ/YOO/YHM/YOW/YXU1) | B20: 19.5 | C20: 16.5 | D20: 15.5 | E20: 14.5 | F20: 开船后第二天开始算20天提取 第21天开始赔偿1元/kg*天 最高赔付3元每公斤 （如遇海关查验，赔偿1元每公斤） （如遇节假日、码头停摆、港口罢工等非人为因素，不参与赔付） | G20: 二截四开
A21: 亚马逊 （温哥华、卡尔加里）-只接FBA （YVR/YXX/YYC/YEG ） | B21: 20.5 | C21: 17.5 | D21: 16.5 | E21: 15.5
A22: 其他亚马逊仓库 | B22: 21.5 | C22: 18.5 | D22: 17.5 | E22: 16.5
A23: 商业地址/私人地址 | B23: 22.5 | C23: 19.5 | D23: 18.5 | E23: 17.5
A24: 重货比优惠：整票实重大于100公斤以上，1:220 减0.2元 / 1:250 减0.5元 / 1:300 减1元 / 1:400以上 减2元；超500以上单询；整票实重/整票方数=货重比
A26: 加拿大 以星限时达 20天赔付（带车架，美国稳定提取）
A27: FBA仓库/重量 | B27: 21KG+ | C27: 51KG+ | D27: 71KG+ | E27: 101KG+ | F27: 备注 | G27: 下单渠道：加拿大 以星限时达海派
A28: 亚马逊 （多伦多、渥太华）-只接FBA （YYZ/YOO/YHM/YOW/YXU1) | B28: 19 | C28: 16 | D28: 15 | E28: 14 | F28: 开船后第二天开始算20天提取 第21天开始赔偿1元/kg*天 最高赔付3元每公斤 （如遇海关查验，赔偿1元每公斤） （如遇节假日、码头停摆、港口罢工等非人为因素，不参与赔付） | G28: 二截四开
A29: 亚马逊 （温哥华、卡尔加里）-只接FBA （YVR/YXX/YYC/YEG ） | B29: 20 | C29: 17 | D29: 16 | E29: 15
A30: 其他亚马逊仓库 | B30: 21 | C30: 18 | D30: 17 | E30: 16
A31: 商业地址/私人地址 | B31: 22 | C31: 19 | D31: 18 | E31: 17
A32: 重货比优惠：整票实重大于100公斤以上，1:220 减0.2元 / 1:250 减0.5元 / 1:300 减1元 / 1:400以上 减2元；超500以上单询；整票实重/整票方数=货重比
A34: 加拿大 统配海派 定时达 25天赔付（COSCO/EMC OA统配，美国稳定提取）
A35: 国家/重量 | B35: 21KG+ | C35: 51KG+ | D35: 71KG+ | E35: 101KG+ | F35: 备注 | G35: 下单渠道：加拿大 统配海派 定时达
A36: 亚马逊 （多伦多、渥太华）-只接FBA （YYZ/YOO/YHM/YOW/YXU1) | B36: 18.5 | C36: 15.5 | D36: 14.5 | E36: 13.5 | F36: 开船后第二天开始算25天提取 第26天开始赔偿0.5元/kg*天 最高赔付2元每公斤 （如遇海关查验，赔偿1元每公斤） （如遇节假日、码头停摆、港口罢工等非人为因素，不参与赔付） | G36: 以COSCO/EMC等OA船开船时间为准
A37: 亚马逊 （温哥华、卡尔加里）-只接FBA （YVR/YXX/YYC/YEG ） | B37: 19.5 | C37: 16.5 | D37: 15.5 | E37: 14.5 | G37: 每周固定周四开船的森罗SML我们也会选择，时效堪比OA普船！
A38: 其他亚马逊仓库 | B38: 21.5 | C38: 18.5 | D38: 17.5 | E38: 16.5
A39: 商业地址/私人地址 | B39: 22.5 | C39: 19.5 | D39: 18.5 | E39: 17.5
A40: 重货比优惠：整票实重大于100公斤以上，1:220 减0.2元 / 1:250 减0.5元 / 1:300 减1元 / 1:400以上 减2元；超500以上单询；整票实重/整票方数=货重比
A41: 单件最低计费12KG，单件不超22公斤； // 后程UPS派送； // FBA偏远+2/KG，商业地址偏远+3元/KG，最低收190元一票； // 报关件，收取350元/票
A42: 此渠道是美国洛杉矶，UPS提取后，经过加拿大海关进行清关，再进入加拿大区域转运的；加拿大的关税是比较高的！！ 主要的附加费：纺织品，皮革，箱包，鞋服包加2元/KG
A43: 注意以下省份区域无法进行UPS派送：（Nunavut 邮编X0A - X0C） （Northwest Territories 邮编X0E - X9Z） （Yukon 邮编Y0A - Y9Z）
A44: 本渠道丢件赔偿100美金/件！！！！！！！！！

Sheet 奥克兰卡派专线
A1: 华东区-奥克兰卡派专线
A2: 奥克兰 直航 散货特价
A3: FBA仓库代码 | B3: 目的邮编 | C3: 12KG+ | D3: 整柜直送 整柜价 （我司仓库装柜，全包到门） | E3: 签收时效 | F3: 配送方式 | G3: 下单渠道：奥克兰普船海卡/散货特价
A4: SCK4 | B4: 95215 | C4: 4.8 | D4: / | E4: 25-35天 | F4: 专车配送 | G4: 指定船型：OA船、EXX船
A5: SCK1 | B5: 95215-9465 | C5: 4.8 | D5: / | E5: 25-35天 | F5: 专车配送
A6: SCK3 | B6: 95336 | C6: 4.8 | D6: / | E6: 25-35天 | F6: 专车配送
A7: SMF3 | B7: 95206 | C7: 4.8 | D7: / | E7: 25-35天 | F7: 专车配送
A8: OAK3 | B8: 95363 | C8: 4.8 | D8: / | E8: 25-35天 | F8: 专车配送
A9: SJC7 | B9: 95377 | C9: 4.8 | D9: / | E9: 25-35天 | F9: 专车配送
A10: SCK8 | B10: 94561 | C10: 4.8 | D10: / | E10: 25-35天 | F10: 专车配送
A11: SCK8 | B11: 94561 | C11: 4.8 | D11: / | E11: 25-35天 | F11: 专车配送
A12: TCY2 | B12: 95215 | C12: 4.8 | D12: / | E12: 25-35天 | F12: 专车配送
A13: SMF6 | B13: 95837 | C13: 4.8 | D13: / | E13: 25-35天 | F13: 专车配送
A14: SMF7 | B14: 95688 | C14: 4.8 | D14: / | E14: 25-35天 | F14: 专车配送
A15: MCC1 | B15: 95742 | C15: 4.8 | D15: / | E15: 25-35天 | F15: 专车配送
A16: MCE1 | B16: 95380-9684 | C16: 4.8 | D16: / | E16: 25-35天 | F16: 专车配送
A17: HLI2 | B17: 95023 | C17: 4.8 | D17: / | E17: 25-35天 | F17: 专车配送
A18: FAT2 | B18: 93725 | C18: 5.1 | D18: / | E18: 25-35天 | F18: 专车配送
A19: RNO4 | B19: 89506 | C19: 5.4 | D19: / | E19: 25-35天 | F19: 专车配送
A20: 货重比：整票实重大于100公斤以上，享受重货比优惠：整票实重/整票方数=货重比 1:190 减0.2元 / 1:200 减0.3元 / 1:220 减0.5元 / 1:250 减0.8元 / 1:300 减1.2元 / 1:350 减1.5元 / 1:400 减1.8元 / 1:450 减2元 / 1:500 减2.2元 / 1:550 减2.5元 / ；超550以上单询；

Sheet UPS海运小包特价
A1: UPS海运小包特价
A2: 海派 美森正班极速达 16天赔付 海运小包 （CLX）
B3: 3KG+ | C3: 5KG+ | D3: 7KG+ | E3: 9KG+ | F3: 11KG+ | G3: 备注
A4: 邮编 8 9 | B4: 30.5 | C4: 24.5 | D4: 23.5 | E4: 21.5 | F4: 20.5 | G4: 开船后第二天开始算16天提取 第17天开始赔偿1元/kg*天 最高赔付2元每公斤 （如遇海关查验，赔偿1元每公斤） （如遇节假日、码头停摆、港口罢工等非人为因素，不参与赔付）
A5: 邮编5 6 7 | B5: 31.5 | C5: 25.5 | D5: 24.5 | E5: 23.5 | F5: 22.5
A6: 邮编 0 1 2 3 4 | B6: 32.5 | C6: 27.5 | D6: 26.5 | E6: 25.5 | F6: 25.5
A7: 下单渠道：海派 美森正班极速达 16天赔付 海运小包 （CLX）
A9: 海派 美森加班限时达 18天赔付 海运小包 （MAX）
B10: 3KG+ | C10: 5KG+ | D10: 7KG+ | E10: 9KG+ | F10: 11KG+ | G10: 备注
A11: 邮编 8 9 | B11: 29.5 | C11: 23.5 | D11: 22.5 | E11: 20.5 | F11: 19.5 | G11: 开船后第二天开始算18天提取 第19天开始赔偿1元/kg*天 最高赔付2元每公斤 （如遇海关查验，赔偿1元每公斤） （如遇节假日、码头停摆、港口罢工等非人为因素，不参与赔付）
A12: 邮编5 6 7 | B12: 30.5 | C12: 24.5 | D12: 23.5 | E12: 22.5 | F12: 21.5
A13: 邮编 0 1 2 3 4 | B13: 31.5 | C13: 26.5 | D13: 25.5 | E13: 24.5 | F13: 24.5
A14: 下单渠道：海派 美森加班限时达 18天赔付 海运小包
A16: 海派 EXX限时达 18天赔付 海运小包
B17: 3KG+ | C17: 5KG+ | D17: 7KG+ | E17: 9KG+ | F17: 11KG+ | G17: 备注
A18: 邮编 8 9 | B18: 28.5 | C18: 22.5 | D18: 21.5 | E18: 19.5 | F18: 18.5 | G18: 开船后第二天开始算18天提取 第19天开始赔偿0.5元/kg*天 最高赔付1元每公斤 （如遇海关查验，赔偿0.5元每公斤） （如遇节假日、码头停摆、港口罢工等非人为因素，不参与赔付）
A19: 邮编5 6 7 | B19: 29.5 | C19: 23.5 | D19: 22.5 | E19: 21.5 | F19: 20.5
A20: 邮编 0 1 2 3 4 | B20: 30.5 | C20: 25.5 | D20: 24.5 | E20: 23.5 | F20: 23.5
A21: 下单渠道：海派 EXX限时达 18天赔付 海运小包
A23: 海派 以星限时达 18天赔付 海运小包 （带车架）
B24: 3KG+ | C24: 5KG+ | D24: 7KG+ | E24: 9KG+ | F24: 11KG+ | G24: 备注
A25: 邮编 8 9 | B25: 28 | C25: 22 | D25: 21 | E25: 19 | F25: 18 | G25: 开船后第二天开始算18天提取 第19天开始赔偿0.5元/kg*天 最高赔付1元每公斤 （如遇海关查验，赔偿0.5元每公斤） （如遇节假日、码头停摆、港口罢工等非人为因素，不参与赔付）
A26: 邮编5 6 7 | B26: 29 | C26: 23 | D26: 22 | E26: 21 | F26: 20
A27: 邮编 0 1 2 3 4 | B27: 30 | C27: 25 | D27: 24 | E27: 23 | F27: 23
A28: 下单渠道：海派 以星限时达 18天赔付 海运小包
A30: 海派 OA快普 海运小包
B31: 3KG+ | C31: 5KG+ | D31: 7KG+ | E31: 9KG+ | F31: 11KG+ | G31: 备注
A32: 邮编 8 9 | B32: 27.5 | C32: 21.5 | D32: 20.5 | E32: 18.5 | F32: 17.5 | G32: 20-25天
A33: 邮编5 6 7 | B33: 28.5 | C33: 22.5 | D33: 21.5 | E33: 20.5 | F33: 19.5
A34: 邮编 0 1 2 3 4 | B34: 29.5 | C34: 24.5 | D34: 23.5 | E34: 22.5 | F34: 22.5
A35: 下单渠道：海派 OA快普 海运小包
A36: 本渠道没有货重比优惠，丢件按照40元/公斤赔付
A37: 非FBA地址：整票+5元/KG； FBA地址和商业地址：无附加费 偏远收费：30元/件 商检费300/票 报关件350/票

Sheet 美西海卡不包税
A1: 华东区-美西海卡-不包税 各渠道汇总表 注意：不接0税率产品！！！！
A2: FBA仓库代码 目的邮编 | E2: 下单渠道： 海卡/美森正班船-不包税 | G2: 下单渠道： 海卡/美森加班船-不包税 | I2: 下单渠道： 海卡/EXX-不包税 | K2: 下单渠道： 海卡/以星带车架-不包税 | M2: 下单渠道： 海卡/合德快提-不包税 | O2: 下单渠道： 海卡/COSCO、EMC定提 普船统配-不包税 | Q2: 下单渠道： 海卡/普船经济线-不包税
A3: ONT8 | B3: 92551 | C3: A【一区】 12KG+ | D3: 1方起收 | E3: 1350 | F3: 15-22天 | G3: 1250 | H3: 17-23天 | I3: 950 | J3: 25天左右 | K3: 750 | L3: 25天左右 | M3: 800 | N3: 25天左右 | O3: 700 | P3: 20-25天 | Q3: 650 | R3: 25-30天
A4: LAX9 | B4: 92337 | E4: 1350 | F4: 15-22天 | G4: 1250 | H4: 17-23天 | I4: 950 | J4: 25天左右 | K4: 750 | L4: 25天左右 | M4: 800 | N4: 25天左右 | O4: 700 | P4: 20-25天 | Q4: 650 | R4: 25-30天
A5: LGB8 | B5: 92376 | E5: 1350 | F5: 15-22天 | G5: 1250 | H5: 17-23天 | I5: 950 | J5: 25天左右 | K5: 750 | L5: 25天左右 | M5: 800 | N5: 25天左右 | O5: 700 | P5: 20-25天 | Q5: 650 | R5: 25-30天
A6: SBD1 | B6: 92316-3819 | E6: 1350 | F6: 15-22天 | G6: 1250 | H6: 17-23天 | I6: 950 | J6: 25天左右 | K6: 750 | L6: 25天左右 | M6: 800 | N6: 25天左右 | O6: 700 | P6: 20-25天 | Q6: 650 | R6: 25-30天
A7: SNA4 | B7: 92376 | C7: B【一区】 12KG+ | D7: 1方起收 | E7: 1400 | F7: 15-22天 | G7: 1300 | H7: 17-23天 | I7: 1000 | J7: 25天左右 | K7: 800 | L7: 25天左右 | M7: 850 | N7: 25天左右 | O7: 750 | P7: 20-25天 | Q7: 700 | R7: 25-30天
A8: SBD2 | B8: 92408 | E8: 1400 | F8: 15-22天 | G8: 1300 | H8: 17-23天 | I8: 1000 | J8: 25天左右 | K8: 800 | L8: 25天左右 | M8: 850 | N8: 25天左右 | O8: 750 | P8: 20-25天 | Q8: 700 | R8: 25-30天
A9: SBD3 | B9: 92407 | E9: 1400 | F9: 15-22天 | G9: 1300 | H9: 17-23天 | I9: 1000 | J9: 25天左右 | K9: 800 | L9: 25天左右 | M9: 850 | N9: 25天左右 | O9: 750 | P9: 20-25天 | Q9: 700 | R9: 25-30天
A10: LGB4 | B10: 92374 | E10: 1400 | F10: 15-22天 | G10: 1300 | H10: 17-23天 | I10: 1000 | J10: 25天左右 | K10: 800 | L10: 25天左右 | M10: 850 | N10: 25天左右 | O10: 750 | P10: 20-25天 | Q10: 700 | R10: 25-30天
A11: LGB6 | B11: 92518-1513 | E11: 1400 | F11: 15-22天 | G11: 1300 | H11: 17-23天 | I11: 1000 | J11: 25天左右 | K11: 800 | L11: 25天左右 | M11: 850 | N11: 25天左右 | O11: 750 | P11: 20-25天 | Q11: 700 | R11: 25-30天
A12: LGB9 | B12: 90810 | E12: 1400 | F12: 15-22天 | G12: 1300 | H12: 17-23天 | I12: 1000 | J12: 25天左右 | K12: 800 | L12: 25天左右 | M12: 850 | N12: 25天左右 | O12: 750 | P12: 20-25天 | Q12: 700 | R12: 25-30天
A13: ONT2 | B13: 92408-0123 | E13: 1400 | F13: 15-22天 | G13: 1300 | H13: 17-23天 | I13: 1000 | J13: 25天左右 | K13: 800 | L13: 25天左右 | M13: 850 | N13: 25天左右 | O13: 750 | P13: 20-25天 | Q13: 700 | R13: 25-30天
A14: ONT6 | B14: 92551-9561 | E14: 1400 | F14: 15-22天 | G14: 1300 | H14: 17-23天 | I14: 1000 | J14: 25天左右 | K14: 800 | L14: 25天左右 | M14: 850 | N14: 25天左右 | O14: 750 | P14: 20-25天 | Q14: 700 | R14: 25-30天
A15: ONT9 | B15: 92374 | E15: 1400 | F15: 15-22天 | G15: 1300 | H15: 17-23天 | I15: 1000 | J15: 25天左右 | K15: 800 | L15: 25天左右 | M15: 850 | N15: 25天左右 | O15: 750 | P15: 20-25天 | Q15: 700 | R15: 25-30天
A16: XLX7 | B16: 92394 | E16: 1400 | F16: 15-22天 | G16: 1300 | H16: 17-23天 | I16: 1000 | J16: 25天左右 | K16: 800 | L16: 25天左右 | M16: 850 | N16: 25天左右 | O16: 750 | P16: 20-25天 | Q16: 700 | R16: 25-30天
A17: IUSJ | B17: 92223 | E17: 1400 | F17: 15-22天 | G17: 1300 | H17: 17-23天 | I17: 1000 | J17: 25天左右 | K17: 800 | L17: 25天左右 | M17: 850 | N17: 25天左右 | O17: 750 | P17: 20-25天 | Q17: 700 | R17: 25-30天
A18: IUSQ | B18: 92374 | E18: 1400 | F18: 15-22天 | G18: 1300 | H18: 17-23天 | I18: 1000 | J18: 25天左右 | K18: 800 | L18: 25天左右 | M18: 850 | N18: 25天左右 | O18: 750 | P18: 20-25天 | Q18: 700 | R18: 25-30天
A19: IUSP | B19: 92344 | E19: 1400 | F19: 15-22天 | G19: 1300 | H19: 17-23天 | I19: 1000 | J19: 25天左右 | K19: 800 | L19: 25天左右 | M19: 850 | N19: 25天左右 | O19: 750 | P19: 20-25天 | Q19: 700 | R19: 25-30天
A20: POC1 | B20: 92336-1123 | E20: 1400 | F20: 15-22天 | G20: 1300 | H20: 17-23天 | I20: 1000 | J20: 25天左右 | K20: 800 | L20: 25天左右 | M20: 850 | N20: 25天左右 | O20: 750 | P20: 20-25天 | Q20: 700 | R20: 25-30天
A21: POC2 | B21: 91761 | E21: 1400 | F21: 15-22天 | G21: 1300 | H21: 17-23天 | I21: 1000 | J21: 25天左右 | K21: 800 | L21: 25天左右 | M21: 850 | N21: 25天左右 | O21: 750 | P21: 20-25天 | Q21: 700 | R21: 25-30天
A22: POC3 | B22: 92509 | E22: 1400 | F22: 15-22天 | G22: 1300 | H22: 17-23天 | I22: 1000 | J22: 25天左右 | K22: 800 | L22: 25天左右 | M22: 850 | N22: 25天左右 | O22: 750 | P22: 20-25天 | Q22: 700 | R22: 25-30天
A23: LAS1 | B23: 89044 | C23: A【二区】 12KG+ | D23: 1方起收 | E23: 1450 | F23: 15-22天 | G23: 1350 | H23: 17-23天 | I23: 1050 | J23: 28天左右 | K23: 850 | L23: 28天左右 | M23: 900 | N23: 28天左右 | O23: 800 | P23: 23-30天 | Q23: 750 | R23: 25-35天
A24: VGT2 | B24: 89115 | E24: 1450 | F24: 15-22天 | G24: 1350 | H24: 17-23天 | I24: 1050 | J24: 28天左右 | K24: 850 | L24: 28天左右 | M24: 900 | N24: 28天左右 | O24: 800 | P24: 23-30天 | Q24: 750 | R24: 25-35天
A25: GYR2 | B25: 85395-7672 | E25: 1450 | F25: 15-22天 | G25: 1350 | H25: 17-23天 | I25: 1050 | J25: 28天左右 | K25: 850 | L25: 28天左右 | M25: 900 | N25: 28天左右 | O25: 800 | P25: 23-30天 | Q25: 750 | R25: 25-35天
A26: GYR3 | B26: 85043 | E26: 1450 | F26: 15-22天 | G26: 1350 | H26: 17-23天 | I26: 1050 | J26: 28天左右 | K26: 850 | L26: 28天左右 | M26: 900 | N26: 28天左右 | O26: 800 | P26: 23-30天 | Q26: 750 | R26: 25-35天
A27: SMF3 | B27: 95206-8202 | E27: 1450 | F27: 15-22天 | G27: 1350 | H27: 17-23天 | I27: 1050 | J27: 28天左右 | K27: 850 | L27: 28天左右 | M27: 900 | N27: 28天左右 | O27: 800 | P27: 23-30天 | Q27: 750 | R27: 25-35天
A28: SCK4 | B28: 95215-8354 | E28: 1450 | F28: 15-22天 | G28: 1350 | H28: 17-23天 | I28: 1050 | J28: 28天左右 | K28: 850 | L28: 28天左右 | M28: 900 | N28: 28天左右 | O28: 800 | P28: 23-30天 | Q28: 750 | R28: 25-35天
A29: MIT2 | B29: 93263 | E29: 1450 | F29: 15-22天 | G29: 1350 | H29: 17-23天 | I29: 1050 | J29: 28天左右 | K29: 850 | L29: 28天左右 | M29: 900 | N29: 28天左右 | O29: 800 | P29: 23-30天 | Q29: 750 | R29: 25-35天
A30: GEU2 | B30: 85340 | E30: 1450 | F30: 15-22天 | G30: 1350 | H30: 17-23天 | I30: 1050 | J30: 28天左右 | K30: 850 | L30: 28天左右 | M30: 900 | N30: 28天左右 | O30: 800 | P30: 23-30天 | Q30: 750 | R30: 25-35天
A31: GEU3 | B31: 85326 | E31: 1450 | F31: 15-22天 | G31: 1350 | H31: 17-23天 | I31: 1050 | J31: 28天左右 | K31: 850 | L31: 28天左右 | M31: 900 | N31: 28天左右 | O31: 800 | P31: 23-30天 | Q31: 750 | R31: 25-35天
A32: GEU5 | B32: 85395 | E32: 1450 | F32: 15-22天 | G32: 1350 | H32: 17-23天 | I32: 1050 | J32: 28天左右 | K32: 850 | L32: 28天左右 | M32: 900 | N32: 28天左右 | O32: 800 | P32: 23-30天 | Q32: 750 | R32: 25-35天
A33: HLI2 | B33: 95023 | E33: 1450 | F33: 15-22天 | G33: 1350 | H33: 17-23天 | I33: 1050 | J33: 28天左右 | K33: 850 | L33: 28天左右 | M33: 900 | N33: 28天左右 | O33: 800 | P33: 23-30天 | Q33: 750 | R33: 25-35天
A34: TCY1 | B34: 95206 | E34: 1450 | F34: 15-22天 | G34: 1350 | H34: 17-23天 | I34: 1050 | J34: 28天左右 | K34: 850 | L34: 28天左右 | M34: 900 | N34: 28天左右 | O34: 800 | P34: 23-30天 | Q34: 750 | R34: 25-35天
A35: TCY2 | B35: 95215 | E35: 1450 | F35: 15-22天 | G35: 1350 | H35: 17-23天 | I35: 1050 | J35: 28天左右 | K35: 850 | L35: 28天左右 | M35: 900 | N35: 28天左右 | O35: 800 | P35: 23-30天 | Q35: 750 | R35: 25-35天
A36: SCK8 | B36: 94561 | E36: 1450 | F36: 15-22天 | G36: 1350 | H36: 17-23天 | I36: 1050 | J36: 28天左右 | K36: 850 | L36: 28天左右 | M36: 900 | N36: 28天左右 | O36: 800 | P36: 23-30天 | Q36: 750 | R36: 25-35天
A37: SMF6 | B37: 95837 | C37: B【二区】 12KG+ | D37: 1方起收 | E37: 1500 | F37: 15-22天 | G37: 1400 | H37: 17-23天 | I37: 1100 | J37: 28天左右 | K37: 900 | L37: 28天左右 | M37: 950 | N37: 28天左右 | O37: 850 | P37: 23-30天 | Q37: 800 | R37: 25-35天
A38: SJC7 | B38: 95377 | E38: 1500 | F38: 15-22天 | G38: 1400 | H38: 17-23天 | I38: 1100 | J38: 28天左右 | K38: 900 | L38: 28天左右 | M38: 950 | N38: 28天左右 | O38: 850 | P38: 23-30天 | Q38: 800 | R38: 25-35天
A39: OAK3 | B39: 95363 | E39: 1500 | F39: 15-22天 | G39: 1400 | H39: 17-23天 | I39: 1100 | J39: 28天左右 | K39: 900 | L39: 28天左右 | M39: 950 | N39: 28天左右 | O39: 850 | P39: 23-30天 | Q39: 800 | R39: 25-35天
A40: SCK1 | B40: 95215-9465 | E40: 1500 | F40: 15-22天 | G40: 1400 | H40: 17-23天 | I40: 1100 | J40: 28天左右 | K40: 900 | L40: 28天左右 | M40: 950 | N40: 28天左右 | O40: 850 | P40: 23-30天 | Q40: 800 | R40: 25-35天
A41: MCE1 | B41: 95380 | E41: 1500 | F41: 15-22天 | G41: 1400 | H41: 17-23天 | I41: 1100 | J41: 28天左右 | K41: 900 | L41: 28天左右 | M41: 950 | N41: 28天左右 | O41: 850 | P41: 23-30天 | Q41: 800 | R41: 25-35天
A42: FAT2 | B42: 93291 | E42: 1500 | F42: 15-22天 | G42: 1400 | H42: 17-23天 | I42: 1100 | J42: 28天左右 | K42: 900 | L42: 28天左右 | M42: 950 | N42: 28天左右 | O42: 850 | P42: 23-30天 | Q42: 800 | R42: 25-35天
A43: LAS6 | B43: 89115 | E43: 1500 | F43: 15-22天 | G43: 1400 | H43: 17-23天 | I43: 1100 | J43: 28天左右 | K43: 900 | L43: 28天左右 | M43: 950 | N43: 28天左右 | O43: 850 | P43: 23-30天 | Q43: 800 | R43: 25-35天
A44: PHX5 | B44: 85338 | E44: 1500 | F44: 15-22天 | G44: 1400 | H44: 17-23天 | I44: 1100 | J44: 28天左右 | K44: 900 | L44: 28天左右 | M44: 950 | N44: 28天左右 | O44: 850 | P44: 23-30天 | Q44: 800 | R44: 25-35天
A45: PHX7 | B45: 85043 | E45: 1500 | F45: 15-22天 | G45: 1400 | H45: 17-23天 | I45: 1100 | J45: 28天左右 | K45: 900 | L45: 28天左右 | M45: 950 | N45: 28天左右 | O45: 850 | P45: 23-30天 | Q45: 800 | R45: 25-35天
A46: BFL2 | B46: 93263-2246 | E46: 1500 | F46: 15-22天 | G46: 1400 | H46: 17-23天 | I46: 1100 | J46: 28天左右 | K46: 900 | L46: 28天左右 | M46: 950 | N46: 28天左右 | O46: 850 | P46: 23-30天 | Q46: 800 | R46: 25-35天
A47: ABQ2 | B47: 87031 | C47: A【三区】 12KG+ | D47: 1方起收 | E47: 1800 | F47: 20-28天 | G47: 1700 | H47: 20-30天 | I47: 1400 | J47: 27-30天 | K47: 1220 | L47: 30-33天 | M47: 1270 | N47: 30-33天 | O47: 1150 | P47: 25-35天 | Q47: 1100 | R47: 25-38天
A48: FTW1 | B48: 75241 | E48: 1800 | F48: 20-28天 | G48: 1700 | H48: 20-30天 | I48: 1400 | J48: 27-30天 | K48: 1220 | L48: 30-33天 | M48: 1270 | N48: 30-33天 | O48: 1150 | P48: 25-35天 | Q48: 1100 | R48: 25-38天
A49: IUSF | B49: 75241 | E49: 1800 | F49: 20-28天 | G49: 1700 | H49: 20-30天 | I49: 1400 | J49: 27-30天 | K49: 1220 | L49: 30-33天 | M49: 1270 | N49: 30-33天 | O49: 1150 | P49: 25-35天 | Q49: 1100 | R49: 25-38天
A50: DFW6 | B50: 75019 | E50: 1800 | F50: 20-28天 | G50: 1700 | H50: 20-30天 | I50: 1400 | J50: 27-30天 | K50: 1220 | L50: 30-33天 | M50: 1270 | N50: 30-33天 | O50: 1150 | P50: 25-35天 | Q50: 1100 | R50: 25-38天
A51: HOU8 | B51: 77423 | E51: 1800 | F51: 20-28天 | G51: 1700 | H51: 20-30天 | I51: 1400 | J51: 27-30天 | K51: 1220 | L51: 30-33天 | M51: 1270 | N51: 30-33天 | O51: 1150 | P51: 25-35天 | Q51: 1100 | R51: 25-38天
A52: IAH3 | B52: 77032 | E52: 1800 | F52: 20-28天 | G52: 1700 | H52: 20-30天 | I52: 1400 | J52: 27-30天 | K52: 1220 | L52: 30-33天 | M52: 1270 | N52: 30-33天 | O52: 1150 | P52: 25-35天 | Q52: 1100 | R52: 25-38天
A53: AMA1 | B53: 79108 | E53: 1800 | F53: 20-28天 | G53: 1700 | H53: 20-30天 | I53: 1400 | J53: 27-30天 | K53: 1220 | L53: 30-33天 | M53: 1270 | N53: 30-33天 | O53: 1150 | P53: 25-35天 | Q53: 1100 | R53: 25-38天
A54: SAT1 | B54: 78154 | E54: 1800 | F54: 20-28天 | G54: 1700 | H54: 20-30天 | I54: 1400 | J54: 27-30天 | K54: 1220 | L54: 30-33天 | M54: 1270 | N54: 30-33天 | O54: 1150 | P54: 25-35天 | Q54: 1100 | R54: 25-38天
A55: SAT4 | B55: 78245 | E55: 1800 | F55: 20-28天 | G55: 1700 | H55: 20-30天 | I55: 1400 | J55: 27-30天 | K55: 1220 | L55: 30-33天 | M55: 1270 | N55: 30-33天 | O55: 1150 | P55: 25-35天 | Q55: 1100 | R55: 25-38天
A56: PSC2 | B56: 99301 | C56: B【三区】 12KG+ | D56: 1方起收 | E56: 1800 | F56: 20-28天 | G56: 1700 | H56: 20-30天 | I56: 1400 | J56: 27-30天 | K56: 1220 | L56: 30-33天 | M56: 1270 | N56: 30-33天 | O56: 1150 | P56: 25-35天 | Q56: 1100 | R56: 25-38天
A57: IND9 | B57: 46143 | E57: 1800 | F57: 20-28天 | G57: 1700 | H57: 20-30天 | I57: 1400 | J57: 27-30天 | K57: 1220 | L57: 30-33天 | M57: 1270 | N57: 30-33天 | O57: 1150 | P57: 25-35天 | Q57: 1100 | R57: 25-38天
A58: MDW2 | B58: 60433 | E58: 1800 | F58: 20-28天 | G58: 1700 | H58: 20-30天 | I58: 1400 | J58: 27-30天 | K58: 1220 | L58: 30-33天 | M58: 1270 | N58: 30-33天 | O58: 1150 | P58: 25-35天 | Q58: 1100 | R58: 25-38天
A59: FWA4 | B59: 46809-9771 | E59: 1800 | F59: 20-28天 | G59: 1700 | H59: 20-30天 | I59: 1400 | J59: 27-30天 | K59: 1220 | L59: 30-33天 | M59: 1270 | N59: 30-33天 | O59: 1150 | P59: 25-35天 | Q59: 1100 | R59: 25-38天
A60: MEM1 | B60: 38118 | E60: 1800 | F60: 20-28天 | G60: 1700 | H60: 20-30天 | I60: 1400 | J60: 27-30天 | K60: 1220 | L60: 30-33天 | M60: 1270 | N60: 30-33天 | O60: 1150 | P60: 25-35天 | Q60: 1100 | R60: 25-38天
A61: MQJ1 | B61: 46140 | E61: 1800 | F61: 20-28天 | G61: 1700 | H61: 20-30天 | I61: 1400 | J61: 27-30天 | K61: 1220 | L61: 30-33天 | M61: 1270 | N61: 30-33天 | O61: 1150 | P61: 25-35天 | Q61: 1100 | R61: 25-38天
A62: RFD2 | B62: 60142 | E62: 1800 | F62: 20-28天 | G62: 1700 | H62: 20-30天 | I62: 1400 | J62: 27-30天 | K62: 1220 | L62: 30-33天 | M62: 1270 | N62: 30-33天 | O62: 1150 | P62: 25-35天 | Q62: 1100 | R62: 25-38天
A63: RFD4 | B63: 60142 | E63: 1800 | F63: 20-28天 | G63: 1700 | H63: 20-30天 | I63: 1400 | J63: 27-30天 | K63: 1220 | L63: 30-33天 | M63: 1270 | N63: 30-33天 | O63: 1150 | P63: 25-35天 | Q63: 1100 | R63: 25-38天
A64: SLC2 | B64: 84081 | C64: C【三区】 12KG+ | D64: 1方起收 | E64: 1850 | F64: 20-28天 | G64: 1750 | H64: 20-30天 | I64: 1450 | J64: 33天左右 | K64: 1270 | L64: 33天左右 | M64: 1320 | N64: 33天左右 | O64: 1100 | P64: 25-35天 | Q64: 1150 | R64: 25-38天
A65: SLC3 | B65: 84116 | E65: 1850 | F65: 20-28天 | G65: 1750 | H65: 20-30天 | I65: 1450 | J65: 33天左右 | K65: 1270 | L65: 33天左右 | M65: 1320 | N65: 33天左右 | O65: 1100 | P65: 25-35天 | Q65: 1150 | R65: 25-38天
A66: PDX7 | B66: 97317 | C66: D【三区】 12KG+ | D66: 1方起收 | E66: 1850 | F66: 20-28天 | G66: 1750 | H66: 20-30天 | I66: 1450 | J66: 33天左右 | K66: 1270 | L66: 33天左右 | M66: 1320 | N66: 33天左右 | O66: 1100 | P66: 25-35天 | Q66: 1150 | R66: 25-38天
A67: BFI3 | B67: 98327-9607 | E67: 1850 | F67: 20-28天 | G67: 1750 | H67: 20-30天 | I67: 1450 | J67: 33天左右 | K67: 1270 | L67: 33天左右 | M67: 1320 | N67: 33天左右 | O67: 1100 | P67: 25-35天 | Q67: 1150 | R67: 25-38天
A68: GEG2 | B68: 99216 | E68: 1850 | F68: 20-28天 | G68: 1750 | H68: 20-30天 | I68: 1450 | J68: 33天左右 | K68: 1270 | L68: 33天左右 | M68: 1320 | N68: 33天左右 | O68: 1100 | P68: 25-35天 | Q68: 1150 | R68: 25-38天
A69: DEN2 | B69: 80019-3710 | E69: 1850 | F69: 20-28天 | G69: 1750 | H69: 20-30天 | I69: 1450 | J69: 33天左右 | K69: 1270 | L69: 33天左右 | M69: 1320 | N69: 33天左右 | O69: 1100 | P69: 25-35天 | Q69: 1150 | R69: 25-38天
A70: DEN8 | B70: 80018 | E70: 1850 | F70: 20-28天 | G70: 1750 | H70: 20-30天 | I70: 1450 | J70: 33天左右 | K70: 1270 | L70: 33天左右 | M70: 1320 | N70: 33天左右 | O70: 1100 | P70: 25-35天 | Q70: 1150 | R70: 25-38天
A71: OKC2 | B71: 73159 | E71: 1850 | F71: 20-28天 | G71: 1750 | H71: 20-30天 | I71: 1450 | J71: 33天左右 | K71: 1270 | L71: 33天左右 | M71: 1320 | N71: 33天左右 | O71: 1100 | P71: 25-35天 | Q71: 1150 | R71: 25-38天
A72: FTW2 | B72: 75019 | C72: E【三区】 12KG+ | D72: 1方起收 | E72: 1850 | F72: 20-28天 | G72: 1750 | H72: 20-30天 | I72: 1450 | J72: 33天左右 | K72: 1270 | L72: 33天左右 | M72: 1320 | N72: 33天左右 | O72: 1100 | P72: 25-35天 | Q72: 1150 | R72: 25-38天
A73: FTW5 | B73: 75126-3566 | E73: 1850 | F73: 20-28天 | G73: 1750 | H73: 20-30天 | I73: 1450 | J73: 33天左右 | K73: 1270 | L73: 33天左右 | M73: 1320 | N73: 33天左右 | O73: 1100 | P73: 25-35天 | Q73: 1150 | R73: 25-38天
A74: HOU7 | B74: 77064 | E74: 1850 | F74: 20-28天 | G74: 1750 | H74: 20-30天 | I74: 1450 | J74: 33天左右 | K74: 1270 | L74: 33天左右 | M74: 1320 | N74: 33天左右 | O74: 1100 | P74: 25-35天 | Q74: 1150 | R74: 25-38天
A75: FOE1 | B75: 66109 | E75: 1850 | F75: 20-28天 | G75: 1750 | H75: 20-30天 | I75: 1450 | J75: 33天左右 | K75: 1270 | L75: 33天左右 | M75: 1320 | N75: 33天左右 | O75: 1100 | P75: 25-35天 | Q75: 1150 | R75: 25-38天
A76: ICT2 | B76: 67219-1410 | E76: 1850 | F76: 20-28天 | G76: 1750 | H76: 20-30天 | I76: 1450 | J76: 33天左右 | K76: 1270 | L76: 33天左右 | M76: 1320 | N76: 33天左右 | O76: 1100 | P76: 25-35天 | Q76: 1150 | R76: 25-38天
A77: MKC4 | B77: 66021-9588 | E77: 1850 | F77: 20-28天 | G77: 1750 | H77: 20-30天 | I77: 1450 | J77: 33天左右 | K77: 1270 | L77: 33天左右 | M77: 1320 | N77: 33天左右 | O77: 1100 | P77: 25-35天 | Q77: 1150 | R77: 25-38天
A78: LIT2 | B78: 72117 | E78: 1850 | F78: 20-28天 | G78: 1750 | H78: 20-30天 | I78: 1450 | J78: 33天左右 | K78: 1270 | L78: 33天左右 | M78: 1320 | N78: 33天左右 | O78: 1100 | P78: 25-35天 | Q78: 1150 | R78: 25-38天
A79: SAT6 | B79: 78666 | E79: 1850 | F79: 20-28天 | G79: 1750 | H79: 20-30天 | I79: 1450 | J79: 33天左右 | K79: 1270 | L79: 33天左右 | M79: 1320 | N79: 33天左右 | O79: 1100 | P79: 25-35天 | Q79: 1150 | R79: 25-38天
A80: LFT1 | B80: 70507 | E80: 1850 | F80: 20-28天 | G80: 1750 | H80: 20-30天 | I80: 1450 | J80: 33天左右 | K80: 1270 | L80: 33天左右 | M80: 1320 | N80: 33天左右 | O80: 1100 | P80: 25-35天 | Q80: 1150 | R80: 25-38天
A81: MDW6 | B81: 60446 | C81: F【三区】 12KG+ | D81: 1方起收 | E81: 1950 | F81: 20-28天 | G81: 1850 | H81: 20-30天 | I81: 1550 | J81: 33天左右 | K81: 1370 | L81: 33天左右 | M81: 1420 | N81: 33天左右 | O81: 1200 | P81: 25-35天 | Q81: 1250 | R81: 25-38天
A82: MDW9 | B82: 60502 | E82: 1950 | F82: 20-28天 | G82: 1850 | H82: 20-30天 | I82: 1550 | J82: 33天左右 | K82: 1370 | L82: 33天左右 | M82: 1420 | N82: 33天左右 | O82: 1200 | P82: 25-35天 | Q82: 1250 | R82: 25-38天
A83: ORD2 | B83: 60410 | E83: 1950 | F83: 20-28天 | G83: 1850 | H83: 20-30天 | I83: 1550 | J83: 33天左右 | K83: 1370 | L83: 33天左右 | M83: 1420 | N83: 33天左右 | O83: 1200 | P83: 25-35天 | Q83: 1250 | R83: 25-38天
A84: STL3 | B84: 65738-2779 | E84: 1950 | F84: 20-28天 | G84: 1850 | H84: 20-30天 | I84: 1550 | J84: 33天左右 | K84: 1370 | L84: 33天左右 | M84: 1420 | N84: 33天左右 | O84: 1200 | P84: 25-35天 | Q84: 1250 | R84: 25-38天
A85: STL4 | B85: 62025-2815 | E85: 1950 | F85: 20-28天 | G85: 1850 | H85: 20-30天 | I85: 1550 | J85: 33天左右 | K85: 1370 | L85: 33天左右 | M85: 1420 | N85: 33天左右 | O85: 1200 | P85: 25-35天 | Q85: 1250 | R85: 25-38天
A86: JVL1 | B86: 53511 | E86: 1950 | F86: 20-28天 | G86: 1850 | H86: 20-30天 | I86: 1550 | J86: 33天左右 | K86: 1370 | L86: 33天左右 | M86: 1420 | N86: 33天左右 | O86: 1200 | P86: 25-35天 | Q86: 1250 | R86: 25-38天
A87: IGQ2 | B87: 60484 | E87: 1950 | F87: 20-28天 | G87: 1850 | H87: 20-30天 | I87: 1550 | J87: 33天左右 | K87: 1370 | L87: 33天左右 | M87: 1420 | N87: 33天左右 | O87: 1200 | P87: 25-35天 | Q87: 1250 | R87: 25-38天
A88: CMH3 | B88: 45050 | E88: 1950 | F88: 20-28天 | G88: 1850 | H88: 20-30天 | I88: 1550 | J88: 33天左右 | K88: 1370 | L88: 33天左右 | M88: 1420 | N88: 33天左右 | O88: 1200 | P88: 25-35天 | Q88: 1250 | R88: 25-38天
A89: CMH2 | B89: 43125 | E89: 1950 | F89: 20-28天 | G89: 1850 | H89: 20-30天 | I89: 1550 | J89: 33天左右 | K89: 1370 | L89: 33天左右 | M89: 1420 | N89: 33天左右 | O89: 1200 | P89: 25-35天 | Q89: 1250 | R89: 25-38天
A90: MEM6 | B90: 38654-2510 | E90: 1950 | F90: 20-28天 | G90: 1850 | H90: 20-30天 | I90: 1550 | J90: 33天左右 | K90: 1370 | L90: 33天左右 | M90: 1420 | N90: 33天左右 | O90: 1200 | P90: 25-35天 | Q90: 1250 | R90: 25-38天
A91: PPO4 | B91: 46140 | E91: 1950 | F91: 20-28天 | G91: 1850 | H91: 20-30天 | I91: 1550 | J91: 33天左右 | K91: 1370 | L91: 33天左右 | M91: 1420 | N91: 33天左右 | O91: 1200 | P91: 25-35天 | Q91: 1250 | R91: 25-38天
A92: CLT2 | B92: 28214 | C92: A【四区】 12KG+ | D92: 1方起收 | E92: 2050 | F92: 20-32天 | G92: 1950 | H92: 22-33天 | I92: 1650 | J92: 34天左右 | K92: 1470 | L92: 34天左右 | M92: 1520 | N92: 34天左右 | O92: 1300 | P92: 25-38天 | Q92: 1350 | R92: 25-38天
A93: TPA2 | B93: 33811-1808 | E93: 2050 | F93: 20-32天 | G93: 1950 | H93: 22-33天 | I93: 1650 | J93: 34天左右 | K93: 1470 | L93: 34天左右 | M93: 1520 | N93: 34天左右 | O93: 1300 | P93: 25-38天 | Q93: 1350 | R93: 25-38天
A94: TPA3 | B94: 33823-9429 | E94: 2050 | F94: 20-32天 | G94: 1950 | H94: 22-33天 | I94: 1650 | J94: 34天左右 | K94: 1470 | L94: 34天左右 | M94: 1520 | N94: 34天左右 | O94: 1300 | P94: 25-38天 | Q94: 1350 | R94: 25-38天
A95: RDU2 | B95: 27577 | E95: 2050 | F95: 20-32天 | G95: 1950 | H95: 22-33天 | I95: 1650 | J95: 34天左右 | K95: 1470 | L95: 34天左右 | M95: 1520 | N95: 34天左右 | O95: 1300 | P95: 25-38天 | Q95: 1350 | R95: 25-38天
A96: RDU4 | B96: 28303 | E96: 2050 | F96: 20-32天 | G96: 1950 | H96: 22-33天 | I96: 1650 | J96: 34天左右 | K96: 1470 | L96: 34天左右 | M96: 1520 | N96: 34天左右 | O96: 1300 | P96: 25-38天 | Q96: 1350 | R96: 25-38天
A97: MCO2 | B97: 32725 | E97: 2050 | F97: 20-32天 | G97: 1950 | H97: 22-33天 | I97: 1650 | J97: 34天左右 | K97: 1470 | L97: 34天左右 | M97: 1520 | N97: 34天左右 | O97: 1300 | P97: 25-38天 | Q97: 1350 | R97: 25-38天
A98: GSO1 | B98: 27284 | E98: 2050 | F98: 20-32天 | G98: 1950 | H98: 22-33天 | I98: 1650 | J98: 34天左右 | K98: 1470 | L98: 34天左右 | M98: 1520 | N98: 34天左右 | O98: 1300 | P98: 25-38天 | Q98: 1350 | R98: 25-38天
A99: SAV3 | B99: 31216-6427 | E99: 2050 | F99: 20-32天 | G99: 1950 | H99: 22-33天 | I99: 1650 | J99: 34天左右 | K99: 1470 | L99: 34天左右 | M99: 1520 | N99: 34天左右 | O99: 1300 | P99: 25-38天 | Q99: 1350 | R99: 25-38天
A100: JAX3 | B100: 32210-8686 | E100: 2050 | F100: 20-32天 | G100: 1950 | H100: 22-33天 | I100: 1650 | J100: 34天左右 | K100: 1470 | L100: 34天左右 | M100: 1520 | N100: 34天左右 | O100: 1300 | P100: 25-38天 | Q100: 1350 | R100: 25-38天
...

Sheet 西雅图卡派专线
A1: 华东区-西雅图卡派专线
A2: 西雅图 直航 散货特价
A3: FBA仓库代码 | B3: 目的邮编 | C3: 12KG+ | D3: 整柜直送 整柜价 （我司仓库装柜，全包到门） | E3: 签收时效 | F3: 配送方式 | G3: 下单渠道：西雅图海卡/散货特价
A4: PDX6 | B4: 97203 | C4: / | D4: / | E4: 25-30天 | F4: 专车配送 | G4: 指定船型：OA船、SML船
A5: PDX7 | B5: 97317 | C5: / | D5: / | E5: 25-30天 | F5: 专车配送
A6: BFI3 | B6: 98327-9607 | C6: / | D6: / | E6: 25-30天 | F6: 专车配送
A7: BFI7 | B7: 98390 | C7: / | D7: / | E7: 25-30天 | F7: 专车配送
A8: GEG2 | B8: 99216 | C8: / | D8: / | E8: 25-30天 | F8: 专车配送
A9: PSC2 | B9: 99301 | C9: / | D9: / | E9: 25-30天 | F9: 专车配送
A10: 货重比：整票实重大于100公斤以上，享受重货比优惠：整票实重/整票方数=货重比 1:190 减0.2元 / 1:200 减0.3元 / 1:220 减0.5元 / 1:250 减0.8元 / 1:300 减1.2元 / 1:350 减1.5元 / 1:400 减1.8元 / 1:450 减2元 / 1:500 减2.2元 / 1:550 减2.5元 / ；超550以上单询；

Sheet 美西海外仓收费标准
A1: 飞迹国际海外仓 收费标准 | E1: 黄色部分为4.1修改的内容
A2: 收费项目 | B2: 收费标准 | C2: 详情
A3: 拦截费 | B3: $200/票 | C3: 拆送拦截费 | D3: 100件内，超100件部分 每件+1美金。
B4: $800/票 | C4: 卡派整柜直送拦截费
A5: 仓储 | B5: $1/方/天 | C5: 入库15-30天 | D5: 仓库仓储费 免15天 为避免长期仓储导致的丢件，请客户尽量到港前提供操作指令
B6: $1.5/方/天 | C6: 入库30天-60天
B7: $2/方/天 | C7: 入库60天以上
A8: 操作费 | B8: $1/件 | C8: 常规尺寸纸箱货$1/件，超大件等特殊货物单询
A9: 困难操作费 | B9: $1/件-$3.5/件 | C9: 如未说明需要按照标签打托，海外仓混合打托以后，导致后期客户又重新要求按照固定标签打托或者挑货的情况下，会产生较多的人工时间成本，且需要重新拆托再打托，故每多一种标签+0.5美金/件，封顶3.5美金/件。 【例：100件，5种标签，操作其中20件，每种4件，则操作费用为1+（5-1）*0.5=$3/件】
A10: 贴标 | B10: $0.5/张 | C10: 外箱FBA默认贴2张/件，UPS/Fedex快递面单默认贴1张/件，其他根据客户需求贴对应张数
A11: SKU操作费 | B11: / | C11: 单一SKU种类 平均每箱SKU数量≤30个 | D11: 免收
B12: $0.3/个 | C12: 单一SKU种类 平均每箱SKU数量>30个 | D12: SKU操作费
B13: $0.3/个-$1.5/个 | C13: 多种SKU | D13: 每多1种SKU加收0.3美金/种的SKU分拣费，封顶1.5美金/个
A14: SKU清点费 | B14: $0.1/个 | C14: 单一SKU种类 更换SKU总数超过500个 | D14: SKU清点费
B15: $0.3/个 | C15: 多种SKU种类 更换SKU总数超过500个 | D15: SKU清点费
A16: 出库费 | B16: $1/件 | C16: 操作之后需要我司转运出库
A17: 复称/复量 | B17: $5/托 或 $5/件 | C17: 复称：以托盘为1个单位，如客户需要每件称重，则按照$5/件收取 复量：默认以件数为单位
A18: 拍照费 | B18: $2/张-$5/张 | C18: 如只是确认货物是否在仓库，可免收，；如需操作的情况下要求拍照：拍外箱，$2/张；拆箱后拍照，$5/张
A19: 销毁费 | B19: $5/件 | C19: 如木架货物销毁，另收30美金（人工处理费+ 垃圾处理费） 美国和香港一样是不能乱扔大件的垃圾的，只能叫销毁公司上门拉货销毁货物。
A20: 仓储/拦截 仓库 中转货物，费用：库内中转操作费+头程（参考当水“自提-自打单-仓储”价格表）+尾端派送费（快递派送/卡派转运）
A21: 快递派送费（UPS/FEDEX） | B21: 100公斤以上，美西4元/KG，美中6元/KG，美东7元/KG；100公斤以内单询，价格平均贵3-5元/KG，以实际询价为准。 （以上不包含私人地址、商业地址、偏远等）
A22: 卡派转运费用 | B22: 1托为1.8方，1托最高不能超400公斤，超过部分换成体积来核算。如 1.8个方1000KG的货物，则计费重为1000/400=2.5方（计算结果向上取整）=3方，3方需要2托计费。 ONT8/LGB8/LAX9（40/托）, SBD1（50/托） SMF3/SCK4/LAS1/GYR2/GYR3（90/托） FTW1（180/托） MDW2（220/托） MEM1（240/托） FWA4/IND9/MQJ1（230/托） PSC2（250/托） ABQ2（190/托） 其他仓库代码单询
A23: 其余操作中转费单询
A24: 仓库代码始发洛杉矶 （40*48*72板）
A25: LAX9 | B25: 40
A26: LGB8 | B26: 40
A27: SBD1 | B27: 50
A28: ONT8 | B28: 40
A29: IUSJ | B29: 70
A30: IUSP | B30: 70
A31: IUSQ | B31: 70
A32: POC1 | B32: 55
A33: POC2 | B33: 55
A34: POC3 | B34: 55
A35: XLX7 | B35: 70
A36: TCY1 | B36: 90
... A58: MEM1 | B58: 240
A59: 注：以上报价不包含出库费，如仓库代码未在价格表上，请单询

Sheet 奥克兰、芝加哥、休斯顿、纽约海外仓收费标准
A1: 飞迹国际海外仓 收费标准 | E1: 与洛杉矶海外仓费用不同的地方，已经用黄色标记出来了；非洛杉矶海外仓的基础费用普遍偏高一些。
A2: 收费项目 | B2: 收费标准 | C2: 详情
A3: 拦截费 | B3: $200/票 | C3: 拆送拦截费 | D3: 100件内，超100件部分 每件+1美金。
B4: $800/票 | C4: 卡派整柜直送拦截费
A5: 仓储 | B5: $1/方/天 | C5: 入库7-15天 | D5: 仓库仓储费 免7天 为避免长期仓储导致的丢件，请客户尽量到港前提供操作指令 方数向上取整，不足2方的票件按2方计算。
B6: $1.5/方/天 | C6: 入库15天-60天
B7: $2/方/天 | C7: 入库60天以上
A8: 操作费 | B8: $1/件 | C8: 常规尺寸纸箱货$1/件，超大件等特殊货物单询
A9: 困难操作费 | B9: $1/件-$3.5/件 | C9: 如未说明需要按照标签打托，海外仓混合打托以后，导致后期客户又重新要求按照固定标签打托或者挑货的情况下，会产生较多的人工时间成本，且需要重新拆托再打托，故每多一种标签+0.5美金/件，封顶3.5美金/件。 【例：100件，5种标签，操作其中20件，每种4件，则操作费用为1+（5-1）*0.5=$3/件】
A10: 贴标 | B10: $0.5/张 | C10: 外箱FBA默认贴2张/件，UPS/Fedex快递面单默认贴1张/件，其他根据客户需求贴对应张数
A11: SKU操作费 | B11: / | C11: 单一SKU种类 平均每箱SKU数量≤30个 | D11: 免收
B12: $0.5/个 | C12: 单一SKU种类 平均每箱SKU数量>30个 | D12: SKU操作费
B13: $0.5/个-$1.5/个 | C13: 多种SKU | D13: 每多1种SKU加收0.5美金/种的SKU分拣费，封顶1.5美金/个
A14: SKU清点费 | B14: $0.2/个 | C14: 单一SKU种类 更换SKU总数超过500个 | D14: SKU清点费
B15: $0.3/个 | C15: 多种SKU种类 更换SKU总数超过500个 | D15: SKU清点费
A16: 出库费 | B16: $1/件 | C16: 操作之后需要我司转运出库
A17: 复称/复量 | B17: $5/托 或 $5/件 | C17: 复称：以托盘为1个单位，如客户需要每件称重，则按照$5/件收取 复量：默认以件数为单位
A18: 拍照费 | B18: $2/张-$5/张 | C18: 如只是确认货物是否在仓库，可免收，；如需操作的情况下要求拍照：拍外箱，$2/张；拆箱后拍照，$5/张
A19: 销毁费 | B19: $5/件 | C19: 如木架货物销毁，另收80美金（人工处理费+ 垃圾处理费） 美国和香港一样是不能乱扔大件的垃圾的，只能叫销毁公司上门拉货销毁货物。
A20: 仓储/拦截 仓库 中转货物，费用：库内中转操作费+头程（参考当水“自提-自打单-仓储”价格表）+尾端派送费（快递派送/卡派转运）
A21: 快递派送费（UPS/FEDEX） | B21: 实际打单费用为准
A22: 卡派转运费用 | B22: 1托为1.8方，1托最高不能超400公斤，超过部分换成体积来核算。如 1.8个方1000KG的货物，则计费重为1000/400=2.5方（计算结果向上取整）=3方，3方需要2托计费。 仓库代码单询
A23: 其余操作中转费单询
