Workbook
Name FBA仓库代码: [1]亚马逊地址库!$C$2:$C$428
Name 城市: [1]亚马逊地址库!$K$2:$K$428
Name 地址编码: [1]亚马逊地址库!$B$2:$B$428
Name 地址二: [1]亚马逊地址库!$I$2:$I$428
Name 地址简称: [1]亚马逊地址库!$A$2:$A$428
Name 地址三: [1]亚马逊地址库!$J$2:$J$428
Name 地址一: [1]亚马逊地址库!$H$2:$H$428
Name 公司名: [1]亚马逊地址库!$E$2:$E$428
Name 国家: [1]亚马逊地址库!$M$2:$M$428
Name 联系电话: [1]亚马逊地址库!$F$2:$F$428
Name 联系人: [1]亚马逊地址库!$D$2:$D$428
Name 联系手机: [1]亚马逊地址库!$G$2:$G$428
Name 渠道: OFFSET([1]亚马逊地址库!$O$1,1,,COUNTA([1]亚马逊地址库!$O$1:$O$65536)-1,1)
Name 省_洲: [1]亚马逊地址库!$L$2:$L$428
Name 邮编: [1]亚马逊地址库!$N$2:$N$428
Name \0: #REF!
Name _Loc11: [3]Request!$M$135

Sheet 目录
B1: 深圳市商速航供应链有限公司
B3: 区域 | C3: 渠道名称 | D3: 链接价格 | E3: 派送方式 | F3: 渠道优势简介 | G3: 价格动态 | H3: 执行日期
B4: 美国海运 (卡派) | C4: 美森正班-卡派 | D4: 点击进入 | E4: 卡车派 | F4: 预计时效：最快13-22个自然日入仓,热门仓有时效延误理赔！ | G4: 上调 | H4: 46112
C5: 美森MAX-卡派 | D5: 点击进入 | E5: 卡车派 | F5: 预计时效：最快14-24个自然日入仓,热门仓有时效延误理赔！ | G5: 上调 | H5: 46112
C6: 快船EXX-卡派 | D6: 点击进入 | E6: 卡车派 | F6: 预计时效：最快14-24个自然日入仓,热门仓有时效延误理赔！ | G6: 上调 | H6: 46112
C7: 盐田以星南沙合德限时达卡派 | D7: 点击进入 | E7: 卡车派 | F7: 预计时效：最快18-25个自然日入仓.热门仓有时效延误理赔！ | G7: 上调 | H7: 46112
C8: 义乌合德以星限时达卡派 | D8: 点击进入 | E8: 卡车派 | F8: 预计时效：最快18-25个自然日入仓.热门仓有时效延误理赔！ | G8: 上调 | H8: 46112
C9: 普船洛杉矶-卡派 | D9: 点击进入 | E9: 卡车派 | F9: 洛杉矶拆柜-南加州FBA仓库价格优惠,组合仓点大幅调整 | G9: 上调 | H9: 46112
C10: 普船纽约-卡派 | D10: 点击进入 | E10: 卡车派 | F10: 纽约拆柜-美东及周边仓库价格实惠 | G10: 上调 | H10: 46112
C11: 普船萨凡纳-卡派 | D11: 点击进入 | E11: 卡车派 | F11: 萨凡纳拆柜-美东南附近FBA仓库及GA周边仓点最优选择 | G11: 上调 | H11: 46112
B12: 美国海运 (快递派) | C12: 美森正班-海派 | D12: 点击进入 | E12: FEDEX/UPS派 | F12: 预计提取时间:开船后12-15天提取，超时提取有赔付. | G12: 上调 | H12: 46112
C13: 美森加班-海派 | D13: 点击进入 | E13: FEDEX/UPS派 | F13: 预计提取时间:开船后13-16天提取，超时提取有赔付. | G13: 上调 | H13: 46112
C14: 快船EXX-海派 | D14: 点击进入 | E14: FEDEX/UPS派 | F14: 预计提取时间:开船后14-18天提取，超时提取有赔付. | G14: 上调 | H14: 46112
C15: 义乌合德以星限时达海派 | D15: 点击进入 | E15: FEDEX/UPS派 | F15: 预计提取时间:开船后14-18天提取，超时提取有赔付. | G15: 上调 | H15: 46112
C16: 普船洛杉矶-海派 | D16: 点击进入 | E16: FEDEX/UPS派 | F16: 预计提取时间:开船后20-25天提取. | G16: 上调 | H16: 46112
C17: 预配船期表 | D17: 点击进入 | E17: —— | F17: 海运各渠道预配当周及下一周对应船期表. | H17: 46112
B18: 海外仓 | C18: 海外仓收费明细 | D18: 点击进入 | E18: 综合 | F18: 自营海外仓综合服务，一件代发价格单询； | H18: 46112
B21: 其它 | C21: 注意事项 | D21: 点击进入 | E21: —— | F21: 出货前请详细查阅 | H21: 46112
C22: 赔偿说明 | D22: 点击进入 | E22: —— | F22: 出货前请详细查阅 | H22: 46112
C23: 专线出货资料模版 | D23: 点击进入 | E23: —— | F23: 根据渠道仓点变化会不定期更新 | H23: 46112
C24: FBA仓库邮编地址对照表 | D24: 点击进入 | E24: —— | F24: 亚马逊仓点会不定期新增或关闭 | H24: 46112
C25: 交接清单模版 | D25: 点击进入 | E25: —— | F25: 可用任意签名盖章的交接清单 | H25: 46112
C26: 禁运品反倾销及特殊监管产品 | D26: 点击进入 | E26: —— | F26: 美线接货原则，相关产品需要资质认证大体明细 | H26: 46112
C27: 美国对华反倾销产品目录表 | D27: 点击进入 | E27: —— | F27: 美国对于反倾销产品的归类会不定期更新,以实际出货清关为准! | H27: 46112
B28: 特别提示:如客户一旦同意接受我司服务，我司将默认为客户已详细阅读过此价格表内所有备注条款内容，并接受各条款的约束，严格按照备注条款内容执行!
B29: 货物下单网址：http://shangs.nextsls.com/wos
B30: 中性查件网址：http://tracking.nextsls.com/trace?app=607444a03aff974cf203c187
B31: 特别提示：各代理，交货前请下单备好交接清单明细并签名盖章，谢谢配合！
B32: 福永仓库地址：深圳市宝安区福海街道福园一路高新建工业区一楼商速航供应链(岗亭直走到底最里面左手边) （导航：商速航福永仓） 联系人：陆先生：15677767671（紧急联系人李先生：15625507507) 收货时间：周一至周六上午9:00~晚上21:00
B33: 龙华仓库地址：深圳市龙华区福城街道福民社区富康工业区A2栋厂房1楼（商速航龙华仓） 联系人：党先生：15591381931 收货时间：周一至周六12:00~24:00
B34: 义乌仓库地址：浙江省金华市义乌市义乌京东亚洲一号物流园祥瑞路3号门进来右手边上天桥二楼开到头右手边4号库（导航：4栋2楼4号商速航义乌仓） 晚班-联系人：钱先生 电话：18386399460（晚班） 早班-联系人：蔡先生 18083572991（早班） 收货时间：周一至周六上午9:00~晚上21:00
B35: 广州仓地址：广东省广州市白云区狮子岭路35号四横路同星空间A101室 联系人：徐生 13376654475 联系人：李生 19128676486 联系人：袁生 19124276567 收货时间：周一至周六12:00~21:00
B36: 厦门仓库地址：厦门市湖里区渔港中路18号自贸园12号仓（进门左前方）导航搜索：天鹰快运（厦门中心） 电话：0592-5738618 电话：0592-5738628 联系人：张友 13950174628 收货时间：周一至周六9:00~22:00
B37: 泉州仓库地址：泉州市晋江池店镇凤池路凤池路鸿运物流城天鹰快运 电话:0595-22594288 0595-22429199 联系人：黄小姐 13850700342 收货时间：周一至周六9:00~22:00
B38: 福州收货地址：福州晓峰驾驶员培训有限公司（通鹤路东） 联系人：黄强强 19196240796 收货时间：周一至周六10:00~21:00
B39: 美森/义乌普船报关行 义乌市欣扬报关代理有限公司 33189800E6 离境口岸 (310703) ：上海外高桥保税区 出境关别 (2225)：外港海关
B44: 盐田渠道报关件委托报关行更新： 深圳普船 以星 盐田出 报关行请委托以下报关行 深圳市友缘国际物流有限公司 4403980C4Q 离境口岸：盐田（470601） 出境关别（：大鹏海关 （5316）

Sheet 预配船期表
B1: 商速航美国海运装柜计划 (4月1日-4月7日)
B2: 渠道 | C2: 起运港 | D2: 目的港 | E2: 船名航次 | F2: ETD 以实际开船为准 | G2: ETA 以实际到港为准 | H2: 截单时间 收满提前截单 | I2: 预计装柜时间 | J2: 预计最晚装柜时间 | K2: 剩余舱位/CBM
B3: 美森限时达CLX 深圳装柜 | C3: 上海 | D3: 长滩 | E3: MATSON WAIKIKI 023E | F3: 46120 | G3: 46131 | H3: 周六 | I3: 周六 | J3: 周日 | K3: 仓位充足
B4: 美森限时达CLX 义乌装柜 | E4: MATSON WAIKIKI 023E | F4: 46120 | G4: 46131 | H4: 周六 | I4: 周六 | J4: 周一 | K4: 仓位充足
B5: 美森加班MAX 深圳装柜 | C5: 上海 | D5: 长滩 | E5: MANUKAI 254E | F5: 46121 | G5: 46132 | H5: 周六 | I5: 周六 | J5: 周一 | K5: 仓位充足
B6: 美森加班MAX 义乌装柜 | E6: MANUKAI 254E | F6: 46121 | G6: 46132 | H6: 周六 | I6: 周六 | J6: 周二 | K6: 仓位充足
B7: JF美森加班MAX 深圳装柜 | C7: 宁波 | D7: 长滩 | E7: MANUKAI 254E | F7: 46119 | G7: 46132 | H7: 周六下午六点福永截 | I7: 周六 | J7: 周六 | K7: 仓位充足
B8: EXX 快船 深圳装柜 | C8: 上海 | D8: 洛杉矶 | E8: CMA CGM SWORDFISH 0GVMCE1MA | F8: 46121 | G8: 46132 | H8: 周六 | I8: 周六 | J8: 周一 | K8: 仓位充足
B9: EXX 快船 义乌装柜 | C9: 上海 | D9: 洛杉矶 | E9: CMA CGM SWORDFISH 0GVMCE1MA | F9: 46121 | G9: 46132 | H9: 周六 | I9: 周六 | J9: 周二 | K9: 仓位充足
B10: JFEXX 快船 深圳装柜 | C10: 上海 | D10: 洛杉矶 | E10: CMA CGM SWORDFISH 0GVMCE1MA | F10: 46120 | G10: 46132 | H10: 周六下午六点福永截 | I10: 周六 | J10: 周六 | K10: 仓位充足
B11: 盐田以星南沙合德限时达 交货深圳/广州 统配 | C11: 盐田 | D11: 洛杉矶 | E11: NESTOS 15E | F11: 46120 | G11: 46133 | H11: 周六 | I11: 周六 | J11: 周日 | K11: 仓位充足
B12: 盐田以星南沙合德限时达 交货深圳/广州 统配 | C12: 南沙 | D12: 洛杉矶 | E12: HELGOLAND 2603E | F12: 46120 | G12: 46134 | H12: 周六 | I12: 周六 | J12: 周日 | K12: 仓位充足
B13: 义乌合德/以星 统配 交货深圳/广州/义乌装柜 | C13: 上海 | D13: 洛杉矶 | E13: DORIS OCEAN 2603E | F13: 46121 | G13: 46134 | H13: 周六 | I13: 周六 | J13: 周日 | K13: 仓位充足
B14: 义乌合德/以星 统配 交货深圳/广州/义乌装柜 | C14: 宁波 | D14: 洛杉矶 | E14: ZIM ALBATROSS 13E | F14: 46121 | G14: 46134 | H14: 周六 | I14: 周六 | J14: 周一 | K14: 仓位充足
B15: 盐田普船OA | C15: 盐田 | D15: 长滩 | E15: COSCO SHIPPING PANAMA 003E | F15: 46122 | G15: 46137 | H15: 周五 | I15: 周五 | J15: 周六 | K15: 仓位充足
B16: 盐田普船OA | C16: 盐田 | D16: 长滩 | E16: OOCL ATLANTA 172E | F16: 46126 | G16: 46140 | H16: 周五 | I16: 周五 | J16: 周五 | K16: 仓位充足
B17: 义乌普船 深圳装柜-循环装柜 | C17: 义乌 | D17: 长滩 | E17: COSCO ITALY 081E | F17: 46117 | G17: 46132 | H17: 周六 | I17: 周六 | J17: 周二 | K17: 仓位充足
B18: 义乌普船 义乌装柜-循环装柜 | E18: CSCL EAST CHINA SEA 076E | F18: 46121 | G18: 46137 | H18: 周六 | I18: 周六 | J18: 周二 | K18: 仓位充足
B19: 义乌普船 义乌装柜-循环装柜 | C19: 义乌 | D19: 洛杉矶 | E19: EVER LASTING 1215-092E | F19: 46119 | G19: 46133 | H19: 周六 | I19: 周六 | J19: 周二 | K19: 仓位充足
B20: 纽约海卡 | C20: 义乌 | D20: 纽约 | E20: COSCO SHIPPING ORCHID 033E | F20: 46119 | G20: 46149 | H20: 周三 | I20: 周三 | J20: 周三 | K20: 仓位充足
B21: 萨凡纳海卡 | C21: 义乌 | D21: 萨凡纳 | E21: EVER FOND 1260-022E | F21: 46121 | G21: 46152 | H21: 周三 | I21: 周三 | J21: 周三 | K21: 仓位充足
B22: 纽约海卡 | C22: 盐田 | D22: 纽约（两水统配） | E22: OOCL LAVENDER 002E | F22: 46124 | G22: 46154 | H22: 周二 | I22: 周二 | J22: 周二 | K22: 仓位充足
B23: 纽约海卡 | E23: EVER MAGI 1353-012E | F23: 46125 | G23: 46161 | H23: 周二 | I23: 周二 | J23: 周二 | K23: 仓位充足
B24: 萨凡纳海卡 | C24: 盐田 | D24: 萨凡纳（两水统配） | E24: EVER MAGI 1353-012E | F24: 46125 | G24: 46157 | H24: 周二 | I24: 周二 | J24: 周二 | K24: 仓位充足
B25: 萨凡纳海卡 | E25: OOCL LAVENDER 002E | F25: 46124 | G25: 46160 | H25: 周二 | I25: 周二 | J25: 周二 | K25: 仓位充足
B26: 船期来自船司官网，最终船司可能会有调整，包括但不仅限于出现延期或者空班等情况，最终时效以实际开船和到港时间为准！

Sheet 卡派FBA价格速查指引
A1: 输入仓码 | B1: 渠道名称 | C1: 深圳/广州交货价 | G1: 义乌交货价 | K1: 入仓参考时效 （开船后次日起算）
C2: 按方含税(2CBM+) | D2: 包税(12KG+) | E2: 包税(51KG+) | F2: 包税(300KG+) | G2: 按方含税(2CBM+) | H2: 包税(12KG+) | I2: 包税(51KG+) | J2: 包税(300KG+)
A3: SCK8 | B3: 美森正班卡派 | C3: {=IFERROR(VLOOKUP("*"&$A$3&"*",INDIRECT("'"&B3&"'!B:L"),{2,3,4,5,6,7,8,9,10},0),"无")} -> 1900 | D3: 10.5 | E3: 9.5 | F3: 9.5 | G3: 1820 | H3: 10.1 | I3: 9.1 | J3: 9.1 | K3: 13-16天
B4: 美森MAX卡派 | C4: {=IFERROR(VLOOKUP("*"&$A$3&"*",INDIRECT("'"&B4&"'!B:L"),{2,3,4,5,6,7,8,9,10},0),"无")} -> 1840 | D4: 10.2 | E4: 9.2 | F4: 9.2 | G4: 1760 | H4: 9.8 | I4: 8.8 | J4: 8.8 | K4: 14-17天
B5: EXX卡派 | C5: {=IFERROR(VLOOKUP("*"&$A$3&"*",INDIRECT("'"&B5&"'!B:L"),{2,3,4,5,6,7,8,9,10},0),"无")} -> 1360 | D5: 7.8 | E5: 6.8 | F5: 6.8 | G5: 1280 | H5: 7.4 | I5: 6.4 | J5: 6.4 | K5: 14-17天
B6: 美西限时达卡派 | C6: {=IFERROR(VLOOKUP("*"&$A$3&"*",INDIRECT("'"&B6&"'!B:L"),{2,3,4,5,6,7,8,9,10},0),"无")} -> 无
B7: 普船洛杉矶卡派 | C7: {=IFERROR(VLOOKUP("*"&$A$3&"*",INDIRECT("'"&B7&"'!B:L"),{2,3,4,5,6,7,8,9,10},0),"无")} -> 860 | D7: 5.3 | E7: 4.3 | F7: 4.3 | G7: 860 | H7: 5.3 | I7: 4.3 | J7: 4.3 | K7: 23-27天
B8: 美西特惠卡派 | C8: {=IFERROR(VLOOKUP("*"&$A$3&"*",INDIRECT("'"&B8&"'!B:L"),{2,3,4,5,6,7,8,9,10},0),"无")} -> 无 | D8: 无 | E8: 无 | F8: 无 | G8: 无 | H8: 无 | I8: 无 | J8: 无 | K8: 22-26天
A9: 输入仓码 | B9: 渠道名称 | C9: 专仓直送(深圳/广州交货价) | F9: 专仓直送(义乌交货价) | I9: 入仓参考时效 （开船后次日起算）
C10: 按方含税(1CBM+) | D10: 包税(12KG+) | E10: 包税(100KG+) | F10: 按方含税(1CBM+) | G10: 包税(12KG+) | H10: 包税(100KG+)
A11: =A3 -> SCK8 | B11: 普船奥克兰卡派 | C11: {=IFERROR(VLOOKUP("*"&A11&"*",INDIRECT("'"&B11&"'!B:L"),{2,3,4,5,6,7,8},0),"无")} -> 无
B12: 普船芝加哥卡派 | C12: {=IFERROR(VLOOKUP("*"&A11&"*",INDIRECT("'"&B12&"'!B:L"),{2,3,4,5,6,7,8},0),"无")} -> 无
B13: 普船纽约卡派 | C13: {=IFERROR(VLOOKUP("*"&A11&"*",INDIRECT("'"&B13&"'!B:L"),{2,3,4,5,6,7,8},0),"无")} -> 无
B14: 普船萨凡纳卡派 | C14: {=IFERROR(VLOOKUP("*"&A11&"*",INDIRECT("'"&B14&"'!B:L"),{2,3,4,5,6,7,8},0),"无")} -> 无

Sheet 价格汇总
B1: 分区/重量 | C1: 深圳/广州交货 | F1: 义乌交货
C2: 12KG+ | D2: 51KG+ | E2: 100KG+ | F2: 12KG+ | G2: 51KG+ | H2: 100KG+ | I2: 12KG+（系数） | J2: 51KG+（系数） | K2: 深圳和义乌系数
A3: SSH美森正班-海派 | B3: 美西 (邮编8,9开头) | C3: =E3+J3 -> 15.4 | D3: =E3+I3 -> 13.4 | E3: 12.4 | F3: =H3+J3 -> 15 | G3: =H3+I3 -> 13 | H3: =E3-K3 -> 12 | I3: 1 | J3: 3 | K3: 0.4 | M3: 80 | N3: 0.1
B4: 美中 (邮编4,5,6,7开头) | C4: =E4+J4 -> 16.6 | D4: =E4+I4 -> 14.6 | E4: 13.6 | F4: =H4+J4 -> 16.2 | G4: =H4+I4 -> 14.2 | H4: =E4-K4 -> 13.2 | I4: 1 | J4: 3 | K4: 0.4
B5: 美东 (邮编0,1,2,3开头) | C5: =E5+J5 -> 17.6 | D5: =E5+I5 -> 15.6 | E5: 14.6 | F5: =H5+J5 -> 17.2 | G5: =H5+I5 -> 15.2 | H5: =E5-K5 -> 14.2 | I5: 1 | J5: 3 | K5: 0.4
A6: SSH美森MAX-海派 | B6: 美西 (邮编8,9开头) | C6: =E6+J6 -> 15.1 | D6: =E6+I6 -> 13.1 | E6: 12.1 | F6: =H6+J6 -> 14.7 | G6: =H6+I6 -> 12.7 | H6: =E6-K6 -> 11.7 | I6: 1 | J6: 3 | K6: 0.4
B7: 美中 (邮编4,5,6,7开头) | C7: =E7+J7 -> 16.3 | D7: =E7+I7 -> 14.3 | E7: 13.3 | F7: =H7+J7 -> 15.9 | G7: =H7+I7 -> 13.9 | H7: =E7-K7 -> 12.9 | I7: 1 | J7: 3 | K7: 0.4
B8: 美东 (邮编0,1,2,3开头) | C8: =E8+J8 -> 17.3 | D8: =E8+I8 -> 15.3 | E8: 14.3 | F8: =H8+J8 -> 16.9 | G8: =H8+I8 -> 14.9 | H8: =E8-K8 -> 13.9 | I8: 1 | J8: 3 | K8: 0.4
A9: SSH快船EXX-海派 | B9: 美西 (邮编8,9开头) | C9: =E9+J9 -> 13.3 | D9: =E9+I9 -> 11.3 | E9: 10.3 | F9: =H9+J9 -> 12.9 | G9: =H9+I9 -> 10.9 | H9: =E9-K9 -> 9.9 | I9: 1 | J9: 3 | K9: 0.4
B10: 美中 (邮编4,5,6,7开头) | C10: =E10+J10 -> 14.5 | D10: =E10+I10 -> 12.5 | E10: 11.5 | F10: =H10+J10 -> 14.1 | G10: =H10+I10 -> 12.1 | H10: =E10-K10 -> 11.1 | I10: 1 | J10: 3 | K10: 0.4
B11: 美东 (邮编0,1,2,3开头) | C11: =E11+J11 -> 15.5 | D11: =E11+I11 -> 13.5 | E11: 12.5 | F11: =H11+J11 -> 15.1 | G11: =H11+I11 -> 13.1 | H11: =E11-K11 -> 12.1 | I11: 1 | J11: 3 | K11: 0.4
A12: SSH以星限时达海派&长荣定提海派&义乌合德限时达-海派 | B12: 美西 (邮编8,9开头) | C12: =E12+J12 -> 12 | D12: =E12+I12 -> 10 | E12: 9 | F12: =H12+J12 -> 12 | G12: =H12+I12 -> 10 | H12: =E12-K12 -> 9 | I12: 1 | J12: 3 | K12: 0
B13: 美中 (邮编4,5,6,7开头) | C13: =E13+J13 -> 13.2 | D13: =E13+I13 -> 11.2 | E13: 10.2 | F13: =H13+J13 -> 13.2 | G13: =H13+I13 -> 11.2 | H13: =E13-K13 -> 10.2 | I13: 1 | J13: 3 | K13: 0
B14: 美东 (邮编0,1,2,3开头) | C14: =E14+J14 -> 14.2 | D14: =E14+I14 -> 12.2 | E14: 11.2 | F14: =H14+J14 -> 14.2 | G14: =H14+I14 -> 12.2 | H14: =E14-K14 -> 11.2 | I14: 1 | J14: 3 | K14: 0
A15: SSH义乌合德以星限时达-海派 | B15: 美西 (邮编8,9开头) | C15: =E15+J15 -> 12.3 | D15: =E15+I15 -> 10.3 | E15: 9.3 | F15: =H15+J15 -> 12 | G15: =H15+I15 -> 10 | H15: =E15-K15 -> 9 | I15: 1 | J15: 3 | K15: 0.3
B16: 美中 (邮编4,5,6,7开头) | C16: =E16+J16 -> 13.5 | D16: =E16+I16 -> 11.5 | E16: 10.5 | F16: =H16+J16 -> 13.2 | G16: =H16+I16 -> 11.2 | H16: =E16-K16 -> 10.2 | I16: 1 | J16: 3 | K16: 0.3
B17: 美东 (邮编0,1,2,3开头) | C17: =E17+J17 -> 14.5 | D17: =E17+I17 -> 12.5 | E17: 11.5 | F17: =H17+J17 -> 14.2 | G17: =H17+I17 -> 12.2 | H17: =E17-K17 -> 11.2 | I17: 1 | J17: 3 | K17: 0.3
A18: SSH普船洛杉矶-海派 | B18: 美西 (邮编8,9开头) | C18: =E18+J18 -> 10.8 | D18: =E18+I18 -> 8.8 | E18: 7.8 | F18: =H18+J18 -> 10.8 | G18: =H18+I18 -> 8.8 | H18: =E18-K18 -> 7.8 | I18: 1 | J18: 3 | K18: 0
B19: 美中 (邮编4,5,6,7开头) | C19: =E19+J19 -> 12 | D19: =E19+I19 -> 10 | E19: 9 | F19: =H19+J19 -> 12 | G19: =H19+I19 -> 10 | H19: =E19-K19 -> 9 | I19: 1 | J19: 3 | K19: 0
B20: 美东 (邮编0,1,2,3开头) | C20: =E20+J20 -> 13 | D20: =E20+I20 -> 11 | E20: 10 | F20: =H20+J20 -> 13 | G20: =H20+I20 -> 11 | H20: =E20-K20 -> 10 | I20: 1 | J20: 3 | K20: 0
A22: SSH美森正班卡派 | B22: 仓库代码 | C22: 深圳/广州交货价 | G22: 义乌交货价
C23: 按方含税(2CBM+) | D23: 包税(12KG+) | E23: 包税(51KG+) | F23: 包税(300KG+) | G23: 按方含税(2CBM+) | H23: 包税(12KG+) | I23: 包税(51KG+) | J23: 包税(300KG+) | K23: 按方含税(2CBM+) | L23: 包税(12KG+) | M23: 包税(51KG+) | N23: 深圳和义乌系数
B24: ONT8/LGB8/LAX9/SBD1/IUSP IUSQ/IUSJ/POC1/POC2/POC3 | C24: =F24*200 -> 1800 | D24: =F24+L24 -> 10 | E24: =F24+M24 -> 9 | F24: =J24+N24 -> 9 | G24: =J24*200 -> 1720 | H24: =D24-N24 -> 9.6 | I24: =E24-N24 -> 8.6 | J24: 8.6 | K24: 80 | L24: 1 | M24: 0 | N24: 0.4 | P24: 0.3 | Q24: 80
B25: SNA4/SBD2/LGB4/LGB6 XLX7/IUTI/IUSW/PSP3 | C25: =F25*200 -> 1840 | D25: =F25+L25 -> 10.2 | E25: =F25+M25 -> 9.2 | F25: =J25+N25 -> 9.2 | G25: =J25*200 -> 1760 | H25: =D25-N25 -> 9.8 | I25: =E25-N25 -> 8.8 | J25: 8.8 | K25: 80 | L25: 1 | M25: 0 | N25: 0.4
B26: SMF3/SCK4/LAS1/GYR2/GYR3 MIT2/VGT2/GEU2/GEU3/GEU5 HLI2/TCY2/TCY1/SCK8/SMF6 OAK3/MCE1/LAS6/SJC7/FAT2 PHX5/PHX7/IUTE | C26: =F26*200 -> 1900 | D26: =F26+L26 -> 10.5 | E26: =F26+M26 -> 9.5 | F26: =J26+N26 -> 9.5 | G26: =J26*200 -> 1820 | H26: =D26-N26 -> 10.1 | I26: =E26-N26 -> 9.1 | J26: 9.1 | K26: 80 | L26: 1 | M26: 0 | N26: 0.4
B27: ABQ2/QXY8/MCC1 | C27: =F27*200 -> 2060 | D27: =F27+L27 -> 11.3 | E27: =F27+M27 -> 10.3 | F27: =J27+N27 -> 10.3 | G27: =J27*200 -> 1980 | H27: =D27-N27 -> 10.9 | I27: =E27-N27 -> 9.9 | J27: 9.9 | K27: 80 | L27: 1 | M27: 0 | N27: 0.4
B28: FTW1/IUSF/DFW6/IAH3/SAT1 FTW5/STL3/PSC2/PDX7 (标红仓点按12KG起收) 单价按100KG段+1/KG 51KG-100KG按100KG+同价 | C28: =F28*200 -> 2160 | D28: 100KG起收 | E28: 100KG起收 | F28: =J28+N28 -> 10.8 | G28: =J28*200 -> 2080 | H28: 100KG起收 | I28: 100KG起收 | J28: 10.4 | K28: 80 | L28: 1 | M28: 0 | N28: 0.4
B29: IND9/MDW2/FWA4/MEM1 MQJ1/DEN8/RFD2/ORD2/LFT1 (标红仓点按12KG起收) 单价按100KG段+1/KG 51KG-100KG按100KG+同价 | C29: =F29*200 -> 2200 | D29: 100KG起收 | E29: 100KG起收 | F29: =J29+N29 -> 11 | G29: =J29*200 -> 2120 | H29: 100KG起收 | I29: 100KG起收 | J29: 10.6 | K29: 80 | L29: 1 | M29: 0 | N29: 0.4
B30: CLT2/RDU2/CLT3/RDU4 (标红仓点按12KG起收) 单价按100KG段+1/KG 51KG-100KG按100KG+同价 | C30: =F30*200 -> 2380 | D30: 100KG起收 | E30: 100KG起收 | F30: =J30+N30 -> 11.9 | G30: =J30*200 -> 2300 | H30: 100KG起收 | I30: 100KG起收 | J30: 11.5 | K30: 80 | L30: 1 | M30: 0 | N30: 0.4
B31: ABE8/AVP1/TEB3/TEB9/TPA3 RMN3/ORF2/SWF2 (标红仓点按12KG起收) 单价按100KG段+1/KG 51KG-100KG按100KG+同价 | C31: =F31*200 -> 2460 | D31: 100KG起收 | E31: 100KG起收 | F31: =J31+N31 -> 12.3 | G31: =J31*200 -> 2380 | H31: 100KG起收 | I31: 100KG起收 | J31: 11.9 | K31: 80 | L31: 1.5 | M31: 0 | N31: 0.4
B32: 含税自提(含出库费） | C32: =F32*200 -> 1800 | D32: —— | E32: —— | F32: =J32+N32 -> 9 | G32: =J32*200 -> 1720 | H32: —— | I32: —— | J32: 8.6 | K32: 80 | N32: 0.4
A34: SSH美森MAX卡派 | B34: 仓库代码 | C34: 深圳/广州交货价 | G34: 义乌交货价
C35: 按方含税(2CBM+) | D35: 包税(12KG+) | E35: 包税(51KG+) | F35: 包税(300KG+) | G35: 按方含税(2CBM+) | H35: 包税(12KG+) | I35: 包税(51KG+) | J35: 包税(300KG+) | K35: 按方含税(2CBM+) | L35: 包税(12KG+) | M35: 包税(51KG+) | N35: 深圳和义乌系数
B36: ONT8/LGB8/LAX9/SBD1/IUSP IUSQ/IUSJ/POC1/POC2/POC3 | C36: =F36*200 -> 1740 | D36: =F36+L36 -> 9.7 | E36: =F36+M36 -> 8.7 | F36: =J36+N36 -> 8.7 | G36: =J36*200 -> 1660 | H36: =D36-N36 -> 9.3 | I36: =E36-N36 -> 8.3 | J36: 8.3 | K36: 80 | L36: 1 | M36: 0 | N36: 0.4 | P36: 80 | Q36: 0.3
B37: SNA4/SBD2/LGB4/LGB6 XLX7/IUTI/IUSW/PSP3 | C37: =F37*200 -> 1780 | D37: =F37+L37 -> 9.9 | E37: =F37+M37 -> 8.9 | F37: =J37+N37 -> 8.9 | G37: =J37*200 -> 1700 | H37: =D37-N37 -> 9.5 | I37: =E37-N37 -> 8.5 | J37: 8.5 | K37: 80 | L37: 1 | M37: 0 | N37: 0.4
B38: SMF3/SCK4/LAS1/GYR2/GYR3 MIT2/VGT2/GEU2/GEU3/GEU5 HLI2/TCY2/TCY1/SCK8/SMF6 OAK3/MCE1/LAS6/SJC7/FAT2 PHX5/PHX7/IUTE | C38: =F38*200 -> 1840 | D38: =F38+L38 -> 10.2 | E38: =F38+M38 -> 9.2 | F38: =J38+N38 -> 9.2 | G38: =J38*200 -> 1760 | H38: =D38-N38 -> 9.8 | I38: =E38-N38 -> 8.8 | J38: 8.8 | K38: 80 | L38: 1 | M38: 0 | N38: 0.4
B39: ABQ2/QXY8/MCC1 | C39: =F39*200 -> 2000 | D39: =F39+L39 -> 11 | E39: =F39+M39 -> 10 | F39: =J39+N39 -> 10 | G39: =J39*200 -> 1920 | H39: =D39-N39 -> 10.6 | I39: =E39-N39 -> 9.6 | J39: 9.6 | K39: 80 | L39: 1 | M39: 0 | N39: 0.4
B40: FTW1/IUSF/DFW6/IAH3/SAT1 FTW5/STL3/PSC2/PDX7 (标红仓点按12KG起收) 单价按100KG段+1/KG 51KG-100KG按100KG+同价 | C40: =F40*200 -> 2100 | D40: 100KG起收 | E40: 100KG起收 | F40: =J40+N40 -> 10.5 | G40: =J40*200 -> 2020 | H40: 100KG起收 | I40: 100KG起收 | J40: 10.1 | K40: 80 | L40: 1 | M40: 0 | N40: 0.4
B41: IND9/MDW2/FWA4/MEM1 MQJ1/DEN8/RFD2/ORD2/LFT1 (标红仓点按12KG起收) 单价按100KG段+1/KG 51KG-100KG按100KG+同价 | C41: =F41*200 -> 2140 | D41: 100KG起收 | E41: 100KG起收 | F41: =J41+N41 -> 10.7 | G41: =J41*200 -> 2060 | H41: 100KG起收 | I41: 100KG起收 | J41: 10.3 | K41: 80 | L41: 1 | M41: 0 | N41: 0.4
B42: CLT2/RDU2/CLT3/RDU4 (标红仓点按12KG起收) 单价按100KG段+1/KG 51KG-100KG按100KG+同价 | C42: =F42*200 -> 2320 | D42: 100KG起收 | E42: 100KG起收 | F42: =J42+N42 -> 11.6 | G42: =J42*200 -> 2240 | H42: 100KG起收 | I42: 100KG起收 | J42: 11.2 | K42: 80 | L42: 1 | M42: 0 | N42: 0.4
B43: ABE8/AVP1/TEB3/TEB9/TPA3 RMN3/ORF2/SWF2 (标红仓点按12KG起收) 单价按100KG段+1/KG 51KG-100KG按100KG+同价 | C43: =F43*200 -> 2400 | D43: 100KG起收 | E43: 100KG起收 | F43: =J43+N43 -> 12 | G43: =J43*200 -> 2320 | H43: 100KG起收 | I43: 100KG起收 | J43: 11.6 | K43: 80 | L43: 1.5 | M43: 0 | N43: 0.4
B44: 含税自提(含出库费） | C44: =F44*200 -> 1740 | D44: —— | E44: —— | F44: =J44+N44 -> 8.7 | G44: =J44*200 -> 1660 | H44: —— | I44: —— | J44: 8.3 | K44: 80 | N44: 0.4
A46: SSH快船EXX卡派 | B46: 仓库代码 | C46: 深圳/广州交货价 | G46: 义乌交货价
C47: 按方含税(2CBM+) | D47: 包税(12KG+) | E47: 包税(51KG+) | F47: 包税(300KG+) | G47: 按方含税(2CBM+) | H47: 包税(12KG+) | I47: 包税(51KG+) | J47: 包税(300KG+) | K47: 按方含税(2CBM+) | L47: 包税(12KG+) | M47: 包税(51KG+) | N47: 深圳和义乌系数
B48: ONT8/LGB8/LAX9/SBD1/IUSP IUSQ/IUSJ/POC1/POC2/POC3 | C48: =F48*200 -> 1260 | D48: =F48+L48 -> 7.3 | E48: =F48+M48 -> 6.3 | F48: =J48+N48 -> 6.3 | G48: =J48*200 -> 1180 | H48: =D48-N48 -> 6.9 | I48: =E48-N48 -> 5.9 | J48: 5.9 | K48: 80 | L48: 1 | M48: 0 | N48: 0.4 | P48: 80 | Q48: 0.3
B49: SNA4/SBD2/LGB4/LGB6 XLX7/IUTI/IUSW/PSP3 | C49: =F49*200 -> 1300 | D49: =F49+L49 -> 7.5 | E49: =F49+M49 -> 6.5 | F49: =J49+N49 -> 6.5 | G49: =J49*200 -> 1220 | H49: =D49-N49 -> 7.1 | I49: =E49-N49 -> 6.1 | J49: 6.1 | K49: 80 | L49: 1 | M49: 0 | N49: 0.4
B50: SMF3/SCK4/LAS1/GYR2/GYR3 MIT2/VGT2/GEU2/GEU3/GEU5 HLI2/TCY2/TCY1/SCK8/SMF6 OAK3/MCE1/LAS6/SJC7/FAT2 PHX5/PHX7/IUTE | C50: =F50*200 -> 1360 | D50: =F50+L50 -> 7.8 | E50: =F50+M50 -> 6.8 | F50: =J50+N50 -> 6.8 | G50: =J50*200 -> 1280 | H50: =D50-N50 -> 7.4 | I50: =E50-N50 -> 6.4 | J50: 6.4 | K50: 80 | L50: 1 | M50: 0 | N50: 0.4
B51: ABQ2/QXY8/MCC1 | C51: =F51*200 -> 1520 | D51: =F51+L51 -> 8.6 | E51: =F51+M51 -> 7.6 | F51: =J51+N51 -> 7.6 | G51: =J51*200 -> 1440 | H51: =D51-N51 -> 8.2 | I51: =E51-N51 -> 7.2 | J51: 7.2 | K51: 80 | L51: 1 | M51: 0 | N51: 0.4
B52: FTW1/IUSF/DFW6/IAH3/SAT1 FTW5/STL3/PSC2/PDX7 (标红仓点按12KG起收) 单价按100KG段+1/KG 51KG-100KG按100KG+同价 | C52: =F52*200 -> 1620 | D52: 100KG起收 | E52: 100KG起收 | F52: =J52+N52 -> 8.1 | G52: =J52*200 -> 1540 | H52: 100KG起收 | I52: 100KG起收 | J52: 7.7 | K52: 80 | L52: 1 | M52: 0 | N52: 0.4
B53: IND9/MDW2/FWA4/MEM1 MQJ1/DEN8/RFD2/ORD2/LFT1 (标红仓点按12KG起收) 单价按100KG段+1/KG 51KG-100KG按100KG+同价 | C53: =F53*200 -> 1660 | D53: 100KG起收 | E53: 100KG起收 | F53: =J53+N53 -> 8.3 | G53: =J53*200 -> 1580 | H53: 100KG起收 | I53: 100KG起收 | J53: 7.9 | K53: 80 | L53: 1 | M53: 0 | N53: 0.4
B54: CLT2/RDU2/CLT3/RDU4 (标红仓点按12KG起收) 单价按100KG段+1/KG 51KG-100KG按100KG+同价 | C54: =F54*200 -> 1840 | D54: 100KG起收 | E54: 100KG起收 | F54: =J54+N54 -> 9.2 | G54: =J54*200 -> 1760 | H54: 100KG起收 | I54: 100KG起收 | J54: 8.8 | K54: 80 | L54: 1 | M54: 0 | N54: 0.4
B55: ABE8/AVP1/TEB3/TEB9/TPA3 RMN3/ORF2/SWF2 (标红仓点按12KG起收) 单价按100KG段+1/KG 51KG-100KG按100KG+同价 | C55: =F55*200 -> 1920 | D55: 100KG起收 | E55: 100KG起收 | F55: =J55+N55 -> 9.6 | G55: =J55*200 -> 1840 | H55: 100KG起收 | I55: 100KG起收 | J55: 9.2 | K55: 80 | L55: 1.5 | M55: 0 | N55: 0.4
B56: 含税自提(含出库费） | C56: =F56*200 -> 1260 | D56: —— | E56: —— | F56: =J56+N56 -> 6.3 | G56: =J56*200 -> 1180 | H56: —— | I56: —— | J56: 5.9 | K56: 80 | N56: 0.4
A58: SSH以星限时达&长荣定提&义乌合德限时达-卡派 | B58: 仓库代码 | C58: 深圳/广州交货价 | G58: 义乌交货价
C59: 按方含税(2CBM+) | D59: 包税(12KG+) | E59: 包税(51KG+) | F59: 包税(300KG+) | G59: 按方含税(2CBM+) | H59: 包税(12KG+) | I59: 包税(51KG+) | J59: 包税(300KG+) | K59: 按方含税(2CBM+) | L59: 包税(12KG+) | M59: 包税(51KG+) | N59: 深圳和义乌系数
B60: ONT8/LGB8/LAX9/SBD1/IUSP IUSQ/IUSJ/POC1/POC2/POC3 | C60: =F60*200 -> 1060 | D60: =F60+L60 -> 6.3 | E60: =F60+M60 -> 5.3 | F60: =J60+N60 -> 5.3 | G60: =J60*200 -> 1060 | H60: =D60-N60 -> 6.3 | I60: =E60-N60 -> 5.3 | J60: 5.3 | K60: 0 | L60: 1 | M60: 0 | N60: 0 | P60: 40 | Q60: 0.1
B61: SNA4/SBD2/LGB4/LGB6 XLX7/IUTI/IUSW/PSP3 | C61: =F61*200 -> 1100 | D61: =F61+L61 -> 6.5 | E61: =F61+M61 -> 5.5 | F61: =J61+N61 -> 5.5 | G61: =J61*200 -> 1100 | H61: =D61-N61 -> 6.5 | I61: =E61-N61 -> 5.5 | J61: 5.5 | K61: 0 | L61: 1 | M61: 0 | N61: 0
B62: SMF3/SCK4/LAS1/GYR2/GYR3 MIT2/VGT2/GEU2/GEU3/GEU5 HLI2/TCY2/TCY1/SCK8/SMF6 OAK3/MCE1/LAS6/SJC7/FAT2 PHX5/PHX7/IUTE | C62: =F62*200 -> 1160 | D62: =F62+L62 -> 6.8 | E62: =F62+M62 -> 5.8 | F62: =J62+N62 -> 5.8 | G62: =J62*200 -> 1160 | H62: =D62-N62 -> 6.8 | I62: =E62-N62 -> 5.8 | J62: 5.8 | K62: 0 | L62: 1 | M62: 0 | N62: 0
B63: ABQ2/QXY8/MCC1 | C63: =F63*200 -> 1320 | D63: =F63+L63 -> 7.6 | E63: =F63+M63 -> 6.6 | F63: =J63+N63 -> 6.6 | G63: =J63*200 -> 1320 | H63: =D63-N63 -> 7.6 | I63: =E63-N63 -> 6.6 | J63: 6.6 | K63: 0 | L63: 1 | M63: 0 | N63: 0
B64: FTW1/IUSF/DFW6/IAH3/SAT1 FTW5/STL3/PSC2/PDX7 (标红仓点按12KG起收) 单价按100KG段+1/KG 51KG-100KG按100KG+同价 | C64: =F64*200 -> 1420 | D64: 100KG起收 | E64: 100KG起收 | F64: =J64+N64 -> 7.1 | G64: =J64*200 -> 1420 | H64: 100KG起收 | I64: 100KG起收 | J64: 7.1 | K64: 0 | L64: 1 | M64: 0 | N64: 0
B65: IND9/MDW2/FWA4/MEM1 MQJ1/DEN8/RFD2/ORD2/LFT1 (标红仓点按12KG起收) 单价按100KG段+1/KG 51KG-100KG按100KG+同价 | C65: =F65*200 -> 1460 | D65: 100KG起收 | E65: 100KG起收 | F65: =J65+N65 -> 7.3 | G65: =J65*200 -> 1460 | H65: 100KG起收 | I65: 100KG起收 | J65: 7.3 | K65: 0 | L65: 1 | M65: 0 | N65: 0
B66: CLT2/RDU2/CLT3/RDU4 (标红仓点按12KG起收) 单价按100KG段+1/KG 51KG-100KG按100KG+同价 | C66: =F66*200 -> 1640 | D66: 100KG起收 | E66: 100KG起收 | F66: =J66+N66 -> 8.2 | G66: =J66*200 -> 1640 | H66: 100KG起收 | I66: 100KG起收 | J66: 8.2 | K66: 0 | L66: 1 | M66: 0 | N66: 0
B67: ABE8/AVP1/TEB3/TEB9/TPA3 RMN3/ORF2/SWF2 (标红仓点按12KG起收) 单价按100KG段+1/KG 51KG-100KG按100KG+同价 | C67: =F67*200 -> 1720 | D67: 100KG起收 | E67: 100KG起收 | F67: =J67+N67 -> 8.6 | G67: =J67*200 -> 1720 | H67: 100KG起收 | I67: 100KG起收 | J67: 8.6 | K67: 0 | L67: 1.5 | M67: 0 | N67: 0
B68: 含税自提(含出库费） | C68: =F68*200 -> 1060 | D68: —— | E68: —— | F68: =J68+N68 -> 5.3 | G68: =J68*200 -> 1060 | H68: —— | I68: —— | J68: 5.3 | K68: 0 | N68: 0
A71: SSH以星限时达&长荣定提&义乌合德限时达-卡派 | B71: 仓库代码 | C71: 深圳/广州交货价 | G71: 义乌交货价
C72: 按方含税(2CBM+) | D72: 包税(12KG+) | E72: 包税(51KG+) | F72: 包税(300KG+) | G72: 按方含税(2CBM+) | H72: 包税(12KG+) | I72: 包税(51KG+) | J72: 包税(300KG+) | K72: 按方含税(2CBM+) | L72: 包税(12KG+) | M72: 包税(51KG+) | N72: 深圳和义乌系数
B73: ONT8/LGB8/LAX9/SBD1/IUSP IUSQ/IUSJ/POC1/POC2/POC3 | C73: =F73*200 -> 1320 | D73: =F73+L73 -> 7.6 | E73: =F73+M73 -> 6.6 | F73: =J73+N73 -> 6.6 | G73: =J73*200 -> 1320 | H73: =D73-N73 -> 7.6 | I73: =E73-N73 -> 6.6 | J73: 6.6 | K73: 0 | L73: 1 | M73: 0 | N73: 0 | P73: 0.5
B74: SNA4/SBD2/LGB4/LGB6 XLX7/IUTI/IUSW/PSP3 | C74: =F74*200 -> 1360 | D74: =F74+L74 -> 7.8 | E74: =F74+M74 -> 6.8 | F74: =J74+N74 -> 6.8 | G74: =J74*200 -> 1360 | H74: =D74-N74 -> 7.8 | I74: =E74-N74 -> 6.8 | J74: 6.8 | K74: 0 | L74: 1 | M74: 0 | N74: 0
B75: SMF3/SCK4/LAS1/GYR2/GYR3 MIT2/VGT2/GEU2/GEU3/GEU5 HLI2/TCY2/TCY1/SCK8/SMF6 OAK3/MCE1/LAS6/SJC7/FAT2 PHX5/PHX7/IUTE | C75: =F75*200 -> 1420 | D75: =F75+L75 -> 8.1 | E75: =F75+M75 -> 7.1 | F75: =J75+N75 -> 7.1 | G75: =J75*200 -> 1420 | H75: =D75-N75 -> 8.1 | I75: =E75-N75 -> 7.1 | J75: 7.1 | K75: 0 | L75: 1 | M75: 0 | N75: 0
B76: ABQ2/QXY8/MCC1 | C76: =F76*200 -> 1580 | D76: =F76+L76 -> 8.9 | E76: =F76+M76 -> 7.9 | F76: =J76+N76 -> 7.9 | G76: =J76*200 -> 1580 | H76: =D76-N76 -> 8.9 | I76: =E76-N76 -> 7.9 | J76: 7.9 | K76: 0 | L76: 1 | M76: 0 | N76: 0
B77: FTW1/IUSF/DFW6/IAH3/SAT1 FTW5/STL3/PSC2/PDX7 (标红仓点按12KG起收) 单价按100KG段+1/KG 51KG-100KG按100KG+同价 | C77: =F77*200 -> 1680 | D77: 100KG起收 | E77: 100KG起收 | F77: =J77+N77 -> 8.4 | G77: =J77*200 -> 1680 | H77: 100KG起收 | I77: 100KG起收 | J77: 8.4 | K77: 0 | L77: 1 | M77: 0 | N77: 0
B78: IND9/MDW2/FWA4/MEM1 MQJ1/DEN8/RFD2/ORD2/LFT1 (标红仓点按12KG起收) 单价按100KG段+1/KG 51KG-100KG按100KG+同价 | C78: =F78*200 -> 1720 | D78: 100KG起收 | E78: 100KG起收 | F78: =J78+N78 -> 8.6 | G78: =J78*200 -> 1720 | H78: 100KG起收 | I78: 100KG起收 | J78: 8.6 | K78: 0 | L78: 1 | M78: 0 | N78: 0
B79: CLT2/RDU2/CLT3/RDU4 (标红仓点按12KG起收) 单价按100KG段+1/KG 51KG-100KG按100KG+同价 | C79: =F79*200 -> 1900 | D79: 100KG起收 | E79: 100KG起收 | F79: =J79+N79 -> 9.5 | G79: =J79*200 -> 1900 | H79: 100KG起收 | I79: 100KG起收 | J79: 9.5 | K79: 0 | L79: 1 | M79: 0 | N79: 0
B80: ABE8/AVP1/TEB3/TEB9/TPA3 RMN3/ORF2/SWF2 (标红仓点按12KG起收) 单价按100KG段+1/KG 51KG-100KG按100KG+同价 | C80: =F80*200 -> 1980 | D80: 100KG起收 | E80: 100KG起收 | F80: =J80+N80 -> 9.9 | G80: =J80*200 -> 1980 | H80: 100KG起收 | I80: 100KG起收 | J80: 9.9 | K80: 0 | L80: 1.5 | M80: 0 | N80: 0
B81: 含税自提(含出库费） | C81: =F81*200 -> 1320 | D81: —— | E81: —— | F81: =J81+N81 -> 6.6 | G81: =J81*200 -> 1320 | H81: —— | I81: —— | J81: 6.6 | K81: 0 | N81: 0
A84: SSH义乌合德以星限时达卡派 | B84: 仓库代码 | C84: 深圳/广州交货价 | G84: 义乌交货价
C85: 按方含税(2CBM+) | D85: 包税(12KG+) | E85: 包税(51KG+) | F85: 包税(100KG+) | G85: 按方含税(2CBM+) | H85: 包税(12KG+) | I85: 包税(51KG+) | J85: 包税(100KG+) | K85: 按方含税(2CBM+) | L85: 包税(12KG+) | M85: 包税(51KG+) | N85: 深圳和义乌系数
B86: ONT8/LGB8/LAX9/SBD1/IUSP IUSQ/IUSJ/POC1/POC2/POC3 | C86: =F86*200 -> 1120 | D86: =F86+L86 -> 6.6 | E86: =F86+M86 -> 5.6 | F86: =J86+N86 -> 5.6 | G86: =J86*200 -> 1060 | H86: =D86-N86 -> 6.3 | I86: =E86-N86 -> 5.3 | J86: 5.3 | K86: 0 | L86: 1 | M86: 0 | N86: 0.3 | P86: 40 | Q86: 0.3
B87: SNA4/SBD2/LGB4/LGB6 XLX7/IUTI/IUSW/PSP3 | C87: =F87*200 -> 1160 | D87: =F87+L87 -> 6.8 | E87: =F87+M87 -> 5.8 | F87: =J87+N87 -> 5.8 | G87: =J87*200 -> 1100 | H87: =D87-N87 -> 6.5 | I87: =E87-N87 -> 5.5 | J87: 5.5 | K87: 0 | L87: 1 | M87: 0 | N87: 0.3
B88: SMF3/SCK4/LAS1/GYR2/GYR3 MIT2/VGT2/GEU2/GEU3/GEU5 HLI2/TCY2/TCY1/SCK8/SMF6 OAK3/MCE1/LAS6/SJC7/FAT2 PHX5/PHX7/IUTE | C88: =F88*200 -> 1220 | D88: =F88+L88 -> 7.1 | E88: =F88+M88 -> 6.1 | F88: =J88+N88 -> 6.1 | G88: =J88*200 -> 1160 | H88: =D88-N88 -> 6.8 | I88: =E88-N88 -> 5.8 | J88: 5.8 | K88: 0 | L88: 1 | M88: 0 | N88: 0.3
B89: ABQ2/QXY8/MCC1 | C89: =F89*200 -> 1380 | D89: =F89+L89 -> 7.9 | E89: =F89+M89 -> 6.9 | F89: =J89+N89 -> 6.9 | G89: =J89*200 -> 1320 | H89: =D89-N89 -> 7.6 | I89: =E89-N89 -> 6.6 | J89: 6.6 | K89: 0 | L89: 1 | M89: 0 | N89: 0.3
B90: FTW1/IUSF/DFW6/IAH3/SAT1 FTW5/STL3/PSC2/PDX7 (标红仓点按12KG起收) 单价按100KG段+1/KG 51KG-100KG按100KG+同价 | C90: =F90*200 -> 1480 | D90: 100KG起收 | E90: 100KG起收 | F90: =J90+N90 -> 7.4 | G90: =J90*200 -> 1420 | H90: 100KG起收 | I90: 100KG起收 | J90: 7.1 | K90: 0 | L90: 1 | M90: 0 | N90: 0.3
B91: IND9/MDW2/FWA4/MEM1 MQJ1/DEN8/RFD2/ORD2/LFT1 (标红仓点按12KG起收) 单价按100KG段+1/KG 51KG-100KG按100KG+同价 | C91: =F91*200 -> 1520 | D91: 100KG起收 | E91: 100KG起收 | F91: =J91+N91 -> 7.6 | G91: =J91*200 -> 1460 | H91: 100KG起收 | I91: 100KG起收 | J91: 7.3 | K91: 0 | L91: 1 | M91: 0 | N91: 0.3
B92: CLT2/RDU2/CLT3/RDU4 (标红仓点按12KG起收) 单价按100KG段+1/KG 51KG-100KG按100KG+同价 | C92: =F92*200 -> 1700 | D92: 100KG起收 | E92: 100KG起收 | F92: =J92+N92 -> 8.5 | G92: =J92*200 -> 1640 | H92: 100KG起收 | I92: 100KG起收 | J92: 8.2 | K92: 0 | L92: 1 | M92: 0 | N92: 0.3
B93: ABE8/AVP1/TEB3/TEB9/TPA3 RMN3/ORF2/SWF2 (标红仓点按12KG起收) 单价按100KG段+1/KG 51KG-100KG按100KG+同价 | C93: =F93*200 -> 1780 | D93: 100KG起收 | E93: 100KG起收 | F93: =J93+N93 -> 8.9 | G93: =J93*200 -> 1720 | H93: 100KG起收 | I93: 100KG起收 | J93: 8.6 | K93: 0 | L93: 1.5 | M93: 0 | N93: 0.3
B94: 含税自提(含出库费） | C94: =F94*200 -> 1120 | D94: —— | E94: —— | F94: =J94+N94 -> 5.6 | G94: =J94*200 -> 1060 | H94: —— | I94: —— | J94: 5.3 | K94: 0 | N94: 0.3
A98: 组合/混拆 | B98: 仓库代码/渠道名称 | C98: 深圳/广州交货价 | G98: 义乌交货价
C99: 按方含税(2CBM+) | D99: 包税(12KG+) | E99: 包税(51KG+) | F99: 包税(300KG+) | G99: 按方含税(2CBM+) | H99: 包税(12KG+) | I99: 包税(51KG+) | J99: 包税(300KG+) | K99: 按方含税(2CBM+) | L99: 包税(12KG+) | M99: 包税(51KG+) | N99: 深圳和义乌系数
A100: 组合一区 | B100: ONT8/LGB8/LAX9/SBD1/IUSP IUSQ/IUSJ/POC1/POC2/POC3 | C100: =G100+K100 -> 740 | D100: =F100+L100 -> 4.7 | E100: =F100+M100 -> 3.7 | F100: =J100+N100 -> 3.7 | G100: =J100*200 -> 740 | H100: =D100-N100 -> 4.7 | I100: =E100-N100 -> 3.7 | J100: 3.7 | K100: 0 | L100: 1 | M100: 0 | N100: 0 | P100: 80 | Q100: 0.1
A101: 组合二区 | B101: SNA4/SBD2/LGB4/LGB6 XLX7/IUTI/IUSW/PSP3 | C101: =G101+K101 -> 800 | D101: =F101+L101 -> 5 | E101: =F101+M101 -> 4 | F101: =J101+N101 -> 4 | G101: =J101*200 -> 800 | H101: =D101-N101 -> 5 | I101: =E101-N101 -> 4 | J101: 4 | K101: 0 | L101: 1 | M101: 0 | N101: 0
A102: 组合二区Plus | B102: SMF3/SCK4/LAS1/GYR2/GYR3 MIT2/VGT2/GEU2/GEU3/GEU5 HLI2/TCY2/TCY1/SCK8/SMF6 OAK3/MCE1/LAS6/SJC7/FAT2 PHX5/PHX7/IUTE | C102: =G102+K102 -> 860 | D102: =F102+L102 -> 5.3 | E102: =F102+M102 -> 4.3 | F102: =J102+N102 -> 4.3 | G102: =J102*200 -> 860 | H102: =D102-N102 -> 5.3 | I102: =E102-N102 -> 4.3 | J102: 4.3 | K102: 0 | L102: 1 | M102: 0 | N102: 0
A103: 组合三区 | B103: ABQ2/QXY8/MCC1 | C103: =G103+K103 -> 1020 | D103: =F103+L103 -> 6.1 | E103: =F103+M103 -> 5.1 | F103: =J103+N103 -> 5.1 | G103: =J103*200 -> 1020 | H103: =D103-N103 -> 6.1 | I103: =E103-N103 -> 5.1 | J103: 5.1 | K103: 0 | L103: 1 | M103: 0 | N103: 0
A104: 组合四区 | B104: FTW1/IUSF/DFW6/IAH3/SAT1 FTW5/STL3/PSC2/PDX7 (标红仓点按12KG起收) 单价按100KG段+1/KG 51KG-100KG按100KG+同价 | C104: =G104+K104 -> 1120 | D104: 100KG起收 | E104: 100KG起收 | F104: =J104+N104 -> 5.6 | G104: =J104*200 -> 1120 | H104: 100KG起收 | I104: 100KG起收 | J104: 5.6 | K104: 0 | L104: 1 | M104: 0 | N104: 0
A105: 组合五区 | B105: IND9/MDW2/FWA4/MEM1 MQJ1/DEN8/RFD2/ORD2/LFT1 (标红仓点按12KG起收) 单价按100KG段+1/KG 51KG-100KG按100KG+同价 | C105: =G105+K105 -> 1160 | D105: 100KG起收 | E105: 100KG起收 | F105: =J105+N105 -> 5.8 | G105: =J105*200 -> 1160 | H105: 100KG起收 | I105: 100KG起收 | J105: 5.8 | K105: 0 | L105: 1 | M105: 0 | N105: 0
A106: 组合六区 | B106: CLT2/RDU2/CLT3/RDU4 (标红仓点按12KG起收) 单价按100KG段+1/KG 51KG-100KG按100KG+同价 | C106: =G106+K106 -> 1340 | D106: 100KG起收 | E106: 100KG起收 | F106: =J106+N106 -> 6.7 | G106: =J106*200 -> 1340 | H106: 100KG起收 | I106: 100KG起收 | J106: 6.7 | K106: 0 | L106: 1 | M106: 0 | N106: 0
A107: 组合七区 | B107: ABE8/AVP1/TEB3/TEB9/TPA3 RMN3/ORF2/SWF2 (标红仓点按12KG起收) 单价按100KG段+1/KG 51KG-100KG按100KG+同价 | C107: =G107+K107 -> 1420 | D107: 100KG起收 | E107: 100KG起收 | F107: =J107+N107 -> 7.1 | G107: =J107*200 -> 1420 | H107: 100KG起收 | I107: 100KG起收 | J107: 7.1 | K107: 0 | L107: 1 | M107: 0 | N107: 0
A108: 含税自提(含出库费） | C108: =G108+K108 -> 740 | D108: —— | E108: —— | F108: =J108+N108 -> 3.7 | G108: =J108*200 -> 740 | H108: —— | I108: —— | J108: 3.7 | K108: 0 | L108: 0 | M108: 0 | N108: 0
A110: 组合/混拆 | B110: 仓库代码/渠道名称 | C110: 深圳/广州交货价 | G110: 义乌交货价
C111: 按方含税(2CBM+) | D111: 包税(12KG+) | E111: 包税(51KG+) | F111: 包税(300KG+) | G111: 按方含税(2CBM+) | H111: 包税(12KG+) | I111: 包税(51KG+) | J111: 包税(300KG+) | K111: 按方含税(2CBM+) | L111: 包税(12KG+) | M111: 包税(51KG+) | N111: 深圳和义乌系数
A112: 组合一区 | B112: ONT8/LGB8/LAX9/SBD1/IUSP IUSQ/IUSJ/POC1/POC2/POC3 | C112: =G112+K112 -> 1000 | D112: =F112+L112 -> 6 | E112: =F112+M112 -> 5 | F112: =J112+N112 -> 5 | G112: =J112*200 -> 1000 | H112: =D112-N112 -> 6 | I112: =E112-N112 -> 5 | J112: 5 | K112: 0 | L112: 1 | M112: 0 | N112: 0 | P112: 1.3
...

Sheet 美国海派总表
B1: SSH美森正班-海派 渠道代码：SSH01 （进福建内陆费+0.4/KG）
B2: 交货下单渠道：SSH01-海派
B3: 人民币计价 | J3: 执行日期：2026-3-31
B4: 分区/重量 | C4: 深圳/广州交货 | F4: 义乌交货 | I4: 预计提取时间 | J4: 比重货优惠 | K4: 备注 | L4: 预计派送时效 | M4: 返回主页
C5: 21KG+ | D5: 51KG+ | E5: 100KG+ | F5: 21KG+ | G5: 51KG+ | H5: 100KG+
B6: 美西 (邮编8,9开头) | C6: =价格汇总!C3 -> 15.4 | D6: =价格汇总!D3 -> 13.4 | E6: =价格汇总!E3 -> 12.4 | F6: =价格汇总!F3 -> 15 | G6: =价格汇总!G3 -> 13 | H6: =价格汇总!H3 -> 12 | I6: 开船后第二天开始算,15天内提取-晚一天赔1元,提取当天不计赔偿日,最高赔付3元/KG. (如遇海关查验,节假日,码头停摆，码头罢工等不可抗拒因素，不参与时效赔偿) | J6: 单票51KG以上 重货比优惠： 1:200 表价减0.5元 1:250 表价减1.5元 1:300 表价减2元 1:350 表价减2.5元 1:400 表价减3元 1:500以上 表价减3.5元 | K6: 1，尾程FEDEX/UPS派送 2，材积/6000,不分泡 3，包含关税及查验费 4，报关件5CBM起接 5，入仓清单请注明： 美森正班-海派 | L6: 1-2天
B7: 美中 (邮编4,5,6,7开头) | C7: =价格汇总!C4 -> 16.6 | D7: =价格汇总!D4 -> 14.6 | E7: =价格汇总!E4 -> 13.6 | F7: =价格汇总!F4 -> 16.2 | G7: =价格汇总!G4 -> 14.2 | H7: =价格汇总!H4 -> 13.2 | L7: 3-4天
B8: 美东 (邮编0,1,2,3开头) | C8: =价格汇总!C5 -> 17.6 | D8: =价格汇总!D5 -> 15.6 | E8: =价格汇总!E5 -> 14.6 | F8: =价格汇总!F5 -> 17.2 | G8: =价格汇总!G5 -> 15.2 | H8: =价格汇总!H5 -> 14.2 | L8: 4-5天
B9: SSH美森MAX-海派 渠道代码：SSH02 （进福建内陆费+0.4/KG）
B10: 交货下单渠道：SSH02-海派/SSHJF02-海派
B11: 分区/重量 | C11: 深圳/广州交货 | F11: 义乌交货 | I11: 预计提取时间 | J11: 比重货优惠 | K11: 备注 | L11: 预计派送时效
C12: 21KG+ | D12: 51KG+ | E12: 100KG+ | F12: 21KG+ | G12: 51KG+ | H12: 100KG+
B13: 美西 (邮编8,9开头) | C13: =价格汇总!C6 -> 15.1 | D13: =价格汇总!D6 -> 13.1 | E13: =价格汇总!E6 -> 12.1 | F13: =价格汇总!F6 -> 14.7 | G13: =价格汇总!G6 -> 12.7 | H13: =价格汇总!H6 -> 11.7 | I13: 开船后第二天开始算,16天内提取-晚一天赔1元,提取当天不计赔偿日,最高赔付3元/KG.（海关查验及不可抗因素除外） | J13: 单票51KG以上 重货比优惠： 1:200 表价减0.5元 1:250 表价减1.5元 1:300 表价减2元 1:350 表价减2.5元 1:400 表价减3元 1:500以上 表价减3.5元 | K13: 1，尾程FEDEX/UPS派送 2，材积/6000，不分泡 3，包含关税及查验费 4，入仓清单请注明： 美森加班-海派 | L13: 1-2天
B14: 美中 (邮编4,5,6,7开头) | C14: =价格汇总!C7 -> 16.3 | D14: =价格汇总!D7 -> 14.3 | E14: =价格汇总!E7 -> 13.3 | F14: =价格汇总!F7 -> 15.9 | G14: =价格汇总!G7 -> 13.9 | H14: =价格汇总!H7 -> 12.9 | L14: 3-4天
B15: 美东 (邮编0,1,2,3开头) | C15: =价格汇总!C8 -> 17.3 | D15: =价格汇总!D8 -> 15.3 | E15: =价格汇总!E8 -> 14.3 | F15: =价格汇总!F8 -> 16.9 | G15: =价格汇总!G8 -> 14.9 | H15: =价格汇总!H8 -> 13.9 | L15: 4-5天
B16: SSH快船EXX-海派 渠道代码：SSH03 （进福建内陆费+0.4/KG）
B17: 交货下单渠道：SSH03-海派/SSHJF03-海派
B18: 分区/重量 | C18: 深圳/广州交货 | F18: 义乌交货 | I18: 预计提取时间 | J18: 比重货优惠 | K18: 备注 | L18: 预计派送时效
C19: 21KG+ | D19: 51KG+ | E19: 100KG+ | F19: 21KG+ | G19: 51KG+ | H19: 100KG+
B20: 美西 (邮编8,9开头) | C20: =价格汇总!C9 -> 13.3 | D20: =价格汇总!D9 -> 11.3 | E20: =价格汇总!E9 -> 10.3 | F20: =价格汇总!F9 -> 12.9 | G20: =价格汇总!G9 -> 10.9 | H20: =价格汇总!H9 -> 9.9 | I20: 开船后第二天开始算,16天内提取-晚一天赔1元,提取当天不计赔偿日,最高赔付2元/KG.（海关查验及不可抗因素除外） | J20: 单票51KG以上 重货比优惠： 1:200 表价减0.5元 1:250 表价减1.5元 1:300 表价减2元 1:350 表价减2.5元 1:400 表价减3元 1:500以上 表价减3.5元 | K20: 1，尾程FEDEX/UPS派送 2，材积/6000，不分泡 3，包含关税及查验费 4，入仓清单请注明： 快船EXX-海派 | L20: 1-2天
B21: 美中 (邮编4,5,6,7开头) | C21: =价格汇总!C10 -> 14.5 | D21: =价格汇总!D10 -> 12.5 | E21: =价格汇总!E10 -> 11.5 | F21: =价格汇总!F10 -> 14.1 | G21: =价格汇总!G10 -> 12.1 | H21: =价格汇总!H10 -> 11.1 | L21: 3-4天
B22: 美东 (邮编0,1,2,3开头) | C22: =价格汇总!C11 -> 15.5 | D22: =价格汇总!D11 -> 13.5 | E22: =价格汇总!E11 -> 12.5 | F22: =价格汇总!F11 -> 15.1 | G22: =价格汇总!G11 -> 13.1 | H22: =价格汇总!H11 -> 12.1 | L22: 4-5天
B23: SSH盐田以星南沙合德限时达-海派 渠道代码：SSH04
B24: 交货深圳/广州下单渠道：SSH04-海派
B25: 分区/重量 | C25: 深圳交货 | F25: 广州交货 | I25: 预计提取时间 | J25: 比重货优惠 | K25: 备注 | L25: 预计派送时效
C26: 21KG+ | D26: 51KG+ | E26: 100KG+ | F26: 21KG+ | G26: 51KG+ | H26: 100KG+
B27: 美西 (邮编8,9开头) | C27: =价格汇总!C12 -> 12 | D27: =价格汇总!D12 -> 10 | E27: =价格汇总!E12 -> 9 | F27: =价格汇总!F12 -> 12 | G27: =价格汇总!G12 -> 10 | H27: =价格汇总!H12 -> 9 | I27: 开船后第二天开始算,18天内提取-晚一天赔0.5元,提取当天不计赔偿日,最高赔付1元/KG.（海关查验及不可抗因素除外） | J27: 单票51KG以上 重货比优惠： 1:200减0.5 1:250减1 1:300减1.5 1:350减2 1:450及以上减2.5 | K27: 1，尾程FEDEX/UPS派送 2，材积/6000，不分泡 3，包含关税及查验费 4，入仓清单请注明： 美西限时达-海派 | L27: 1-2天
B28: 美中 (邮编4,5,6,7开头) | C28: =价格汇总!C13 -> 13.2 | D28: =价格汇总!D13 -> 11.2 | E28: =价格汇总!E13 -> 10.2 | F28: =价格汇总!F13 -> 13.2 | G28: =价格汇总!G13 -> 11.2 | H28: =价格汇总!H13 -> 10.2 | L28: 3-4天
B29: 美东 (邮编0,1,2,3开头) | C29: =价格汇总!C14 -> 14.2 | D29: =价格汇总!D14 -> 12.2 | E29: =价格汇总!E14 -> 11.2 | F29: =价格汇总!F14 -> 14.2 | G29: =价格汇总!G14 -> 12.2 | H29: =价格汇总!H14 -> 11.2 | L29: 4-5天
B30: SSH义乌合德以星限时达-海派 渠道代码：SSHYW05（进福建内陆费+0.4/KG）
B31: 交货深圳/广州/义乌下单渠道：SSHYW05-海派/SSHYWJF05-海派
B32: 分区/重量 | C32: 深圳、广州交货 | F32: 义乌交货 | I32: 预计提取时间 | J32: 比重货优惠 | K32: 备注 | L32: 预计派送时效
C33: 21KG+ | D33: 51KG+ | E33: 100KG+ | F33: 21KG+ | G33: 51KG+ | H33: 100KG+
B34: 美西 (邮编8,9开头) | C34: =价格汇总!C15 -> 12.3 | D34: =价格汇总!D15 -> 10.3 | E34: =价格汇总!E15 -> 9.3 | F34: =价格汇总!F15 -> 12 | G34: =价格汇总!G15 -> 10 | H34: =价格汇总!H15 -> 9 | I34: 开船后第二天开始算,18天内提取-晚一天赔0.5元,提取当天不计赔偿日,最高赔付1元/KG.（海关查验及不可抗因素除外） | J34: 单票51KG以上 重货比优惠： 1:200减0.5 1:250减1 1:300减1.5 1:350减2 1:450及以上减2.5 | K34: 1，尾程FEDEX/UPS派送 2，材积/6000，不分泡 3，包含关税及查验费 4，入仓清单请注明： 美西限时达-海派 | L34: 1-2天
B35: 美中 (邮编4,5,6,7开头) | C35: =价格汇总!C16 -> 13.5 | D35: =价格汇总!D16 -> 11.5 | E35: =价格汇总!E16 -> 10.5 | F35: =价格汇总!F16 -> 13.2 | G35: =价格汇总!G16 -> 11.2 | H35: =价格汇总!H16 -> 10.2 | L35: 3-4天
B36: 美东 (邮编0,1,2,3开头) | C36: =价格汇总!C17 -> 14.5 | D36: =价格汇总!D17 -> 12.5 | E36: =价格汇总!E17 -> 11.5 | F36: =价格汇总!F17 -> 14.2 | G36: =价格汇总!G17 -> 12.2 | H36: =价格汇总!H17 -> 11.2 | L36: 4-5天
B37: SSH普船洛杉矶-海派 渠道代码：SSH07 （进福建内陆费+0.4/KG）
B38: 交货深圳下单渠道：SSH07-海派 交货义乌下单渠道：SSHYW07-海派/SSHYWJF07--海派（义乌普船进深圳、广州内陆费+0.3/KG）
B39: 分区/重量 | C39: 深圳/广州交货 | F39: 义乌交货 | I39: 预计提取时间 | J39: 比重货优惠 | K39: 备注 | L39: 预计派送时效
C40: 21KG+ | D40: 51KG+ | E40: 100KG+ | F40: 21KG+ | G40: 51KG+ | H40: 100KG+
B41: 美西 (邮编8,9开头) | C41: =价格汇总!C18 -> 10.8 | D41: =价格汇总!D18 -> 8.8 | E41: =价格汇总!E18 -> 7.8 | F41: =价格汇总!F18 -> 10.8 | G41: =价格汇总!G18 -> 8.8 | H41: =价格汇总!H18 -> 7.8 | I41: 开船后20-25天提取（海关查验及不可抗因素除外） | J41: 单票51KG以上 重货比优惠： 1:200减0.3 1:250减0.6 1:300减0.9 1:350减1.2 1:450及以上减1.5 | K41: 1，尾程FEDEX/UPS派送 2，材积/6000，不分泡 3，包含关税及查验费 4，入仓清单请注明： 普船洛杉矶-海派 | L41: 1-2天
B42: 美中 (邮编4,5,6,7开头) | C42: =价格汇总!C19 -> 12 | D42: =价格汇总!D19 -> 10 | E42: =价格汇总!E19 -> 9 | F42: =价格汇总!F19 -> 12 | G42: =价格汇总!G19 -> 10 | H42: =价格汇总!H19 -> 9 | L42: 3-4天
B43: 美东 (邮编0,1,2,3开头) | C43: =价格汇总!C20 -> 13 | D43: =价格汇总!D20 -> 11 | E43: =价格汇总!E20 -> 10 | F43: =价格汇总!F20 -> 13 | G43: =价格汇总!G20 -> 11 | H43: =价格汇总!H20 -> 10 | L43: 4-5天
B45: 一，特殊产品附加费列表 | J45: 税率查询网址： | K45: https://hts.usitc.gov/
B46: 类别 | C46: 以下特殊产品需额外加收附加费 | L46: 加收金额
B47: A类 | C47: 帽子、箱包、鞋类、服装、袜子等全纺织类穿戴产品，圆珠笔类产品 | L47: 1元/KG或200RMB/CBM
B48: 玩具类 | C48: 玩具和儿童用品（适用6岁以下玩具不接），需要CPC认证，CPC report，Track label(permanent mark),无CPC认证不接! 出货前请提供有效认证，并保证货物符合美国进口要求。我司不保证所有认证和产品被海关认可，如遇查验最终以海关判断为准，我司不承担任何责任. | L48: 1元/KG或200RMB/CBM
B49: 额外声明 | C49: 2025年3月4号以后如果美国对华临时增税，清关税率平均每上涨10%，公司会针对在途未清关的货物补收增加的关税成本0.5RMB/KG或100元/方,以此类推！ | L49: 0.5元/KG或100RMB/CBM
B50: 拒收类 | C50: 1、手机、笔记本电脑、激光类产品，液体、粉末、U盘、光驱、内存条、打火机，活性植物，太阳眼镜、化妆品，食品、婴儿用品（包括衣服），药品、易燃易爆、古董、货币等国家禁止出口产品，如发现罚款￥2000-5000/票，情节严重上报公安局处理！ 2、航空箱，超大件，变形软箱，无规则易破损纸箱，非纸箱包装，不可拆封产品，强烈气味产品。 3、反倾销产品(参考美国对华反倾销产品目录表) | L50: 拒收
B51: 二，其它附加费用说明
B52: 费用类别 | K52: 收费标准 | L52: 是否叠加
B53: 1，高价值产品(平均价值大于1500$/100KG，大于5000$/100KG高价值产品单询)，建议购买跨境类保险. | K53: 1元RMB/KG | L53: 不叠加
B54: 2，关于超重：单箱实重不得超过22KG，如有实重超22KG，加收RMB150/箱，单箱超22.5KG无服务。 关于超长：最长边超过120CM，或次长边超75CM，或长+2*（宽+高）超过260cm，满足其中一项则需加收RMB150/箱；超大尺寸不接： ①、单件实重超22.5KGKG；②、最长边超过230cm；③、长+2*（宽+高）超过300cm的货物。 关于偏远：亚马逊邮编偏远+2RMB/KG；私人住宅+25RMB/件；非亚马逊（商业地址、私人住宅）邮编偏远+3RMB/KG；偏远费用账单，我司可在发货后六个月内进行补收。 关于地址修正费用：如果发件人通知UPS/FEDEX进行地址修改，或者UPS/FEDEX自动更正地址的账单，发件人需无条件支付（单证制单错误除外），最低200RMB/箱，如超出具体以实际产生的为准。 关于包装额外处理费：绑带、保鲜膜或者布料、或者圆形的包装、木的金属的还有其他的一些情况都会产生包装额外处理费，具体金额按照UPS/FEDEX账单加乘账号使用费实报实销。 货物打单后更改地址，重新贴标签：收费USD10/件最低USD150/票，分货费实报实销;退再寄货物二次派送UPS/FEDEX寄件费用另计。目的港送货退回美国仓库USD1.5/KG 最低收费USD150/票仓租另计； | K54: 30元RMB/个 | L54: 叠加
B55: 3，单独报关，请对接报关专员提供授权码（报关文件资料请单独对接我司报关专员，如未对接报关专员漏报不负责，如因客户单证申报不祥产生仓租柜租罚款由寄件人承担所有费用，10万美金以上的单证不接），如漏报关最高赔偿报关费3倍！（另：如海关查验报关单与实际产品不符产生罚款由寄件人承担100%责任！） | K55: 200RMB/票 | L55: 叠加
B56: 4，商检费，竹木藤条等出口需要商检报关的产品： 单独报关费200RMB/票。 商检费：买单报关件木制品商检费+0.5RMB/KG或800RMB/票；报关退税件木制品商检费客户可自行做商检。需要商检的货物：木家私，木制工艺品，木架，竹制品，藤制品等（仅供参考） | K56: 见左侧说明 | L56: 叠加
B57: 5，拦截扣件：海运渠道如需在美国扣件请在船舶到港前的5个工作日前通知，改派地址或拦截扣件会产生手续费及仓库杂费，UPS取件后如需申请退件，并不保证100%申请退件成功，并会产生退件手续费和UPS二次派送费！ | K57: $0.5/件*该柜总件数 （最低收费$200/票） | L57: 叠加
B58: 6，扣件事项特别说明： 1>:扣件必需要在船舶到港前5个工作日前通知，按正常收取扣件费， 2>:船舶到港前的5个工作日内通知扣件需额外加收200$/票， 3>:船舶已到港后通知扣件的，需额外加收扣件费500$/票，并不保证100%能扣件成功。 | K58: 见左侧说明 | L58: 叠加
B59: 7,运费结算说明： 1>:我司以上渠道请在收到账单后三天内核对并即时付款，如未即时核对账单并支付运费，我司将做留仓处理; 2>:如已出仓并在柜子到港前3个工作日前还未全部结清运费，我司将在海外仓做扣件处理，扣件费$1000/票，由此造成的时效延误及扣件产生的所有费用全部由寄件人承担，非常感谢您的理解和配合！ | K59: 1000$ | L59: 叠加
B60: 特别声明：不得谎报漏报品名，拒收液体，粉未，仿牌，食品，医疗美容产品，纯电池，反倾销类,集运货,水烟壶及配件等敏感产品！一旦查出罚款5000RMB/票，并由发货方承担由此产生的海关扣关罚款及连带责任！
B62: 三，拒接产品
B63: 1.FDA产品：皮肤接触类产品:活性植物，口杯，牙刷头、温度计、眼镜、纹眉笔、剃毛器，按摩仪器，医疗用品，化妆品，内衣，婴儿及儿童产品儿童玩具，毛绒玩具等需FDA认证产品 2.侵权产品：蓝牙标及包装有蓝牙字样及标识产品，三叉戟数据线，CE,HDMI,FCC,LACEY ACT DOT,RW,标识。 3.违禁品：护照身份证私人物品，成人男女性用品，打火机(包括USB打火机),手机，对讲机，移动电源，电子烟，彩印，硒鼓，墨盒，血压计，安全锤，手推车，电动滑板车，钢钉，文具本，手表，铅笔，折叠型金属桌椅，仿牌，冒牌，侵权，纯电池，危险品，液体，和木箱/铁箱等包装难以打开检查的货物，不规则货物，非纸箱货物。 4.反倾销类产品：智能手环， 蜡烛灯(有蜡)，折叠礼品盒，铁钳合金，邹纹纸，天然猪鬃油漆刷及刷头，重煅造手工具，薄页纸，刹车转子，无可锻性铸铁管件，镁金属，铁制建筑铸件，纯镁，圆锥滚子轴承及部件，硅金属，折叠金属桌椅，草坪和花园铁制栅栏支架，彩色电视机，氯代异氰，画布，碳钢焊接接口，落地式金属台面烫衣板及部件，石油蜡烛，钢筋，铸造焦碳，原聚酯棉印花布，文具纸(记事本），螺旋形弹簧锁垫圈，定尺碳钢板，颗粒状纯镁，热轧碳钢板，棕刚玉，曲别针，搪瓷厨具，铅笔，硅锰合金，"可锻性玛钢管件"，咔唑紫颜料，手推车，钢钉，圆形焊接碳钢管件，新充气工程机械轮胎，低克重热敏纸，未加工橡胶磁，小直径石墨电极，圆形焊接奥氏体不锈高压套管，汽车大灯及汽车设备部件，贱金属及其制品(铁、钢、铜、镍、铝、铅、锌、锡、钨), 化学产品，木制卧室家具，复合木地板，非晶硅织物，晶体硅光伏电池，小直径石墨电极，机械电气设备及部件，纸及纸制品，纺织制品-聚酯人造纤维，编织电热毯，预制食品与饮料，复合编织袋，聚乙烯手提袋，矿石及矿物燃料，家用电器，自行车，车船运输设备及部件，建材与玻璃制品等。
B64: 四，海运专线赔偿方案：
B65: 索赔程序： | C65: 如有货件部分UPS未提取或未签收，请客户在7-10个工作日内查询FBA后台是否上架，10个工作日后提供货物未上架后台截图(需带有电脑屏幕右下角当下真实时间)至我司方可进入索赔程序，索赔请以书面形式向我司发起，超过20工作日不予受理。
B66: 赔偿方案: | C66: 情况1：货物在运输过程中丢失(整票UPS未提取)，按提供的商业发票申报货值赔偿但最高不超40RMB/KG赔偿，不退运费； 情况2：已交UPS后(包括整票货件偶尔未扫描货件，此为UPS常见漏扫现象我司不负责)丢失的不退运费,按UPS赔偿方案做申报价值赔偿最高不超100USD/票。索赔请以书面形式向我司发起（温馨提示：高货值产品烦请自行购买货物运输保险！）
B67: 扣关赔偿方案： | C67: 扣关起达到60个工作日以上（如因发件人低申报、品名申报不符、产品涉及反倾销、认证、侵权等情况，责任由发件人承担）按申报货值赔偿最高不超过￥15元/KG，不退运费，索赔请以书面形式向我司发起。
B68: 特别提示:如客户一旦同意接受我司服务，我司将默认为客户已详细阅读过此价格表内所有备注条款内容，并接受各条款的约束，严格按照备注条款内容执行!

Sheet 美森正班卡派
B1: SSH美森正班卡派 渠道代码：SSH01 （进福建内陆费+0.4/KG）
B3: 下单渠道：SSH01卡派/SSH01卡派-按方计费
B4: 人民币报价 | K4: 执行日期：2026-3-31
B5: 仓库代码 | C5: 深圳/广州交货价 | G5: 义乌交货价 | K5: 入仓参考时效 （开船后次日起算） | L5: 理赔时效 (自然日) | M5: 返回主页
C6: 按方含税(2CBM+) | D6: 包税(12KG+) | E6: 包税(51KG+) | F6: 包税(100KG+) | G6: 按方含税(2CBM+) | H6: 包税(12KG+) | I6: 包税(51KG+) | J6: 包税(100KG+)
B7: ONT8/LGB8/LAX9/SBD1 IUSP/IUSQ/IUSJ/POC1 POC2/POC3 | C7: =价格汇总!C24 -> 1800 | D7: =价格汇总!D24 -> 10 | E7: =价格汇总!E24 -> 9 | F7: =价格汇总!F24 -> 9 | G7: =价格汇总!G24 -> 1720 | H7: =价格汇总!H24 -> 9.6 | I7: =价格汇总!I24 -> 8.6 | J7: =价格汇总!J24 -> 8.6 | K7: 12-15天 | L7: 16天 (开船第二天开始,承诺16天内入仓(送仓当日不算赔付时效),第17天开始, 退0.5元/KG/每天,最多退2元/KG)
B8: SNA4/SBD2/LGB4/LGB6 XLX7/IUTI/IUSW/PSP3 | C8: =价格汇总!C25 -> 1840 | D8: =价格汇总!D25 -> 10.2 | E8: =价格汇总!E25 -> 9.2 | F8: =价格汇总!F25 -> 9.2 | G8: =价格汇总!G25 -> 1760 | H8: =价格汇总!H25 -> 9.8 | I8: =价格汇总!I25 -> 8.8 | J8: =价格汇总!J25 -> 8.8 | K8: 13-16天 | L8: 无时效理赔
B9: SMF3/SCK4/LAS1/GYR2 GYR3/MIT2/VGT2/GEU2 GEU3/GEU5/HLI2/TCY2 TCY1/SCK8/SMF6/OAK3 MCE1/LAS6/SJC7/FAT2 PHX5/PHX7/IUTE | C9: =价格汇总!C26 -> 1900 | D9: =价格汇总!D26 -> 10.5 | E9: =价格汇总!E26 -> 9.5 | F9: =价格汇总!F26 -> 9.5 | G9: =价格汇总!G26 -> 1820 | H9: =价格汇总!H26 -> 10.1 | I9: =价格汇总!I26 -> 9.1 | J9: =价格汇总!J26 -> 9.1 | K9: 13-16天 | L9: 无时效理赔
B10: ABQ2/QXY8/MCC1 | C10: =价格汇总!C27 -> 2060 | D10: =价格汇总!D27 -> 11.3 | E10: =价格汇总!E27 -> 10.3 | F10: =价格汇总!F27 -> 10.3 | G10: =价格汇总!G27 -> 1980 | H10: =价格汇总!H27 -> 10.9 | I10: =价格汇总!I27 -> 9.9 | J10: =价格汇总!J27 -> 9.9 | K10: 13-16天 | L10: 17天 (开船第二天开始,承诺17天内入仓(送仓当日不算赔付时效),第18天开始, 退0.5元/KG/每天,最多退2元/KG)
B11: FTW1/IUSF/DFW6/IAH3 SAT1/FTW5/STL3/PSC2 PDX7 (标红仓点按12KG起收) 单价按100KG段+1/KG 51KG-100KG按100KG+同价 | C11: =价格汇总!C28 -> 2160 | D11: =价格汇总!D28 -> 100KG起收 | E11: =价格汇总!E28 -> 100KG起收 | F11: =价格汇总!F28 -> 10.8 | G11: =价格汇总!G28 -> 2080 | H11: =价格汇总!H28 -> 100KG起收 | I11: =价格汇总!I28 -> 100KG起收 | J11: =价格汇总!J28 -> 10.4 | K11: 14-17天 | L11: 无时效理赔
B12: IND9/MDW2/FWA4/MEM1 MQJ1/DEN8/RFD2/ORD2 LFT1 (标红仓点按12KG起收) 单价按100KG段+1/KG 51KG-100KG按100KG+同价 | C12: =价格汇总!C29 -> 2200 | D12: =价格汇总!D29 -> 100KG起收 | E12: =价格汇总!E29 -> 100KG起收 | F12: =价格汇总!F29 -> 11 | G12: =价格汇总!G29 -> 2120 | H12: =价格汇总!H29 -> 100KG起收 | I12: =价格汇总!I29 -> 100KG起收 | J12: =价格汇总!J29 -> 10.6 | K12: 15-18天 | L12: 无时效理赔
B13: CLT2/RDU2/CLT3/RDU4 (标红仓点按12KG起收) 单价按100KG段+1/KG 51KG-100KG按100KG+同价 | C13: =价格汇总!C30 -> 2380 | D13: =价格汇总!D30 -> 100KG起收 | E13: =价格汇总!E30 -> 100KG起收 | F13: =价格汇总!F30 -> 11.9 | G13: =价格汇总!G30 -> 2300 | H13: =价格汇总!H30 -> 100KG起收 | I13: =价格汇总!I30 -> 100KG起收 | J13: =价格汇总!J30 -> 11.5 | K13: 15-18天 | L13: 无时效理赔
B14: ABE8/AVP1/TEB3/TEB9 TPA3 /RMN3/ORF2/SWF2 (标红仓点按12KG起收) 单价按100KG段+1/KG 51KG-100KG按100KG+同价 | C14: =价格汇总!C31 -> 2460 | D14: =价格汇总!D31 -> 100KG起收 | E14: =价格汇总!E31 -> 100KG起收 | F14: =价格汇总!F31 -> 12.3 | G14: =价格汇总!G31 -> 2380 | H14: =价格汇总!H31 -> 100KG起收 | I14: =价格汇总!I31 -> 100KG起收 | J14: =价格汇总!J31 -> 11.9 | K14: 18-20天 | L14: 无时效理赔
B15: 含税自提(出库费15美金/托 汇率7） | C15: =价格汇总!C32 -> 1800 | D15: =价格汇总!D32 -> —— | E15: =价格汇总!E32 -> —— | F15: =价格汇总!F32 -> 9 | G15: =价格汇总!G32 -> 1720 | H15: =价格汇总!H32 -> —— | I15: =价格汇总!I32 -> —— | J15: =价格汇总!J32 -> 8.6 | K15: 13-16天 | L15: 无时效理赔
B16: 单票51KG以上,重货减免优惠：1:200减0.5,1:250减1.5,1:300减2,1:350减2.5,1:450减3,1:500及以上减3.5.
B17: 理赔注意事项
B18: 1>以上按方/按公斤含税价格含海关查验及查验引起的其它费用.包税价格含查验费,除查验费外的其他费用，例如亚马逊爆仓引起的仓租/柜租，非我司原因导致的亚马逊拒收产生的相关费用，申报不符海关惩罚金,扣关,退运等包税价格都是不包含的，请客户将这些官方收费也考虑到成本中，以免引起误会； 2>按方含税价格包含海关查验费，如因报关资料问题引起的出口查验由客人承担所有相关费用（如仓租，柜租，改船费等),因为国外清关资质认证问题或者产品本身问题导致的查验费及额外费用由这票货来承担； 3>不可抗力因素造成的时效延误不在赔偿范围内，如：海关查验，如自然灾害、如台风、地震、洪水、冰雹,，暴风雪；政府行为，社会异常事件，如罢工、骚乱三方面，疫情原因导致仓库预约困难或延识误等。 4>拒收一切敏感货，冲货如被海关扣货罚没销毁等，不退运费，我司也不承担任何责任.品名必需如实申报,如遇查验,申报与实际品名不一致将会产生巨额关税,客户自负.
B22: 服务小贴士
B23: 1>为了更好的服务客户和统计仓位，来货请务必贴上我司的进仓标签. 2>空仓费产生情况：过了截单时间做的行为；更改渠道、客户原因延船期等；货物在截货时间前未到我司国内仓库.
B25: 其它费用
B26: 按方渠道的计费重是按实际立方数和实重/363取大值计算的,卡派单箱无最低计费重量限制，托盘货物不按方算. 最长边超过120CM小于165CM加收RMB1/KG(按方含税+200/CBM),单边超过165CM拒收； 报关费按200RMB/票。 托盘、木架、木箱类货物泡货计费重*1.1*1.1算计费重； 实重托盘比重达到1:200的比重系数*0.75算比重系数，计费重不*1.1。 自提出库费按“单板限2方/1200磅”取较大值计费，超出部分按第二板计算；超大件自提费用请单独咨询客服。

Sheet 美森MAX卡派
B1: SSH美森MAX卡派 渠道代码：SSH02 （进福建内陆费+0.4/KG）
B3: 下单渠道：SSH02卡派/SSHJF02卡派 SSH02卡派-按方计费/SSHJF02-按方计费
B4: 人民币报价 | K4: 执行日期：2026-3-31
B5: 仓库代码 | C5: 深圳/广州交货价 | G5: 义乌交货价 | K5: 入仓参考时效 （开船后次日起算） | L5: 理赔时效 (自然日) | M5: 返回主页
C6: 按方含税(2CBM+) | D6: 包税(12KG+) | E6: 包税(51KG+) | F6: 包税(100KG+) | G6: 按方含税(2CBM+) | H6: 包税(12KG+) | I6: 包税(51KG+) | J6: 包税(100KG+)
B7: ONT8/LGB8/LAX9/SBD1 IUSP/IUSQ/IUSJ/POC1 POC2/POC3 | C7: =价格汇总!C36 -> 1740 | D7: =价格汇总!D36 -> 9.7 | E7: =价格汇总!E36 -> 8.7 | F7: =价格汇总!F36 -> 8.7 | G7: =价格汇总!G36 -> 1660 | H7: =价格汇总!H36 -> 9.3 | I7: =价格汇总!I36 -> 8.3 | J7: =价格汇总!J36 -> 8.3 | K7: 13-16天 | L7: 17天 (开船第二天开始,承诺17天内入仓(送仓当日不算赔付时效),第18天开始, 退0.5元/KG/每天,最多退2元/KG)
B8: SNA4/SBD2/LGB4/LGB6 XLX7/IUTI/IUSW/PSP3 | C8: =价格汇总!C37 -> 1780 | D8: =价格汇总!D37 -> 9.9 | E8: =价格汇总!E37 -> 8.9 | F8: =价格汇总!F37 -> 8.9 | G8: =价格汇总!G37 -> 1700 | H8: =价格汇总!H37 -> 9.5 | I8: =价格汇总!I37 -> 8.5 | J8: =价格汇总!J37 -> 8.5 | K8: 14-17天 | L8: 无时效理赔
B9: SMF3/SCK4/LAS1/GYR2 GYR3/MIT2/VGT2/GEU2 GEU3/GEU5/HLI2/TCY2 TCY1/SCK8/SMF6/OAK3 MCE1/LAS6/SJC7/FAT2 PHX5/PHX7/IUTE | C9: =价格汇总!C38 -> 1840 | D9: =价格汇总!D38 -> 10.2 | E9: =价格汇总!E38 -> 9.2 | F9: =价格汇总!F38 -> 9.2 | G9: =价格汇总!G38 -> 1760 | H9: =价格汇总!H38 -> 9.8 | I9: =价格汇总!I38 -> 8.8 | J9: =价格汇总!J38 -> 8.8 | K9: 14-17天 | L9: 18天 (开船第二天开始,承诺18天内入仓(送仓当日不算赔付时效),第19天开始, 退0.5元/KG/每天,最多退2元/KG)
B10: ABQ2/QXY8/MCC1 | C10: =价格汇总!C39 -> 2000 | D10: =价格汇总!D39 -> 11 | E10: =价格汇总!E39 -> 10 | F10: =价格汇总!F39 -> 10 | G10: =价格汇总!G39 -> 1920 | H10: =价格汇总!H39 -> 10.6 | I10: =价格汇总!I39 -> 9.6 | J10: =价格汇总!J39 -> 9.6 | K10: 15-18天 | L10: 无时效理赔
B11: FTW1/IUSF/DFW6/IAH3 SAT1/FTW5/STL3/PSC2 PDX7 (标红仓点按12KG起收) 单价按100KG段+1/KG 51KG-100KG按100KG+同价 | C11: =价格汇总!C40 -> 2100 | D11: =价格汇总!D40 -> 100KG起收 | E11: =价格汇总!E40 -> 100KG起收 | F11: =价格汇总!F40 -> 10.5 | G11: =价格汇总!G40 -> 2020 | H11: =价格汇总!H40 -> 100KG起收 | I11: =价格汇总!I40 -> 100KG起收 | J11: =价格汇总!J40 -> 10.1 | K11: 15-18天 | L11: 无时效理赔
B12: IND9/MDW2/FWA4/MEM1 MQJ1/DEN8/RFD2/ORD2 LFT1 (标红仓点按12KG起收) 单价按100KG段+1/KG 51KG-100KG按100KG+同价 | C12: =价格汇总!C41 -> 2140 | D12: =价格汇总!D41 -> 100KG起收 | E12: =价格汇总!E41 -> 100KG起收 | F12: =价格汇总!F41 -> 10.7 | G12: =价格汇总!G41 -> 2060 | H12: =价格汇总!H41 -> 100KG起收 | I12: =价格汇总!I41 -> 100KG起收 | J12: =价格汇总!J41 -> 10.3 | K12: 19-25天 | L12: 无时效理赔
B13: CLT2/RDU2/CLT3/RDU4 (标红仓点按12KG起收) 单价按100KG段+1/KG 51KG-100KG按100KG+同价 | C13: =价格汇总!C42 -> 2320 | D13: =价格汇总!D42 -> 100KG起收 | E13: =价格汇总!E42 -> 100KG起收 | F13: =价格汇总!F42 -> 11.6 | G13: =价格汇总!G42 -> 2240 | H13: =价格汇总!H42 -> 100KG起收 | I13: =价格汇总!I42 -> 100KG起收 | J13: =价格汇总!J42 -> 11.2 | K13: 19-25天 | L13: 无时效理赔
B14: ABE8/AVP1/TEB3/TEB9 TPA3 /RMN3/ORF2/SWF2 (标红仓点按12KG起收) 单价按100KG段+1/KG 51KG-100KG按100KG+同价 | C14: =价格汇总!C43 -> 2400 | D14: =价格汇总!D43 -> 100KG起收 | E14: =价格汇总!E43 -> 100KG起收 | F14: =价格汇总!F43 -> 12 | G14: =价格汇总!G43 -> 2320 | H14: =价格汇总!H43 -> 100KG起收 | I14: =价格汇总!I43 -> 100KG起收 | J14: =价格汇总!J43 -> 11.6 | K14: 19-25天 | L14: 无时效理赔
B15: 含税自提(出库费15美金/托 汇率7） | C15: =价格汇总!C44 -> 1740 | D15: =价格汇总!D44 -> —— | E15: =价格汇总!E44 -> —— | F15: =价格汇总!F44 -> 8.7 | G15: =价格汇总!G44 -> 1660 | H15: =价格汇总!H44 -> —— | I15: =价格汇总!I44 -> —— | J15: =价格汇总!J44 -> 8.3 | K15: 13-15天 | L15: 无时效理赔
B16: 单票51KG以上,重货减免优惠：1:200减0.5,1:250减1.5,1:300减2,1:350减2.5,1:450减3,1:500及以上减3.5.
B17: 理赔注意事项
B18: 1>以上按方/按公斤含税价格含海关查验及查验引起的其它费用.包税价格含查验费,除查验费外的其他费用，例如亚马逊爆仓引起的仓租/柜租，非我司原因导致的亚马逊拒收产生的相关费用，申报不符海关惩罚金,扣关,退运等包税价格都是不包含的，请客户将这些官方收费也考虑到成本中，以免引起误会； 2>按方含税价格包含海关查验费，如因报关资料问题引起的出口查验由客人承担所有相关费用（如仓租，柜租，改船费等),因为国外清关资质认证问题或者产品本身问题导致的查验费及额外费用由这票货来承担； 3>不可抗力因素造成的时效延误不在赔偿范围内，如：海关查验，如自然灾害、如台风、地震、洪水、冰雹,，暴风雪；政府行为，社会异常事件，如罢工、骚乱三方面，疫情原因导致仓库预约困难或延识误等。 4>拒收一切敏感货，冲货如被海关扣货罚没销毁等，不退运费，我司也不承担任何责任.品名必需如实申报,如遇查验,申报与实际品名不一致将会产生巨额关税,客户自负.
B22: 服务小贴士
B23: 1>为了更好的服务客户和统计仓位，来货请务必贴上我司的进仓标签.
B24: 2>空仓费产生情况：过了截单时间做的行为；更改渠道、客户原因延船期等；货物在截货时间前未到我司国内仓库.
B25: 其它费用
B26: 按方渠道的计费重是按实际立方数和实重/363取大值计算的,卡派单箱无最低计费重量限制，托盘货物不按方算. 最长边超过120CM小于165CM加收RMB1/KG(按方含税+200/CBM),单边超过165CM拒收； 报关费按200RMB/票。 托盘、木架、木箱类货物泡货计费重*1.1*1.1算计费重； 实重托盘比重达到1:200的比重系数*0.75算比重系数，计费重不*1.1。 自提出库费按“单板限2方/1200磅”取较大值计费，超出部分按第二板计算；超大件自提费用请单独咨询客服。

Sheet EXX卡派
B1: SSH快船EXX卡派 渠道代码：SSH03 （进福建内陆费+0.4/KG）
B3: 下单渠道：SSH03卡派/SSHJF03卡派 SSH03卡派-按方计费/SSHJF03-按方计费
B4: 人民币报价 | K4: 执行日期：2026-3-31
B5: 仓库代码 | C5: 深圳/广州交货价 | G5: 义乌交货价 | K5: 入仓参考时效 （开船后次日起算） | L5: 理赔时效 (自然日) | M5: 返回主页
C6: 按方含税(2CBM+) | D6: 包税(12KG+) | E6: 包税(51KG+) | F6: 包税(100KG+) | G6: 按方含税(2CBM+) | H6: 包税(12KG+) | I6: 包税(51KG+) | J6: 包税(100KG+)
B7: ONT8/LGB8/LAX9/SBD1 IUSP/IUSQ/IUSJ/POC1 POC2/POC3 | C7: =价格汇总!C48 -> 1260 | D7: =价格汇总!D48 -> 7.3 | E7: =价格汇总!E48 -> 6.3 | F7: =价格汇总!F48 -> 6.3 | G7: =价格汇总!G48 -> 1180 | H7: =价格汇总!H48 -> 6.9 | I7: =价格汇总!I48 -> 5.9 | J7: =价格汇总!J48 -> 5.9 | K7: 14-17天 | L7: 18天 (开船第二天开始,承诺18天内入仓(送仓当日不算赔付时效),第19天开始, 退0.5元/KG/每天,最多退2元/KG)
B8: SNA4/SBD2/LGB4/LGB6 XLX7/IUTI/IUSW/PSP3 | C8: =价格汇总!C49 -> 1300 | D8: =价格汇总!D49 -> 7.5 | E8: =价格汇总!E49 -> 6.5 | F8: =价格汇总!F49 -> 6.5 | G8: =价格汇总!G49 -> 1220 | H8: =价格汇总!H49 -> 7.1 | I8: =价格汇总!I49 -> 6.1 | J8: =价格汇总!J49 -> 6.1 | K8: 14-17天 | L8: 无时效理赔
B9: SMF3/SCK4/LAS1/GYR2 GYR3/MIT2/VGT2/GEU2 GEU3/GEU5/HLI2/TCY2 TCY1/SCK8/SMF6/OAK3 MCE1/LAS6/SJC7/FAT2 PHX5/PHX7/IUTE | C9: =价格汇总!C50 -> 1360 | D9: =价格汇总!D50 -> 7.8 | E9: =价格汇总!E50 -> 6.8 | F9: =价格汇总!F50 -> 6.8 | G9: =价格汇总!G50 -> 1280 | H9: =价格汇总!H50 -> 7.4 | I9: =价格汇总!I50 -> 6.4 | J9: =价格汇总!J50 -> 6.4 | K9: 14-17天 | L9: 19天 (开船第二天开始,承诺19天内入仓(送仓当日不算赔付时效),第20天开始, 退0.5元/KG/每天,最多退2元/KG)
B10: ABQ2/QXY8/MCC1 | C10: =价格汇总!C51 -> 1520 | D10: =价格汇总!D51 -> 8.6 | E10: =价格汇总!E51 -> 7.6 | F10: =价格汇总!F51 -> 7.6 | G10: =价格汇总!G51 -> 1440 | H10: =价格汇总!H51 -> 8.2 | I10: =价格汇总!I51 -> 7.2 | J10: =价格汇总!J51 -> 7.2 | K10: 15-18天 | L10: 无时效理赔
B11: FTW1/IUSF/DFW6/IAH3 SAT1/FTW5/STL3/PSC2 PDX7 (标红仓点按12KG起收) 单价按100KG段+1/KG 51KG-100KG按100KG+同价 | C11: =价格汇总!C52 -> 1620 | D11: =价格汇总!D52 -> 100KG起收 | E11: =价格汇总!E52 -> 100KG起收 | F11: =价格汇总!F52 -> 8.1 | G11: =价格汇总!G52 -> 1540 | H11: =价格汇总!H52 -> 100KG起收 | I11: =价格汇总!I52 -> 100KG起收 | J11: =价格汇总!J52 -> 7.7 | K11: 15-18天 | L11: 无时效理赔
B12: IND9/MDW2/FWA4/MEM1 MQJ1/DEN8/RFD2/ORD2 LFT1 (标红仓点按12KG起收) 单价按100KG段+1/KG 51KG-100KG按100KG+同价 | C12: =价格汇总!C53 -> 1660 | D12: =价格汇总!D53 -> 100KG起收 | E12: =价格汇总!E53 -> 100KG起收 | F12: =价格汇总!F53 -> 8.3 | G12: =价格汇总!G53 -> 1580 | H12: =价格汇总!H53 -> 100KG起收 | I12: =价格汇总!I53 -> 100KG起收 | J12: =价格汇总!J53 -> 7.9 | K12: 19-25天 | L12: 无时效理赔
B13: CLT2/RDU2/CLT3/RDU4 (标红仓点按12KG起收) 单价按100KG段+1/KG 51KG-100KG按100KG+同价 | C13: =价格汇总!C54 -> 1840 | D13: =价格汇总!D54 -> 100KG起收 | E13: =价格汇总!E54 -> 100KG起收 | F13: =价格汇总!F54 -> 9.2 | G13: =价格汇总!G54 -> 1760 | H13: =价格汇总!H54 -> 100KG起收 | I13: =价格汇总!I54 -> 100KG起收 | J13: =价格汇总!J54 -> 8.8 | K13: 19-25天 | L13: 无时效理赔
B14: ABE8/AVP1/TEB3/TEB9 TPA3 /RMN3/ORF2/SWF2 (标红仓点按12KG起收) 单价按100KG段+1/KG 51KG-100KG按100KG+同价 | C14: =价格汇总!C55 -> 1920 | D14: =价格汇总!D55 -> 100KG起收 | E14: =价格汇总!E55 -> 100KG起收 | F14: =价格汇总!F55 -> 9.6 | G14: =价格汇总!G55 -> 1840 | H14: =价格汇总!H55 -> 100KG起收 | I14: =价格汇总!I55 -> 100KG起收 | J14: =价格汇总!J55 -> 9.2 | K14: 19-25天 | L14: 无时效理赔
B15: 含税自提(出库费15美金/托 汇率7） | C15: =价格汇总!C56 -> 1260 | D15: =价格汇总!D56 -> —— | E15: =价格汇总!E56 -> —— | F15: =价格汇总!F56 -> 6.3 | G15: =价格汇总!G56 -> 1180 | H15: =价格汇总!H56 -> —— | I15: =价格汇总!I56 -> —— | J15: =价格汇总!J56 -> 5.9 | K15: 13-16天 | L15: 无时效理赔
B16: 单票51KG以上,重货减免优惠：1:200减0.5,1:250减1.5,1:300减2,1:350减2.5,1:450减3,1:500及以上减3.5.
B17: 理赔注意事项
B18: 1>以上按方/按公斤含税价格含海关查验及查验引起的其它费用.包税价格含查验费,除查验费外的其他费用，例如亚马逊爆仓引起的仓租/柜租，非我司原因导致的亚马逊拒收产生的相关费用，申报不符海关惩罚金,扣关,退运等包税价格都是不包含的，请客户将这些官方收费也考虑到成本中，以免引起误会； 2>按方含税价格包含海关查验费，如因报关资料问题引起的出口查验由客人承担所有相关费用（如仓租，柜租，改船费等),因为国外清关资质认证问题或者产品本身问题导致的查验费及额外费用由这票货来承担； 3>不可抗力因素造成的时效延误不在赔偿范围内，如：海关查验，如自然灾害、如台风、地震、洪水、冰雹,，暴风雪；政府行为，社会异常事件，如罢工、骚乱三方面，疫情原因导致仓库预约困难或延识误等。 4>拒收一切敏感货，冲货如被海关扣货罚没销毁等，不退运费，我司也不承担任何责任.品名必需如实申报,如遇查验,申报与实际品名不一致将会产生巨额关税,客户自负.
B22: 服务小贴士
B23: 1>为了更好的服务客户和统计仓位，来货请务必贴上我司的进仓标签.
B24: 2>空仓费产生情况：过了截单时间做的行为；更改渠道、客户原因延船期等；货物在截货时间前未到我司国内仓库.
B25: 其它费用
B26: 按方渠道的计费重是按实际立方数和实重/363取大值计算的,卡派单箱无最低计费重量限制，托盘货物不按方算. 最长边超过120CM小于165CM加收RMB1/KG(按方含税+200/CBM),单边超过165CM拒收； 报关费按200RMB/票。 托盘、木架、木箱类货物泡货计费重*1.1*1.1算计费重； 实重托盘比重达到1:200的比重系数*0.75算比重系数，计费重不*1.1。 自提出库费按“单板限2方/1200磅”取较大值计费，超出部分按第二板计算；超大件自提费用请单独咨询客服。

Sheet 盐田以星南沙合德限时达卡派
B1: SSH盐田以星南沙合德限时达卡派
B3: 下单渠道：SSH04卡派/SSH04卡派-按方计费
B4: 人民币报价 | K4: 执行日期：2026-3-31
B5: 仓库代码 | C5: 深圳交货价 | G5: 广州交货价 | K5: 入仓参考时效 （开船后次日起算） | L5: 理赔时效 (自然日) | M5: 返回主页
C6: 按方含税(2CBM+) | D6: 包税(12KG+) | E6: 包税(51KG+) | F6: 包税(100KG+) | G6: 按方含税(2CBM+) | H6: 包税(12KG+) | I6: 包税(51KG+) | J6: 包税(100KG+)
B7: ONT8/LGB8/LAX9/SBD1 IUSP/IUSQ/IUSJ/POC1 POC2/POC3 | C7: =价格汇总!C60 -> 1060 | D7: =价格汇总!D60 -> 6.3 | E7: =价格汇总!E60 -> 5.3 | F7: =价格汇总!F60 -> 5.3 | G7: =价格汇总!G60 -> 1060 | H7: =价格汇总!H60 -> 6.3 | I7: =价格汇总!I60 -> 5.3 | J7: =价格汇总!J60 -> 5.3 | K7: 18-20天 | L7: 18天 (开船第二天开始,承诺18天内入仓(送仓当日不算赔付时效),第19天开始, 退0.5元/KG/每天,最多退2元/KG)
B8: SNA4/SBD2/LGB4/LGB6 XLX7/IUTI/IUSW/PSP3 | C8: =价格汇总!C61 -> 1100 | D8: =价格汇总!D61 -> 6.5 | E8: =价格汇总!E61 -> 5.5 | F8: =价格汇总!F61 -> 5.5 | G8: =价格汇总!G61 -> 1100 | H8: =价格汇总!H61 -> 6.5 | I8: =价格汇总!I61 -> 5.5 | J8: =价格汇总!J61 -> 5.5 | K8: 18-20天 | L8: 无时效理赔
B9: SMF3/SCK4/LAS1/GYR2 GYR3/MIT2/VGT2/GEU2 GEU3/GEU5/HLI2/TCY2 TCY1/SCK8/SMF6/OAK3 MCE1/LAS6/SJC7/FAT2 PHX5/PHX7/IUTE | C9: =价格汇总!C62 -> 1160 | D9: =价格汇总!D62 -> 6.8 | E9: =价格汇总!E62 -> 5.8 | F9: =价格汇总!F62 -> 5.8 | G9: =价格汇总!G62 -> 1160 | H9: =价格汇总!H62 -> 6.8 | I9: =价格汇总!I62 -> 5.8 | J9: =价格汇总!J62 -> 5.8 | K9: 20-22天 | L9: 19天 (开船第二天开始,承诺19天内入仓(送仓当日不算赔付时效),第20天开始, 退0.5元/KG/每天,最多退2元/KG)
B10: ABQ2/QXY8/MCC1 | C10: =价格汇总!C63 -> 1320 | D10: =价格汇总!D63 -> 7.6 | E10: =价格汇总!E63 -> 6.6 | F10: =价格汇总!F63 -> 6.6 | G10: =价格汇总!G63 -> 1320 | H10: =价格汇总!H63 -> 7.6 | I10: =价格汇总!I63 -> 6.6 | J10: =价格汇总!J63 -> 6.6 | K10: 20-22天 | L10: 无时效理赔
B11: FTW1/IUSF/DFW6/IAH3 SAT1/FTW5/STL3/PSC2 PDX7 (标红仓点按12KG起收) 单价按100KG段+1/KG 51KG-100KG按100KG+同价 | C11: =价格汇总!C64 -> 1420 | D11: =价格汇总!D64 -> 100KG起收 | E11: =价格汇总!E64 -> 100KG起收 | F11: =价格汇总!F64 -> 7.1 | G11: =价格汇总!G64 -> 1420 | H11: =价格汇总!H64 -> 100KG起收 | I11: =价格汇总!I64 -> 100KG起收 | J11: =价格汇总!J64 -> 7.1 | K11: 20-22天 | L11: 无时效理赔
B12: IND9/MDW2/FWA4/MEM1 MQJ1/DEN8/RFD2/ORD2 LFT1 (标红仓点按12KG起收) 单价按100KG段+1/KG 51KG-100KG按100KG+同价 | C12: =价格汇总!C65 -> 1460 | D12: =价格汇总!D65 -> 100KG起收 | E12: =价格汇总!E65 -> 100KG起收 | F12: =价格汇总!F65 -> 7.3 | G12: =价格汇总!G65 -> 1460 | H12: =价格汇总!H65 -> 100KG起收 | I12: =价格汇总!I65 -> 100KG起收 | J12: =价格汇总!J65 -> 7.3 | K12: 20-22天 | L12: 无时效理赔
B13: CLT2/RDU2/CLT3/RDU4 (标红仓点按12KG起收) 单价按100KG段+1/KG 51KG-100KG按100KG+同价 | C13: =价格汇总!C66 -> 1640 | D13: =价格汇总!D66 -> 100KG起收 | E13: =价格汇总!E66 -> 100KG起收 | F13: =价格汇总!F66 -> 8.2 | G13: =价格汇总!G66 -> 1640 | H13: =价格汇总!H66 -> 100KG起收 | I13: =价格汇总!I66 -> 100KG起收 | J13: =价格汇总!J66 -> 8.2 | K13: 20-22天 | L13: 无时效理赔
B14: ABE8/AVP1/TEB3/TEB9 TPA3 /RMN3/ORF2/SWF2 (标红仓点按12KG起收) 单价按100KG段+1/KG 51KG-100KG按100KG+同价 | C14: =价格汇总!C67 -> 1720 | D14: =价格汇总!D67 -> 100KG起收 | E14: =价格汇总!E67 -> 100KG起收 | F14: =价格汇总!F67 -> 8.6 | G14: =价格汇总!G67 -> 1720 | H14: =价格汇总!H67 -> 100KG起收 | I14: =价格汇总!I67 -> 100KG起收 | J14: =价格汇总!J67 -> 8.6 | K14: 20-22天 | L14: 无时效理赔
B15: 含税自提(出库费15美金/托 汇率7） | C15: =价格汇总!C68 -> 1060 | D15: =价格汇总!D68 -> —— | E15: =价格汇总!E68 -> —— | F15: =价格汇总!F68 -> 5.3 | G15: =价格汇总!G68 -> 1060 | H15: =价格汇总!H68 -> —— | I15: =价格汇总!I68 -> —— | J15: =价格汇总!J68 -> 5.3 | K15: 16-20天 | L15: 无时效理赔
B16: 单票51KG以上,重货减免优惠：1:200减0.5,1:250减1.5,1:300减2,1:350减2.5,1:450减3,1:500及以上减3.5.
B17: 理赔注意事项
B18: 1>以上按方/按公斤含税价格含海关查验及查验引起的其它费用.包税价格含查验费,除查验费外的其他费用，例如亚马逊爆仓引起的仓租/柜租，非我司原因导致的亚马逊拒收产生的相关费用，申报不符海关惩罚金,扣关,退运等包税价格都是不包含的，请客户将这些官方收费也考虑到成本中，以免引起误会； 2>按方含税价格包含海关查验费，如因报关资料问题引起的出口查验由客人承担所有相关费用（如仓租，柜租，改船费等),因为国外清关资质认证问题或者产品本身问题导致的查验费及额外费用由这票货来承担； 3>不可抗力因素造成的时效延误不在赔偿范围内，如：海关查验，如自然灾害、如台风、地震、洪水、冰雹,，暴风雪；政府行为，社会异常事件，如罢工、骚乱三方面，疫情原因导致仓库预约困难或延识误等。 4>拒收一切敏感货，冲货如被海关扣货罚没销毁等，不退运费，我司也不承担任何责任.品名必需如实申报,如遇查验,申报与实际品名不一致将会产生巨额关税,客户自负.
B22: 服务小贴士
B23: 1>为了更好的服务客户和统计仓位，来货请务必贴上我司的进仓标签.
B24: 2>空仓费产生情况：过了截单时间做的行为；更改渠道、客户原因延船期等；货物在截货时间前未到我司国内仓库.
B25: 其它费用
B26: 按方渠道的计费重是按实际立方数和实重/363取大值计算的,卡派单箱无最低计费重量限制，托盘货物不按方算. 最长边超过120CM小于165CM加收RMB1/KG(按方含税+200/CBM),单边超过165CM拒收； 报关费按200RMB/票。 托盘、木架、木箱类货物泡货计费重*1.1*1.1算计费重； 实重托盘比重达到1:200的比重系数*0.75算比重系数，计费重不*1.1。 自提出库费按“单板限2方/1200磅”取较大值计费，超出部分按第二板计算；超大件自提费用请单独咨询客服。

Sheet 盐田以星南沙合德DG限时达卡派
B1: SSH盐田以星南沙合德DG限时达卡派
B3: 下单渠道：SSHDG04卡派
B4: 人民币报价 | I4: 执行日期：2026-3-31
B5: 仓库代码 | C5: 深圳交货价 | F5: 广州交货价 | I5: 入仓参考时效 （开船后次日起算） | J5: 理赔时效 (自然日) | K5: 返回主页
C6: 包税(12KG+) | D6: 包税(51KG+) | E6: 包税(100KG+) | F6: 包税(12KG+) | G6: 包税(51KG+) | H6: 包税(100KG+)
B7: ONT8/LGB8/LAX9/SBD1 IUSP/IUSQ/IUSJ/POC1 POC2/POC3 | C7: =价格汇总!D73 -> 7.6 | D7: =价格汇总!E73 -> 6.6 | E7: =价格汇总!F73 -> 6.6 | F7: =价格汇总!H73 -> 7.6 | G7: =价格汇总!I73 -> 6.6 | H7: =价格汇总!J73 -> 6.6 | I7: 18-20天 | J7: 18天 (开船第二天开始,承诺18天内入仓(送仓当日不算赔付时效),第19天开始, 退0.5元/KG/每天,最多退2元/KG)
B8: SNA4/SBD2/LGB4/LGB6 XLX7/IUTI/IUSW/PSP3 | C8: =价格汇总!D74 -> 7.8 | D8: =价格汇总!E74 -> 6.8 | E8: =价格汇总!F74 -> 6.8 | F8: =价格汇总!H74 -> 7.8 | G8: =价格汇总!I74 -> 6.8 | H8: =价格汇总!J74 -> 6.8 | I8: 18-20天 | J8: 无时效理赔
B9: SMF3/SCK4/LAS1/GYR2 GYR3/MIT2/VGT2/GEU2 GEU3/GEU5/HLI2/TCY2 TCY1/SCK8/SMF6/OAK3 MCE1/LAS6/SJC7/FAT2 PHX5/PHX7/IUTE | C9: =价格汇总!D75 -> 8.1 | D9: =价格汇总!E75 -> 7.1 | E9: =价格汇总!F75 -> 7.1 | F9: =价格汇总!H75 -> 8.1 | G9: =价格汇总!I75 -> 7.1 | H9: =价格汇总!J75 -> 7.1 | I9: 20-22天 | J9: 19天 (开船第二天开始,承诺19天内入仓(送仓当日不算赔付时效),第20天开始, 退0.5元/KG/每天,最多退2元/KG)
B10: ABQ2/QXY8/MCC1 | C10: =价格汇总!D76 -> 8.9 | D10: =价格汇总!E76 -> 7.9 | E10: =价格汇总!F76 -> 7.9 | F10: =价格汇总!H76 -> 8.9 | G10: =价格汇总!I76 -> 7.9 | H10: =价格汇总!J76 -> 7.9 | I10: 20-22天 | J10: 无时效理赔
B11: FTW1/IUSF/DFW6/IAH3 SAT1/FTW5/STL3/PSC2 PDX7 (标红仓点按12KG起收) 单价按100KG段+1/KG 51KG-100KG按100KG+同价 | C11: =价格汇总!D77 -> 100KG起收 | D11: =价格汇总!E77 -> 100KG起收 | E11: =价格汇总!F77 -> 8.4 | F11: =价格汇总!H77 -> 100KG起收 | G11: =价格汇总!I77 -> 100KG起收 | H11: =价格汇总!J77 -> 8.4 | I11: 20-22天 | J11: 无时效理赔
B12: IND9/MDW2/FWA4/MEM1 MQJ1/DEN8/RFD2/ORD2 LFT1 (标红仓点按12KG起收) 单价按100KG段+1/KG 51KG-100KG按100KG+同价 | C12: =价格汇总!D78 -> 100KG起收 | D12: =价格汇总!E78 -> 100KG起收 | E12: =价格汇总!F78 -> 8.6 | F12: =价格汇总!H78 -> 100KG起收 | G12: =价格汇总!I78 -> 100KG起收 | H12: =价格汇总!J78 -> 8.6 | I12: 20-22天 | J12: 无时效理赔
B13: CLT2/RDU2/CLT3/RDU4 (标红仓点按12KG起收) 单价按100KG段+1/KG 51KG-100KG按100KG+同价 | C13: =价格汇总!D79 -> 100KG起收 | D13: =价格汇总!E79 -> 100KG起收 | E13: =价格汇总!F79 -> 9.5 | F13: =价格汇总!H79 -> 100KG起收 | G13: =价格汇总!I79 -> 100KG起收 | H13: =价格汇总!J79 -> 9.5 | I13: 20-22天 | J13: 无时效理赔
B14: ABE8/AVP1/TEB3/TEB9 TPA3 /RMN3/ORF2/SWF2 (标红仓点按12KG起收) 单价按100KG段+1/KG 51KG-100KG按100KG+同价 | C14: =价格汇总!D80 -> 100KG起收 | D14: =价格汇总!E80 -> 100KG起收 | E14: =价格汇总!F80 -> 9.9 | F14: =价格汇总!H80 -> 100KG起收 | G14: =价格汇总!I80 -> 100KG起收 | H14: =价格汇总!J80 -> 9.9 | I14: 20-22天 | J14: 无时效理赔
B15: 含税自提(出库费15美金/托 汇率7） | C15: =价格汇总!D81 -> —— | D15: =价格汇总!E81 -> —— | E15: =价格汇总!F81 -> 6.6 | F15: =价格汇总!H81 -> —— | G15: =价格汇总!I81 -> —— | H15: =价格汇总!J81 -> 6.6 | I15: 16-20天 | J15: 无时效理赔
B16: 发货与责任条款 为保障运输顺利，请贵司务必遵守以下条款，使用我司服务即视为完全同意本规定。
B17: 一、发货须知 出货前，须与我司客服确认货物可运性与清关要求。发货人必须提供准确、完整的报关及产品认证文件（如MSDS、UN38.3、危包证等）。如因私自发货、资料不全或错误、货物不合规（含侵权、反倾销产品）导致的一切风险、退货费用及责任，概由贵司承担。
B18: 二、包装要求 所有货物外箱及产品上须有永久性“MADE IN CHINA”标识。纯电池/危险品货物须按我司要求使用合规包装，并牢固张贴对应危险品标签（如9类标签、UN标签）及运输标签（如FBA标签）。因包装或标识不合规导致的清关或派送问题，由贵司负责。
B19: 三、货物交付要求说明 对于派送货物，收货人签收POD单即视为妥投，异常须在签收时注明或于三日内反馈。亚马逊仓库货物，入仓后一个月内未反馈上架异常则视为正常签收。我司将以POD签收记录作为货物交付完成的最终凭证。
B20: 四、赔偿及索赔说明 如未购买保险，货物丢失、损毁赔偿上限为40元人民币/公斤（扣关/提取前），且不退运费。对于运输延误、海关查验、已签收未上架、包装完好内物破损等情况，我司不承担赔偿责任。任何索赔须在货物实际派送日起30天内提出，逾期无效。因贵司申报不符、资料问题或货物自身原因导致的任何损失，我司不承担赔偿责任。
B21: 服务小贴士
B22: 1>为了更好的服务客户和统计仓位，来货请务必贴上我司的进仓标签.
B23: 2>空仓费产生情况：过了截单时间做的行为；更改渠道、客户原因延船期等；货物在截货时间前未到我司国内仓库.
B24: 其它费用
B25: 按方渠道的计费重是按实际立方数和实重/363取大值计算的,卡派单箱无最低计费重量限制，托盘货物不按方算. 最长边超过120CM小于165CM加收RMB1/KG(按方含税+200/CBM),单边超过165CM拒收； 报关费按200RMB/票。 托盘、木架、木箱类货物泡货计费重*1.1*1.1算计费重； 实重托盘比重达到1:200的比重系数*0.75算比重系数，计费重不*1.1。 自提出库费按“单板限2方/1200磅”取较大值计费，超出部分按第二板计算；超大件自提费用请单独咨询客服。

Sheet 义乌合德以星限时达卡派
B1: SSH义乌合德以星限时达卡派 （进福建内陆费+0.4/KG）
B3: 下单渠道：SSHYW05卡派/SSHYW05卡派-按方计费 SSHYWJF05卡派/SSHYWJF05卡派-按方计费
B4: 人民币报价 | K4: 执行日期：2026-3-31
B5: 仓库代码 | C5: 深圳/广州交货价 | G5: 义乌交货价 | K5: 入仓参考时效 （开船后次日起算） | L5: 理赔时效 (自然日) | M5: 返回主页
C6: 按方含税(2CBM+) | D6: 包税(12KG+) | E6: 包税(51KG+) | F6: 包税(100KG+) | G6: 按方含税(2CBM+) | H6: 包税(12KG+) | I6: 包税(51KG+) | J6: 包税(100KG+)
B7: ONT8/LGB8/LAX9/SBD1 IUSP/IUSQ/IUSJ/POC1 POC2/POC3 | C7: =价格汇总!C86 -> 1120 | D7: =价格汇总!D86 -> 6.6 | E7: =价格汇总!E86 -> 5.6 | F7: =价格汇总!F86 -> 5.6 | G7: =价格汇总!G86 -> 1060 | H7: =价格汇总!H86 -> 6.3 | I7: =价格汇总!I86 -> 5.3 | J7: =价格汇总!J86 -> 5.3 | K7: 18-20天 | L7: 18天 (开船第二天开始,承诺18天内入仓(送仓当日不算赔付时效),第19天开始, 退0.5元/KG/每天,最多退2元/KG)
B8: SNA4/SBD2/LGB4/LGB6 XLX7/IUTI/IUSW/PSP3 | C8: =价格汇总!C87 -> 1160 | D8: =价格汇总!D87 -> 6.8 | E8: =价格汇总!E87 -> 5.8 | F8: =价格汇总!F87 -> 5.8 | G8: =价格汇总!G87 -> 1100 | H8: =价格汇总!H87 -> 6.5 | I8: =价格汇总!I87 -> 5.5 | J8: =价格汇总!J87 -> 5.5 | K8: 18-20天 | L8: 无时效理赔
B9: SMF3/SCK4/LAS1/GYR2 GYR3/MIT2/VGT2/GEU2 GEU3/GEU5/HLI2/TCY2 TCY1/SCK8/SMF6/OAK3 MCE1/LAS6/SJC7/FAT2 PHX5/PHX7/IUTE | C9: =价格汇总!C88 -> 1220 | D9: =价格汇总!D88 -> 7.1 | E9: =价格汇总!E88 -> 6.1 | F9: =价格汇总!F88 -> 6.1 | G9: =价格汇总!G88 -> 1160 | H9: =价格汇总!H88 -> 6.8 | I9: =价格汇总!I88 -> 5.8 | J9: =价格汇总!J88 -> 5.8 | K9: 20-22天 | L9: 19天 (开船第二天开始,承诺19天内入仓(送仓当日不算赔付时效),第20天开始, 退0.5元/KG/每天,最多退2元/KG)
B10: ABQ2/QXY8/MCC1 | C10: =价格汇总!C89 -> 1380 | D10: =价格汇总!D89 -> 7.9 | E10: =价格汇总!E89 -> 6.9 | F10: =价格汇总!F89 -> 6.9 | G10: =价格汇总!G89 -> 1320 | H10: =价格汇总!H89 -> 7.6 | I10: =价格汇总!I89 -> 6.6 | J10: =价格汇总!J89 -> 6.6 | K10: 20-22天 | L10: 无时效理赔
B11: FTW1/IUSF/DFW6/IAH3 SAT1/FTW5/STL3/PSC2 PDX7 (标红仓点按12KG起收) 单价按100KG段+1/KG 51KG-100KG按100KG+同价 | C11: =价格汇总!C90 -> 1480 | D11: =价格汇总!D90 -> 100KG起收 | E11: =价格汇总!E90 -> 100KG起收 | F11: =价格汇总!F90 -> 7.4 | G11: =价格汇总!G90 -> 1420 | H11: =价格汇总!H90 -> 100KG起收 | I11: =价格汇总!I90 -> 100KG起收 | J11: =价格汇总!J90 -> 7.1 | K11: 20-22天 | L11: 无时效理赔
B12: IND9/MDW2/FWA4/MEM1 MQJ1/DEN8/RFD2/ORD2 LFT1 (标红仓点按12KG起收) 单价按100KG段+1/KG 51KG-100KG按100KG+同价 | C12: =价格汇总!C91 -> 1520 | D12: =价格汇总!D91 -> 100KG起收 | E12: =价格汇总!E91 -> 100KG起收 | F12: =价格汇总!F91 -> 7.6 | G12: =价格汇总!G91 -> 1460 | H12: =价格汇总!H91 -> 100KG起收 | I12: =价格汇总!I91 -> 100KG起收 | J12: =价格汇总!J91 -> 7.3 | K12: 20-22天 | L12: 无时效理赔
B13: CLT2/RDU2/CLT3/RDU4 (标红仓点按12KG起收) 单价按100KG段+1/KG 51KG-100KG按100KG+同价 | C13: =价格汇总!C92 -> 1700 | D13: =价格汇总!D92 -> 100KG起收 | E13: =价格汇总!E92 -> 100KG起收 | F13: =价格汇总!F92 -> 8.5 | G13: =价格汇总!G92 -> 1640 | H13: =价格汇总!H92 -> 100KG起收 | I13: =价格汇总!I92 -> 100KG起收 | J13: =价格汇总!J92 -> 8.2 | K13: 20-22天 | L13: 无时效理赔
B14: ABE8/AVP1/TEB3/TEB9 TPA3 /RMN3/ORF2/SWF2 (标红仓点按12KG起收) 单价按100KG段+1/KG 51KG-100KG按100KG+同价 | C14: =价格汇总!C93 -> 1780 | D14: =价格汇总!D93 -> 100KG起收 | E14: =价格汇总!E93 -> 100KG起收 | F14: =价格汇总!F93 -> 8.9 | G14: =价格汇总!G93 -> 1720 | H14: =价格汇总!H93 -> 100KG起收 | I14: =价格汇总!I93 -> 100KG起收 | J14: =价格汇总!J93 -> 8.6 | K14: 20-22天 | L14: 无时效理赔
B15: 含税自提(出库费15美金/托 汇率7） | C15: =价格汇总!C94 -> 1120 | D15: =价格汇总!D94 -> —— | E15: =价格汇总!E94 -> —— | F15: =价格汇总!F94 -> 5.6 | G15: =价格汇总!G94 -> 1060 | H15: =价格汇总!H94 -> —— | I15: =价格汇总!I94 -> —— | J15: =价格汇总!J94 -> 5.3 | K15: 16-20天 | L15: 无时效理赔
B16: 单票51KG以上,重货减免优惠：1:200减0.5,1:250减1.5,1:300减2,1:350减2.5,1:450减3,1:500及以上减3.5.
B17: 理赔注意事项
B18: 1>以上按方/按公斤含税价格含海关查验及查验引起的其它费用.包税价格含查验费,除查验费外的其他费用，例如亚马逊爆仓引起的仓租/柜租，非我司原因导致的亚马逊拒收产生的相关费用，申报不符海关惩罚金,扣关,退运等包税价格都是不包含的，请客户将这些官方收费也考虑到成本中，以免引起误会； 2>按方含税价格包含海关查验费，如因报关资料问题引起的出口查验由客人承担所有相关费用（如仓租，柜租，改船费等),因为国外清关资质认证问题或者产品本身问题导致的查验费及额外费用由这票货来承担； 3>不可抗力因素造成的时效延误不在赔偿范围内，如：海关查验，如自然灾害、如台风、地震、洪水、冰雹,，暴风雪；政府行为，社会异常事件，如罢工、骚乱三方面，疫情原因导致仓库预约困难或延识误等。 4>拒收一切敏感货，冲货如被海关扣货罚没销毁等，不退运费，我司也不承担任何责任.品名必需如实申报,如遇查验,申报与实际品名不一致将会产生巨额关税,客户自负.
B22: 服务小贴士
B23: 1>为了更好的服务客户和统计仓位，来货请务必贴上我司的进仓标签.
B24: 2>空仓费产生情况：过了截单时间做的行为；更改渠道、客户原因延船期等；货物在截货时间前未到我司国内仓库.
B25: 其它费用
B26: 按方渠道的计费重是按实际立方数和实重/363取大值计算的,卡派单箱无最低计费重量限制，托盘货物不按方算. 最长边超过120CM小于165CM加收RMB1/KG(按方含税+200/CBM),单边超过165CM拒收； 报关费按200RMB/票。 托盘、木架、木箱类货物泡货计费重*1.1*1.1算计费重； 实重托盘比重达到1:200的比重系数*0.75算比重系数，计费重不*1.1。 自提出库费按“单板限2方/1200磅”取较大值计费，超出部分按第二板计算；超大件自提费用请单独咨询客服。

Sheet 盐田以星南沙合德普提卡派
B1: SSH盐田以星南沙合德普提卡派
B3: 下单渠道：SSH06卡派/SSH06卡派-按方计费
B4: 人民币报价 | K4: 执行日期：2026-2-26
B5: 仓库代码 | C5: 深圳交货价 | G5: 广州交货价 | K5: 入仓参考时效 （开船后次日起算） | L5: 理赔时效 (自然日) | M5: 返回主页
C6: 按方含税(2CBM+) | D6: 包税(12KG+) | E6: 包税(51KG+) | F6: 包税(100KG+) | G6: 按方含税(2CBM+) | H6: 包税(12KG+) | I6: 包税(51KG+) | J6: 包税(100KG+)
B7: ONT8/LGB8/LAX9/SBD1 IUSP/IUSQ/IUSJ/POC1 POC2/POC3 | C7: =价格汇总!#REF! -> #REF! | D7: =价格汇总!#REF! -> #REF! | E7: =价格汇总!#REF! -> #REF! | F7: =价格汇总!#REF! -> #REF! | G7: =价格汇总!#REF! -> #REF! | H7: =价格汇总!#REF! -> #REF! | I7: =价格汇总!#REF! -> #REF! | J7: =价格汇总!#REF! -> #REF! | K7: 18-20天 | L7: 无时效理赔
B8: SNA4/SBD2/LGB4/LGB6 XLX7/IUTI/IUSW/PSP3 | C8: =价格汇总!#REF! -> #REF! | D8: =价格汇总!#REF! -> #REF! | E8: =价格汇总!#REF! -> #REF! | F8: =价格汇总!#REF! -> #REF! | G8: =价格汇总!#REF! -> #REF! | H8: =价格汇总!#REF! -> #REF! | I8: =价格汇总!#REF! -> #REF! | J8: =价格汇总!#REF! -> #REF! | K8: 18-20天 | L8: 无时效理赔
B9: SMF3/SCK4/LAS1/GYR2 GYR3/MIT2/VGT2/GEU2 GEU3/GEU5/HLI2/TCY2 TCY1/SCK8/SMF6/OAK3 MCE1/LAS6/SJC7/FAT2 PHX5/PHX7/IUTE | C9: =价格汇总!#REF! -> #REF! | D9: =价格汇总!#REF! -> #REF! | E9: =价格汇总!#REF! -> #REF! | F9: =价格汇总!#REF! -> #REF! | G9: =价格汇总!#REF! -> #REF! | H9: =价格汇总!#REF! -> #REF! | I9: =价格汇总!#REF! -> #REF! | J9: =价格汇总!#REF! -> #REF! | K9: 20-22天 | L9: 无时效理赔
B10: ABQ2/QXY8/MCC1 | C10: =价格汇总!#REF! -> #REF! | D10: =价格汇总!#REF! -> #REF! | E10: =价格汇总!#REF! -> #REF! | F10: =价格汇总!#REF! -> #REF! | G10: =价格汇总!#REF! -> #REF! | H10: =价格汇总!#REF! -> #REF! | I10: =价格汇总!#REF! -> #REF! | J10: =价格汇总!#REF! -> #REF! | K10: 20-22天 | L10: 无时效理赔
B11: FTW1/IUSF/DFW6/IAH3 SAT1/FTW5/STL3/PSC2 PDX7 (标红仓点按12KG起收) 单价按100KG段+1/KG 51KG-100KG按100KG+同价 | C11: =价格汇总!#REF! -> #REF! | D11: =价格汇总!#REF! -> #REF! | E11: =价格汇总!#REF! -> #REF! | F11: =价格汇总!#REF! -> #REF! | G11: =价格汇总!#REF! -> #REF! | H11: =价格汇总!#REF! -> #REF! | I11: =价格汇总!#REF! -> #REF! | J11: =价格汇总!#REF! -> #REF! | K11: 20-22天 | L11: 无时效理赔
B12: IND9/MDW2/FWA4/MEM1 MQJ1/DEN8/RFD2/ORD2 LFT1 (标红仓点按12KG起收) 单价按100KG段+1/KG 51KG-100KG按100KG+同价 | C12: =价格汇总!#REF! -> #REF! | D12: =价格汇总!#REF! -> #REF! | E12: =价格汇总!#REF! -> #REF! | F12: =价格汇总!#REF! -> #REF! | G12: =价格汇总!#REF! -> #REF! | H12: =价格汇总!#REF! -> #REF! | I12: =价格汇总!#REF! -> #REF! | J12: =价格汇总!#REF! -> #REF! | K12: 20-22天 | L12: 无时效理赔
B13: CLT2/RDU2/CLT3/RDU4 (标红仓点按12KG起收) 单价按100KG段+1/KG 51KG-100KG按100KG+同价 | C13: =价格汇总!#REF! -> #REF! | D13: =价格汇总!#REF! -> #REF! | E13: =价格汇总!#REF! -> #REF! | F13: =价格汇总!#REF! -> #REF! | G13: =价格汇总!#REF! -> #REF! | H13: =价格汇总!#REF! -> #REF! | I13: =价格汇总!#REF! -> #REF! | J13: =价格汇总!#REF! -> #REF! | K13: 20-22天 | L13: 无时效理赔
B14: ABE8/AVP1/TEB3/TEB9 TPA3 /RMN3/ORF2/SWF2 (标红仓点按12KG起收) 单价按100KG段+1/KG 51KG-100KG按100KG+同价 | C14: =价格汇总!#REF! -> #REF! | D14: =价格汇总!#REF! -> #REF! | E14: =价格汇总!#REF! -> #REF! | F14: =价格汇总!#REF! -> #REF! | G14: =价格汇总!#REF! -> #REF! | H14: =价格汇总!#REF! -> #REF! | I14: =价格汇总!#REF! -> #REF! | J14: =价格汇总!#REF! -> #REF! | K14: 20-22天 | L14: 无时效理赔
B15: 含税自提(含出库费） | C15: =价格汇总!#REF! -> #REF! | D15: =价格汇总!#REF! -> #REF! | E15: =价格汇总!#REF! -> #REF! | F15: =价格汇总!#REF! -> #REF! | G15: =价格汇总!#REF! -> #REF! | H15: =价格汇总!#REF! -> #REF! | I15: =价格汇总!#REF! -> #REF! | J15: =价格汇总!#REF! -> #REF! | K15: 16-20天 | L15: 无时效理赔
B16: 单票51KG以上,重货减免优惠：1:200减0.3,1:250减0.6,1:300减0.9,1:350减1.2,1:450及以上减1.5.
B17: 理赔注意事项
B18: 1>以上按方/按公斤含税价格含海关查验及查验引起的其它费用.包税价格含查验费,除查验费外的其他费用，例如亚马逊爆仓引起的仓租/柜租，非我司原因导致的亚马逊拒收产生的相关费用，申报不符海关惩罚金,扣关,退运等包税价格都是不包含的，请客户将这些官方收费也考虑到成本中，以免引起误会； 2>按方含税价格包含海关查验费，如因报关资料问题引起的出口查验由客人承担所有相关费用（如仓租，柜租，改船费等),因为国外清关资质认证问题或者产品本身问题导致的查验费及额外费用由这票货来承担； 3>不可抗力因素造成的时效延误不在赔偿范围内，如：海关查验，如自然灾害、如台风、地震、洪水、冰雹,，暴风雪；政府行为，社会异常事件，如罢工、骚乱三方面，疫情原因导致仓库预约困难或延识误等。 4>拒收一切敏感货，冲货如被海关扣货罚没销毁等，不退运费，我司也不承担任何责任.品名必需如实申报,如遇查验,申报与实际品名不一致将会产生巨额关税,客户自负.
B22: 服务小贴士
B23: 1>为了更好的服务客户和统计仓位，来货请务必贴上我司的进仓标签.
B24: 2>空仓费产生情况：过了截单时间做的行为；更改渠道、客户原因延船期等；货物在截货时间前未到我司国内仓库.
B25: 其它费用
B26: 按方渠道的计费重是按实际立方数和实重/363取大值计算的,卡派单箱无最低计费重量限制，托盘货物不按方算. 最长边超过120CM小于165CM加收RMB1/KG(按方含税+200/CBM),单边超过165CM拒收； 报关费按200RMB/票。 托盘、木架、木箱类货物泡货计费重*1.1*1.1算计费重； 实重托盘比重达到1:200的比重系数*0.75算比重系数，计费重不*1.1。

Sheet 普船洛杉矶卡派
A1: SSH普船洛杉矶卡派 （进福建内陆费+0.4/KG）
A3: 交货深圳下单渠道：SSH07卡派/SSH07卡派-按方计费 交货义乌下单渠道：SSHYW07卡派/SSHYW07-按方计费 SSHYWJF07卡派/SSHYWJF07卡派-按方计费（义乌普船进深圳、广州内陆费+0.3/KG）
A4: 人民币报价 | K4: 执行日期：2026-3-31
A5: 组合/混拆 | B5: 仓库代码/渠道名称 | C5: 深圳/广州交货价 | G5: 义乌交货价 | K5: 入仓参考时效 （开船后次日起算） | L5: 备注 | M5: 返回主页
C6: 按方含税(2CBM+) | D6: 包税(12KG+) | E6: 包税(51KG+) | F6: 包税(100KG+) | G6: 按方含税(2CBM+) | H6: 包税(12KG+) | I6: 包税(51KG+) | J6: 包税(100KG+)
A7: 组合一区 | B7: ONT8/LGB8/LAX9/SBD1/IUSP IUSQ/IUSJ/POC1/POC2/POC3 | C7: =价格汇总!C100 -> 740 | D7: =价格汇总!D100 -> 4.7 | E7: =价格汇总!E100 -> 3.7 | F7: =价格汇总!F100 -> 3.7 | G7: =价格汇总!G100 -> 740 | H7: =价格汇总!H100 -> 4.7 | I7: =价格汇总!I100 -> 3.7 | J7: =价格汇总!J100 -> 3.7 | K7: 20-25天 | L7: 普船ZIM/合德/OA 等统配根据到货时间顺序就近 安排船期-循环装柜 (目的港：洛杉矶) 入仓单请注明渠道： 普船洛杉矶卡派 -组合柜 （按方包税/公斤包税）
A8: 组合二区 | B8: SNA4/SBD2/LGB4/LGB6 XLX7/IUTI/IUSW/PSP3 | C8: =价格汇总!C101 -> 800 | D8: =价格汇总!D101 -> 5 | E8: =价格汇总!E101 -> 4 | F8: =价格汇总!F101 -> 4 | G8: =价格汇总!G101 -> 800 | H8: =价格汇总!H101 -> 5 | I8: =价格汇总!I101 -> 4 | J8: =价格汇总!J101 -> 4 | K8: 22-26天
A9: 组合二区Plus | B9: SMF3/SCK4/LAS1/GYR2/GYR3 MIT2/VGT2/GEU2/GEU3/GEU5 HLI2/TCY2/TCY1/SCK8/SMF6 OAK3/MCE1/LAS6/SJC7/FAT2 PHX5/PHX7/IUTE | C9: =价格汇总!C102 -> 860 | D9: =价格汇总!D102 -> 5.3 | E9: =价格汇总!E102 -> 4.3 | F9: =价格汇总!F102 -> 4.3 | G9: =价格汇总!G102 -> 860 | H9: =价格汇总!H102 -> 5.3 | I9: =价格汇总!I102 -> 4.3 | J9: =价格汇总!J102 -> 4.3 | K9: 23-27天
A10: 组合三区 | B10: ABQ2/QXY8/MCC1 | C10: =价格汇总!C103 -> 1020 | D10: =价格汇总!D103 -> 6.1 | E10: =价格汇总!E103 -> 5.1 | F10: =价格汇总!F103 -> 5.1 | G10: =价格汇总!G103 -> 1020 | H10: =价格汇总!H103 -> 6.1 | I10: =价格汇总!I103 -> 5.1 | J10: =价格汇总!J103 -> 5.1 | K10: 25-28天
A11: 组合四区 | B11: FTW1/IUSF/DFW6/IAH3/SAT1 FTW5/STL3/PSC2/PDX7 (标红仓点按12KG起收) 单价按100KG段+1/KG 51KG-100KG按100KG+同价 | C11: =价格汇总!C104 -> 1120 | D11: =价格汇总!D104 -> 100KG起收 | E11: =价格汇总!E104 -> 100KG起收 | F11: =价格汇总!F104 -> 5.6 | G11: =价格汇总!G104 -> 1120 | H11: =价格汇总!H104 -> 100KG起收 | I11: =价格汇总!I104 -> 100KG起收 | J11: =价格汇总!J104 -> 5.6 | K11: 28-32天
A12: 组合五区 | B12: IND9/MDW2/FWA4/MEM1 MQJ1/DEN8/RFD2/ORD2/LFT1 (标红仓点按12KG起收) 单价按100KG段+1/KG 51KG-100KG按100KG+同价 | C12: =价格汇总!C105 -> 1160 | D12: =价格汇总!D105 -> 100KG起收 | E12: =价格汇总!E105 -> 100KG起收 | F12: =价格汇总!F105 -> 5.8 | G12: =价格汇总!G105 -> 1160 | H12: =价格汇总!H105 -> 100KG起收 | I12: =价格汇总!I105 -> 100KG起收 | J12: =价格汇总!J105 -> 5.8 | K12: 28-32天
A13: 组合六区 | B13: CLT2/RDU2/CLT3/RDU4 (标红仓点按12KG起收) 单价按100KG段+1/KG 51KG-100KG按100KG+同价 | C13: =价格汇总!C106 -> 1340 | D13: =价格汇总!D106 -> 100KG起收 | E13: =价格汇总!E106 -> 100KG起收 | F13: =价格汇总!F106 -> 6.7 | G13: =价格汇总!G106 -> 1340 | H13: =价格汇总!H106 -> 100KG起收 | I13: =价格汇总!I106 -> 100KG起收 | J13: =价格汇总!J106 -> 6.7 | K13: 30-35天
A14: 组合七区 | B14: ABE8/AVP1/TEB3/TEB9/TPA3 RMN3/ORF2/SWF2 (标红仓点按12KG起收) 单价按100KG段+1/KG 51KG-100KG按100KG+同价 | C14: =价格汇总!C107 -> 1420 | D14: =价格汇总!D107 -> 100KG起收 | E14: =价格汇总!E107 -> 100KG起收 | F14: =价格汇总!F107 -> 7.1 | G14: =价格汇总!G107 -> 1420 | H14: =价格汇总!H107 -> 100KG起收 | I14: =价格汇总!I107 -> 100KG起收 | J14: =价格汇总!J107 -> 7.1 | K14: 30-35天
A15: 含税自提(出库费15美金/托 汇率7） | C15: =价格汇总!C108 -> 740 | D15: =价格汇总!D108 -> —— | E15: =价格汇总!E108 -> —— | F15: =价格汇总!F108 -> 3.7 | G15: =价格汇总!G108 -> 740 | H15: =价格汇总!H108 -> —— | I15: =价格汇总!I108 -> —— | J15: =价格汇总!J108 -> 3.7 | K15: 20-25天
A16: 单票51KG以上,重货减免优惠：1:200减0.3,1:250减0.6,1:300减0.9,1:350减1.2,1:450及以上减1.5.
A17: 理赔注意事项
A18: 1>以上按方/按公斤含税价格含海关查验及查验引起的其它费用.包税价格含查验费,除查验费外的其他费用，例如亚马逊爆仓引起的仓租/柜租，非我司原因导致的亚马逊拒收产生的相关费用，申报不符海关惩罚金,扣关,退运等包税价格都是不包含的，请客户将这些官方收费也考虑到成本中，以免引起误会； 2>按方含税价格包含海关查验费，如因报关资料问题引起的出口查验由客人承担所有相关费用（如仓租，柜租，改船费等),因为国外清关资质认证问题或者产品本身问题导致的查验费及额外费用由这票货来承担； 3>不可抗力因素造成的时效延误不在赔偿范围内，如：海关查验，如自然灾害、如台风、地震、洪水、冰雹,，暴风雪；政府行为，社会异常事件，如罢工、骚乱三方面，疫情原因导致仓库预约困难或延识误等。 4>拒收一切敏感货，冲货如被海关扣货罚没销毁等，不退运费，我司也不承担任何责任.品名必需如实申报,如遇查验,申报与实际品名不一致将会产生巨额关税,客户自负.
A22: 服务小贴士
A23: 1>为了更好的服务客户和统计仓位，来货请务必贴上我司的进仓标签. 2>空仓费产生情况：过了截单时间做的行为；更改渠道、客户原因延船期等；货物在截货时间前未到我司国内仓库.
A25: 其它费用
A26: 按方渠道的计费重是按实际立方数和实重/363取大值计算的,卡派单箱无最低计费重量限制，托盘货物不按方算. 最长边超过120CM小于165CM加收RMB1/KG(按方含税+200/CBM),单边超过165CM拒收； 报关费按200RMB/票。 托盘、木架、木箱类货物泡货计费重*1.1*1.1算计费重； 实重托盘比重达到1:200的比重系数*0.75算比重系数，计费重不*1.1。 自提出库费按“单板限2方/1200磅”取较大值计费，超出部分按第二板计算；超大件自提费用请单独咨询客服。

Sheet 美西特惠卡派
B1: SSH美西特惠卡派（货满安排最近一水）
B3: 交货深圳下单渠道：SSH盐田美西特惠卡派一区 至 七区/SSH盐田美西特惠卡派一区 至 七区-按方计费 交货广州下单渠道：SSH广州美西特惠卡派一区 至 七区/SSH广州美西特惠卡派一区 至 七区-按方计费 交货义乌下单渠道：SSH义乌美西特惠卡派一区 至 七区/SSH义乌美西特惠卡派一区 至 七区-按方计费 SSH义乌JF美西特惠卡派一区 至 七区/SSH义乌JF美西特惠卡派一区 至 七区-按方计费
B4: 人民币报价 | K4: 执行日期：2025-8-12
A5: 组合/混拆 | B5: 仓库代码/渠道名称 | C5: 深圳/广州交货价 | G5: 义乌交货价 | K5: 入仓参考时效 （开船后次日起算） | L5: 备注 | M5: 返回主页
C6: 按方含税(2CBM+) | D6: 包税(12KG+) | E6: 包税(51KG+) | F6: 包税(100KG+) | G6: 按方含税(2CBM+) | H6: 包税(12KG+) | I6: 包税(51KG+) | J6: 包税(100KG+)
A7: 组合一区 | B7: ONT8/LGB8/LAX9/SBD1/POC1/ POC3/IUSP/IUSQ/IUSJ | C7: =价格汇总!#REF! -> #REF! | D7: =价格汇总!#REF! -> #REF! | E7: =价格汇总!#REF! -> #REF! | F7: =价格汇总!#REF! -> #REF! | G7: =价格汇总!#REF! -> #REF! | H7: =价格汇总!#REF! -> #REF! | I7: =价格汇总!#REF! -> #REF! | J7: =价格汇总!#REF! -> #REF! | K7: 20-25天 | L7: 普船SML/YML/ONE等统配根据到货时间顺序就近安排船期循环装柜 (目的港：洛杉矶) 入仓单请注明渠道： 美西特惠卡派 （按方包税/公斤包税）
A8: 组合二区 | B8: GYR3/GYR2/LAS1/SMF3/SCK4/ FAT2/GEU3/GEU2/GEU5/ MIT2/VGT2/TCY1/TCY2/SCK8 | C8: =价格汇总!#REF! -> #REF! | D8: =价格汇总!#REF! -> #REF! | E8: =价格汇总!#REF! -> #REF! | F8: =价格汇总!#REF! -> #REF! | G8: =价格汇总!#REF! -> #REF! | H8: =价格汇总!#REF! -> #REF! | I8: =价格汇总!#REF! -> #REF! | J8: =价格汇总!#REF! -> #REF! | K8: 22-26天
A9: 组合三区 | B9: SLC2/FTW1/SAT1/IAH3/ABQ2/ AMA1/SAT4/DFW6/IUSF/ FTW3/FTW5/SLC3/HOU7/HOU8 | C9: =价格汇总!#REF! -> #REF! | D9: =价格汇总!#REF! -> #REF! | E9: =价格汇总!#REF! -> #REF! | F9: =价格汇总!#REF! -> #REF! | G9: =价格汇总!#REF! -> #REF! | H9: =价格汇总!#REF! -> #REF! | I9: =价格汇总!#REF! -> #REF! | J9: =价格汇总!#REF! -> #REF! | K9: 25-28天
A10: 组合四区 | B10: IND9/MDW2/FWA4/MEM1/ MQJ1/DEN8/DEN2/PPO4/RFD2/ ORD2/LFT1/LIT2 | C10: =价格汇总!#REF! -> #REF! | D10: =价格汇总!#REF! -> #REF! | E10: =价格汇总!#REF! -> #REF! | F10: =价格汇总!#REF! -> #REF! | G10: =价格汇总!#REF! -> #REF! | H10: =价格汇总!#REF! -> #REF! | I10: =价格汇总!#REF! -> #REF! | J10: =价格汇总!#REF! -> #REF! | K10: 28-32天
A11: 组合五区 | B11: STL3/PSC2/STL4/OKC2/ICT2/ PDX7/GEG2/BFI3/OKC2/ ICT2/PDX7/GEG2 | C11: =价格汇总!#REF! -> #REF! | D11: =价格汇总!#REF! -> #REF! | E11: =价格汇总!#REF! -> #REF! | F11: =价格汇总!#REF! -> #REF! | G11: =价格汇总!#REF! -> #REF! | H11: =价格汇总!#REF! -> #REF! | I11: =价格汇总!#REF! -> #REF! | J11: =价格汇总!#REF! -> #REF! | K11: 28-32天
A12: 组合六区 | B12: CLT2/RDU2/CLT3/RDU4/GSO1 | C12: =价格汇总!#REF! -> #REF! | D12: =价格汇总!#REF! -> #REF! | E12: =价格汇总!#REF! -> #REF! | F12: =价格汇总!#REF! -> #REF! | G12: =价格汇总!#REF! -> #REF! | H12: =价格汇总!#REF! -> #REF! | I12: =价格汇总!#REF! -> #REF! | J12: =价格汇总!#REF! -> #REF! | K12: 30-35天
A13: 组合七区 | B13: ABE4/ABE8/AVP1/TEB3/TEB6/ TEB9/ACY2/TPA3/PBI3/ RMN3/ORF2/SWF2/SWF1/ALB1/CHO1 | C13: =价格汇总!#REF! -> #REF! | D13: =价格汇总!#REF! -> #REF! | E13: =价格汇总!#REF! -> #REF! | F13: =价格汇总!#REF! -> #REF! | G13: =价格汇总!#REF! -> #REF! | H13: =价格汇总!#REF! -> #REF! | I13: =价格汇总!#REF! -> #REF! | J13: =价格汇总!#REF! -> #REF! | K13: 30-35天
B14: 美西特惠卡派渠道有甩柜概率，仓保难度大，如介意请谨慎选择！对于时效要求高的可优先选择普船洛杉矶卡派仓保几率更高。
B15: 单票51KG以上,重货减免优惠：1:200减0.3,1:250减0.6,1:300减0.9,1:350减1.2,1:450及以上减1.5.
B16: 理赔注意事项
B17: 1>以上按方/按公斤含税价格含海关查验及查验引起的其它费用.包税价格含查验费,除查验费外的其他费用，例如亚马逊爆仓引起的仓租/柜租，非我司原因导致的亚马逊拒收产生的相关费用，申报不符海关惩罚金,扣关,退运等包税价格都是不包含的，请客户将这些官方收费也考虑到成本中，以免引起误会； 2>按方含税价格包含海关查验费，如因报关资料问题引起的出口查验由客人承担所有相关费用（如仓租，柜租，改船费等),因为国外清关资质认证问题或者产品本身问题导致的查验费及额外费用由这票货来承担； 3>不可抗力因素造成的时效延误不在赔偿范围内，如：海关查验，如自然灾害、如台风、地震、洪水、冰雹,，暴风雪；政府行为，社会异常事件，如罢工、骚乱三方面，疫情原因导致仓库预约困难或延识误等。 4>拒收一切敏感货，冲货如被海关扣货罚没销毁等，不退运费，我司也不承担任何责任.品名必需如实申报,如遇查验,申报与实际品名不一致将会产生巨额关税,客户自负.
B21: 服务小贴士
B22: 1>为了更好的服务客户和统计仓位，来货请务必贴上我司的进仓标签. 2>空仓费产生情况：过了截单时间做的行为；更改渠道、客户原因延船期等；货物在截货时间前未到我司国内仓库.
B24: 其它费用
B25: 按方渠道的计费重是按实际立方数和实重/363取大值计算的,卡派单箱无最低计费重量限制，托盘货物+0.5/KG附加，不按方算. 最长边超过120CM小于165CM加收RMB1/KG(按方含税+200/CBM),单边超过165CM拒收； 报关费按350RMB/票。 托盘、木架、木箱类货物计费重*1.1计费，例如：一块托盘货物的实重是500KG，材积重600KG，实际计费重取材积大600KG，因托盘类货物额外计费重按660KG计费。

Sheet DG洛杉矶卡派
A1: SSHDG洛杉矶卡派
A3: 交货深圳、广州下单渠道：SSHDG07卡派
A4: 人民币报价 | I4: 执行日期：2026-3-31
A5: 组合/混拆 | B5: 仓库代码/渠道名称 | C5: 深圳交货价 | F5: 广州交货价 | I5: 入仓参考时效 （开船后次日起算） | J5: 备注 | K5: 返回主页
C6: 包税(12KG+) | D6: 包税(51KG+) | E6: 包税(100KG+) | F6: 包税(12KG+) | G6: 包税(51KG+) | H6: 包税(100KG+)
A7: 组合一区 | B7: ONT8/LGB8/LAX9/SBD1/IUSP IUSQ/IUSJ/POC1/POC2/POC3 | C7: =价格汇总!D112 -> 6 | D7: =价格汇总!E112 -> 5 | E7: =价格汇总!F112 -> 5 | F7: =价格汇总!H112 -> 6 | G7: =价格汇总!I112 -> 5 | H7: =价格汇总!J112 -> 5 | I7: 20-25天 | J7: 普船ZIM/合德/OA 等统配根据到货时间顺序就近 安排船期-循环装柜 (目的港：洛杉矶) 入仓单请注明渠道： 普船洛杉矶卡派 -组合柜 （按方包税/公斤包税）
A8: 组合二区 | B8: SNA4/SBD2/LGB4/LGB6 XLX7/IUTI/IUSW/PSP3 | C8: =价格汇总!D113 -> 6.3 | D8: =价格汇总!E113 -> 5.3 | E8: =价格汇总!F113 -> 5.3 | F8: =价格汇总!H113 -> 6.3 | G8: =价格汇总!I113 -> 5.3 | H8: =价格汇总!J113 -> 5.3 | I8: 22-26天
A9: 组合二区Plus | B9: SMF3/SCK4/LAS1/GYR2/GYR3 MIT2/VGT2/GEU2/GEU3/GEU5 HLI2/TCY2/TCY1/SCK8/SMF6 OAK3/MCE1/LAS6/SJC7/FAT2 PHX5/PHX7/IUTE | C9: =价格汇总!D114 -> 6.6 | D9: =价格汇总!E114 -> 5.6 | E9: =价格汇总!F114 -> 5.6 | F9: =价格汇总!H114 -> 6.6 | G9: =价格汇总!I114 -> 5.6 | H9: =价格汇总!J114 -> 5.6 | I9: 23-27天
A10: 组合三区 | B10: ABQ2/QXY8/MCC1 | C10: =价格汇总!D115 -> 7.4 | D10: =价格汇总!E115 -> 6.4 | E10: =价格汇总!F115 -> 6.4 | F10: =价格汇总!H115 -> 7.4 | G10: =价格汇总!I115 -> 6.4 | H10: =价格汇总!J115 -> 6.4 | I10: 25-28天
A11: 组合四区 | B11: FTW1/IUSF/DFW6/IAH3/SAT1 FTW5/STL3/PSC2/PDX7 (标红仓点按12KG起收) 单价按100KG段+1/KG 51KG-100KG按100KG+同价 | C11: =价格汇总!D116 -> 100KG起收 | D11: =价格汇总!E116 -> 100KG起收 | E11: =价格汇总!F116 -> 6.9 | F11: =价格汇总!H116 -> 100KG起收 | G11: =价格汇总!I116 -> 100KG起收 | H11: =价格汇总!J116 -> 6.9 | I11: 28-32天
A12: 组合五区 | B12: IND9/MDW2/FWA4/MEM1 MQJ1/DEN8/RFD2/ORD2/LFT1 (标红仓点按12KG起收) 单价按100KG段+1/KG 51KG-100KG按100KG+同价 | C12: =价格汇总!D117 -> 100KG起收 | D12: =价格汇总!E117 -> 100KG起收 | E12: =价格汇总!F117 -> 7.1 | F12: =价格汇总!H117 -> 100KG起收 | G12: =价格汇总!I117 -> 100KG起收 | H12: =价格汇总!J117 -> 7.1 | I12: 28-32天
A13: 组合六区 | B13: CLT2/RDU2/CLT3/RDU4 (标红仓点按12KG起收) 单价按100KG段+1/KG 51KG-100KG按100KG+同价 | C13: =价格汇总!D118 -> 100KG起收 | D13: =价格汇总!E118 -> 100KG起收 | E13: =价格汇总!F118 -> 8 | F13: =价格汇总!H118 -> 100KG起收 | G13: =价格汇总!I118 -> 100KG起收 | H13: =价格汇总!J118 -> 8 | I13: 30-35天
A14: 组合七区 | B14: ABE8/AVP1/TEB3/TEB9/TPA3 RMN3/ORF2/SWF2 (标红仓点按12KG起收) 单价按100KG段+1/KG 51KG-100KG按100KG+同价 | C14: =价格汇总!D119 -> 100KG起收 | D14: =价格汇总!E119 -> 100KG起收 | E14: =价格汇总!F119 -> 8.4 | F14: =价格汇总!H119 -> 100KG起收 | G14: =价格汇总!I119 -> 100KG起收 | H14: =价格汇总!J119 -> 8.4 | I14: 30-35天
A15: 含税自提(出库费15美金/托 汇率7） | C15: =价格汇总!D120 -> —— | D15: =价格汇总!E120 -> —— | E15: =价格汇总!F120 -> 5 | F15: =价格汇总!H120 -> —— | G15: =价格汇总!I120 -> —— | H15: =价格汇总!J120 -> 5 | I15: 20-25天
B16: 发货与责任条款 为保障运输顺利，请贵司务必遵守以下条款，使用我司服务即视为完全同意本规定。
B17: 一、发货须知 出货前，须与我司客服确认货物可运性与清关要求。发货人必须提供准确、完整的报关及产品认证文件（如MSDS、UN38.3、危包证等）。如因私自发货、资料不全或错误、货物不合规（含侵权、反倾销产品）导致的一切风险、退货费用及责任，概由贵司承担。
B18: 二、包装要求 所有货物外箱及产品上须有永久性“MADE IN CHINA”标识。纯电池/危险品货物须按我司要求使用合规包装，并牢固张贴对应危险品标签（如9类标签、UN标签）及运输标签（如FBA标签）。因包装或标识不合规导致的清关或派送问题，由贵司负责。
B19: 三、货物交付要求说明 对于派送货物，收货人签收POD单即视为妥投，异常须在签收时注明或于三日内反馈。亚马逊仓库货物，入仓后一个月内未反馈上架异常则视为正常签收。我司将以POD签收记录作为货物交付完成的最终凭证。
B20: 四、赔偿及索赔说明 如未购买保险，货物丢失、损毁赔偿上限为40元人民币/公斤（扣关/提取前），且不退运费。对于运输延误、海关查验、已签收未上架、包装完好内物破损等情况，我司不承担赔偿责任。任何索赔须在货物实际派送日起30天内提出，逾期无效。因贵司申报不符、资料问题或货物自身原因导致的任何损失，我司不承担赔偿责任。
A21: 服务小贴士
A22: 1>为了更好的服务客户和统计仓位，来货请务必贴上我司的进仓标签. 2>空仓费产生情况：过了截单时间做的行为；更改渠道、客户原因延船期等；货物在截货时间前未到我司国内仓库.
A24: 其它费用
A25: 按方渠道的计费重是按实际立方数和实重/363取大值计算的,卡派单箱无最低计费重量限制，托盘货物不按方算. 最长边超过120CM小于165CM加收RMB1/KG(按方含税+200/CBM),单边超过165CM拒收； 报关费按200RMB/票。 托盘、木架、木箱类货物泡货计费重*1.1*1.1算计费重； 实重托盘比重达到1:200的比重系数*0.75算比重系数，计费重不*1.1。 自提出库费按“单板限2方/1200磅”取较大值计费，超出部分按第二板计算；超大件自提费用请单独咨询客服。

Sheet 普船芝加哥卡派
B1: SSH普船芝加哥卡派
B3: 交货深圳/广州下单渠道：SSH普船芝加哥卡派/SSH普船芝加哥卡派-按方计费 交货义乌下单渠道：SSH义乌普船芝加哥卡派/SSH义乌普船芝加哥卡派-按方计费
B4: 人民币报价 | J4: 执行日期：2026-1-13
B5: 组合/混拆 | C5: 仓库代码/渠道名称 | D5: 深圳/广州交货价 | G5: 义乌交货价 | J5: 入仓参考时效 （开船后次日起算） | K5: 备注
D6: 按方含税(2CBM+) | E6: 包税(100KG+) | F6: 包税(300KG+) | G6: 按方含税(2CBM+) | H6: 包税(100KG+) | I6: 包税(300KG+)
B7: 组合一区 | C7: MDW2/ORD2/IGQ2/MDW6/ MDW8/MDW9/RFD2/RFD4/JVL1 | D7: =(价格汇总!#REF!) -> #REF! | E7: =(价格汇总!#REF!) -> #REF! | F7: =(价格汇总!#REF!) -> #REF! | G7: =(价格汇总!#REF!) -> #REF! | H7: =(价格汇总!#REF!) -> #REF! | I7: =(价格汇总!#REF!) -> #REF! | J7: 40-45天 | K7: 普船统配根据到货时间顺序就近安排船期 (目的港：芝加哥) 入仓单请注明渠道： 普船芝加哥卡派-组合柜 （按方包税/公斤包税）
B8: 组合二区 | C8: IND9/FWA4/MQJ1/MQJ2/STL4/ IND2/IND4/IND5 | D8: =(价格汇总!#REF!) -> #REF! | E8: =(价格汇总!#REF!) -> #REF! | F8: =(价格汇总!#REF!) -> #REF! | G8: =(价格汇总!#REF!) -> #REF! | H8: =(价格汇总!#REF!) -> #REF! | I8: =(价格汇总!#REF!) -> #REF! | J8: 40-45天
B9: 组合三区 | C9: DET1/DET2/CMH2/CMH3 | D9: =(价格汇总!#REF!) -> #REF! | E9: =(价格汇总!#REF!) -> #REF! | F9: =(价格汇总!#REF!) -> #REF! | G9: =(价格汇总!#REF!) -> #REF! | H9: =(价格汇总!#REF!) -> #REF! | I9: =(价格汇总!#REF!) -> #REF! | J9: 40-45天
B10: 组合四区 | C10: FOE1/MKC4/MEM1/MEM6/MCI3/STL3 | D10: =(价格汇总!#REF!) -> #REF! | E10: =(价格汇总!#REF!) -> #REF! | F10: =(价格汇总!#REF!) -> #REF! | G10: =(价格汇总!#REF!) -> #REF! | H10: =(价格汇总!#REF!) -> #REF! | I10: =(价格汇总!#REF!) -> #REF! | J10: 40-45天
C11: 含税自提(含出库费） | D11: =(价格汇总!#REF!) -> #REF! | F11: —— | G11: —— | H11: —— | I11: =(价格汇总!#REF!) -> #REF! | J11: 30-35天
B12: 单票51KG以上,重货减免优惠:1:200减0.5,1:250减1,1:300减1.5,1:350减2,1:450及以上减2.5.
B13: 理赔注意事项
B14: 1>以上按方/按公斤含税价格含海关查验及查验引起的其它费用.包税价格含查验费,除查验费外的其他费用，例如亚马逊爆仓引起的仓租/柜租，非我司原因导致的亚马逊拒收产生的相关费用，申报不符海关惩罚金,扣关,退运等包税价格都是不包含的，请客户将这些官方收费也考虑到成本中，以免引起误会； 2>按方含税价格包含海关查验费，如因报关资料问题引起的出口查验由客人承担所有相关费用（如仓租，柜租，改船费等),因为国外清关资质认证问题或者产品本身问题导致的查验费及额外费用由这票货来承担； 3>不可抗力因素造成的时效延误不在赔偿范围内，如：海关查验，如自然灾害、如台风、地震、洪水、冰雹,，暴风雪；政府行为，社会异常事件，如罢工、骚乱三方面，疫情原因导致仓库预约困难或延识误等。 4>拒收一切敏感货，冲货如被海关扣货罚没销毁等，不退运费，我司也不承担任何责任.品名必需如实申报,如遇查验,申报与实际品名不一致将会产生巨额关税,客户自负.
B18: 服务小贴士
B19: 1>为了更好的服务客户和统计仓位，来货请务必贴上我司的进仓标签. 2>空仓费产生情况：过了截单时间做的行为；更改渠道、客户原因延船期等；货物在截货时间前未到我司国内仓库.
B21: 其它费用
B22: 按方渠道的计费重是按实际立方数和实重/363取大值计算的,卡派单箱无最低计费重量限制，托盘货物+0.5/KG附加，不按方算. 最长边超过120CM小于165CM加收RMB1/KG(按方含税+200/CBM),单边超过165CM拒收； 报关费按200RMB/票。 托盘、木架、木箱类货物计费重*1.1计费，例如：一块托盘货物的实重是500KG，材积重600KG，实际计费重取材积大600KG，因托盘类货物额外计费重按660KG计费。 木箱木架、托盘货物，因占货柜容积率，无比重优惠，以此执行！

Sheet 普船纽约卡派
A1: SSH普船纽约卡派（进福建内陆费+0.4/KG）
A2: 交货深圳/广州下单渠道：SSH普船纽约卡派/SSH普船纽约卡派-按方计费 交货义乌下单渠道：SSH义乌普船纽约卡派/SSH义乌普船纽约卡派-按方计费 （义乌纽约进深圳、广州内陆费+0.3/KG）
A3: 人民币报价 | K3: 执行日期：2026-3-31
A4: 组合/混拆 | B4: 仓库代码/渠道名称 | C4: 深圳/广州交货价 | G4: 义乌交货价 | K4: 入仓参考时效 （开船后次日起算） | L4: 备注
C5: 按方含税(2CBM+) | D5: 包税(12KG+) | E5: 包税(51KG+) | F5: 包税(100KG+) | G5: 按方含税(2CBM+) | H5: 包税(12KG+) | I5: 包税(51KG+) | J5: 包税(100KG+)
A6: 组合一区 | B6: ABE8/ACY2/TEB6/TEB9/TTN2 TEB3/TEB4 | C6: =(价格汇总!G124) -> 940 | D6: =(价格汇总!H124) -> 5.7 | E6: =(价格汇总!M124) -> 5.2 | F6: =(价格汇总!I124) -> 4.7 | G6: =(价格汇总!J124) -> 940 | H6: =(价格汇总!K124) -> 5.7 | I6: =(价格汇总!N124) -> 5.2 | J6: =(价格汇总!L124) -> 4.7 | K6: 40-45天 | L6: OA船/ZIM统配根据到货时间顺序就近安排 船期(目的港：纽约) 入仓单请注明渠道： 普船纽约卡派 （按方包税/公斤包税）
A7: 组合二区 | B7: ABE4/ABE2/ABE3/XEW5 AVP1/AVP3/AVP9/HIA1 HEA2/PHL4/PHL5/PHL6 | C7: =(价格汇总!G125) -> 1000 | D7: =(价格汇总!H125) -> 6 | E7: =(价格汇总!M125) -> 5.5 | F7: =(价格汇总!I125) -> 5 | G7: =(价格汇总!J125) -> 1000 | H7: =(价格汇总!K125) -> 6 | I7: =(价格汇总!N125) -> 5.5 | J7: =(价格汇总!L125) -> 5 | K7: 40-45天
A8: 组合三区 | B8: MDT1/MDT4/WBW2/ALB1 SWF1/SWF2/XLX1/IUST/IUSL MDT2/DCA6/ILG1 | C8: =(价格汇总!G126) -> 1040 | D8: =(价格汇总!H126) -> 6.2 | E8: =(价格汇总!M126) -> 5.7 | F8: =(价格汇总!I126) -> 5.2 | G8: =(价格汇总!J126) -> 1040 | H8: =(价格汇总!K126) -> 6.2 | I8: =(价格汇总!N126) -> 5.7 | J8: =(价格汇总!L126) -> 5.2 | K8: 45-50天
A9: 组合四区 | B9: PIT2/LBE1/XRI3/RIC1/RIC3 RMN3/CHO1/ORF2/BWI4 BOS7/HGR2/HGR6 | C9: =(价格汇总!G127) -> 1080 | D9: =(价格汇总!H127) -> 6.4 | E9: =(价格汇总!M127) -> 5.9 | F9: =(价格汇总!I127) -> 5.4 | G9: =(价格汇总!J127) -> 1080 | H9: =(价格汇总!K127) -> 6.4 | I9: =(价格汇总!N127) -> 5.9 | J9: =(价格汇总!L127) -> 5.4 | K9: 45-50天
A10: 组合五区 | B10: XLX6/CLT2/CLT3/CLT6/CMH2CMH6/CMH3/AKR1/DET1 DET2/DET3/DTW3/LAN2 GSO1/RDU2/RDU4 | C10: =(价格汇总!G128) -> 1140 | D10: =(价格汇总!H128) -> 6.7 | E10: =(价格汇总!M128) -> 6.2 | F10: =(价格汇总!I128) -> 5.7 | G10: =(价格汇总!J128) -> 1140 | H10: =(价格汇总!K128) -> 6.7 | I10: =(价格汇总!N128) -> 6.2 | J10: =(价格汇总!L128) -> 5.7 | K10: 45-50天
A11: 组合六区 | B11: RFD2/RFD4/MDW2/MDW6 MDW9/ORD2/IGQ2/FWA4 MQJ1/MQJ2/IND4/IND5 IND9/RYY2 | C11: =(价格汇总!G129) -> 1200 | D11: =(价格汇总!H129) -> 7 | E11: =(价格汇总!M129) -> 6.5 | F11: =(价格汇总!I129) -> 6 | G11: =(价格汇总!J129) -> 1200 | H11: =(价格汇总!K129) -> 7 | I11: =(价格汇总!N129) -> 6.5 | J11: =(价格汇总!L129) -> 6 | K11: 45-50天
A12: 组合七区 | B12: TPA2/TPA3/TPA6/MCO1 MCO2/JAX3/XHH3 | C12: =(价格汇总!G130) -> 1440 | D12: =(价格汇总!H130) -> 8.2 | E12: =(价格汇总!M130) -> 7.7 | F12: =(价格汇总!I130) -> 7.2 | G12: =(价格汇总!J130) -> 1440 | H12: =(价格汇总!K130) -> 8.2 | I12: =(价格汇总!N130) -> 7.7 | J12: =(价格汇总!L130) -> 7.2 | K12: 45-50天
B13: 含税自提(出库费15美金/托 汇率7） | C13: =(价格汇总!G131) -> 940 | D13: =(价格汇总!I131) -> 4.7 | G13: =(价格汇总!J131) -> 940 | H13: =(价格汇总!L131) -> 4.7 | K13: 40-45天
A14: 单票51KG以上,重货减免优惠:1:200减0.5,1:250减1,1:300减1.5,1:350减2,1:450及以上减2.5.
A15: 理赔注意事项
A16: 1>以上按方/按公斤含税价格含海关查验及查验引起的其它费用.包税价格含查验费,除查验费外的其他费用，例如亚马逊爆仓引起的仓租/柜租，非我司原因导致的亚马逊拒收产生的相关费用，申报不符海关惩罚金,扣关,退运等包税价格都是不包含的，请客户将这些官方收费也考虑到成本中，以免引起误会； 2>按方含税价格包含海关查验费，如因报关资料问题引起的出口查验由客人承担所有相关费用（如仓租，柜租，改船费等),因为国外清关资质认证问题或者产品本身问题导致的查验费及额外费用由这票货来承担； 3>不可抗力因素造成的时效延误不在赔偿范围内，如：海关查验，如自然灾害、如台风、地震、洪水、冰雹,，暴风雪；政府行为，社会异常事件，如罢工、骚乱三方面，疫情原因导致仓库预约困难或延识误等。 4>拒收一切敏感货，冲货如被海关扣货罚没销毁等，不退运费，我司也不承担任何责任.品名必需如实申报,如遇查验,申报与实际品名不一致将会产生巨额关税,客户自负.
A20: 服务小贴士
A21: 1>为了更好的服务客户和统计仓位，来货请务必贴上我司的进仓标签. 2>空仓费产生情况：过了截单时间做的行为；更改渠道、客户原因延船期等；货物在截货时间前未到我司国内仓库.
A23: 其它费用
A24: 按方渠道的计费重是按实际立方数和实重/363取大值计算的,卡派单箱无最低计费重量限制，托盘货物不按方算. 最长边超过120CM小于165CM加收RMB1/KG(按方含税+200/CBM),单边超过165CM拒收； 报关费按200RMB/票。 托盘、木架、木箱类货物泡货计费重*1.1*1.1算计费重； 实重托盘比重达到1:200的比重系数*0.75算比重系数，计费重不*1.1。 自提出库费按“单板限2方/1200磅”取较大值计费，超出部分按第二板计算；超大件自提费用请单独咨询客服。

Sheet 普船萨凡纳卡派
A1: SSH普船萨凡纳卡派
A4: 交货深圳/广州下单渠道：SSH普船萨凡纳卡派/SSH普船萨凡纳卡派-按方计费 交货义乌下单渠道：SSH义乌普船萨凡纳卡派/SSH义乌普船萨凡纳卡派-按方计费
A5: 人民币报价 | K5: 执行日期：2026-3-31
A6: 组合/混拆 | B6: 仓库代码/渠道名称 | C6: 深圳/广州交货价 | G6: 义乌交货价 | K6: 入仓参考时效 （开船后次日起算） | L6: 备注 | M6: 返回主页
C7: 按方含税(2CBM+) | D7: 包税(12KG+) | E7: 包税(51KG+) | F7: 包税(100KG+) | G7: 按方含税(2CBM+) | H7: 包税(12KG+) | I7: 包税(51KG+) | J7: 包税(100KG+)
A8: 组合一区 | B8: MGE1/MGE3/SAV3/JAX3/沃尔玛-ATL1/XAV3 | C8: =(价格汇总!G135) -> 1100 | D8: =(价格汇总!H135) -> 6.5 | E8: =(价格汇总!M135) -> 6 | F8: =(价格汇总!I135) -> 5.5 | G8: =(价格汇总!J135) -> 1100 | H8: =(价格汇总!K135) -> 6.5 | I8: =(价格汇总!N135) -> 6 | J8: =(价格汇总!L135) -> 5.5 | K8: 40-45天 | L8: OA直航船根据到货时间顺序就近安排船期 (目的港：萨凡纳) 入仓单请注明渠道： 普船萨凡纳卡派 （按方包税/公斤包税）
A9: 组合二区 | B9: RYY2/CLT2/CLT3/RDU2/RDU4/GSO1/GSP1/IUSR | C9: =(价格汇总!G136) -> 1180 | D9: =(价格汇总!H136) -> 6.9 | E9: =(价格汇总!M136) -> 6.4 | F9: =(价格汇总!I136) -> 5.9 | G9: =(价格汇总!J136) -> 1180 | H9: =(价格汇总!K136) -> 6.9 | I9: =(价格汇总!N136) -> 6.4 | J9: =(价格汇总!L136) -> 5.9 | K9: 40-45天
A10: 组合三区 | B10: TPA2/TPA3/TPA6/PBI2/PBI3/CHA2/MCO2/沃尔玛-ATL8/沃尔玛- ATL2/沃尔玛- MCO1/XPB2 | C10: =(价格汇总!G137) -> 1200 | D10: =(价格汇总!H137) -> 7 | E10: =(价格汇总!M137) -> 6.5 | F10: =(价格汇总!I137) -> 6 | G10: =(价格汇总!J137) -> 1200 | H10: =(价格汇总!K137) -> 7 | I10: =(价格汇总!N137) -> 6.5 | J10: =(价格汇总!L137) -> 6 | K10: 40-45天
A11: 组合四区 | B11: HSV1/HSV2/BNA2/BNA3/MEM1/MEM8 | C11: =(价格汇总!G138) -> 1240 | D11: =(价格汇总!H138) -> 7.2 | E11: =(价格汇总!M138) -> 6.7 | F11: =(价格汇总!I138) -> 6.2 | G11: =(价格汇总!J138) -> 1240 | H11: =(价格汇总!K138) -> 7.2 | I11: =(价格汇总!N138) -> 6.7 | J11: =(价格汇总!L138) -> 6.2 | K11: 40-45天
A12: 组合五区 | B12: BNA6/TMB8/沃尔玛-MEM1s | C12: =(价格汇总!G139) -> 1260 | D12: =(价格汇总!H139) -> 7.3 | E12: =(价格汇总!M139) -> 6.8 | F12: =(价格汇总!I139) -> 6.3 | G12: =(价格汇总!J139) -> 1260 | H12: =(价格汇总!K139) -> 7.3 | I12: =(价格汇总!N139) -> 6.8 | J12: =(价格汇总!L139) -> 6.3 | K12: 40-45天
A13: 含税自提(出库费15美金/托 汇率7） | C13: =(价格汇总!G140) -> 1100 | D13: =(价格汇总!I140) -> 5.5 | G13: =(价格汇总!J140) -> 1100 | H13: =(价格汇总!L140) -> 5.5 | K13: 40-45天
A14: 单票51KG以上,重货减免优惠:1:200减0.5,1:250减1,1:300减1.5,1:350减2,1:450及以上减2.5.
A15: 理赔注意事项
A16: 1>以上按方/按公斤含税价格含海关查验及查验引起的其它费用.包税价格含查验费,除查验费外的其他费用，例如亚马逊爆仓引起的仓租/柜租，非我司原因导致的亚马逊拒收产生的相关费用，申报不符海关惩罚金,扣关,退运等包税价格都是不包含的，请客户将这些官方收费也考虑到成本中，以免引起误会； 2>按方含税价格包含海关查验费，如因报关资料问题引起的出口查验由客人承担所有相关费用（如仓租，柜租，改船费等),因为国外清关资质认证问题或者产品本身问题导致的查验费及额外费用由这票货来承担； 3>不可抗力因素造成的时效延误不在赔偿范围内，如：海关查验，如自然灾害、如台风、地震、洪水、冰雹,，暴风雪；政府行为，社会异常事件，如罢工、骚乱三方面，疫情原因导致仓库预约困难或延识误等。 4>拒收一切敏感货，冲货如被海关扣货罚没销毁等，不退运费，我司也不承担任何责任.品名必需如实申报,如遇查验,申报与实际品名不一致将会产生巨额关税,客户自负.
A20: 服务小贴士
A21: 1>为了更好的服务客户和统计仓位，来货请务必贴上我司的进仓标签. 2>空仓费产生情况：过了截单时间做的行为；更改渠道、客户原因延船期等；货物在截货时间前未到我司国内仓库.
A23: 其它费用
A24: 按方渠道的计费重是按实际立方数和实重/363取大值计算的,卡派单箱无最低计费重量限制，托盘货物不按方算. 最长边超过120CM小于165CM加收RMB1/KG(按方含税+200/CBM),单边超过165CM拒收； 报关费按200RMB/票。 托盘、木架、木箱类货物泡货计费重*1.1*1.1算计费重； 实重托盘比重达到1:200的比重系数*0.75算比重系数，计费重不*1.1。 自提出库费按“单板限2方/1200磅”取较大值计费，超出部分按第二板计算；超大件自提费用请单独咨询客服。

Sheet 赔偿说明
B2: 赔偿标准和免赔声明
B3: 一、时效赔付界定：以不同渠道时效说明为准 | I3: 返回主页
B4: 二、时效免赔说明
B5: 1、船公司船期/航线变更/延迟到港，自然灾害、天气原因，如台风、地震、洪水、冰雹,，暴风雪，雾；政府行为，社会异常事件包括战争，罢工等
B6: 2、海关查验
B7: 3、亚马逊拒收或者亚马逊更改预约时间
B8: 4、亚马逊爆仓及预约困难
B9: 5、客户FBA ID & 内部编码失误等相关原因
B10: 6、客户要求扣货后派送或者因客户自身原因导致的延误
B11: 7、由于疫情，国内仓库无法出货，船公司卸船效率慢，预约困难，拒收等不可抗力导致的延迟交仓,不在赔偿范围,此项如与具体渠道的时效赔付标准有区分，则与具体渠道的标准为准
B12: 三、赔偿标准（所有赔偿只有一种，不能多种赔偿同时赔付）
B13: 1、在运输过程中如是我司原因导致货物丢失，损坏,经我司确认后按货物申报货值赔偿，最高不超40元/KG赔偿，不免相关物流费用。三个月后还未上架或者部分上架，需要提供最新日期的未上架证明，未上架部分不足1箱的没有赔偿。理赔需要提供采购发票和最新日期的未上架证明等相关资料，以便对货值的合理性进行评估。即40元/KG，采购货值，申报货值三者取低赔偿 ,(针对美线全渠道卡派)
B14: 2、高货值产品及易碎品建议客人购买保险并打好包装，我司亦可提供购买保险服务；如若在运输过程中出因现包装原因而造成的损失而客人没有购买保险，我司概不负责。
B15: 3、卡派货交亚马逊仓库，POD（预约号与FBA ID无法对应），但是整票未上架的，我司接受理赔申请，赔偿金额按照我司合同条款 ；（不包括FBA号过期导致的亚马逊拒收和不上架 ；FBA号过期后客户仍然要求我们派送，导致的亚马逊拒收和不上架）
... B30: 2、快递派索赔程序： ①未提取的，请在打单日起算最早第30个自然日向我司客服人员发起开查申请，同时提供快递开查相关资料，最晚发起时间应当在打单日（含打单当天）起第60个自然日内提供完整资料，逾期我司将不再接受理赔申请。 ②已提取未签收的以快递开查结果为准，不在我司索赔责任范围内； 注：若逾期未提供完整相应索赔资料，则相应责任由客户自行承担，我司不再接受理赔申请。

Sheet 注意事项
B1: 注意事项 | I1: 返回主页
B2: 1、包装要求：只接方正/硬朗纸箱，拒接其他包装,每件外箱必须贴有2个以上FBA标签（条形码字体清晰，防潮湿耐磨）,外箱和产品贴有“MADE IN CHINA”标签。如因包装及标签问题导致亚马逊仓库拒收或清关出现问题，所有责任及费用由发货人承担。
B3: 2、资料要求：按要求提供货物的真实信息，提供准确的美国的海关编码，如不能提供准确的美国的海关编码,我司清关行会根据实际品名,材质和用途申报，最终产生的关税以海关提供的税金单为准，不得争议。实际货物必须如实申报，货物信息要与发票资料一致，不可瞒报漏报（例如：有牌子申报无牌）和申报不符，如因申报不符导致海关扣货等后果及产生的所有费用由发货人承担，并且罚款RMB2000/票.
B4: 3、禁止运输的货物：液体，纯电池，食品，粉末，医疗用品，仿牌商品，化工产品，儿童玩具用品及美国反倾销产品等。如发现冲货罚款RMB2000/票。不接纯电池，内置电池请提供图片及MSDS,海运运输鉴定报告单独确认。
B5: 4、如美国海关认定货物涉及品牌侵权或蓝牙、HDMI、FCC、UL、FDA,DOT，EPA等认证问题，客户需按要求提供相关认证和品牌授权书等文件，如因无法提供或者提供的文件得不到美国海关及相关部门的认可而导致扣货或者退运，所有责任和费用由该发货人承担。
B6: 5.关税豁免的产品：出货前提供详细的产品说明（图片，用途参数，销售链接或其他有用产品信息）审核货物是否符合豁免关税资格，最终以海关审核结果为准
B7: 6、装柜后如需扣货或更改派送计划，要求最迟在货物到港前5天向我司提出才可操作，扣货和更改派送计划将收取操作费$200/票，由于扣货/更改派送计划所产生的所有费用由客户承担，具体费用请单独咨询。扣货或更改派送方式有风险，我司不承担任何责任且不保证扣货成功或更改派送方式成功。
B8: 7、以下情况，我司会协助处理，不承担任何责任 A.产品如需要FCC,CE,FDA,TSCA,DOT，CPSC,CPC，EPA等认证而客户无法提供有效证明及文件，导致海关扣货等后果 B.产品不符合美国当地法规的，如反倾销，侵权且无法提供有效证及及文件，导致海关扣货等后果 如因以上情况而产生的退运，销毁，仓租等一切费用，由发货方自行承担
B9: 8.因美国本地费用变化频繁且即时生效，我司保留即时更改价格的权利(包括在途中的货物), 2025年3月4号以后如果美国对华临时增税，清关税率平均每上涨10%，公司会针对在途未清关的货物补收增加的关税成本0.5RMB/KG或100元/方,以此类推！

Sheet 海外仓收费明细
A1: 海外仓贴标转运涉及海外仓费用：
A2: 出库收费表：
A3: 费用名称 | B3: 计费单位(Unit) | C3: 单价(USD) | D3: 备注
A4: pallet out-整托出货 | B4: Per pallet/每托 | C4: 10 | D4: FBA/UPS/FEDEX/私人地址等
A5: 分拣费 | B5: PCS(每箱或是拆箱挑每盒) | C5: 1 | D5: 标准件正常收费，超重超尺寸件单询
A6: 托盘材料费 | B6: Per pallet/每托 | C6: 10 | D6: 仅限物料费：如果托盘需要重新打胶膜或换托盘或箱子破损需重新整理.
A7: 出库重新拣货打托， 多件合并打托 | B7: Per pallet/每托 | C7: 15 | D7: 包含托盘物料费人工费，按照亚马逊仓库要求打托
A8: 快递出库费 | B8: Box/每箱 | C8: 1.5 | D8: 留仓件快递出库
A9: 换箱换包装费 | B9: Box | C9: AT COST 实报实销 | D9: $1.0-$2.5/个
A10: 贴标费 | B10: Label/每个 | C10: 0.5 | D10: UPS/FEDEX/FBA/SKU Labels
A11: 出库文件制作费 | B11: 每票 | C11: 减免 | D11: FBA/UPS/FEDEX 预约交仓文件
A12: 附加说明：其它人工费用，不在以上计费项目的额外人工费另计：$50/小时
A14: 库存管理费：
A15: 费用名称 | B15: 计费单位(Unit) | C15: 单价(USD) | D15: 备注
A16: 入库后仓储费 (最低1托起收，不足1托按1托收取,1托按1.8CBM计) | B16: Per pallet/每托/周 | C16: 0 | D16: 免一周
B17: Per pallet/每托/周 | C17: 15 | D17: 2-4 周
B18: Per pallet/每托/周 | C18: 20 | D18: 5-8 周
B19: Per pallet/每托/周 | C19: 25 | D19: 9 周以上

Sheet FBA仓库邮编对照表
A1: 服务分区 | B1: 仓库编号 | C1: 州名简称 | D1: 邮编 | E1: 地址 | F1: 返回主页
A2: 美西 | B2: BFI1/ BFIX | C2: WA | D2: 98390 | E2: 1800 140th Avenue E.,Sumner,Washington,USA,98390-9624
A3: 美西 | B3: BFI7 | C3: WA | D3: 98390
A4: 美西 | B4: BFI3 | C4: WA | D4: 98327 | E4: 2700 Center Drive,Dupont,Washington,USA,98327-9607
A5: 美西 | B5: SEA6 | C5: WA | D5: 98144
A6: 美西 | B6: UWA2 | C6: WA | D6: 98133 | E6: 13537 Aurora Ave.N.,North Seattle,Washington,USA,98133
A7: 美西 | B7: UWA3 | C7: WA | D7: 98121 | E7: 2121 8th Ave.,Seattle,Washington,USA,98121
A8: 美西 | B8: DSE2 | C8: WA | D8: 98108 | E8: 6705 E Marginal Way,Seattle,Washington,USA,98108
A9: 美西 | B9: UWA1 | C9: WA | D9: 98034 | E9: 11710 118th Ave. N.E.,Building B,Kirkland,Washington,USA,98034
A10: 美西 | B10: BFI4 | C10: WA | D10: 98032 | E10: 21005 64th Ave.S,Kent,Washington,USA,98032-2423
A11: 美西 | B11: BFI5 | C11: WA | D11: 98032 | E11: 20529 59th Place South,Building B,Kent,Washington,USA,98032
A12: 美西 | B12: BFI6 | C12: WA | D12: 98032 | E12: 20280 84th Ave S.,Kent,Washington,USA,98032
A13: 美西 | B13: SEA6/ SEA8 | C13: WA | D13: 98005 | E13: 1227 124th Ave NE,Building 2,Bellevue,Washington,USA,98005-2111
A14: 美西 | B14: UOR1 | C14: CA | D14: 97210 | E14: 2250 Northwest 22nd Avenue,Portland,Oregon,USA,97210
A15: 美西 | B15: PDX5 | C15: CA | D15: 97124 | E15: 5647 NW Huffman Street,Washington,Hillsboro,Oregon,USA,97124-5848
A16: 美西 | B16: PDX1 | C16: CA | D16: 97060 | E16: Swigert Way,Troutdale Reynolds Industrial Park,Troutdale,Oregon,USA,97060
A17: 美西 | B17: SMF1 | C17: CA | D17: 95837
A18: 美西 | B18: UCA9 | C18: CA | D18: 95826 | E18: 2934 Ramona Avenue,Sacramento,California,USA,95826-3813
A19: 美西 | B19: SJC7 | C19: CA | D19: 95377 | E19: 188 Mountain House Parkway,Tracy,California,USA,95377-8906
A20: 美西 | B20: OAK3 | C20: CA | D20: 95363 | E20: 255 Park Center Drive,Patterson,California,USA,95363-8876
A21: 美西 | B21: OAK4/OAK6 | C21: CA | D21: 95304 | E21: 1555 N.Chrisman Rd.,Tracy,California,USA,95304-9370
A22: 美西 | B22: XUSD | C22: CA | D22: 95206 | E22: 1909 Zephy Street,Stockton,California,USA,95206
A23: 美西 | B23: SMF3 | C23: CA | D23: 95206 | E23: 3923 S B ST Stockton,California, USA 95206-8202
A24: 美西 | B24: DSF3 | C24: CA | D24: 95131 | E24: 1700 Montague Expy,San Jose,California,USA,95131
A25: 美西 | B25: UCA8 | C25: CA | D25: 94702 | E25: 3100 San Pablo Ave.Ste 120,West Berkley,California,USA,94702
A26: 美西 | B26: DSF1 | C26: CA | D26: 94577 | E26: 990 Beecher St,San Leandro,California,USA,94577
A27: 美西 | B27: OAK5/OAK7 | C27: CA | D27: 94560 | E27: 38811 Cherry Street,Newark,California,USA,94560-4939
A28: 美西 | B28: UCA1 | C28: CA | D28: 94112 | E28: 888 Tennessee Street,San Francisco,California,USA,94112
A29: 美西 | B29: UCA7 | C29: CA | D29: 94085 | E29: 222 Commercial Street,Sunnyvale,California,USA,94085-4508
... A44: 美西 | B44: LGB4 | C44: CA | D44: 92374 | E44: 27517 Pioneer Avenue Redlands, CA 92374-1501 US (LGB4)
A45: 美西 | B45: ONT7 | C45: CA | D45: 92374
A46: 美西 | B46: ONT9 | C46: CA | D46: 92374 | E46: 2125 W. San Bernardino Ave,Redlands,California,USA,92374-5005
A47: 美西 | B47: DSD1 | C47: CA | D47: 92121 | E47: 7130 Miramar Rd.300A,San Diego,California,USA,92121
A48: 美西 | B48: LAX9 | C48: CA | D48: 92337 | E48: 11263 Oleander Ave FONTANA CA 92337
A49: 美西 | B49: PDX7 | C49: OR | D49: 97317 | E49: 4775 Depot Ct SE Salem, OR 97317-8983
A50: 美西 | B50: UCA6 | C50: CA | D50: 92110 | E50: 2727 Kurtz St,San Diego,California,USA,92110
A51: 美西 | B51: DSD2 | C51: CA | D51: 92010 | E51: 2777 Loker Ave W, Carlsbad,California,USA,92010-6517
A52: 美西 | B52: SNA6/SNA9 | C52: CA | D52: 91752 | E52: 5250 Goodman Way,Eastvale,California,USA,91752-5088
A53: 美西 | B53: DLA4 | C53: CA | D53: 91311 | E53: 9031 Lurline Ave,Chatsworth,California,USA,91311
A54: 美西 | B54: DLA2 | C54: CA | D54: 90621 | E54: 5650 Dolly Ave,Buena Park,California,USA,90621
A55: 美西 | B55: DLA1 | C55: CA | D55: 90301 | E55: 900 W Florence Ave,Inglewood,California,USA,90301
A56: 美西 | B56: UCA2 | C56: CA | D56: 90277 | E56: Redondo Beach,California,USA,90277
A57: 美西 | B57: DLA8 | C57: CA | D57: 90250 | E57: 2815 W.El Segundo Blvd.,Hawthorne,California,USA,90250
... A62: 美西 | B62: RNO3 | C62: NV | D62: 89434 | E62: 555 Milan Dr,Sparks,Nevada,USA,89434
A63: 美西 | B63: RNO1 | C63: NV | D63: 89408
A64: 美西 | B64: UNV1 | C64: NV | D64: 89120 | E64: 3650 East Post Road,Sutte E,Las Vegas,Nevada,USA,89120-6297
A65: 美西 | B65: LAS6 | C65: NV | D65: 89115 | E65: 4550 Nexus Way Las Vegas,Nevada,USA, 89115-1826
A66: 美西 | B66: LAS2 | C66: NV | D66: 89030 | E66: 3837 Bay Lake Trail,North Las Vegas,Nevada,USA,89030
A67: 美西 | B67: RNO2 | C67: NV | D67: 85906
A68: 美西 | B68: PHX5 | C68: AZ | D68: 85338 | E68: 16920 W. Commerce Dr.,Goodyear,Arizona,USA,85338-3620
A69: 美西 | B69: DPX2 | C69: AZ | D69: 85043 | E69: 800 N 75th Ave,Phoenix,Arizona,USA,85043
A70: 美西 | B70: PHX3 | C70: AZ | D70: 85043 | E70: 6835 West Buckeye Road,Phoenix,Arizona,USA,85043
A71: 美西 | B71: PHX6/TFC1 | C71: AZ | D71: 85043 | E71: 4750 & 5050 West Mohave Street,Phoenix,Arizona,USA,85043-4428
A72: 美西 | B72: PHX7/PHX8 | C72: AZ | D72: 85043 | E72: 800 N.75th Ave,Phoenix,Arizona,USA,85043-3101
A73: 美西 | B73: DPX1 | C73: AZ | D73: 85034 | E73: 500 S.48th Street,Phoenix,Arizona,USA,85034
A74: 美西 | B74: IVSE | C74: NV | D74: 89115 | E74: 2951 MARION DR UNIT 101 LAS VEGAS, NV 89115-3467
A75: 美西 | B75: DEN2 | C75: CO | D75: 80019 | E75: Amazon.com.dedcLLC22205East19thAveAurora,CO80019US
A76: 美西 | B76: IVSF | C76: NV | D76: 89115-3477 | E76: 2821 MARIONDRSTE109 LASVEGAS,NV89115-3477
A77: 美西 | B77: UAZ1 | C77: AZ | D77: 85001 | E77: Phoenix,Arizona,USA,85001
A78: 美西 | B78: DEN6 | C78: AZ | D78: 80216 | E78: Crossroads Commerce Park,Building,2 480 E.55th Ave.,Adams Denver,Colorado,USA,80216
A79: 美西 | B79: DEN1 | C79: AZ | D79: 80019 | E79: East 19th Avenue North,Prologis Park 70 Aurira,Colorado,USA,80019
A80: 美西 | B80: DEN5 | C80: AZ | D80: 80011 | E80: 19799 E.36th Avenue,Majestic Commercenter Building #29 Aurora,Colorado,USA,80011-8189
A81: 美西 | B81: SAT2 | C81: TX | D81: 78666 | E81: 1401 East McCarty Lane,San Marcos,Texas,USA,78666-8969
A82: 美西 | B82: SAT5 | C82: TX | D82: 78227 | E82: 1410 S.Callaghan Road,Bexar,San Antonio,Texas,USA,78227-2204
A83: 美西 | B83: SAT1 | C83: TX | D83: 78154 | E83: 6000 Enterprise Avenue,Schertz,Texas,USA,78154-1461
A84: 美西 | B84: HOU1 | C84: TX | D84: 77338 | E84: 8120 Humble Westfield Rd,Humble,Texas,USA,77338-4142
A85: 美西 | B85: UTX3 | C85: TX | D85: 77001 | E85: Houston,Texas,USA,77001
A86: 美西 | B86: DFW7 | C86: TX | D86: 76177 | E86: 700 Westport Parkway,(Haslet)Fort Worth,Texas,USA,76177-4513
A87: 美西 | B87: FTW3 | C87: TX | D87: 76177 | E87: 15201 Heritage Parkway,Fort Worth,Texas,USA,76177-2517
A88: 美西 | B88: XUSB | C88: TX | D88: 76155 | E88: 14900 Frye Road,Fort Worth,Texas,USA,76155
... A94: 美西 | B94: DFW8/DFW9 | C94: TX | D94: 75063 | E94: 2700 Regent Blvd,Irving,Texas,USA,75063
A95: 美西 | B95: FTW2 | C95: TX | D95: 75019
A96: 美西 | B96: DFW6 | C96: TX | D96: 75019 | E96: 940 W.Bethel Road,Coppell,Texas,USA,75019-4424
A97: 美西 | B97: UTX1 | C97: TX | D97: 75014 | E97: Irving,Texas,USA,75014
A98: 美西 | B98: UTX2 | C98: TX | D98: 73301 | E98: Auston,Texas,USA,73301
A99: 美西 | B99: PWA5 | C99: TX | D99: 73179 | E99: Northeast corner of SW 15th and s Council Road,Oklahoma City,Oklahoma,USA,73179
A100: 美西 | B100: DFW1 | C100: TX | D100: 75261 | E100: 2700 Regent Blvd DFW Airport Dallas TX 75261
A101: 美西 | B101: ITX2 | C101: TX | D101: 77040-1437 | E101: 6911FAIRBANKSNHOUSTONRDSUITE160 Houston,TX77040-1437
A102: 美西 | B102: HOU2 | C102: TX | D102: 77038 | E102: 10550 Ella Blvd. Houston TX 77038-2324
A103: 美西 | B103: ITX1 | C103: TX | D103: 77064 | E103: ook Pines Drive Suite 100 Houston, TX 77064-3329
A104: 美西 | B104: HOU3 | C104: TX | D104: 77423 | E104: 31555 Highway 90E Brook shire,TX 77423-2769
A105: 美西 | B105: TUL1 | C105: KS | D105: 67337
A106: 美中 | B106: MCI5 | C106: KS | D106: 66219 | E106: 16851W 113th St,Lenexa Logistics Center,Lecexa,Kansas,USA,66219
A107: 美中 | B107: MCI1 | C107: KS | D107: 66102 | E107: Turner Commerce Center,6925 Riverview Ave.Kansas City,Kansas,USA,66102
A108: 美中 | B108: MCI7 | C108: KS | D108: 66031 | E108: 27200 West 157th Street Johnson(New Century),Kansas,USA,66031
A109: 美中 | B109: MKC4 | C109: KS | D109: 66030 | E109: 19645 Waverly Rd,Gardner,Kansas,USA,66030
A110: 美中 | B110: MKC6 | C110: KS | D110: 66102 | E110: amazon.com 6925 Riverview Avenue Kansas City 66102
A111: 美中 | B111: MDW4 | C111: IL | D111: 62025 | E111: 201 Emerald Drive,Joliet,Illinois,USA,62025-2815
A112: 美中 | B112: STL4 | C112: IL | D112: 62025 | E112: 3050 Gateway Commerce Center Drive South,Edwardsville,Illinois,USA,62025-2815
A113: 美中 | B113: STL6 | C113: IL | D113: 62025 | E113: 3931 Lakeview Corporate Dr,Edwardsville,Illinois,USA,62025-2801
A114: 美中 | B114: MDW5 | C114: IL | D114: 60642 | E114: 1111 N.Cherry Ave.,Goose Island,Illinois,USA,60642
A115: 美中 | B115: DCH1 | C115: IL | D115: 60608 | E115: 2801 S.Western Ave,Chicago,Illinois,USA,60608
A116: 美中 | B116: DCH3 | C116: IL | D116: 60532 | E116: 4500 Western Ave,Lisle,Illinois,USA,60532
A117: 美中 | B117: MDW9 | C117: IL | D117: 60502
A118: 美中 | B118: MDW7 | C118: IL | D118: 60449 | E118: 6521 W.Monee Manhattan Road,Monee,Illinois,USA,60449
A119: 美中 | B119: MDW8 | C119: IL | D119: 60449 | E119: 1750 Bridge Drive,Waukegan,Illinois,USA,60449
A120: 美中 | B120: MDW6 | C120: IL | D120: 60446 | E120: 1125 Remington Blvd,Romeoville,Illinois,USA,60446-6529
A121: 美中 | B121: MDW2 | C121: IL | D121: 60433 | E121: 401E.Laraway Road,Joliet,Illinois,USA,60433-9462
A122: 美中 | B122: ORD6 | C122: IL | D122: 60191 | E122: 1250 N.Mittel Blvd,Wood Dale,Illinois,USA,60191
A123: 美中 | B123: DCH2 | C123: IL | D123: 60053 | E123: 8220 Austin Ave,Morton Grove,Illinois,USA,60053
...

Sheet 交接清单
A1: 公司名称:
A2: 序号 | B2: 系统下单单号 | C2: 交货渠道 | D2: 件数 | E2: 方数 | F2: 是否单独报关
A3: 1
A4: 2
A5: 3
A6: 4
A7: 5
A8: 6
A9: 合计 件
A10: 客户签名：
A11: 收货人签名：
A12: 福永仓库地址：深圳市宝安区福海街道福园一路高新建工业区一楼商速航供应链(岗亭直走到底最里面左手边) 联系人：李先生 联系电话：15625507507（紧急联系人涂先生：17722682149) 收货时间：周一至周六上午9:00~晚上21:00
A13: 龙华仓库地址：深圳市龙华区福城街道福民社区富康工业区A2栋厂房1楼（商速航）党先生：15591381931 龙华仓上班时间：周一至周六12:00~24:00
A14: 义乌仓库地址：浙江省金华市义乌市义乌京东亚洲一号物流园祥瑞路3号门进来右手边上天桥二楼开到头右手边4号库（导航：4栋2楼4号商速航义乌仓） 晚班-联系人：钱先生 电话：18386399460（晚班） 早班-联系人：蔡先生 18083572991（早班） 收货时间：周一至周六上午9:00~晚上21:00
A15: 广州仓库地址：广州市白云区均禾街道办罗岗村白头岭东街86号1栋1层内 收货人：韦先生19978716660（紧急联系人：袁欢13997511522 ）

Sheet 禁运品反倾销及特殊监管产品
A1: 禁运品反倾销及特殊监管产品 | N1: 返回主页
A2: 全球禁止入仓的货物
A3: 根据《国际海运危险货物规则》和国家标准《危险货物品名表》所列的危险品，目前，我司仓库不接收的货物品名如下（包括但不限于以下品名）：
A4: (1)爆炸品：炸药、雷管、火药、子弹、烟花、鞭炮等；
A5: (2)易燃气体：打火机、打火机油、空气清新剂、摩丝(发胶、头发定型剂)、液化气，灭火器等；
A6: (3)易燃液体：油漆、酒精、白酒、胶黏剂、粘合剂、丙酮、汽油、柴油、天那水、胶水、 粘合剂、油墨、定型水、指甲油、香水等；
A7: (4)易燃固体：火柴、硫磺、明胶、硝基、磷、镁、乒乓球、蜡烛等；
A8: (5)毒性物质：砷、尼古丁、氰化物、氰化钾、杀虫剂、农药等；
A9: (6)腐蚀品：硫酸、盐酸、氢氧化钠、氢氧化钾、水银、双氧水、电镀用溶液、蓄电池、清洗液、清洁水等；
A10: (7)杂类：安全气囊、太阳能移动电源、字画、古玩，二手物品等；
A11: (8)仿牌类：凡是在中国海关和其他国家/地区海关网站上能查到登记信息的任何仿牌货物都禁止入仓，非牌子货需提供品牌申明书；
A12: 其他限制入仓货物：不属于以上危险品目录范围的货物以及其它外包装上带有易燃、 易爆、易腐蚀标示的货物等，请在交货时提供产品说明、MSDS及保函（审批后确认是否可以入仓）。
A13: 美国反倾销产品目录
A14: (1)贱金属及其制品 | C14: 钢钉、钢管、碳合金钢丝条、金属硅、金刚石锯片、不锈钢货架、不锈钢加压管、定尺碳素钢板、石油专用管材、冷轴碳钢、薄壁矩形钢管、熨衣架及部件、螺纹钢筋、弹簧垫圈、非封闭内置弹簧部件、不锈钢拉制深水槽、冷轧钢板、无缝碳钢和合金钢标准管、管线管和压力管、圆锥滚子轴承、铸铁件、金属镁、镀锌板、重锻造手动工具（斧子、撬杠、锤子、镐头）、钢制高压气瓶
A15: (2)化学产品 | C15: 己内酰胺（又称碳酸锂）、聚对苯二甲酸乙二酯膜片和条、聚乙烯醇、高锰酸钾、三聚氰胺、天然猪鬃油漆刷及刷头
A16: (3)杂项制品 | C16: 木制卧室家具、复合木地板、硬木胶合板产品，非晶硅织物、晶体硅光伏电池、小直径石墨电极
A17: (4)机械电气设备及部件 | C17: 滚球轴承、汽车挡风玻璃、刹车鼓与刹车转子，轮毂，轮胎
A18: (5)纸及纸制品 | C18: 铜版纸、格记录纸、薄绵纸、折叠礼品盒、皱纹纸、无涂层纸，低克重热敏纸
A19: (6)纺织制品 | C19: 聚酯纤维、画布、编织电热毯，原聚酯棉印花布，窄幅梭织缎带
A20: (7)预制食品与饮料 | C20: 淹渍蘑菇罐头、柠檬酸与柠檬酸盐、华糖醇、冷冻的和罐装的暖水虾
A21: (8)塑料与橡胶制品 | C21: 复合编织袋、聚乙烯手提袋、新充气工程机械轮胎
A22: (9)日常生活用品 | C22: 折叠金属椅子，搪瓷厨具，钢丝衣架，蜡烛（所有石蜡制品），曲别针，铅笔
A23: (10)家用电器 | C23: 彩色电视机、家用大型洗衣机
A24: (11)车船运输设备及部件 | C24: 自行车、手推车
A25: (12)建材与玻璃制品 | C25: 铝型材、双轴土工格栅、镁碳砖
A26: (13)蔬菜产品 | C26: 蜂蜜
A27: 美国特殊监管产品
A28: (1) FDA 食品和药物管理局 食品，药品，医疗器械，化妆品
A29: 分为两种，一种是美国注册FDA,FILE FDA，，另一种是要生产厂商的FDA 注册号和产品的注册号。
A30: FILE FDA:
A31: 日用品：碗、锅、勺子叉子（户外烧烤刀叉可以不需要）、蛋糕模型、披萨盘模型、不锈钢刀、杯子、醒酒器、酒瓶、不锈钢冰块、烟灰缸，水瓶， 饭盒，杯子，瓶子，榨汁机。
A32: 化妆品：BB箱，睫毛膏，面膜
A33: FDA 认证: 食品，药品，大部分化妆品,医疗器械，电子烟及烟草，动物皮毛制品，成人用品，管制刀具，植物种子
A34: 常见FDA认证产品：
A35: 日用品：太阳镜，各种眼镜，急救包，陶瓷用品，电动牙刷，洗澡刷、电动牙刷、牙膏
A36: 美容仪器：面膜、眼膜、纹身针、化妆刷、
A37: 理疗产品：按摩器、性用品、温度计、
A38: 宠物用品：激光灯类、红外线类、猫薄荷、防潮剂
... A45: (6) 需授权类的产品：蓝牙，HIMI等。

Sheet 美国对华反倾销产品目录
A1: 美国对华反倾销产品目录表 截止2016年1月1日 | G1: 返回主页
A2: 以下反倾销的品名严格拒收
A3: 1、不锈钢货架, 2、太阳能类, 3、带线条笔记本, 4、石蜡类 。
A4: Order | B4: POR | D4: Current PRC-wide Rate | E4: Date of AD
A5: Jan.
A6: A-570-001 | B6: Potassium Permanganate | C6: 高锰酸钾 | D6: 1.2894 | E6: 1984.01.31 | F6: 01.01 - 12.31
A7: A-570-866 | B7: Folding Gift Boxes | C7: 折叠礼品盒 | D7: 1.6475 | E7: 2002.01.08 | F7: 01.01 - 12.31
A8: A-570-873 | B8: Ferrovanadium | C8: 铁钒合金 | D8: 0.6671 | E8: 2003.01.28 | F8: 01.01 - 12.31
A9: A-570-895 | B9: Crepe Paper | C9: 皱纹纸 | D9: 2.6683 | E9: 2005.01.25 | F9: 01.01 - 12.31
A10: A-570-890 | B10: Wooden Bedroom Furniture | C10: 木制卧室家具 | D10: 2.1601 | E10: 2005.01.04 | F10: 01.01 -12.31
A11: Feb.
A12: A-570-501 | B12: Natural Bristle Paintbrushes and Brush Heads | C12: 天然猪鬃油漆刷及刷头 | D12: 3.5192 | E12: 1986.02.14 | F12: 02.01 - 01.31
A13: A-570-803 | B13: Heavy Forged Hand Tools | C13: 重锻造手动工具 | D13: 斧子：174.58%; 撬杠：139.31%; 锤子：45.52%; 镐头：98.77% | E13: 1991.02.19 | F13: 02.01 - 01.31
A14: A-570-851 | B14: Preserved Mushrooms | C14: 淹渍蘑菇 | D14: 1.9863 | E14: 1997.02.19 | F14: 02.01 - 01.31
A15: A-570-893 | B15: Frozen and Canned Warmwater Shrimp | C15: 冷冻的和罐装的暖水虾 | D15: 1.1281 | E15: 2005.02.01 | F15: 02.01 - 01.31
A16: A-570-928 | B16: Uncovered Innerspring Units | C16: 非封闭内置弹簧部件 | D16: 2.3451 | E16: 2009.02.19 | F16: 02.01 - 01.31
A17: A-570-929 | B17: Small Diameter Graphite Electrodes | C17: 小直径石墨电极 | D17: 1.5964 | E17: 2009.02.26 | F17: 02.01 - 01.31
A18: A-570-981 | B18: Utility Scale Wind Towers | C18: 风塔 | D18: 0.7063 | E18: 2013.02.15 | F18: 02.01-01.31
A19: March
A20: A-570-002 | B20: Chloropicrin | C20: 三氯硝基甲烷 | D20: 0.58 | E20: 1984.03.22 | F20: 03.01 - 02.28
A21: A-570-836 | B21: Glycine | C21: 氨基乙酸.甘氨酸 | D21: 155.89% 453.79% | E21: 1995.03.29 | F21: 03.01 - 02.28
A22: A-570-894 | B22: Tissue Paper | C22: 薄页纸 | D22: 1.1264 | E22: 2005.03.30 | F22: 03.01 - 02.28
A23: A-570-908 | B23: Sodium Hexametaphosphate | C23: 六偏磷酸钠 | D23: 1.8805 | E23: 2008.03.19 | F23: 03.01 - 02.28
A24: A-570-930 | B24: Circular Welded Austenitic Stainless Pressure Pipe | C24: 圆形焊接奥氏体不锈高压套管 | D24: 0.5521 | E24: 2009.03.17 | F24: 03.01 - 02.28
A25: A-570-965 | B25: Drill Pipe | C25: 钻杆 | D25: 4.2995 | E25: 2011.03.03 | F25: 03.01 - 02.28
A26: A-570-973 | B26: Certain Steel Wheels | C26: 钢制轮毂 | D26: 1.9354 | E26: 2012.03.23
A27: A-570-975 | B27: Galvanized Steel Wire | C27: 镀锌钢丝 | D27: 2.35 | E27: 2012.03.26
A28: April
A29: A-570-867 | B29: Automotive Replacement Glass Windshields | C29: 汽车挡风玻璃 | D29: 1.245 | E29: 2002.04.04 | F29: 04.01-03.31
A30: A-570-875 | B30: Non-malleable Cast Iron Pipe Fittings | C30: 无可锻性铸铁管件 | D30: 0.755 | E30: 2003.04.07 | F30: 04.01 - 03.31
A31: A-570-896 | B31: Magnesium metal | C31: 镁金属 | D31: 1.4149 | E31: 2005.04.15 | F31: 04.01 - 03.31
A32: A-570-904 | B32: Certain Activated Carbon | C32: 活性碳 | D32: 2.2811 | E32: 2007.04.27 | F32: 04.01-03.31
A33: A-570-932 | B33: Steel Threaded Rod | C33: 钢制螺杆 | D33: 2.06 | E33: 2009.04.17 | F33: 04.01-03.31
A34: A-570-933 | B34: Frontseating Service Valves | C34: 空调用截止阀 | D34: 0.5562 | E34: 2009.04.28 | F34: 04.01-03.31
A35: A-570-934 | B35: 1-Hydroxyethylidene-1,1-Diphosphonic Acid (Hedp) | C35: 羟基亚乙基二膦酸 | D35: 0.7242 | E35: 2009.04.28 | F35: 04.01-03.31
A36: A-570-983 | B36: Drawn Stainless Steel Sinks | C36: 不锈钢拉制水槽 | D36: 0.7653 | E36: 2013.04.11 | F36: 04.01-03.31
A37: May
A38: A-570-502 | B38: Iron Construction Castings | C38: 铁制建筑铸件 | D38: 0.2552 | E38: 1986.05.09 | F38: 05.01- 04.30
A39: A-570-832 | B39: Pure Magnesium | C39: 纯镁 | D39: 1.0826 | E39: 1995.05.12 | F39: 05.01-04.30
A40: A-570-935 | B40: Certain circular welded carbon quality steel line pipe | C40: 圆形焊接碳钢线管 | D40: 1.011 | E40: 2009.05.13 | F40: 05.01-04.30
A41: A-570-937 | B41: Citric Acid and Certain Citrate Salts | C41: 柠檬酸和柠檬酸盐 | D41: 1.5687 | E41: 2009.05.29 | F41: 05.01-04.30
A42: A-570-943 | B42: Oil Country Tubular Goods | C42: 石油专用管材 | D42: 0.9914 | E42: 2010.05.21 | F42: 05.01-04.30
A43: A-570-967 | B43: Aluminum Extrusions | C43: 铝型材 | D43: 0.3328 | E43: 2011.05.26 | F43: 05.01-04.30
A44: June
A45: A-570-601 | B45: Tapered Roller Bearings and Parts | C45: 圆锥滚子轴承及部件 | D45: 0.9284 | E45: 1987.06.15 | F45: 06.01 - 05.31
A46: A-570-806 | B46: Silicon Metal | C46: 硅金属 | D46: 1.3949 | E46: 1991.06.10 | F46: 06.01 - 05.31
A47: A-570-835 | B47: Furfuryl Alcohol | C47: 糠醇 | D47: 0.4527 | E47: 06.21.1995 | F47: 06.01 - 05.31
A48: A-570-868 | B48: Folding Metal Tables and Chairs | C48: 折叠金属桌椅 | D48: 0.7071 | E48: 2002.06.27 | F48: 06.01 - 05.31
A49: A-570-898 | B49: Chlorinated Isocyanurates | C49: 氯代异氰(三氯异氰尿酸) | D49: 2.8563 | E49: 2005.06.24 | F49: 06.01 - 05.31
A50: A-570-899 | B50: Artist Canvas | C50: 画布 | D50: 2.6409 | E50: 2006.06.01 | F50: 06.01 - 05.31
A51: A-570-905 | B51: Certain Polyester Staple Fiber | C51: 聚酯纤维 | D51: 0.443 | E51: 2007.06.01 | F51: 06.01 - 05.31
A52: A-570-977 | B52: High Pressure Steel Cylinders | C52: 钢制高压气瓶 | D52: 0.3121 | E52: 2012.6.21 | F52: 06.01-05.31
A53: A-570-945 | B53: Prestressed Concrete Steel WireStrand | C53: 预应力混凝土用钢绞线 | D53: 1.9355 | E53: 2010.06.29 | F53: 06.01-05.31
A54: A-570-949 | B54: Wire Decking | C54: 金属网片 | D54: 1.43 | E54: 2010.6.10
A55: July
A56: A-570-814 | B56: Carbon Steel Butt-weld Pipe Fittings | C56: 碳钢焊接接口 | D56: 1.829 | E56: 1992.07.06 | F56: 07.01 - 06.30
A57: A-570-847 | B57: Persulfates | C57: 过硫酸盐 | D57: 1.1902 | E57: 1997.07.07 | F57: 07.01 - 06.30
A58: A-570-853 | B58: Bulk Aspirin | C58: 散装阿斯匹林 | D58: 1.4402 | E58: 2000.07.11 | F58: 07.01 - 06.30
A59: A-570-910 | B59: Circular Welded Carbon Quality Steel Pipe | C59: 圆形焊接碳钢管件 | D59: 0.6824 | E59: 2008.07.22 | F59: 07.01 - 06.30
A60: A-570-878 | B60: Saccharin | C60: 糖精钠 | D60: 3.2994 | E60: 2003.06.12 | F60: 07.01-06.30
A61: A-570-947 | B61: Certain Steel Grating | C61: 钢格板 | D61: 1.4518 | E61: 2010.07.23 | F61: 07.01-06.30
A62: A-570-962 | B62: Certain Sodium and Potassium Phosphate Salts | C62: 钠和钾磷盐 | D62: 0.954 | E62: 2010.07.22 | F62: 07.01-06.30
A63: August
A64: A-570-815 | B64: Sulfanlic Acid | C64: 对氨基苯磺酸 | D64: 0.852 | E64: 1992.08.19 | F64: 08.01 - 07.31
A65: A-570-886 | B65: Polyethylene Retail Carrier Bags | C65: 聚乙烯零售包装袋 | D65: 0.7757 | E65: 2004.08.09 | F65: 08.01 - 07.31
A66: A-570-887 | B66: Tetrahydrofurfuryl Alcohol | C66: 四氢糠醇 | D66: 1.3686 | E66: 2004.08.06 | F66: 08.01 - 07.31
A67: A-570-888 | B67: Floor-Standing, Metal-Top Ironing Tables and Certain Parts | C67: 落地式金属台面烫衣板及部件 | D67: 1.5768 | E67: 2004.08.06 | F67: 08.01 - 07.31
A68: A-570-504 | B68: Petroleum Wax Candles | C68: 石油蜡烛 | D68: 1.083 | E68: 1986.08.28 | F68: 08.01- 07.31
A69: A-570-909 | B69: Steel Nail | C69: 钢钉 | D69: 1.1804 | E69: 2008.08.01 | F69: 08.01- 07.31
A70: A-570-914 | B70: Light-Walled Rectangular Pipe and Tube | C70: 薄壁矩形钢管 | D70: 2.6464 | E70: 2008.08.05 | F70: 08.01-07.31
A71: A-570-916 | B71: Laminated Woven Sacks | C71: 复合编织袋 | D71: 0.9173 | E71: 2008.08.07 | F71: 08.01- 07.31
A72: A-570-925 | B72: Sodium Nitrite | C72: 亚硝酸钠 | D72: 1.9074 | E72: 2008.08.27 | F72: 08.01- 07.31
A73: A-570-939 | B73: Certain Tow-Behind Lawn Groomers and Certain Parts Thereof | C73: 后拖式草地维护设备及零部件 | D73: 3.8628 | E73: 2009.08.03 | F73: 08.01- 07.31
A74: A-570-951 | B74: Certain Woven Electric Blankets | C74: 编织电热毯 | D74: 1.7485 | E74: 2010.08.18 | F74: 08.01-07.31
A75: Sep.
A76: A-570-860 | B76: Steel Concrete Reinforcing Bars | C76: 钢筋 | D76: 1.3253 | E76: 2001.09.07 | F76: 09.01 - 08.31
A77: A-570-862 | B77: Foundry Coke Products | C77: 铸造焦碳 | D77: 2.1489 | E77: 2001.09.17 | F77: 09.01 - 08.31
A78: A-570-101 | B78: Greig Polyester Cotton Print Cloth | C78: 原聚酯棉印花布 | D78: 0.224 | E78: 1983.09.16 | F78: 09.01 - 08.31
A79: A-570-848 | B79: Freshwater Crawfish Tail Meat | C79: 淡水小龙虾尾肉 | D79: 2.2301 | E79: 1997.09.15 | F79: 09.01 - 08.31
A80: A-570-901 | B80: Lined Paper Products | C80: 文具纸 | D80: 2.5821 | E80: 2006.10.26 | F80: 09.01-08.31
A81: A-570-912 | B81: New pneumatic off-the-road tires | C81: 新充气工程机械轮胎 | D81: 2.1048 | E81: 2008.09.04 | F81: 09.01-08.31
A82: A-570-922 | B82: Raw Flexible Magnets | C82: 未加工橡胶磁 | D82: 1.8528 | E82: 2008.09.17 | F82: 09.01-08.31
A83: A-570-941 | B83: Certain Kitchen Appliance Shelving and Racks | C83: 厨房用搁板和网架 | D83: 0.9599 | E83: 2009.09.14 | F83: 09.01-08.31
A84: A-570-952 | B84: Narrow Woven Ribbons with Woven Selvedge | C84: 窄幅梭织缎带 | D84: 2.4765 | E84: 2010.09.01 | F84: 09.01-08.31
A85: A-570-954 | B85: Certain Magnesia Carbon Bricks | C85: 镁碳砖 | D85: 2.36 | E85: 2010.09.20 | F85: 09.01-08.31
A86: A-570-986 | B86: Hardwood Plywood | C86: 硬木胶合板产品 | D86: 1.2165 | E86: 2013.09.23
A87: Oct.
A88: A-570-007 | B88: Barium Chloride | C88: 氯化钡 | D88: 1.555 | E88: 1984.10.17 | F88: 10.01 - 09.30
A89: A-570-822 | B89: Helical Spring Lock Washers | C89: 螺旋形弹簧锁垫圈 | D89: 1.2863 | E89: 1993.10.19 | F89: 10.01 - 09.30
A90: A-570-880 | B90: Barium Carbonate | C90: 碳酸钡 | D90: 0.813 | E90: 2003.10.01 | F90: 10.01 - 09.30
A91: A-570-879 | B91: Polyvinyl Alcohol | C91: 聚乙烯醇 | D91: 0.0786 | E91: 2003.10.01 | F91: 10.01 - 09.30
A92: A-570-918 | B92: Steel Wire Garment Hangers | C92: 钢丝衣架 | D92: 1.8725 | E92: 2008.10.06 | F92: 10.01 - 09.30
A93: A-570-919 | B93: Electrolytic Manganese Dioxide | C93: 电解二氧化锰 | D93: 1.4992 | E93: 2008.10.07 | F93: 10.01 - 09.30
A94: Nov.
A95: A-570-849 | B95: Cut-to-length Carbon Steel Plate | C95: 定尺碳钢板 | D95: 1.2859 | E95: 1997.10.24 | F95: 11.01 - 10.31
A96: A-570-864 | B96: Pure Magnesium in Granular | C96: 颗粒状纯镁 | D96: 3.0556 | E96: 2001.11.19 | F96: 11.01 - 10.30
A97: A-570-865 | B97: Hot-rolled Carbon Steel Flat Products | C97: 热轧碳钢板 | D97: 0.9083 | E97: 2001.11.29 | F97: 11.01 - 10.30
A98: A-570-831 | B98: Fresh Garlic | C98: 鲜蒜 | D98: 3.7667 | E98: 1994.11.16 | F98: 11.01 - 10.31
A99: A-570-882 | B99: Refined Brown Aluminum Oxide | C99: 棕刚玉 | D99: 1.3518 | E99: 2003.11.19 | F99: 11.01 - 10.31
A100: A-570-826 | B100: Paper Clips | C100: 曲别针 | D100: 1.2694 | E100: 1994.11.25 | F100: 11.01- 10.31
...

Sheet 下单发票模板
A1: 客户订单号*
A2: 服务* | B2: 广州美西卡派组合二区
A3: 地址库编码* | B3: POC3-FEDEX
A4: 收件人姓名* | B4: =VLOOKUP(B3,[2]美国FBA地址库!$A1:$IV65536,2,0) -> POC3-FEDEX
A5: 收件人公司* | B5: =VLOOKUP(B3,[2]美国FBA地址库!D$1:O$65536,3,0) -> AMAZON
A6: 收件人地址一* | B6: =VLOOKUP(B3,[2]美国FBA地址库!D$1:O$65536,6,0) -> 6120 Clinker Drive | E6: 填写完整地址 请勿包含双重城市名
A7: 收件人地址二
A8: 收件人地址三
A9: 收件人城市* | B9: =VLOOKUP(B3,[2]美国FBA地址库!D$1:O$65536,9,0) -> Jurupa Valley
A10: 收件人省份/州* | B10: =VLOOKUP(B3,[2]美国FBA地址库!D$1:O$65536,10,0) -> CA
A11: 收件人邮编* | B11: =VLOOKUP(B3,[2]美国FBA地址库!D$1:O$65536,12,0) -> 92509
A12: 收件人国家代码(二字代码)* | B12: =VLOOKUP(B3,[2]美国FBA地址库!D$1:O$65536,11,0) -> US
A13: 收件人电话 | B13: =VLOOKUP(B3,[2]美国FBA地址库!D$1:O$65536,4,0) -> 0000000000
A14: 带电* | B14: 否
A15: 报关方式* | B15: 买单报关
A16: 箱数* | B16: 2
A17: 备注
A18: 货箱编号* | B18: 货箱重量(KG)* | C18: 货箱长度(CM)* | D18: 货箱宽度(CM)* | E18: 货箱高度(CM)* | F18: 产品英文品名* | G18: 产品中文品名* | H18: 产品申报单价USD* | I18: 产品申报数量* | J18: 产品材质* | K18: 产品海关编码* | L18: 产品用途* | M18: 英文产品品牌* | N18: 中文产品品牌* | O18: 产品型号* | P18: PONumber（卡派填写）* | Q18: 产品图片*
A19: FBA18G2GLLJZU000001 | B19: 16 | C19: 58 | D19: 46 | E19: 38 | F19: Vacuum sealing machine | G19: 真空密封机 | H19: 42.68 | I19: 4 | J19: PC与电子元件 | K19: 8414100090 | L19: For vacuum sealing | M19: INKBIRD | N19: INKBIRD | O19: V7230 | P19: 23U7RUGH
A20: FBA18G2GLLJZU000002 | B20: 16 | C20: 58 | D20: 46 | E20: 38 | F20: Vacuum sealing machine | G20: 真空密封机 | H20: 42.68 | I20: 4 | J20: PC与电子元件 | K20: 8414100090 | L20: For vacuum sealing | M20: INKBIRD | N20: INKBIRD | O20: V7230 | P20: 23U7RUGH

Sheet Sheet2
